Workbook

Sheet Painel
A1: Painel ZBR Importado | R1: =IF(A5="Todos","*",A5) -> * | AS1: Todos | AU1: 46274 | AV1: Todos | AW1: 2665-E4-U71 | AX1: 252800202 | AY1: =IF(OR($A$5="Todos",AW1=$A$5),1,0) -> 1 | AZ1: KG | BA1: Todas
A2: Entradas, saídas e estoque físico por SKU e lote · centro BR01 · movimentos de 09/09 a 01/10/2026 | R2: =IF(OR(D5="Todos",D5=""),"*",D5) -> * | AS2: 2665-E4-U71 | AU2: 46275 | AV2: =IFERROR(INDEX($AX$1:$AX$94,MATCH(1,$AY$1:$AY$94,0)),"") -> 252800202 | AW2: 70-30-38-BR-25A | AX2: 260070301 | AY2: =IF(OR($A$5="Todos",AW2=$A$5),MAX(AY$1:AY1)+1,0) -> 2 | AZ2: UN | BA2: Entrada
R3: =IF(A5="Todos",J5,IFERROR(INDEX($U$40:$U$133,MATCH(A5,$T$40:$T$133,0)),J5)) -> KG | AS3: 70-30-38-BR-25A | AU3: 46276 | AV3: =IFERROR(INDEX($AX$1:$AX$94,MATCH(2,$AY$1:$AY$94,0)),"") -> 260070301 | AW3: 70-30-38-BR-25A | AX3: 260370301 | AY3: =IF(OR($A$5="Todos",AW3=$A$5),MAX(AY$1:AY2)+1,0) -> 3 | AZ3: CX | BA3: Saída
A4: SKU | D4: LOTE | F4: DATA INICIAL | H4: DATA FINAL | J4: UNIDADE | K4: MOVIMENTAÇÃO | R4: =IF(K5="Entrada","Entrada",IF(K5="Saída","Saída",IF(K5="Recebido no 2008","Recebido no 2008",IF(K5="Estorno","Estorno","*")))) -> * | AS4: 70-30-38-BR-D94 | AU4: 46277 | AV4: =IFERROR(INDEX($AX$1:$AX$94,MATCH(3,$AY$1:$AY$94,0)),"") -> 260370301 | AW4: 70-30-38-BR-D94 | AX4: 253213449 | AY4: =IF(OR($A$5="Todos",AW4=$A$5),MAX(AY$1:AY3)+1,0) -> 4 | BA4: Recebido no 2008
A5: Todos | D5: Todos | F5: 46274 | H5: 46296 | J5: KG | K5: Todas | R5: =Resumo!$C$7 -> 0.01 | AS5: 805-BR-D94 | AU5: 46278 | AV5: =IFERROR(INDEX($AX$1:$AX$94,MATCH(4,$AY$1:$AY$94,0)),"") -> 253213449 | AW5: 805-BR-D94 | AX5: 251633359 | AY5: =IF(OR($A$5="Todos",AW5=$A$5),MAX(AY$1:AY4)+1,0) -> 5 | BA5: Estorno
A6: ▼ Filtros: clique numa célula azul e depois na seta que aparece ao lado para escolher. “Todos” mostra tudo. A lista de lotes mostra só os lotes do SKU escolhido. | AS6: 811-BR-25A | AU6: 46279 | AV6: =IFERROR(INDEX($AX$1:$AX$94,MATCH(5,$AY$1:$AY$94,0)),"") -> 251633359 | AW6: 805-BR-D94 | AX6: 260130779 | AY6: =IF(OR($A$5="Todos",AW6=$A$5),MAX(AY$1:AY5)+1,0) -> 6
A7: ="Mostrando: "&IF(A5="Todos","todos os SKUs",A5)&IF(D5="Todos",""," · lote "&D5)&" · "&DAY(F5)&"/"&MONTH(F5)&"/"&YEAR(F5)&" a "&DAY(H5)&"/"&MONTH(H5)&"/"&YEAR(H5)&" · unidade "&$R$3&IF(K5="Todas",""," · movimentação "&K5) -> Mostrando: todos os SKUs · 9/9/2026 a 1/10/2026 · unidade KG | AS7: 811-BR-D94 | AU7: 46280 | AV7: =IFERROR(INDEX($AX$1:$AX$94,MATCH(6,$AY$1:$AY$94,0)),"") -> 260130779 | AW7: 811-BR-25A | AX7: 250880301 | AY7: =IF(OR($A$5="Todos",AW7=$A$5),MAX(AY$1:AY6)+1,0) -> 7
AS8: 811NV-132 | AU8: 46281 | AV8: =IFERROR(INDEX($AX$1:$AX$94,MATCH(7,$AY$1:$AY$94,0)),"") -> 250880301 | AW8: 811-BR-25A | AX8: 252450301 | AY8: =IF(OR($A$5="Todos",AW8=$A$5),MAX(AY$1:AY7)+1,0) -> 8
A9: ="ENTROU · "&$R$3 -> ENTROU · KG | C9: ="SAIU · "&$R$3 -> SAIU · KG | F9: ="DEVERIA TER · "&$R$3 -> DEVERIA TER · KG | H9: ="ESTOQUE FÍSICO · "&$R$3 -> ESTOQUE FÍSICO · KG | J9: ="DIFERENÇA · "&$R$3 -> DIFERENÇA · KG | L9: ="Confere: "&COUNTIFS($AA$40:$AA$133,1,$AC$40:$AC$133,"Confere")&" SKU·lote" -> Confere: 58 SKU·lote | AS9: 811NV-595 | AU9: 46282 | AV9: =IFERROR(INDEX($AX$1:$AX$94,MATCH(8,$AY$1:$AY$94,0)),"") -> 252450301 | AW9: 811-BR-D94 | AX9: 251643289 | AY9: =IF(OR($A$5="Todos",AW9=$A$5),MAX(AY$1:AY8)+1,0) -> 9
A10: =SUMPRODUCT($AA$40:$AA$133,$W$40:$W$133) -> 65930.28 | C10: =SUMPRODUCT($AA$40:$AA$133,$X$40:$X$133) -> 26268.8 | F10: =A10-C10 -> 39661.48 | H10: =SUMPRODUCT($AA$40:$AA$133,$Y$40:$Y$133) -> 59270.487 | J10: =ROUND(H10-F10,3) -> 19609.007 | L10: ="Sobrando: "&COUNTIFS($AA$40:$AA$133,1,$AC$40:$AC$133,"Sobrando")&" SKU·lote" -> Sobrando: 20 SKU·lote | AS10: 823-BR-25A | AU10: 46283 | AV10: =IFERROR(INDEX($AX$1:$AX$94,MATCH(9,$AY$1:$AY$94,0)),"") -> 251643289 | AW10: 811NV-132 | AX10: 252510301 | AY10: =IF(OR($A$5="Todos",AW10=$A$5),MAX(AY$1:AY9)+1,0) -> 10
A11: transferido do 2008 para o ZBR | C11: vendas e entregas | F11: entrou − saiu | H11: o que tem no depósito hoje | J11: =IF(OR(F5<>DATE(2026,9,9),H5<>DATE(2026,10,1)),"período parcial: compare com cuidado",IF(ABS(J10)<=$R$5,"tudo confere",IF(J10>0,"sobrando no estoque","faltando no estoque"))) -> sobrando no estoque | L11: ="Faltando: "&COUNTIFS($AA$40:$AA$133,1,$AC$40:$AC$133,"Faltando")&" SKU·lote" -> Faltando: 3 SKU·lote | AS11: 823-BR-D94 | AU11: 46284 | AV11: =IFERROR(INDEX($AX$1:$AX$94,MATCH(10,$AY$1:$AY$94,0)),"") -> 252510301 | AW11: 811NV-132 | AX11: 253280301 | AY11: =IF(OR($A$5="Todos",AW11=$A$5),MAX(AY$1:AY10)+1,0) -> 11
AS12: 823NV-132 | AU12: 46285 | AV12: =IFERROR(INDEX($AX$1:$AX$94,MATCH(11,$AY$1:$AY$94,0)),"") -> 253280301 | AW12: 811NV-595 | AX12: 260900702 | AY12: =IF(OR($A$5="Todos",AW12=$A$5),MAX(AY$1:AY11)+1,0) -> 12
A13: Movimentação por dia | G13: Maiores diferenças | AS13: 823NV-595 | AU13: 46286 | AV13: =IFERROR(INDEX($AX$1:$AX$94,MATCH(12,$AY$1:$AY$94,0)),"") -> 260900702 | AW13: 811NV-595 | AX13: 260920702 | AY13: =IF(OR($A$5="Todos",AW13=$A$5),MAX(AY$1:AY12)+1,0) -> 13
A14: Azul: entrou no ZBR · Laranja: saiu (abaixo de zero). Recebimentos no 2008 ficam fora. | G14: Por SKU · lote. Diferença = estoque físico − (entrou − saiu). Amarelo: sobrando · Vermelho: faltando. | AS14: BIG-PF-1BO-401 | AU14: 46287 | AV14: =IFERROR(INDEX($AX$1:$AX$94,MATCH(13,$AY$1:$AY$94,0)),"") -> 260920702 | AW14: 811NV-595 | AX14: 261146101 | AY14: =IF(OR($A$5="Todos",AW14=$A$5),MAX(AY$1:AY13)+1,0) -> 14
AS15: CHD-BB-308BY-357 | AU15: 46288 | AV15: =IFERROR(INDEX($AX$1:$AX$94,MATCH(14,$AY$1:$AY$94,0)),"") -> 261146101 | AW15: 811NV-595 | AX15: 261146102 | AY15: =IF(OR($A$5="Todos",AW15=$A$5),MAX(AY$1:AY14)+1,0) -> 15
AS16: CHD-DR-75Y5-E1-U68 | AU16: 46289 | AV16: =IFERROR(INDEX($AX$1:$AX$94,MATCH(15,$AY$1:$AY$94,0)),"") -> 261146102 | AW16: 823-BR-25A | AX16: 252100301 | AY16: =IF(OR($A$5="Todos",AW16=$A$5),MAX(AY$1:AY15)+1,0) -> 16
AS17: CHD-SP-1M-2B-U77 | AU17: 46290 | AV17: =IFERROR(INDEX($AX$1:$AX$94,MATCH(16,$AY$1:$AY$94,0)),"") -> 252100301 | AW17: 823-BR-25A | AX17: 252900303 | AY17: =IF(OR($A$5="Todos",AW17=$A$5),MAX(AY$1:AY16)+1,0) -> 17
AS18: CHD-SP-1M-BR-U73 | AU18: 46291 | AV18: =IFERROR(INDEX($AX$1:$AX$94,MATCH(17,$AY$1:$AY$94,0)),"") -> 252900303 | AW18: 823-BR-25A | AX18: 252940301 | AY18: =IF(OR($A$5="Todos",AW18=$A$5),MAX(AY$1:AY17)+1,0) -> 18
AS19: CHD-SP-9Z4-BR-U73 | AU19: 46292 | AV19: =IFERROR(INDEX($AX$1:$AX$94,MATCH(18,$AY$1:$AY$94,0)),"") -> 252940301 | AW19: 823-BR-D94 | AX19: 252103049 | AY19: =IF(OR($A$5="Todos",AW19=$A$5),MAX(AY$1:AY18)+1,0) -> 19
AS20: CHD-TS-22350E0-999 | AU20: 46293 | AV20: =IFERROR(INDEX($AX$1:$AX$94,MATCH(19,$AY$1:$AY$94,0)),"") -> 252103049 | AW20: 823NV-132 | AX20: 260880201 | AY20: =IF(OR($A$5="Todos",AW20=$A$5),MAX(AY$1:AY19)+1,0) -> 20
AS21: CHD-VR-Z2S-E0-U68 | AU21: 46294 | AV21: =IFERROR(INDEX($AX$1:$AX$94,MATCH(20,$AY$1:$AY$94,0)),"") -> 260880201 | AW21: 823NV-595 | AX21: 260416102 | AY21: =IF(OR($A$5="Todos",AW21=$A$5),MAX(AY$1:AY20)+1,0) -> 21
AS22: CHK-D-413 | AU22: 46295 | AV22: =IFERROR(INDEX($AX$1:$AX$94,MATCH(21,$AY$1:$AY$94,0)),"") -> 260416102 | AW22: 823NV-595 | AX22: 261376101 | AY22: =IF(OR($A$5="Todos",AW22=$A$5),MAX(AY$1:AY21)+1,0) -> 22
AS23: CHK-R30GOLD-BR-25A | AU23: 46296 | AV23: =IFERROR(INDEX($AX$1:$AX$94,MATCH(22,$AY$1:$AY$94,0)),"") -> 261376101 | AW23: BIG-PF-1BO-401 | AX23: 26044019 | AY23: =IF(OR($A$5="Todos",AW23=$A$5),MAX(AY$1:AY22)+1,0) -> 23
AS24: CHK-R30GOLD-E0-D94 | AV24: =IFERROR(INDEX($AX$1:$AX$94,MATCH(23,$AY$1:$AY$94,0)),"") -> 26044019 | AW24: BIG-PF-1BO-401 | AX24: 26093039 | AY24: =IF(OR($A$5="Todos",AW24=$A$5),MAX(AY$1:AY23)+1,0) -> 24
AS25: CHK-W-413 | AV25: =IFERROR(INDEX($AX$1:$AX$94,MATCH(24,$AY$1:$AY$94,0)),"") -> 26093039 | AW25: BIG-PF-1BO-401 | AX25: 26126039 | AY25: =IF(OR($A$5="Todos",AW25=$A$5),MAX(AY$1:AY24)+1,0) -> 25
AS26: CHM-BS-9U15-E0-07B | AV26: =IFERROR(INDEX($AX$1:$AX$94,MATCH(25,$AY$1:$AY$94,0)),"") -> 26126039 | AW26: CHD-BB-308BY-357 | AX26: 250827800 | AY26: =IF(OR($A$5="Todos",AW26=$A$5),MAX(AY$1:AY25)+1,0) -> 26
AS27: CHM-CU-7X80-E5-U70 | AV27: =IFERROR(INDEX($AX$1:$AX$94,MATCH(26,$AY$1:$AY$94,0)),"") -> 250827800 | AW27: CHD-BB-308BY-357 | AX27: 2529678000 | AY27: =IF(OR($A$5="Todos",AW27=$A$5),MAX(AY$1:AY26)+1,0) -> 27
AS28: CHM-Q41ALUN-2B-U73 | AV28: =IFERROR(INDEX($AX$1:$AX$94,MATCH(27,$AY$1:$AY$94,0)),"") -> 2529678000 | AW28: CHD-BB-308BY-357 | AX28: 2529778000 | AY28: =IF(OR($A$5="Todos",AW28=$A$5),MAX(AY$1:AY27)+1,0) -> 28
AS29: CHM-SP-Z3L-BR-U73 | AV29: =IFERROR(INDEX($AX$1:$AX$94,MATCH(28,$AY$1:$AY$94,0)),"") -> 2529778000 | AW29: CHD-BB-308BY-357 | AX29: 2609078000 | AY29: =IF(OR($A$5="Todos",AW29=$A$5),MAX(AY$1:AY28)+1,0) -> 29
AS30: CHM-SP-Z3L-E0-U72 | AV30: =IFERROR(INDEX($AX$1:$AX$94,MATCH(29,$AY$1:$AY$94,0)),"") -> 2609078000 | AW30: CHD-BB-308BY-357 | AX30: 2609178000 | AY30: =IF(OR($A$5="Todos",AW30=$A$5),MAX(AY$1:AY29)+1,0) -> 30
AS31: CHM-TS-22351E0-999 | AV31: =IFERROR(INDEX($AX$1:$AX$94,MATCH(30,$AY$1:$AY$94,0)),"") -> 2609178000 | AW31: CHD-BB-308BY-357 | AX31: 2611378000 | AY31: =IF(OR($A$5="Todos",AW31=$A$5),MAX(AY$1:AY30)+1,0) -> 31
A32: Cruzamento por SKU e lote | E32: =COUNT($AB$40:$AB$133)&" linhas no filtro atual" -> 81 linhas no filtro atual | AS32: CHM-TS-P23-E0-999 | AV32: =IFERROR(INDEX($AX$1:$AX$94,MATCH(31,$AY$1:$AY$94,0)),"") -> 2611378000 | AW32: CHD-DR-75Y5-E1-U68 | AX32: 252810301 | AY32: =IF(OR($A$5="Todos",AW32=$A$5),MAX(AY$1:AY31)+1,0) -> 32
A33: SKU | B33: LOTE | C33: UM | D33: RECEBIDO 2008 | E33: ENTROU | F33: SAIU | G33: DEVERIA TER | H33: ESTOQUE FÍSICO | I33: DIFERENÇA | J33: SITUAÇÃO | K33: LANÇAMENTOS | L33: DESCRIÇÃO | AS33: CHM-VR-Z3S-E0-U68 | AV33: =IFERROR(INDEX($AX$1:$AX$94,MATCH(32,$AY$1:$AY$94,0)),"") -> 252810301 | AW33: CHD-SP-1M-2B-U77 | AX33: 260880101 | AY33: =IF(OR($A$5="Todos",AW33=$A$5),MAX(AY$1:AY32)+1,0) -> 33
A34: =IF(IFERROR(MATCH(1,$AB$40:$AB$133,0),0)=0,"",INDEX($T$40:$T$133,IFERROR(MATCH(1,$AB$40:$AB$133,0),0))) -> CHK-R30GOLD-BR-25A | B34: =IF(IFERROR(MATCH(1,$AB$40:$AB$133,0),0)=0,"",INDEX($AG$40:$AG$133,IFERROR(MATCH(1,$AB$40:$AB$133,0),0))) -> 261130301 | C34: =IF(IFERROR(MATCH(1,$AB$40:$AB$133,0),0)=0,"",INDEX($U$40:$U$133,IFERROR(MATCH(1,$AB$40:$AB$133,0),0))) -> KG | D34: =IF(IFERROR(MATCH(1,$AB$40:$AB$133,0),0)=0,"",INDEX($V$40:$V$133,IFERROR(MATCH(1,$AB$40:$AB$133,0),0))) -> 1025.1 | E34: =IF(IFERROR(MATCH(1,$AB$40:$AB$133,0),0)=0,"",INDEX($W$40:$W$133,IFERROR(MATCH(1,$AB$40:$AB$133,0),0))) -> 2673.3 | F34: =IF(IFERROR(MATCH(1,$AB$40:$AB$133,0),0)=0,"",INDEX($X$40:$X$133,IFERROR(MATCH(1,$AB$40:$AB$133,0),0))) -> 1005 | G34: =IF(A34="","",E34-F34) -> 1668.3 | H34: =IF(IFERROR(MATCH(1,$AB$40:$AB$133,0),0)=0,"",INDEX($Y$40:$Y$133,IFERROR(MATCH(1,$AB$40:$AB$133,0),0))) -> 1226.1 | I34: =IF(IFERROR(MATCH(1,$AB$40:$AB$133,0),0)=0,"",INDEX($Z$40:$Z$133,IFERROR(MATCH(1,$AB$40:$AB$133,0),0))) -> -442.2 | J34: =IF(IFERROR(MATCH(1,$AB$40:$AB$133,0),0)=0,"",INDEX($AC$40:$AC$133,IFERROR(MATCH(1,$AB$40:$AB$133,0),0))) -> Faltando | K34: =IF(IFERROR(MATCH(1,$AB$40:$AB$133,0),0)=0,"",INDEX($AD$40:$AD$133,IFERROR(MATCH(1,$AB$40:$AB$133,0),0))) -> 17 | L34: =IF(IFERROR(MATCH(1,$AB$40:$AB$133,0),0)=0,"",INDEX($AE$40:$AE$133,IFERROR(MATCH(1,$AB$40:$AB$133,0),0))&"") -> CA MOEDAS 2,01KG/UC 10UC/CX 30CX/PAL | AS34: CHM-VR-Z3S-E0-U72 | AV34: =IFERROR(INDEX($AX$1:$AX$94,MATCH(33,$AY$1:$AY$94,0)),"") -> 260880101 | AW34: CHD-SP-1M-BR-U73 | AX34: 260310301 | AY34: =IF(OR($A$5="Todos",AW34=$A$5),MAX(AY$1:AY33)+1,0) -> 34
A35: =IF(IFERROR(MATCH(2,$AB$40:$AB$133,0),0)=0,"",INDEX($T$40:$T$133,IFERROR(MATCH(2,$AB$40:$AB$133,0),0))) -> CHM-TS-P23-E0-999 | B35: =IF(IFERROR(MATCH(2,$AB$40:$AB$133,0),0)=0,"",INDEX($AG$40:$AG$133,IFERROR(MATCH(2,$AB$40:$AB$133,0),0))) -> 2605567696 | C35: =IF(IFERROR(MATCH(2,$AB$40:$AB$133,0),0)=0,"",INDEX($U$40:$U$133,IFERROR(MATCH(2,$AB$40:$AB$133,0),0))) -> KG | D35: =IF(IFERROR(MATCH(2,$AB$40:$AB$133,0),0)=0,"",INDEX($V$40:$V$133,IFERROR(MATCH(2,$AB$40:$AB$133,0),0))) -> 0 | E35: =IF(IFERROR(MATCH(2,$AB$40:$AB$133,0),0)=0,"",INDEX($W$40:$W$133,IFERROR(MATCH(2,$AB$40:$AB$133,0),0))) -> 261.12 | F35: =IF(IFERROR(MATCH(2,$AB$40:$AB$133,0),0)=0,"",INDEX($X$40:$X$133,IFERROR(MATCH(2,$AB$40:$AB$133,0),0))) -> 0 | G35: =IF(A35="","",E35-F35) -> 261.12 | H35: =IF(IFERROR(MATCH(2,$AB$40:$AB$133,0),0)=0,"",INDEX($Y$40:$Y$133,IFERROR(MATCH(2,$AB$40:$AB$133,0),0))) -> 0 | I35: =IF(IFERROR(MATCH(2,$AB$40:$AB$133,0),0)=0,"",INDEX($Z$40:$Z$133,IFERROR(MATCH(2,$AB$40:$AB$133,0),0))) -> -261.12 | J35: =IF(IFERROR(MATCH(2,$AB$40:$AB$133,0),0)=0,"",INDEX($AC$40:$AC$133,IFERROR(MATCH(2,$AB$40:$AB$133,0),0))) -> Faltando | K35: =IF(IFERROR(MATCH(2,$AB$40:$AB$133,0),0)=0,"",INDEX($AD$40:$AD$133,IFERROR(MATCH(2,$AB$40:$AB$133,0),0))) -> 1 | L35: =IF(IFERROR(MATCH(2,$AB$40:$AB$133,0),0)=0,"",INDEX($AE$40:$AE$133,IFERROR(MATCH(2,$AB$40:$AB$133,0),0))&"") | AS35: CHP-20SICHP-760 | AV35: =IFERROR(INDEX($AX$1:$AX$94,MATCH(34,$AY$1:$AY$94,0)),"") -> 260310301 | AW35: CHD-SP-1M-BR-U73 | AX35: 260880301 | AY35: =IF(OR($A$5="Todos",AW35=$A$5),MAX(AY$1:AY34)+1,0) -> 35
A36: =IF(IFERROR(MATCH(3,$AB$40:$AB$133,0),0)=0,"",INDEX($T$40:$T$133,IFERROR(MATCH(3,$AB$40:$AB$133,0),0))) -> BIG-PF-1BO-401 | B36: =IF(IFERROR(MATCH(3,$AB$40:$AB$133,0),0)=0,"",INDEX($AG$40:$AG$133,IFERROR(MATCH(3,$AB$40:$AB$133,0),0))) -> 26044019 | C36: =IF(IFERROR(MATCH(3,$AB$40:$AB$133,0),0)=0,"",INDEX($U$40:$U$133,IFERROR(MATCH(3,$AB$40:$AB$133,0),0))) -> KG | D36: =IF(IFERROR(MATCH(3,$AB$40:$AB$133,0),0)=0,"",INDEX($V$40:$V$133,IFERROR(MATCH(3,$AB$40:$AB$133,0),0))) -> 0 | E36: =IF(IFERROR(MATCH(3,$AB$40:$AB$133,0),0)=0,"",INDEX($W$40:$W$133,IFERROR(MATCH(3,$AB$40:$AB$133,0),0))) -> 480 | F36: =IF(IFERROR(MATCH(3,$AB$40:$AB$133,0),0)=0,"",INDEX($X$40:$X$133,IFERROR(MATCH(3,$AB$40:$AB$133,0),0))) -> 60 | G36: =IF(A36="","",E36-F36) -> 420 | H36: =IF(IFERROR(MATCH(3,$AB$40:$AB$133,0),0)=0,"",INDEX($Y$40:$Y$133,IFERROR(MATCH(3,$AB$40:$AB$133,0),0))) -> 210 | I36: =IF(IFERROR(MATCH(3,$AB$40:$AB$133,0),0)=0,"",INDEX($Z$40:$Z$133,IFERROR(MATCH(3,$AB$40:$AB$133,0),0))) -> -210 | J36: =IF(IFERROR(MATCH(3,$AB$40:$AB$133,0),0)=0,"",INDEX($AC$40:$AC$133,IFERROR(MATCH(3,$AB$40:$AB$133,0),0))) -> Faltando | K36: =IF(IFERROR(MATCH(3,$AB$40:$AB$133,0),0)=0,"",INDEX($AD$40:$AD$133,IFERROR(MATCH(3,$AB$40:$AB$133,0),0))) -> 5 | L36: =IF(IFERROR(MATCH(3,$AB$40:$AB$133,0),0)=0,"",INDEX($AE$40:$AE$133,IFERROR(MATCH(3,$AB$40:$AB$133,0),0))&"") -> CB PAILLETÉ FEUILLETINE 2.5KG/UC 4UC/BOX | AS36: CHR-Q37RB2-2B-U75 | AV36: =IFERROR(INDEX($AX$1:$AX$94,MATCH(35,$AY$1:$AY$94,0)),"") -> 260880301 | AW36: CHD-SP-9Z4-BR-U73 | AX36: 250500301 | AY36: =IF(OR($A$5="Todos",AW36=$A$5),MAX(AY$1:AY35)+1,0) -> 36
A37: =IF(IFERROR(MATCH(4,$AB$40:$AB$133,0),0)=0,"",INDEX($T$40:$T$133,IFERROR(MATCH(4,$AB$40:$AB$133,0),0))) -> 811-BR-D94 | B37: =IF(IFERROR(MATCH(4,$AB$40:$AB$133,0),0)=0,"",INDEX($AG$40:$AG$133,IFERROR(MATCH(4,$AB$40:$AB$133,0),0))) -> 251643289 | C37: =IF(IFERROR(MATCH(4,$AB$40:$AB$133,0),0)=0,"",INDEX($U$40:$U$133,IFERROR(MATCH(4,$AB$40:$AB$133,0),0))) -> KG | D37: =IF(IFERROR(MATCH(4,$AB$40:$AB$133,0),0)=0,"",INDEX($V$40:$V$133,IFERROR(MATCH(4,$AB$40:$AB$133,0),0))) -> 0 | E37: =IF(IFERROR(MATCH(4,$AB$40:$AB$133,0),0)=0,"",INDEX($W$40:$W$133,IFERROR(MATCH(4,$AB$40:$AB$133,0),0))) -> 2.8 | F37: =IF(IFERROR(MATCH(4,$AB$40:$AB$133,0),0)=0,"",INDEX($X$40:$X$133,IFERROR(MATCH(4,$AB$40:$AB$133,0),0))) -> 226.8 | G37: =IF(A37="","",E37-F37) -> -224 | H37: =IF(IFERROR(MATCH(4,$AB$40:$AB$133,0),0)=0,"",INDEX($Y$40:$Y$133,IFERROR(MATCH(4,$AB$40:$AB$133,0),0))) -> 5513.2 | I37: =IF(IFERROR(MATCH(4,$AB$40:$AB$133,0),0)=0,"",INDEX($Z$40:$Z$133,IFERROR(MATCH(4,$AB$40:$AB$133,0),0))) -> 5737.2 | J37: =IF(IFERROR(MATCH(4,$AB$40:$AB$133,0),0)=0,"",INDEX($AC$40:$AC$133,IFERROR(MATCH(4,$AB$40:$AB$133,0),0))) -> Sobrando | K37: =IF(IFERROR(MATCH(4,$AB$40:$AB$133,0),0)=0,"",INDEX($AD$40:$AD$133,IFERROR(MATCH(4,$AB$40:$AB$133,0),0))) -> 17 | L37: =IF(IFERROR(MATCH(4,$AB$40:$AB$133,0),0)=0,"",INDEX($AE$40:$AE$133,IFERROR(MATCH(4,$AB$40:$AB$133,0),0))&"") -> CA MOEDAS 0,4KG/UC 7UC/CX 144CX/PAL | AS37: CHR-Q37RB2-E0-D94 | AV37: =IFERROR(INDEX($AX$1:$AX$94,MATCH(36,$AY$1:$AY$94,0)),"") -> 250500301 | AW37: CHD-TS-22350E0-999 | AX37: 2520443650 | AY37: =IF(OR($A$5="Todos",AW37=$A$5),MAX(AY$1:AY36)+1,0) -> 37
A38: =IF(IFERROR(MATCH(5,$AB$40:$AB$133,0),0)=0,"",INDEX($T$40:$T$133,IFERROR(MATCH(5,$AB$40:$AB$133,0),0))) -> CHM-SP-Z3L-BR-U73 | B38: =IF(IFERROR(MATCH(5,$AB$40:$AB$133,0),0)=0,"",INDEX($AG$40:$AG$133,IFERROR(MATCH(5,$AB$40:$AB$133,0),0))) -> 251880301 | C38: =IF(IFERROR(MATCH(5,$AB$40:$AB$133,0),0)=0,"",INDEX($U$40:$U$133,IFERROR(MATCH(5,$AB$40:$AB$133,0),0))) -> KG | D38: =IF(IFERROR(MATCH(5,$AB$40:$AB$133,0),0)=0,"",INDEX($V$40:$V$133,IFERROR(MATCH(5,$AB$40:$AB$133,0),0))) -> 0 | E38: =IF(IFERROR(MATCH(5,$AB$40:$AB$133,0),0)=0,"",INDEX($W$40:$W$133,IFERROR(MATCH(5,$AB$40:$AB$133,0),0))) -> 966 | F38: =IF(IFERROR(MATCH(5,$AB$40:$AB$133,0),0)=0,"",INDEX($X$40:$X$133,IFERROR(MATCH(5,$AB$40:$AB$133,0),0))) -> 906 | G38: =IF(A38="","",E38-F38) -> 60 | H38: =IF(IFERROR(MATCH(5,$AB$40:$AB$133,0),0)=0,"",INDEX($Y$40:$Y$133,IFERROR(MATCH(5,$AB$40:$AB$133,0),0))) -> 3754.998 | I38: =IF(IFERROR(MATCH(5,$AB$40:$AB$133,0),0)=0,"",INDEX($Z$40:$Z$133,IFERROR(MATCH(5,$AB$40:$AB$133,0),0))) -> 3694.998 | J38: =IF(IFERROR(MATCH(5,$AB$40:$AB$133,0),0)=0,"",INDEX($AC$40:$AC$133,IFERROR(MATCH(5,$AB$40:$AB$133,0),0))) -> Sobrando | K38: =IF(IFERROR(MATCH(5,$AB$40:$AB$133,0),0)=0,"",INDEX($AD$40:$AD$133,IFERROR(MATCH(5,$AB$40:$AB$133,0),0))) -> 30 | L38: =IF(IFERROR(MATCH(5,$AB$40:$AB$133,0),0)=0,"",INDEX($AE$40:$AE$133,IFERROR(MATCH(5,$AB$40:$AB$133,0),0))&"") -> CA MILK LARGE FLAKES SPLITTERS 1KG/UC | AS38: CW2-BR-25A | AV38: =IFERROR(INDEX($AX$1:$AX$94,MATCH(37,$AY$1:$AY$94,0)),"") -> 2520443650 | AW38: CHD-VR-Z2S-E0-U68 | AX38: 261160301 | AY38: =IF(OR($A$5="Todos",AW38=$A$5),MAX(AY$1:AY37)+1,0) -> 38
A39: =IF(IFERROR(MATCH(6,$AB$40:$AB$133,0),0)=0,"",INDEX($T$40:$T$133,IFERROR(MATCH(6,$AB$40:$AB$133,0),0))) -> CHD-SP-9Z4-BR-U73 | B39: =IF(IFERROR(MATCH(6,$AB$40:$AB$133,0),0)=0,"",INDEX($AG$40:$AG$133,IFERROR(MATCH(6,$AB$40:$AB$133,0),0))) -> 250500301 | C39: =IF(IFERROR(MATCH(6,$AB$40:$AB$133,0),0)=0,"",INDEX($U$40:$U$133,IFERROR(MATCH(6,$AB$40:$AB$133,0),0))) -> KG | D39: =IF(IFERROR(MATCH(6,$AB$40:$AB$133,0),0)=0,"",INDEX($V$40:$V$133,IFERROR(MATCH(6,$AB$40:$AB$133,0),0))) -> 0 | E39: =IF(IFERROR(MATCH(6,$AB$40:$AB$133,0),0)=0,"",INDEX($W$40:$W$133,IFERROR(MATCH(6,$AB$40:$AB$133,0),0))) -> 240 | F39: =IF(IFERROR(MATCH(6,$AB$40:$AB$133,0),0)=0,"",INDEX($X$40:$X$133,IFERROR(MATCH(6,$AB$40:$AB$133,0),0))) -> 6 | G39: =IF(A39="","",E39-F39) -> 234 | H39: =IF(IFERROR(MATCH(6,$AB$40:$AB$133,0),0)=0,"",INDEX($Y$40:$Y$133,IFERROR(MATCH(6,$AB$40:$AB$133,0),0))) -> 3432 | I39: =IF(IFERROR(MATCH(6,$AB$40:$AB$133,0),0)=0,"",INDEX($Z$40:$Z$133,IFERROR(MATCH(6,$AB$40:$AB$133,0),0))) -> 3198 | J39: =IF(IFERROR(MATCH(6,$AB$40:$AB$133,0),0)=0,"",INDEX($AC$40:$AC$133,IFERROR(MATCH(6,$AB$40:$AB$133,0),0))) -> Sobrando | K39: =IF(IFERROR(MATCH(6,$AB$40:$AB$133,0),0)=0,"",INDEX($AD$40:$AD$133,IFERROR(MATCH(6,$AB$40:$AB$133,0),0))) -> 2 | L39: =IF(IFERROR(MATCH(6,$AB$40:$AB$133,0),0)=0,"",INDEX($AE$40:$AE$133,IFERROR(MATCH(6,$AB$40:$AB$133,0),0))&"") -> 96_FU:CHD-SP-1L-BR-U73 | AJ39: Produto | AK39: Sobrando | AL39: Faltando | AP39: Entrou no ZBR | AQ39: Saiu | AS39: CW2NV-595 | AV39: =IFERROR(INDEX($AX$1:$AX$94,MATCH(38,$AY$1:$AY$94,0)),"") -> 261160301 | AW39: CHK-D-413 | AX39: 261756201 | AY39: =IF(OR($A$5="Todos",AW39=$A$5),MAX(AY$1:AY38)+1,0) -> 39
A40: =IF(IFERROR(MATCH(7,$AB$40:$AB$133,0),0)=0,"",INDEX($T$40:$T$133,IFERROR(MATCH(7,$AB$40:$AB$133,0),0))) -> 823-BR-D94 | B40: =IF(IFERROR(MATCH(7,$AB$40:$AB$133,0),0)=0,"",INDEX($AG$40:$AG$133,IFERROR(MATCH(7,$AB$40:$AB$133,0),0))) -> 252103049 | C40: =IF(IFERROR(MATCH(7,$AB$40:$AB$133,0),0)=0,"",INDEX($U$40:$U$133,IFERROR(MATCH(7,$AB$40:$AB$133,0),0))) -> KG | D40: =IF(IFERROR(MATCH(7,$AB$40:$AB$133,0),0)=0,"",INDEX($V$40:$V$133,IFERROR(MATCH(7,$AB$40:$AB$133,0),0))) -> 0 | E40: =IF(IFERROR(MATCH(7,$AB$40:$AB$133,0),0)=0,"",INDEX($W$40:$W$133,IFERROR(MATCH(7,$AB$40:$AB$133,0),0))) -> 2.8 | F40: =IF(IFERROR(MATCH(7,$AB$40:$AB$133,0),0)=0,"",INDEX($X$40:$X$133,IFERROR(MATCH(7,$AB$40:$AB$133,0),0))) -> 677.6 | G40: =IF(A40="","",E40-F40) -> -674.8 | H40: =IF(IFERROR(MATCH(7,$AB$40:$AB$133,0),0)=0,"",INDEX($Y$40:$Y$133,IFERROR(MATCH(7,$AB$40:$AB$133,0),0))) -> 1853.6 | I40: =IF(IFERROR(MATCH(7,$AB$40:$AB$133,0),0)=0,"",INDEX($Z$40:$Z$133,IFERROR(MATCH(7,$AB$40:$AB$133,0),0))) -> 2528.4 | J40: =IF(IFERROR(MATCH(7,$AB$40:$AB$133,0),0)=0,"",INDEX($AC$40:$AC$133,IFERROR(MATCH(7,$AB$40:$AB$133,0),0))) -> Sobrando | K40: =IF(IFERROR(MATCH(7,$AB$40:$AB$133,0),0)=0,"",INDEX($AD$40:$AD$133,IFERROR(MATCH(7,$AB$40:$AB$133,0),0))) -> 53 | L40: =IF(IFERROR(MATCH(7,$AB$40:$AB$133,0),0)=0,"",INDEX($AE$40:$AE$133,IFERROR(MATCH(7,$AB$40:$AB$133,0),0))&"") -> CA MOEDAS 0,4KG/UC 7UC/CX 144CX/PAL | T40: CHK-R30GOLD-BR-25A | U40: KG | V40: =SUMIFS(Lançamentos!$H$2:$H$607,Lançamentos!$A$2:$A$607,">="&$F$5,Lançamentos!$A$2:$A$607,"<="&$H$5,Lançamentos!$C$2:$C$607,$T40,Lançamentos!$D$2:$D$607,$AG40,Lançamentos!$B$2:$B$607,"Recebido no 2008") -> 1025.1 | W40: =SUMIFS(Lançamentos!$I$2:$I$607,Lançamentos!$A$2:$A$607,">="&$F$5,Lançamentos!$A$2:$A$607,"<="&$H$5,Lançamentos!$C$2:$C$607,$T40,Lançamentos!$D$2:$D$607,$AG40) -> 2673.3 | X40: =SUMIFS(Lançamentos!$J$2:$J$607,Lançamentos!$A$2:$A$607,">="&$F$5,Lançamentos!$A$2:$A$607,"<="&$H$5,Lançamentos!$C$2:$C$607,$T40,Lançamentos!$D$2:$D$607,$AG40) -> 1005 | Y40: =SUMIFS('Estoque físico'!$J$2:$J$229,'Estoque físico'!$A$2:$A$229,$T40,'Estoque físico'!$B$2:$B$229,$AG40) -> 1226.1 | Z40: =ROUND(Y40-(W40-X40),3) -> -442.2 | AA40: =IF(AND(U40=$R$3,OR($R$1="*",T40=$R$1),OR($R$2="*",AG40=$R$2),ABS(V40)+ABS(W40)+ABS(X40)+ABS(Y40)>0),1,0) -> 1 | AB40: =IF(AA40=1,SUM(AA$40:AA40),"") -> 1 | AC40: =IF(ABS(Z40)<=$R$5,"Confere",IF(Z40>0,"Sobrando","Faltando")) -> Faltando | AD40: =COUNTIFS(Lançamentos!$A$2:$A$607,">="&$F$5,Lançamentos!$A$2:$A$607,"<="&$H$5,Lançamentos!$C$2:$C$607,$T40,Lançamentos!$D$2:$D$607,$AG40,Lançamentos!$B$2:$B$607,$R$4,Lançamentos!$G$2:$G$607,U40) -> 17 | AE40: CA MOEDAS 2,01KG/UC 10UC/CX 30CX/PAL | AF40: =IF(AND(AA40=1,AC40<>"Confere"),ABS(Z40)+ROW()/10000000,0) -> 442.2 | AG40: 261130301 | AH40: =LARGE($AF$40:$AF$133,1) -> 5737.2 | AI40: =IF(AH40>0,MATCH(AH40,$AF$40:$AF$133,0),"") -> 6 | AJ40: =IF(AI40="","",INDEX($T$40:$T$133,AI40)&" · "&INDEX($AG$40:$AG$133,AI40)) -> 811-BR-D94 · 251643289 | AK40: =IF(AI40="",0,MAX(INDEX($Z$40:$Z$133,AI40),0)) -> 5737.2 | AL40: =IF(AI40="",0,MIN(INDEX($Z$40:$Z$133,AI40),0)) -> 0 | AN40: 09/09 | AO40: 46274 | AP40: =IF(AND(AO40>=$F$5,AO40<=$H$5),SUMIFS(Lançamentos!$I$2:$I$607,Lançamentos!$A$2:$A$607,$AO40,Lançamentos!$C$2:$C$607,$R$1,Lançamentos!$D$2:$D$607,$R$2,Lançamentos!$G$2:$G$607,$R$3,Lançamentos!$B$2:$B$607,$R$4),0) -> 490.96 | AQ40: =IF(AND(AO40>=$F$5,AO40<=$H$5),-SUMIFS(Lançamentos!$J$2:$J$607,Lançamentos!$A$2:$A$607,$AO40,Lançamentos!$C$2:$C$607,$R$1,Lançamentos!$D$2:$D$607,$R$2,Lançamentos!$G$2:$G$607,$R$3,Lançamentos!$B$2:$B$607,$R$4),0) -> -11.2 | AS40: DCP-10BONOI-89B | AV40: =IFERROR(INDEX($AX$1:$AX$94,MATCH(39,$AY$1:$AY$94,0)),"") -> 261756201 | AW40: CHK-R30GOLD-BR-25A | AX40: 252750301 | AY40: =IF(OR($A$5="Todos",AW40=$A$5),MAX(AY$1:AY39)+1,0) -> 40
A41: =IF(IFERROR(MATCH(8,$AB$40:$AB$133,0),0)=0,"",INDEX($T$40:$T$133,IFERROR(MATCH(8,$AB$40:$AB$133,0),0))) -> 805-BR-D94 | B41: =IF(IFERROR(MATCH(8,$AB$40:$AB$133,0),0)=0,"",INDEX($AG$40:$AG$133,IFERROR(MATCH(8,$AB$40:$AB$133,0),0))) -> 251633359 | C41: =IF(IFERROR(MATCH(8,$AB$40:$AB$133,0),0)=0,"",INDEX($U$40:$U$133,IFERROR(MATCH(8,$AB$40:$AB$133,0),0))) -> KG | D41: =IF(IFERROR(MATCH(8,$AB$40:$AB$133,0),0)=0,"",INDEX($V$40:$V$133,IFERROR(MATCH(8,$AB$40:$AB$133,0),0))) -> 0 | E41: =IF(IFERROR(MATCH(8,$AB$40:$AB$133,0),0)=0,"",INDEX($W$40:$W$133,IFERROR(MATCH(8,$AB$40:$AB$133,0),0))) -> 313.6 | F41: =IF(IFERROR(MATCH(8,$AB$40:$AB$133,0),0)=0,"",INDEX($X$40:$X$133,IFERROR(MATCH(8,$AB$40:$AB$133,0),0))) -> 221.2 | G41: =IF(A41="","",E41-F41) -> 92.4 | H41: =IF(IFERROR(MATCH(8,$AB$40:$AB$133,0),0)=0,"",INDEX($Y$40:$Y$133,IFERROR(MATCH(8,$AB$40:$AB$133,0),0))) -> 1360.8 | I41: =IF(IFERROR(MATCH(8,$AB$40:$AB$133,0),0)=0,"",INDEX($Z$40:$Z$133,IFERROR(MATCH(8,$AB$40:$AB$133,0),0))) -> 1268.4 | J41: =IF(IFERROR(MATCH(8,$AB$40:$AB$133,0),0)=0,"",INDEX($AC$40:$AC$133,IFERROR(MATCH(8,$AB$40:$AB$133,0),0))) -> Sobrando | K41: =IF(IFERROR(MATCH(8,$AB$40:$AB$133,0),0)=0,"",INDEX($AD$40:$AD$133,IFERROR(MATCH(8,$AB$40:$AB$133,0),0))) -> 26 | L41: =IF(IFERROR(MATCH(8,$AB$40:$AB$133,0),0)=0,"",INDEX($AE$40:$AE$133,IFERROR(MATCH(8,$AB$40:$AB$133,0),0))&"") -> CA MOEDAS 0,4KG/UC 7UC/CX 144CX/PAL | T41: CHM-TS-P23-E0-999 | U41: KG | V41: =SUMIFS(Lançamentos!$H$2:$H$607,Lançamentos!$A$2:$A$607,">="&$F$5,Lançamentos!$A$2:$A$607,"<="&$H$5,Lançamentos!$C$2:$C$607,$T41,Lançamentos!$D$2:$D$607,$AG41,Lançamentos!$B$2:$B$607,"Recebido no 2008") -> 0 | W41: =SUMIFS(Lançamentos!$I$2:$I$607,Lançamentos!$A$2:$A$607,">="&$F$5,Lançamentos!$A$2:$A$607,"<="&$H$5,Lançamentos!$C$2:$C$607,$T41,Lançamentos!$D$2:$D$607,$AG41) -> 261.12 | X41: =SUMIFS(Lançamentos!$J$2:$J$607,Lançamentos!$A$2:$A$607,">="&$F$5,Lançamentos!$A$2:$A$607,"<="&$H$5,Lançamentos!$C$2:$C$607,$T41,Lançamentos!$D$2:$D$607,$AG41) -> 0 | Y41: =SUMIFS('Estoque físico'!$J$2:$J$229,'Estoque físico'!$A$2:$A$229,$T41,'Estoque físico'!$B$2:$B$229,$AG41) -> 0 | Z41: =ROUND(Y41-(W41-X41),3) -> -261.12 | AA41: =IF(AND(U41=$R$3,OR($R$1="*",T41=$R$1),OR($R$2="*",AG41=$R$2),ABS(V41)+ABS(W41)+ABS(X41)+ABS(Y41)>0),1,0) -> 1 | AB41: =IF(AA41=1,SUM(AA$40:AA41),"") -> 2 | AC41: =IF(ABS(Z41)<=$R$5,"Confere",IF(Z41>0,"Sobrando","Faltando")) -> Faltando | AD41: =COUNTIFS(Lançamentos!$A$2:$A$607,">="&$F$5,Lançamentos!$A$2:$A$607,"<="&$H$5,Lançamentos!$C$2:$C$607,$T41,Lançamentos!$D$2:$D$607,$AG41,Lançamentos!$B$2:$B$607,$R$4,Lançamentos!$G$2:$G$607,U41) -> 1 | AF41: =IF(AND(AA41=1,AC41<>"Confere"),ABS(Z41)+ROW()/10000000,0) -> 261.12 | AG41: 2605567696 | AH41: =LARGE($AF$40:$AF$133,2) -> 3694.998 | AI41: =IF(AH41>0,MATCH(AH41,$AF$40:$AF$133,0),"") -> 7 | AJ41: =IF(AI41="","",INDEX($T$40:$T$133,AI41)&" · "&INDEX($AG$40:$AG$133,AI41)) -> CHM-SP-Z3L-BR-U73 · 251880301 | AK41: =IF(AI41="",0,MAX(INDEX($Z$40:$Z$133,AI41),0)) -> 3694.998 | AL41: =IF(AI41="",0,MIN(INDEX($Z$40:$Z$133,AI41),0)) -> 0 | AN41: 10/09 | AO41: 46275 | AP41: =IF(AND(AO41>=$F$5,AO41<=$H$5),SUMIFS(Lançamentos!$I$2:$I$607,Lançamentos!$A$2:$A$607,$AO41,Lançamentos!$C$2:$C$607,$R$1,Lançamentos!$D$2:$D$607,$R$2,Lançamentos!$G$2:$G$607,$R$3,Lançamentos!$B$2:$B$607,$R$4),0) -> 0 | AQ41: =IF(AND(AO41>=$F$5,AO41<=$H$5),-SUMIFS(Lançamentos!$J$2:$J$607,Lançamentos!$A$2:$A$607,$AO41,Lançamentos!$C$2:$C$607,$R$1,Lançamentos!$D$2:$D$607,$R$2,Lançamentos!$G$2:$G$607,$R$3,Lançamentos!$B$2:$B$607,$R$4),0) -> -559.4 | AS41: DCP-20BODEC-89B | AV41: =IFERROR(INDEX($AX$1:$AX$94,MATCH(40,$AY$1:$AY$94,0)),"") -> 252750301 | AW41: CHK-R30GOLD-BR-25A | AX41: 253620301 | AY41: =IF(OR($A$5="Todos",AW41=$A$5),MAX(AY$1:AY40)+1,0) -> 41
A42: =IF(IFERROR(MATCH(9,$AB$40:$AB$133,0),0)=0,"",INDEX($T$40:$T$133,IFERROR(MATCH(9,$AB$40:$AB$133,0),0))) -> W3-BR-25A | B42: =IF(IFERROR(MATCH(9,$AB$40:$AB$133,0),0)=0,"",INDEX($AG$40:$AG$133,IFERROR(MATCH(9,$AB$40:$AB$133,0),0))) -> 253540301 | C42: =IF(IFERROR(MATCH(9,$AB$40:$AB$133,0),0)=0,"",INDEX($U$40:$U$133,IFERROR(MATCH(9,$AB$40:$AB$133,0),0))) -> KG | D42: =IF(IFERROR(MATCH(9,$AB$40:$AB$133,0),0)=0,"",INDEX($V$40:$V$133,IFERROR(MATCH(9,$AB$40:$AB$133,0),0))) -> 20 | E42: =IF(IFERROR(MATCH(9,$AB$40:$AB$133,0),0)=0,"",INDEX($W$40:$W$133,IFERROR(MATCH(9,$AB$40:$AB$133,0),0))) -> 0 | F42: =IF(IFERROR(MATCH(9,$AB$40:$AB$133,0),0)=0,"",INDEX($X$40:$X$133,IFERROR(MATCH(9,$AB$40:$AB$133,0),0))) -> 542.7 | G42: =IF(A42="","",E42-F42) -> -542.7 | H42: =IF(IFERROR(MATCH(9,$AB$40:$AB$133,0),0)=0,"",INDEX($Y$40:$Y$133,IFERROR(MATCH(9,$AB$40:$AB$133,0),0))) -> 540.69 | I42: =IF(IFERROR(MATCH(9,$AB$40:$AB$133,0),0)=0,"",INDEX($Z$40:$Z$133,IFERROR(MATCH(9,$AB$40:$AB$133,0),0))) -> 1083.39 | J42: =IF(IFERROR(MATCH(9,$AB$40:$AB$133,0),0)=0,"",INDEX($AC$40:$AC$133,IFERROR(MATCH(9,$AB$40:$AB$133,0),0))) -> Sobrando | K42: =IF(IFERROR(MATCH(9,$AB$40:$AB$133,0),0)=0,"",INDEX($AD$40:$AD$133,IFERROR(MATCH(9,$AB$40:$AB$133,0),0))) -> 15 | L42: =IF(IFERROR(MATCH(9,$AB$40:$AB$133,0),0)=0,"",INDEX($AE$40:$AE$133,IFERROR(MATCH(9,$AB$40:$AB$133,0),0))&"") -> CA MOEDAS 2,01KG/UC 10UC/CX 30CX/PAL | T42: BIG-PF-1BO-401 | U42: KG | V42: =SUMIFS(Lançamentos!$H$2:$H$607,Lançamentos!$A$2:$A$607,">="&$F$5,Lançamentos!$A$2:$A$607,"<="&$H$5,Lançamentos!$C$2:$C$607,$T42,Lançamentos!$D$2:$D$607,$AG42,Lançamentos!$B$2:$B$607,"Recebido no 2008") -> 0 | W42: =SUMIFS(Lançamentos!$I$2:$I$607,Lançamentos!$A$2:$A$607,">="&$F$5,Lançamentos!$A$2:$A$607,"<="&$H$5,Lançamentos!$C$2:$C$607,$T42,Lançamentos!$D$2:$D$607,$AG42) -> 480 | X42: =SUMIFS(Lançamentos!$J$2:$J$607,Lançamentos!$A$2:$A$607,">="&$F$5,Lançamentos!$A$2:$A$607,"<="&$H$5,Lançamentos!$C$2:$C$607,$T42,Lançamentos!$D$2:$D$607,$AG42) -> 60 | Y42: =SUMIFS('Estoque físico'!$J$2:$J$229,'Estoque físico'!$A$2:$A$229,$T42,'Estoque físico'!$B$2:$B$229,$AG42) -> 210 | Z42: =ROUND(Y42-(W42-X42),3) -> -210 | AA42: =IF(AND(U42=$R$3,OR($R$1="*",T42=$R$1),OR($R$2="*",AG42=$R$2),ABS(V42)+ABS(W42)+ABS(X42)+ABS(Y42)>0),1,0) -> 1 | AB42: =IF(AA42=1,SUM(AA$40:AA42),"") -> 3 | AC42: =IF(ABS(Z42)<=$R$5,"Confere",IF(Z42>0,"Sobrando","Faltando")) -> Faltando | AD42: =COUNTIFS(Lançamentos!$A$2:$A$607,">="&$F$5,Lançamentos!$A$2:$A$607,"<="&$H$5,Lançamentos!$C$2:$C$607,$T42,Lançamentos!$D$2:$D$607,$AG42,Lançamentos!$B$2:$B$607,$R$4,Lançamentos!$G$2:$G$607,U42) -> 5 | AE42: CB PAILLETÉ FEUILLETINE 2.5KG/UC 4UC/BOX | AF42: =IF(AND(AA42=1,AC42<>"Confere"),ABS(Z42)+ROW()/10000000,0) -> 210 | AG42: 26044019 | AH42: =LARGE($AF$40:$AF$133,3) -> 3198 | AI42: =IF(AH42>0,MATCH(AH42,$AF$40:$AF$133,0),"") -> 8 | AJ42: =IF(AI42="","",INDEX($T$40:$T$133,AI42)&" · "&INDEX($AG$40:$AG$133,AI42)) -> CHD-SP-9Z4-BR-U73 · 250500301 | AK42: =IF(AI42="",0,MAX(INDEX($Z$40:$Z$133,AI42),0)) -> 3198 | AL42: =IF(AI42="",0,MIN(INDEX($Z$40:$Z$133,AI42),0)) -> 0 | AN42: 11/09 | AO42: 46276 | AP42: =IF(AND(AO42>=$F$5,AO42<=$H$5),SUMIFS(Lançamentos!$I$2:$I$607,Lançamentos!$A$2:$A$607,$AO42,Lançamentos!$C$2:$C$607,$R$1,Lançamentos!$D$2:$D$607,$R$2,Lançamentos!$G$2:$G$607,$R$3,Lançamentos!$B$2:$B$607,$R$4),0) -> 6720.9 | AQ42: =IF(AND(AO42>=$F$5,AO42<=$H$5),-SUMIFS(Lançamentos!$J$2:$J$607,Lançamentos!$A$2:$A$607,$AO42,Lançamentos!$C$2:$C$607,$R$1,Lançamentos!$D$2:$D$607,$R$2,Lançamentos!$G$2:$G$607,$R$3,Lançamentos!$B$2:$B$607,$R$4),0) -> -2836.4 | AS42: DCP-22ZEPLA-89B | AV42: =IFERROR(INDEX($AX$1:$AX$94,MATCH(41,$AY$1:$AY$94,0)),"") -> 253620301 | AW42: CHK-R30GOLD-BR-25A | AX42: 261130301 | AY42: =IF(OR($A$5="Todos",AW42=$A$5),MAX(AY$1:AY41)+1,0) -> 42
A43: =IF(IFERROR(MATCH(10,$AB$40:$AB$133,0),0)=0,"",INDEX($T$40:$T$133,IFERROR(MATCH(10,$AB$40:$AB$133,0),0))) -> CW2-BR-25A | B43: =IF(IFERROR(MATCH(10,$AB$40:$AB$133,0),0)=0,"",INDEX($AG$40:$AG$133,IFERROR(MATCH(10,$AB$40:$AB$133,0),0))) -> 253470301 | C43: =IF(IFERROR(MATCH(10,$AB$40:$AB$133,0),0)=0,"",INDEX($U$40:$U$133,IFERROR(MATCH(10,$AB$40:$AB$133,0),0))) -> KG | D43: =IF(IFERROR(MATCH(10,$AB$40:$AB$133,0),0)=0,"",INDEX($V$40:$V$133,IFERROR(MATCH(10,$AB$40:$AB$133,0),0))) -> 0 | E43: =IF(IFERROR(MATCH(10,$AB$40:$AB$133,0),0)=0,"",INDEX($W$40:$W$133,IFERROR(MATCH(10,$AB$40:$AB$133,0),0))) -> 763.8 | F43: =IF(IFERROR(MATCH(10,$AB$40:$AB$133,0),0)=0,"",INDEX($X$40:$X$133,IFERROR(MATCH(10,$AB$40:$AB$133,0),0))) -> 924.6 | G43: =IF(A43="","",E43-F43) -> -160.8 | H43: =IF(IFERROR(MATCH(10,$AB$40:$AB$133,0),0)=0,"",INDEX($Y$40:$Y$133,IFERROR(MATCH(10,$AB$40:$AB$133,0),0))) -> 763.8 | I43: =IF(IFERROR(MATCH(10,$AB$40:$AB$133,0),0)=0,"",INDEX($Z$40:$Z$133,IFERROR(MATCH(10,$AB$40:$AB$133,0),0))) -> 924.6 | J43: =IF(IFERROR(MATCH(10,$AB$40:$AB$133,0),0)=0,"",INDEX($AC$40:$AC$133,IFERROR(MATCH(10,$AB$40:$AB$133,0),0))) -> Sobrando | K43: =IF(IFERROR(MATCH(10,$AB$40:$AB$133,0),0)=0,"",INDEX($AD$40:$AD$133,IFERROR(MATCH(10,$AB$40:$AB$133,0),0))) -> 12 | L43: =IF(IFERROR(MATCH(10,$AB$40:$AB$133,0),0)=0,"",INDEX($AE$40:$AE$133,IFERROR(MATCH(10,$AB$40:$AB$133,0),0))&"") -> CA MOEDAS 2,01KG/UC 10UC/CX 30CX/PAL | T43: NIBS-S502-X47 | U43: CX | V43: =SUMIFS(Lançamentos!$H$2:$H$607,Lançamentos!$A$2:$A$607,">="&$F$5,Lançamentos!$A$2:$A$607,"<="&$H$5,Lançamentos!$C$2:$C$607,$T43,Lançamentos!$D$2:$D$607,$AG43,Lançamentos!$B$2:$B$607,"Recebido no 2008") -> 0 | W43: =SUMIFS(Lançamentos!$I$2:$I$607,Lançamentos!$A$2:$A$607,">="&$F$5,Lançamentos!$A$2:$A$607,"<="&$H$5,Lançamentos!$C$2:$C$607,$T43,Lançamentos!$D$2:$D$607,$AG43) -> 487 | X43: =SUMIFS(Lançamentos!$J$2:$J$607,Lançamentos!$A$2:$A$607,">="&$F$5,Lançamentos!$A$2:$A$607,"<="&$H$5,Lançamentos!$C$2:$C$607,$T43,Lançamentos!$D$2:$D$607,$AG43) -> 0 | Y43: =SUMIFS('Estoque físico'!$J$2:$J$229,'Estoque físico'!$A$2:$A$229,$T43,'Estoque físico'!$B$2:$B$229,$AG43) -> 367 | Z43: =ROUND(Y43-(W43-X43),3) -> -120 | AA43: =IF(AND(U43=$R$3,OR($R$1="*",T43=$R$1),OR($R$2="*",AG43=$R$2),ABS(V43)+ABS(W43)+ABS(X43)+ABS(Y43)>0),1,0) -> 0 | AB43: =IF(AA43=1,SUM(AA$40:AA43),"") | AC43: =IF(ABS(Z43)<=$R$5,"Confere",IF(Z43>0,"Sobrando","Faltando")) -> Faltando | AD43: =COUNTIFS(Lançamentos!$A$2:$A$607,">="&$F$5,Lançamentos!$A$2:$A$607,"<="&$H$5,Lançamentos!$C$2:$C$607,$T43,Lançamentos!$D$2:$D$607,$AG43,Lançamentos!$B$2:$B$607,$R$4,Lançamentos!$G$2:$G$607,U43) -> 4 | AE43: CA NIBS S 0.8KG/UC 4UC/BOX 120BOX/PAL | AF43: =IF(AND(AA43=1,AC43<>"Confere"),ABS(Z43)+ROW()/10000000,0) -> 0 | AG43: 253490619 | AH43: =LARGE($AF$40:$AF$133,4) -> 2528.4 | AI43: =IF(AH43>0,MATCH(AH43,$AF$40:$AF$133,0),"") -> 9 | AJ43: =IF(AI43="","",INDEX($T$40:$T$133,AI43)&" · "&INDEX($AG$40:$AG$133,AI43)) -> 823-BR-D94 · 252103049 | AK43: =IF(AI43="",0,MAX(INDEX($Z$40:$Z$133,AI43),0)) -> 2528.4 | AL43: =IF(AI43="",0,MIN(INDEX($Z$40:$Z$133,AI43),0)) -> 0 | AN43: 12/09 | AO43: 46277 | AP43: =IF(AND(AO43>=$F$5,AO43<=$H$5),SUMIFS(Lançamentos!$I$2:$I$607,Lançamentos!$A$2:$A$607,$AO43,Lançamentos!$C$2:$C$607,$R$1,Lançamentos!$D$2:$D$607,$R$2,Lançamentos!$G$2:$G$607,$R$3,Lançamentos!$B$2:$B$607,$R$4),0) -> 0 | AQ43: =IF(AND(AO43>=$F$5,AO43<=$H$5),-SUMIFS(Lançamentos!$J$2:$J$607,Lançamentos!$A$2:$A$607,$AO43,Lançamentos!$C$2:$C$607,$R$1,Lançamentos!$D$2:$D$607,$R$2,Lançamentos!$G$2:$G$607,$R$3,Lançamentos!$B$2:$B$607,$R$4),0) -> -173.1 | AS43: GIA-145 | AV43: =IFERROR(INDEX($AX$1:$AX$94,MATCH(42,$AY$1:$AY$94,0)),"") -> 261130301 | AW43: CHK-R30GOLD-E0-D94 | AX43: 260720939 | AY43: =IF(OR($A$5="Todos",AW43=$A$5),MAX(AY$1:AY42)+1,0) -> 43
A44: =IF(IFERROR(MATCH(11,$AB$40:$AB$133,0),0)=0,"",INDEX($T$40:$T$133,IFERROR(MATCH(11,$AB$40:$AB$133,0),0))) -> CHP-20SICHP-760 | B44: =IF(IFERROR(MATCH(11,$AB$40:$AB$133,0),0)=0,"",INDEX($AG$40:$AG$133,IFERROR(MATCH(11,$AB$40:$AB$133,0),0))) -> 252843369 | C44: =IF(IFERROR(MATCH(11,$AB$40:$AB$133,0),0)=0,"",INDEX($U$40:$U$133,IFERROR(MATCH(11,$AB$40:$AB$133,0),0))) -> KG | D44: =IF(IFERROR(MATCH(11,$AB$40:$AB$133,0),0)=0,"",INDEX($V$40:$V$133,IFERROR(MATCH(11,$AB$40:$AB$133,0),0))) -> 0 | E44: =IF(IFERROR(MATCH(11,$AB$40:$AB$133,0),0)=0,"",INDEX($W$40:$W$133,IFERROR(MATCH(11,$AB$40:$AB$133,0),0))) -> 918 | F44: =IF(IFERROR(MATCH(11,$AB$40:$AB$133,0),0)=0,"",INDEX($X$40:$X$133,IFERROR(MATCH(11,$AB$40:$AB$133,0),0))) -> 186 | G44: =IF(A44="","",E44-F44) -> 732 | H44: =IF(IFERROR(MATCH(11,$AB$40:$AB$133,0),0)=0,"",INDEX($Y$40:$Y$133,IFERROR(MATCH(11,$AB$40:$AB$133,0),0))) -> 1272 | I44: =IF(IFERROR(MATCH(11,$AB$40:$AB$133,0),0)=0,"",INDEX($Z$40:$Z$133,IFERROR(MATCH(11,$AB$40:$AB$133,0),0))) -> 540 | J44: =IF(IFERROR(MATCH(11,$AB$40:$AB$133,0),0)=0,"",INDEX($AC$40:$AC$133,IFERROR(MATCH(11,$AB$40:$AB$133,0),0))) -> Sobrando | K44: =IF(IFERROR(MATCH(11,$AB$40:$AB$133,0),0)=0,"",INDEX($AD$40:$AD$133,IFERROR(MATCH(11,$AB$40:$AB$133,0),0))) -> 13 | L44: =IF(IFERROR(MATCH(11,$AB$40:$AB$133,0),0)=0,"",INDEX($AE$40:$AE$133,IFERROR(MATCH(11,$AB$40:$AB$133,0),0))&"") -> CA SILKY CHOCO POWDER POWDER 1KG/UC | T44: CHD-BB-308BY-357 | U44: UN | V44: =SUMIFS(Lançamentos!$H$2:$H$607,Lançamentos!$A$2:$A$607,">="&$F$5,Lançamentos!$A$2:$A$607,"<="&$H$5,Lançamentos!$C$2:$C$607,$T44,Lançamentos!$D$2:$D$607,$AG44,Lançamentos!$B$2:$B$607,"Recebido no 2008") -> 0 | W44: =SUMIFS(Lançamentos!$I$2:$I$607,Lançamentos!$A$2:$A$607,">="&$F$5,Lançamentos!$A$2:$A$607,"<="&$H$5,Lançamentos!$C$2:$C$607,$T44,Lançamentos!$D$2:$D$607,$AG44) -> 30 | X44: =SUMIFS(Lançamentos!$J$2:$J$607,Lançamentos!$A$2:$A$607,">="&$F$5,Lançamentos!$A$2:$A$607,"<="&$H$5,Lançamentos!$C$2:$C$607,$T44,Lançamentos!$D$2:$D$607,$AG44) -> 0 | Y44: =SUMIFS('Estoque físico'!$J$2:$J$229,'Estoque físico'!$A$2:$A$229,$T44,'Estoque físico'!$B$2:$B$229,$AG44) -> 4.219 | Z44: =ROUND(Y44-(W44-X44),3) -> -25.781 | AA44: =IF(AND(U44=$R$3,OR($R$1="*",T44=$R$1),OR($R$2="*",AG44=$R$2),ABS(V44)+ABS(W44)+ABS(X44)+ABS(Y44)>0),1,0) -> 0 | AB44: =IF(AA44=1,SUM(AA$40:AA44),"") | AC44: =IF(ABS(Z44)<=$R$5,"Confere",IF(Z44>0,"Sobrando","Faltando")) -> Faltando | AD44: =COUNTIFS(Lançamentos!$A$2:$A$607,">="&$F$5,Lançamentos!$A$2:$A$607,"<="&$H$5,Lançamentos!$C$2:$C$607,$T44,Lançamentos!$D$2:$D$607,$AG44,Lançamentos!$B$2:$B$607,$R$4,Lançamentos!$G$2:$G$607,U44) -> 1 | AE44: CB EXTRUDED 8CM STICKS 1.6KG/UC 15UC/BOX | AF44: =IF(AND(AA44=1,AC44<>"Confere"),ABS(Z44)+ROW()/10000000,0) -> 0 | AG44: 250827800 | AH44: =LARGE($AF$40:$AF$133,5) -> 1268.4 | AI44: =IF(AH44>0,MATCH(AH44,$AF$40:$AF$133,0),"") -> 10 | AJ44: =IF(AI44="","",INDEX($T$40:$T$133,AI44)&" · "&INDEX($AG$40:$AG$133,AI44)) -> 805-BR-D94 · 251633359 | AK44: =IF(AI44="",0,MAX(INDEX($Z$40:$Z$133,AI44),0)) -> 1268.4 | AL44: =IF(AI44="",0,MIN(INDEX($Z$40:$Z$133,AI44),0)) -> 0 | AN44: 13/09 | AO44: 46278 | AP44: =IF(AND(AO44>=$F$5,AO44<=$H$5),SUMIFS(Lançamentos!$I$2:$I$607,Lançamentos!$A$2:$A$607,$AO44,Lançamentos!$C$2:$C$607,$R$1,Lançamentos!$D$2:$D$607,$R$2,Lançamentos!$G$2:$G$607,$R$3,Lançamentos!$B$2:$B$607,$R$4),0) -> 0 | AQ44: =IF(AND(AO44>=$F$5,AO44<=$H$5),-SUMIFS(Lançamentos!$J$2:$J$607,Lançamentos!$A$2:$A$607,$AO44,Lançamentos!$C$2:$C$607,$R$1,Lançamentos!$D$2:$D$607,$R$2,Lançamentos!$G$2:$G$607,$R$3,Lançamentos!$B$2:$B$607,$R$4),0) -> -410.8 | AS44: MALCHOC-D-123 | AV44: =IFERROR(INDEX($AX$1:$AX$94,MATCH(43,$AY$1:$AY$94,0)),"") -> 260720939 | AW44: CHK-W-413 | AX44: 260536201 | AY44: =IF(OR($A$5="Todos",AW44=$A$5),MAX(AY$1:AY43)+1,0) -> 44
A45: =IF(IFERROR(MATCH(12,$AB$40:$AB$133,0),0)=0,"",INDEX($T$40:$T$133,IFERROR(MATCH(12,$AB$40:$AB$133,0),0))) -> 70-30-38-BR-25A | B45: =IF(IFERROR(MATCH(12,$AB$40:$AB$133,0),0)=0,"",INDEX($AG$40:$AG$133,IFERROR(MATCH(12,$AB$40:$AB$133,0),0))) -> 260370301 | C45: =IF(IFERROR(MATCH(12,$AB$40:$AB$133,0),0)=0,"",INDEX($U$40:$U$133,IFERROR(MATCH(12,$AB$40:$AB$133,0),0))) -> KG | D45: =IF(IFERROR(MATCH(12,$AB$40:$AB$133,0),0)=0,"",INDEX($V$40:$V$133,IFERROR(MATCH(12,$AB$40:$AB$133,0),0))) -> 6633 | E45: =IF(IFERROR(MATCH(12,$AB$40:$AB$133,0),0)=0,"",INDEX($W$40:$W$133,IFERROR(MATCH(12,$AB$40:$AB$133,0),0))) -> 603 | F45: =IF(IFERROR(MATCH(12,$AB$40:$AB$133,0),0)=0,"",INDEX($X$40:$X$133,IFERROR(MATCH(12,$AB$40:$AB$133,0),0))) -> 321.6 | G45: =IF(A45="","",E45-F45) -> 281.4 | H45: =IF(IFERROR(MATCH(12,$AB$40:$AB$133,0),0)=0,"",INDEX($Y$40:$Y$133,IFERROR(MATCH(12,$AB$40:$AB$133,0),0))) -> 623.1 | I45: =IF(IFERROR(MATCH(12,$AB$40:$AB$133,0),0)=0,"",INDEX($Z$40:$Z$133,IFERROR(MATCH(12,$AB$40:$AB$133,0),0))) -> 341.7 | J45: =IF(IFERROR(MATCH(12,$AB$40:$AB$133,0),0)=0,"",INDEX($AC$40:$AC$133,IFERROR(MATCH(12,$AB$40:$AB$133,0),0))) -> Sobrando | K45: =IF(IFERROR(MATCH(12,$AB$40:$AB$133,0),0)=0,"",INDEX($AD$40:$AD$133,IFERROR(MATCH(12,$AB$40:$AB$133,0),0))) -> 13 | L45: =IF(IFERROR(MATCH(12,$AB$40:$AB$133,0),0)=0,"",INDEX($AE$40:$AE$133,IFERROR(MATCH(12,$AB$40:$AB$133,0),0))&"") -> CA MOEDAS 2,01KG/UC 10UC/CX 30CX/PAL | T45: 811-BR-D94 | U45: KG | V45: =SUMIFS(Lançamentos!$H$2:$H$607,Lançamentos!$A$2:$A$607,">="&$F$5,Lançamentos!$A$2:$A$607,"<="&$H$5,Lançamentos!$C$2:$C$607,$T45,Lançamentos!$D$2:$D$607,$AG45,Lançamentos!$B$2:$B$607,"Recebido no 2008") -> 0 | W45: =SUMIFS(Lançamentos!$I$2:$I$607,Lançamentos!$A$2:$A$607,">="&$F$5,Lançamentos!$A$2:$A$607,"<="&$H$5,Lançamentos!$C$2:$C$607,$T45,Lançamentos!$D$2:$D$607,$AG45) -> 2.8 | X45: =SUMIFS(Lançamentos!$J$2:$J$607,Lançamentos!$A$2:$A$607,">="&$F$5,Lançamentos!$A$2:$A$607,"<="&$H$5,Lançamentos!$C$2:$C$607,$T45,Lançamentos!$D$2:$D$607,$AG45) -> 226.8 | Y45: =SUMIFS('Estoque físico'!$J$2:$J$229,'Estoque físico'!$A$2:$A$229,$T45,'Estoque físico'!$B$2:$B$229,$AG45) -> 5513.2 | Z45: =ROUND(Y45-(W45-X45),3) -> 5737.2 | AA45: =IF(AND(U45=$R$3,OR($R$1="*",T45=$R$1),OR($R$2="*",AG45=$R$2),ABS(V45)+ABS(W45)+ABS(X45)+ABS(Y45)>0),1,0) -> 1 | AB45: =IF(AA45=1,SUM(AA$40:AA45),"") -> 4 | AC45: =IF(ABS(Z45)<=$R$5,"Confere",IF(Z45>0,"Sobrando","Faltando")) -> Sobrando | AD45: =COUNTIFS(Lançamentos!$A$2:$A$607,">="&$F$5,Lançamentos!$A$2:$A$607,"<="&$H$5,Lançamentos!$C$2:$C$607,$T45,Lançamentos!$D$2:$D$607,$AG45,Lançamentos!$B$2:$B$607,$R$4,Lançamentos!$G$2:$G$607,U45) -> 17 | AE45: CA MOEDAS 0,4KG/UC 7UC/CX 144CX/PAL | AF45: =IF(AND(AA45=1,AC45<>"Confere"),ABS(Z45)+ROW()/10000000,0) -> 5737.2 | AG45: 251643289 | AH45: =LARGE($AF$40:$AF$133,6) -> 1083.39 | AI45: =IF(AH45>0,MATCH(AH45,$AF$40:$AF$133,0),"") -> 11 | AJ45: =IF(AI45="","",INDEX($T$40:$T$133,AI45)&" · "&INDEX($AG$40:$AG$133,AI45)) -> W3-BR-25A · 253540301 | AK45: =IF(AI45="",0,MAX(INDEX($Z$40:$Z$133,AI45),0)) -> 1083.39 | AL45: =IF(AI45="",0,MIN(INDEX($Z$40:$Z$133,AI45),0)) -> 0 | AN45: 14/09 | AO45: 46279 | AP45: =IF(AND(AO45>=$F$5,AO45<=$H$5),SUMIFS(Lançamentos!$I$2:$I$607,Lançamentos!$A$2:$A$607,$AO45,Lançamentos!$C$2:$C$607,$R$1,Lançamentos!$D$2:$D$607,$R$2,Lançamentos!$G$2:$G$607,$R$3,Lançamentos!$B$2:$B$607,$R$4),0) -> 0 | AQ45: =IF(AND(AO45>=$F$5,AO45<=$H$5),-SUMIFS(Lançamentos!$J$2:$J$607,Lançamentos!$A$2:$A$607,$AO45,Lançamentos!$C$2:$C$607,$R$1,Lançamentos!$D$2:$D$607,$R$2,Lançamentos!$G$2:$G$607,$R$3,Lançamentos!$B$2:$B$607,$R$4),0) -> -163 | AS45: NIBS-S502-X47 | AV45: =IFERROR(INDEX($AX$1:$AX$94,MATCH(44,$AY$1:$AY$94,0)),"") -> 260536201 | AW45: CHM-BS-9U15-E0-07B | AX45: 260701069 | AY45: =IF(OR($A$5="Todos",AW45=$A$5),MAX(AY$1:AY44)+1,0) -> 45
A46: =IF(IFERROR(MATCH(13,$AB$40:$AB$133,0),0)=0,"",INDEX($T$40:$T$133,IFERROR(MATCH(13,$AB$40:$AB$133,0),0))) -> 811-BR-25A | B46: =IF(IFERROR(MATCH(13,$AB$40:$AB$133,0),0)=0,"",INDEX($AG$40:$AG$133,IFERROR(MATCH(13,$AB$40:$AB$133,0),0))) -> 250880301 | C46: =IF(IFERROR(MATCH(13,$AB$40:$AB$133,0),0)=0,"",INDEX($U$40:$U$133,IFERROR(MATCH(13,$AB$40:$AB$133,0),0))) -> KG | D46: =IF(IFERROR(MATCH(13,$AB$40:$AB$133,0),0)=0,"",INDEX($V$40:$V$133,IFERROR(MATCH(13,$AB$40:$AB$133,0),0))) -> 0 | E46: =IF(IFERROR(MATCH(13,$AB$40:$AB$133,0),0)=0,"",INDEX($W$40:$W$133,IFERROR(MATCH(13,$AB$40:$AB$133,0),0))) -> 180.9 | F46: =IF(IFERROR(MATCH(13,$AB$40:$AB$133,0),0)=0,"",INDEX($X$40:$X$133,IFERROR(MATCH(13,$AB$40:$AB$133,0),0))) -> 180.9 | G46: =IF(A46="","",E46-F46) -> 0 | H46: =IF(IFERROR(MATCH(13,$AB$40:$AB$133,0),0)=0,"",INDEX($Y$40:$Y$133,IFERROR(MATCH(13,$AB$40:$AB$133,0),0))) -> 273.36 | I46: =IF(IFERROR(MATCH(13,$AB$40:$AB$133,0),0)=0,"",INDEX($Z$40:$Z$133,IFERROR(MATCH(13,$AB$40:$AB$133,0),0))) -> 273.36 | J46: =IF(IFERROR(MATCH(13,$AB$40:$AB$133,0),0)=0,"",INDEX($AC$40:$AC$133,IFERROR(MATCH(13,$AB$40:$AB$133,0),0))) -> Sobrando | K46: =IF(IFERROR(MATCH(13,$AB$40:$AB$133,0),0)=0,"",INDEX($AD$40:$AD$133,IFERROR(MATCH(13,$AB$40:$AB$133,0),0))) -> 5 | L46: =IF(IFERROR(MATCH(13,$AB$40:$AB$133,0),0)=0,"",INDEX($AE$40:$AE$133,IFERROR(MATCH(13,$AB$40:$AB$133,0),0))&"") -> CA MOEDAS 2,01KG/UC 10UC/CX 30CX/PAL | T46: CHM-SP-Z3L-BR-U73 | U46: KG | V46: =SUMIFS(Lançamentos!$H$2:$H$607,Lançamentos!$A$2:$A$607,">="&$F$5,Lançamentos!$A$2:$A$607,"<="&$H$5,Lançamentos!$C$2:$C$607,$T46,Lançamentos!$D$2:$D$607,$AG46,Lançamentos!$B$2:$B$607,"Recebido no 2008") -> 0 | W46: =SUMIFS(Lançamentos!$I$2:$I$607,Lançamentos!$A$2:$A$607,">="&$F$5,Lançamentos!$A$2:$A$607,"<="&$H$5,Lançamentos!$C$2:$C$607,$T46,Lançamentos!$D$2:$D$607,$AG46) -> 966 | X46: =SUMIFS(Lançamentos!$J$2:$J$607,Lançamentos!$A$2:$A$607,">="&$F$5,Lançamentos!$A$2:$A$607,"<="&$H$5,Lançamentos!$C$2:$C$607,$T46,Lançamentos!$D$2:$D$607,$AG46) -> 906 | Y46: =SUMIFS('Estoque físico'!$J$2:$J$229,'Estoque físico'!$A$2:$A$229,$T46,'Estoque físico'!$B$2:$B$229,$AG46) -> 3754.998 | Z46: =ROUND(Y46-(W46-X46),3) -> 3694.998 | AA46: =IF(AND(U46=$R$3,OR($R$1="*",T46=$R$1),OR($R$2="*",AG46=$R$2),ABS(V46)+ABS(W46)+ABS(X46)+ABS(Y46)>0),1,0) -> 1 | AB46: =IF(AA46=1,SUM(AA$40:AA46),"") -> 5 | AC46: =IF(ABS(Z46)<=$R$5,"Confere",IF(Z46>0,"Sobrando","Faltando")) -> Sobrando | AD46: =COUNTIFS(Lançamentos!$A$2:$A$607,">="&$F$5,Lançamentos!$A$2:$A$607,"<="&$H$5,Lançamentos!$C$2:$C$607,$T46,Lançamentos!$D$2:$D$607,$AG46,Lançamentos!$B$2:$B$607,$R$4,Lançamentos!$G$2:$G$607,U46) -> 30 | AE46: CA MILK LARGE FLAKES SPLITTERS 1KG/UC | AF46: =IF(AND(AA46=1,AC46<>"Confere"),ABS(Z46)+ROW()/10000000,0) -> 3694.998 | AG46: 251880301 | AH46: =LARGE($AF$40:$AF$133,7) -> 924.60001 | AI46: =IF(AH46>0,MATCH(AH46,$AF$40:$AF$133,0),"") -> 12 | AJ46: =IF(AI46="","",INDEX($T$40:$T$133,AI46)&" · "&INDEX($AG$40:$AG$133,AI46)) -> CW2-BR-25A · 253470301 | AK46: =IF(AI46="",0,MAX(INDEX($Z$40:$Z$133,AI46),0)) -> 924.6 | AL46: =IF(AI46="",0,MIN(INDEX($Z$40:$Z$133,AI46),0)) -> 0 | AN46: 15/09 | AO46: 46280 | AP46: =IF(AND(AO46>=$F$5,AO46<=$H$5),SUMIFS(Lançamentos!$I$2:$I$607,Lançamentos!$A$2:$A$607,$AO46,Lançamentos!$C$2:$C$607,$R$1,Lançamentos!$D$2:$D$607,$R$2,Lançamentos!$G$2:$G$607,$R$3,Lançamentos!$B$2:$B$607,$R$4),0) -> 0 | AQ46: =IF(AND(AO46>=$F$5,AO46<=$H$5),-SUMIFS(Lançamentos!$J$2:$J$607,Lançamentos!$A$2:$A$607,$AO46,Lançamentos!$C$2:$C$607,$R$1,Lançamentos!$D$2:$D$607,$R$2,Lançamentos!$G$2:$G$607,$R$3,Lançamentos!$B$2:$B$607,$R$4),0) -> -340 | AS46: PNP-T14 | AV46: =IFERROR(INDEX($AX$1:$AX$94,MATCH(45,$AY$1:$AY$94,0)),"") -> 260701069 | AW46: CHM-CU-7X80-E5-U70 | AX46: 2528749307 | AY46: =IF(OR($A$5="Todos",AW46=$A$5),MAX(AY$1:AY45)+1,0) -> 46
A47: =IF(IFERROR(MATCH(14,$AB$40:$AB$133,0),0)=0,"",INDEX($T$40:$T$133,IFERROR(MATCH(14,$AB$40:$AB$133,0),0))) -> CHM-BS-9U15-E0-07B | B47: =IF(IFERROR(MATCH(14,$AB$40:$AB$133,0),0)=0,"",INDEX($AG$40:$AG$133,IFERROR(MATCH(14,$AB$40:$AB$133,0),0))) -> 260701069 | C47: =IF(IFERROR(MATCH(14,$AB$40:$AB$133,0),0)=0,"",INDEX($U$40:$U$133,IFERROR(MATCH(14,$AB$40:$AB$133,0),0))) -> KG | D47: =IF(IFERROR(MATCH(14,$AB$40:$AB$133,0),0)=0,"",INDEX($V$40:$V$133,IFERROR(MATCH(14,$AB$40:$AB$133,0),0))) -> 1920 | E47: =IF(IFERROR(MATCH(14,$AB$40:$AB$133,0),0)=0,"",INDEX($W$40:$W$133,IFERROR(MATCH(14,$AB$40:$AB$133,0),0))) -> 960 | F47: =IF(IFERROR(MATCH(14,$AB$40:$AB$133,0),0)=0,"",INDEX($X$40:$X$133,IFERROR(MATCH(14,$AB$40:$AB$133,0),0))) -> 176 | G47: =IF(A47="","",E47-F47) -> 784 | H47: =IF(IFERROR(MATCH(14,$AB$40:$AB$133,0),0)=0,"",INDEX($Y$40:$Y$133,IFERROR(MATCH(14,$AB$40:$AB$133,0),0))) -> 1032 | I47: =IF(IFERROR(MATCH(14,$AB$40:$AB$133,0),0)=0,"",INDEX($Z$40:$Z$133,IFERROR(MATCH(14,$AB$40:$AB$133,0),0))) -> 248 | J47: =IF(IFERROR(MATCH(14,$AB$40:$AB$133,0),0)=0,"",INDEX($AC$40:$AC$133,IFERROR(MATCH(14,$AB$40:$AB$133,0),0))) -> Sobrando | K47: =IF(IFERROR(MATCH(14,$AB$40:$AB$133,0),0)=0,"",INDEX($AD$40:$AD$133,IFERROR(MATCH(14,$AB$40:$AB$133,0),0))) -> 20 | L47: =IF(IFERROR(MATCH(14,$AB$40:$AB$133,0),0)=0,"",INDEX($AE$40:$AE$133,IFERROR(MATCH(14,$AB$40:$AB$133,0),0))&"") -> CA MILK BLOSSOMS BLOSSOMS 1KG/UC 4UC/BOX | T47: CHD-SP-9Z4-BR-U73 | U47: KG | V47: =SUMIFS(Lançamentos!$H$2:$H$607,Lançamentos!$A$2:$A$607,">="&$F$5,Lançamentos!$A$2:$A$607,"<="&$H$5,Lançamentos!$C$2:$C$607,$T47,Lançamentos!$D$2:$D$607,$AG47,Lançamentos!$B$2:$B$607,"Recebido no 2008") -> 0 | W47: =SUMIFS(Lançamentos!$I$2:$I$607,Lançamentos!$A$2:$A$607,">="&$F$5,Lançamentos!$A$2:$A$607,"<="&$H$5,Lançamentos!$C$2:$C$607,$T47,Lançamentos!$D$2:$D$607,$AG47) -> 240 | X47: =SUMIFS(Lançamentos!$J$2:$J$607,Lançamentos!$A$2:$A$607,">="&$F$5,Lançamentos!$A$2:$A$607,"<="&$H$5,Lançamentos!$C$2:$C$607,$T47,Lançamentos!$D$2:$D$607,$AG47) -> 6 | Y47: =SUMIFS('Estoque físico'!$J$2:$J$229,'Estoque físico'!$A$2:$A$229,$T47,'Estoque físico'!$B$2:$B$229,$AG47) -> 3432 | Z47: =ROUND(Y47-(W47-X47),3) -> 3198 | AA47: =IF(AND(U47=$R$3,OR($R$1="*",T47=$R$1),OR($R$2="*",AG47=$R$2),ABS(V47)+ABS(W47)+ABS(X47)+ABS(Y47)>0),1,0) -> 1 | AB47: =IF(AA47=1,SUM(AA$40:AA47),"") -> 6 | AC47: =IF(ABS(Z47)<=$R$5,"Confere",IF(Z47>0,"Sobrando","Faltando")) -> Sobrando | AD47: =COUNTIFS(Lançamentos!$A$2:$A$607,">="&$F$5,Lançamentos!$A$2:$A$607,"<="&$H$5,Lançamentos!$C$2:$C$607,$T47,Lançamentos!$D$2:$D$607,$AG47,Lançamentos!$B$2:$B$607,$R$4,Lançamentos!$G$2:$G$607,U47) -> 2 | AE47: 96_FU:CHD-SP-1L-BR-U73 | AF47: =IF(AND(AA47=1,AC47<>"Confere"),ABS(Z47)+ROW()/10000000,0) -> 3198 | AG47: 250500301 | AH47: =LARGE($AF$40:$AF$133,8) -> 540.00001 | AI47: =IF(AH47>0,MATCH(AH47,$AF$40:$AF$133,0),"") -> 13 | AJ47: =IF(AI47="","",INDEX($T$40:$T$133,AI47)&" · "&INDEX($AG$40:$AG$133,AI47)) -> CHP-20SICHP-760 · 252843369 | AK47: =IF(AI47="",0,MAX(INDEX($Z$40:$Z$133,AI47),0)) -> 540 | AL47: =IF(AI47="",0,MIN(INDEX($Z$40:$Z$133,AI47),0)) -> 0 | AN47: 16/09 | AO47: 46281 | AP47: =IF(AND(AO47>=$F$5,AO47<=$H$5),SUMIFS(Lançamentos!$I$2:$I$607,Lançamentos!$A$2:$A$607,$AO47,Lançamentos!$C$2:$C$607,$R$1,Lançamentos!$D$2:$D$607,$R$2,Lançamentos!$G$2:$G$607,$R$3,Lançamentos!$B$2:$B$607,$R$4),0) -> 0 | AQ47: =IF(AND(AO47>=$F$5,AO47<=$H$5),-SUMIFS(Lançamentos!$J$2:$J$607,Lançamentos!$A$2:$A$607,$AO47,Lançamentos!$C$2:$C$607,$R$1,Lançamentos!$D$2:$D$607,$R$2,Lançamentos!$G$2:$G$607,$R$3,Lançamentos!$B$2:$B$607,$R$4),0) -> -94.6 | AS47: PRA-T14 | AV47: =IFERROR(INDEX($AX$1:$AX$94,MATCH(46,$AY$1:$AY$94,0)),"") -> 2528749307 | AW47: CHM-Q41ALUN-2B-U73 | AX47: 260660303 | AY47: =IF(OR($A$5="Todos",AW47=$A$5),MAX(AY$1:AY46)+1,0) -> 47
A48: =IF(IFERROR(MATCH(15,$AB$40:$AB$133,0),0)=0,"",INDEX($T$40:$T$133,IFERROR(MATCH(15,$AB$40:$AB$133,0),0))) -> 70-30-38-BR-D94 | B48: =IF(IFERROR(MATCH(15,$AB$40:$AB$133,0),0)=0,"",INDEX($AG$40:$AG$133,IFERROR(MATCH(15,$AB$40:$AB$133,0),0))) -> 253213449 | C48: =IF(IFERROR(MATCH(15,$AB$40:$AB$133,0),0)=0,"",INDEX($U$40:$U$133,IFERROR(MATCH(15,$AB$40:$AB$133,0),0))) -> KG | D48: =IF(IFERROR(MATCH(15,$AB$40:$AB$133,0),0)=0,"",INDEX($V$40:$V$133,IFERROR(MATCH(15,$AB$40:$AB$133,0),0))) -> 0 | E48: =IF(IFERROR(MATCH(15,$AB$40:$AB$133,0),0)=0,"",INDEX($W$40:$W$133,IFERROR(MATCH(15,$AB$40:$AB$133,0),0))) -> 940.8 | F48: =IF(IFERROR(MATCH(15,$AB$40:$AB$133,0),0)=0,"",INDEX($X$40:$X$133,IFERROR(MATCH(15,$AB$40:$AB$133,0),0))) -> 781.2 | G48: =IF(A48="","",E48-F48) -> 159.6 | H48: =IF(IFERROR(MATCH(15,$AB$40:$AB$133,0),0)=0,"",INDEX($Y$40:$Y$133,IFERROR(MATCH(15,$AB$40:$AB$133,0),0))) -> 333.2 | I48: =IF(IFERROR(MATCH(15,$AB$40:$AB$133,0),0)=0,"",INDEX($Z$40:$Z$133,IFERROR(MATCH(15,$AB$40:$AB$133,0),0))) -> 173.6 | J48: =IF(IFERROR(MATCH(15,$AB$40:$AB$133,0),0)=0,"",INDEX($AC$40:$AC$133,IFERROR(MATCH(15,$AB$40:$AB$133,0),0))) -> Sobrando | K48: =IF(IFERROR(MATCH(15,$AB$40:$AB$133,0),0)=0,"",INDEX($AD$40:$AD$133,IFERROR(MATCH(15,$AB$40:$AB$133,0),0))) -> 26 | L48: =IF(IFERROR(MATCH(15,$AB$40:$AB$133,0),0)=0,"",INDEX($AE$40:$AE$133,IFERROR(MATCH(15,$AB$40:$AB$133,0),0))&"") -> CA MOEDAS 0,4KG/UC 7UC/CX 144CX/PAL | T48: 823-BR-D94 | U48: KG | V48: =SUMIFS(Lançamentos!$H$2:$H$607,Lançamentos!$A$2:$A$607,">="&$F$5,Lançamentos!$A$2:$A$607,"<="&$H$5,Lançamentos!$C$2:$C$607,$T48,Lançamentos!$D$2:$D$607,$AG48,Lançamentos!$B$2:$B$607,"Recebido no 2008") -> 0 | W48: =SUMIFS(Lançamentos!$I$2:$I$607,Lançamentos!$A$2:$A$607,">="&$F$5,Lançamentos!$A$2:$A$607,"<="&$H$5,Lançamentos!$C$2:$C$607,$T48,Lançamentos!$D$2:$D$607,$AG48) -> 2.8 | X48: =SUMIFS(Lançamentos!$J$2:$J$607,Lançamentos!$A$2:$A$607,">="&$F$5,Lançamentos!$A$2:$A$607,"<="&$H$5,Lançamentos!$C$2:$C$607,$T48,Lançamentos!$D$2:$D$607,$AG48) -> 677.6 | Y48: =SUMIFS('Estoque físico'!$J$2:$J$229,'Estoque físico'!$A$2:$A$229,$T48,'Estoque físico'!$B$2:$B$229,$AG48) -> 1853.6 | Z48: =ROUND(Y48-(W48-X48),3) -> 2528.4 | AA48: =IF(AND(U48=$R$3,OR($R$1="*",T48=$R$1),OR($R$2="*",AG48=$R$2),ABS(V48)+ABS(W48)+ABS(X48)+ABS(Y48)>0),1,0) -> 1 | AB48: =IF(AA48=1,SUM(AA$40:AA48),"") -> 7 | AC48: =IF(ABS(Z48)<=$R$5,"Confere",IF(Z48>0,"Sobrando","Faltando")) -> Sobrando | AD48: =COUNTIFS(Lançamentos!$A$2:$A$607,">="&$F$5,Lançamentos!$A$2:$A$607,"<="&$H$5,Lançamentos!$C$2:$C$607,$T48,Lançamentos!$D$2:$D$607,$AG48,Lançamentos!$B$2:$B$607,$R$4,Lançamentos!$G$2:$G$607,U48) -> 53 | AE48: CA MOEDAS 0,4KG/UC 7UC/CX 144CX/PAL | AF48: =IF(AND(AA48=1,AC48<>"Confere"),ABS(Z48)+ROW()/10000000,0) -> 2528.4 | AG48: 252103049 | AH48: =LARGE($AF$40:$AF$133,9) -> 442.2 | AI48: =IF(AH48>0,MATCH(AH48,$AF$40:$AF$133,0),"") -> 1 | AJ48: =IF(AI48="","",INDEX($T$40:$T$133,AI48)&" · "&INDEX($AG$40:$AG$133,AI48)) -> CHK-R30GOLD-BR-25A · 261130301 | AK48: =IF(AI48="",0,MAX(INDEX($Z$40:$Z$133,AI48),0)) -> 0 | AL48: =IF(AI48="",0,MIN(INDEX($Z$40:$Z$133,AI48),0)) -> -442.2 | AN48: 17/09 | AO48: 46282 | AP48: =IF(AND(AO48>=$F$5,AO48<=$H$5),SUMIFS(Lançamentos!$I$2:$I$607,Lançamentos!$A$2:$A$607,$AO48,Lançamentos!$C$2:$C$607,$R$1,Lançamentos!$D$2:$D$607,$R$2,Lançamentos!$G$2:$G$607,$R$3,Lançamentos!$B$2:$B$607,$R$4),0) -> 0 | AQ48: =IF(AND(AO48>=$F$5,AO48<=$H$5),-SUMIFS(Lançamentos!$J$2:$J$607,Lançamentos!$A$2:$A$607,$AO48,Lançamentos!$C$2:$C$607,$R$1,Lançamentos!$D$2:$D$607,$R$2,Lançamentos!$G$2:$G$607,$R$3,Lançamentos!$B$2:$B$607,$R$4),0) -> -337.5 | AS48: SPLIT-4-D-413 | AV48: =IFERROR(INDEX($AX$1:$AX$94,MATCH(47,$AY$1:$AY$94,0)),"") -> 260660303 | AW48: CHM-SP-Z3L-BR-U73 | AX48: 250880301 | AY48: =IF(OR($A$5="Todos",AW48=$A$5),MAX(AY$1:AY47)+1,0) -> 48
A49: =IF(IFERROR(MATCH(16,$AB$40:$AB$133,0),0)=0,"",INDEX($T$40:$T$133,IFERROR(MATCH(16,$AB$40:$AB$133,0),0))) -> CW2-BR-25A | B49: =IF(IFERROR(MATCH(16,$AB$40:$AB$133,0),0)=0,"",INDEX($AG$40:$AG$133,IFERROR(MATCH(16,$AB$40:$AB$133,0),0))) -> 252650301 | C49: =IF(IFERROR(MATCH(16,$AB$40:$AB$133,0),0)=0,"",INDEX($U$40:$U$133,IFERROR(MATCH(16,$AB$40:$AB$133,0),0))) -> KG | D49: =IF(IFERROR(MATCH(16,$AB$40:$AB$133,0),0)=0,"",INDEX($V$40:$V$133,IFERROR(MATCH(16,$AB$40:$AB$133,0),0))) -> 40 | E49: =IF(IFERROR(MATCH(16,$AB$40:$AB$133,0),0)=0,"",INDEX($W$40:$W$133,IFERROR(MATCH(16,$AB$40:$AB$133,0),0))) -> 2271.3 | F49: =IF(IFERROR(MATCH(16,$AB$40:$AB$133,0),0)=0,"",INDEX($X$40:$X$133,IFERROR(MATCH(16,$AB$40:$AB$133,0),0))) -> 562.8 | G49: =IF(A49="","",E49-F49) -> 1708.5 | H49: =IF(IFERROR(MATCH(16,$AB$40:$AB$133,0),0)=0,"",INDEX($Y$40:$Y$133,IFERROR(MATCH(16,$AB$40:$AB$133,0),0))) -> 1829.1 | I49: =IF(IFERROR(MATCH(16,$AB$40:$AB$133,0),0)=0,"",INDEX($Z$40:$Z$133,IFERROR(MATCH(16,$AB$40:$AB$133,0),0))) -> 120.6 | J49: =IF(IFERROR(MATCH(16,$AB$40:$AB$133,0),0)=0,"",INDEX($AC$40:$AC$133,IFERROR(MATCH(16,$AB$40:$AB$133,0),0))) -> Sobrando | K49: =IF(IFERROR(MATCH(16,$AB$40:$AB$133,0),0)=0,"",INDEX($AD$40:$AD$133,IFERROR(MATCH(16,$AB$40:$AB$133,0),0))) -> 15 | L49: =IF(IFERROR(MATCH(16,$AB$40:$AB$133,0),0)=0,"",INDEX($AE$40:$AE$133,IFERROR(MATCH(16,$AB$40:$AB$133,0),0))&"") -> CA MOEDAS 2,01KG/UC 10UC/CX 30CX/PAL | T49: 805-BR-D94 | U49: KG | V49: =SUMIFS(Lançamentos!$H$2:$H$607,Lançamentos!$A$2:$A$607,">="&$F$5,Lançamentos!$A$2:$A$607,"<="&$H$5,Lançamentos!$C$2:$C$607,$T49,Lançamentos!$D$2:$D$607,$AG49,Lançamentos!$B$2:$B$607,"Recebido no 2008") -> 0 | W49: =SUMIFS(Lançamentos!$I$2:$I$607,Lançamentos!$A$2:$A$607,">="&$F$5,Lançamentos!$A$2:$A$607,"<="&$H$5,Lançamentos!$C$2:$C$607,$T49,Lançamentos!$D$2:$D$607,$AG49) -> 313.6 | X49: =SUMIFS(Lançamentos!$J$2:$J$607,Lançamentos!$A$2:$A$607,">="&$F$5,Lançamentos!$A$2:$A$607,"<="&$H$5,Lançamentos!$C$2:$C$607,$T49,Lançamentos!$D$2:$D$607,$AG49) -> 221.2 | Y49: =SUMIFS('Estoque físico'!$J$2:$J$229,'Estoque físico'!$A$2:$A$229,$T49,'Estoque físico'!$B$2:$B$229,$AG49) -> 1360.8 | Z49: =ROUND(Y49-(W49-X49),3) -> 1268.4 | AA49: =IF(AND(U49=$R$3,OR($R$1="*",T49=$R$1),OR($R$2="*",AG49=$R$2),ABS(V49)+ABS(W49)+ABS(X49)+ABS(Y49)>0),1,0) -> 1 | AB49: =IF(AA49=1,SUM(AA$40:AA49),"") -> 8 | AC49: =IF(ABS(Z49)<=$R$5,"Confere",IF(Z49>0,"Sobrando","Faltando")) -> Sobrando | AD49: =COUNTIFS(Lançamentos!$A$2:$A$607,">="&$F$5,Lançamentos!$A$2:$A$607,"<="&$H$5,Lançamentos!$C$2:$C$607,$T49,Lançamentos!$D$2:$D$607,$AG49,Lançamentos!$B$2:$B$607,$R$4,Lançamentos!$G$2:$G$607,U49) -> 26 | AE49: CA MOEDAS 0,4KG/UC 7UC/CX 144CX/PAL | AF49: =IF(AND(AA49=1,AC49<>"Confere"),ABS(Z49)+ROW()/10000000,0) -> 1268.4 | AG49: 251633359 | AH49: =LARGE($AF$40:$AF$133,10) -> 341.70001 | AI49: =IF(AH49>0,MATCH(AH49,$AF$40:$AF$133,0),"") -> 14 | AJ49: =IF(AI49="","",INDEX($T$40:$T$133,AI49)&" · "&INDEX($AG$40:$AG$133,AI49)) -> 70-30-38-BR-25A · 260370301 | AK49: =IF(AI49="",0,MAX(INDEX($Z$40:$Z$133,AI49),0)) -> 341.7 | AL49: =IF(AI49="",0,MIN(INDEX($Z$40:$Z$133,AI49),0)) -> 0 | AN49: 18/09 | AO49: 46283 | AP49: =IF(AND(AO49>=$F$5,AO49<=$H$5),SUMIFS(Lançamentos!$I$2:$I$607,Lançamentos!$A$2:$A$607,$AO49,Lançamentos!$C$2:$C$607,$R$1,Lançamentos!$D$2:$D$607,$R$2,Lançamentos!$G$2:$G$607,$R$3,Lançamentos!$B$2:$B$607,$R$4),0) -> 0 | AQ49: =IF(AND(AO49>=$F$5,AO49<=$H$5),-SUMIFS(Lançamentos!$J$2:$J$607,Lançamentos!$A$2:$A$607,$AO49,Lançamentos!$C$2:$C$607,$R$1,Lançamentos!$D$2:$D$607,$R$2,Lançamentos!$G$2:$G$607,$R$3,Lançamentos!$B$2:$B$607,$R$4),0) -> -10.8 | AS49: SPLIT-4-M-413 | AV49: =IFERROR(INDEX($AX$1:$AX$94,MATCH(48,$AY$1:$AY$94,0)),"") -> 250880301 | AW49: CHM-SP-Z3L-BR-U73 | AX49: 251880301 | AY49: =IF(OR($A$5="Todos",AW49=$A$5),MAX(AY$1:AY48)+1,0) -> 49
A50: =IF(IFERROR(MATCH(17,$AB$40:$AB$133,0),0)=0,"",INDEX($T$40:$T$133,IFERROR(MATCH(17,$AB$40:$AB$133,0),0))) -> CHK-R30GOLD-BR-25A | B50: =IF(IFERROR(MATCH(17,$AB$40:$AB$133,0),0)=0,"",INDEX($AG$40:$AG$133,IFERROR(MATCH(17,$AB$40:$AB$133,0),0))) -> 253620301 | C50: =IF(IFERROR(MATCH(17,$AB$40:$AB$133,0),0)=0,"",INDEX($U$40:$U$133,IFERROR(MATCH(17,$AB$40:$AB$133,0),0))) -> KG | D50: =IF(IFERROR(MATCH(17,$AB$40:$AB$133,0),0)=0,"",INDEX($V$40:$V$133,IFERROR(MATCH(17,$AB$40:$AB$133,0),0))) -> 0 | E50: =IF(IFERROR(MATCH(17,$AB$40:$AB$133,0),0)=0,"",INDEX($W$40:$W$133,IFERROR(MATCH(17,$AB$40:$AB$133,0),0))) -> 40.2 | F50: =IF(IFERROR(MATCH(17,$AB$40:$AB$133,0),0)=0,"",INDEX($X$40:$X$133,IFERROR(MATCH(17,$AB$40:$AB$133,0),0))) -> 40.2 | G50: =IF(A50="","",E50-F50) -> 0 | H50: =IF(IFERROR(MATCH(17,$AB$40:$AB$133,0),0)=0,"",INDEX($Y$40:$Y$133,IFERROR(MATCH(17,$AB$40:$AB$133,0),0))) -> 116.58 | I50: =IF(IFERROR(MATCH(17,$AB$40:$AB$133,0),0)=0,"",INDEX($Z$40:$Z$133,IFERROR(MATCH(17,$AB$40:$AB$133,0),0))) -> 116.58 | J50: =IF(IFERROR(MATCH(17,$AB$40:$AB$133,0),0)=0,"",INDEX($AC$40:$AC$133,IFERROR(MATCH(17,$AB$40:$AB$133,0),0))) -> Sobrando | K50: =IF(IFERROR(MATCH(17,$AB$40:$AB$133,0),0)=0,"",INDEX($AD$40:$AD$133,IFERROR(MATCH(17,$AB$40:$AB$133,0),0))) -> 3 | L50: =IF(IFERROR(MATCH(17,$AB$40:$AB$133,0),0)=0,"",INDEX($AE$40:$AE$133,IFERROR(MATCH(17,$AB$40:$AB$133,0),0))&"") -> CA MOEDAS 2,01KG/UC 10UC/CX 30CX/PAL | T50: W3-BR-25A | U50: KG | V50: =SUMIFS(Lançamentos!$H$2:$H$607,Lançamentos!$A$2:$A$607,">="&$F$5,Lançamentos!$A$2:$A$607,"<="&$H$5,Lançamentos!$C$2:$C$607,$T50,Lançamentos!$D$2:$D$607,$AG50,Lançamentos!$B$2:$B$607,"Recebido no 2008") -> 20 | W50: =SUMIFS(Lançamentos!$I$2:$I$607,Lançamentos!$A$2:$A$607,">="&$F$5,Lançamentos!$A$2:$A$607,"<="&$H$5,Lançamentos!$C$2:$C$607,$T50,Lançamentos!$D$2:$D$607,$AG50) -> 0 | X50: =SUMIFS(Lançamentos!$J$2:$J$607,Lançamentos!$A$2:$A$607,">="&$F$5,Lançamentos!$A$2:$A$607,"<="&$H$5,Lançamentos!$C$2:$C$607,$T50,Lançamentos!$D$2:$D$607,$AG50) -> 542.7 | Y50: =SUMIFS('Estoque físico'!$J$2:$J$229,'Estoque físico'!$A$2:$A$229,$T50,'Estoque físico'!$B$2:$B$229,$AG50) -> 540.69 | Z50: =ROUND(Y50-(W50-X50),3) -> 1083.39 | AA50: =IF(AND(U50=$R$3,OR($R$1="*",T50=$R$1),OR($R$2="*",AG50=$R$2),ABS(V50)+ABS(W50)+ABS(X50)+ABS(Y50)>0),1,0) -> 1 | AB50: =IF(AA50=1,SUM(AA$40:AA50),"") -> 9 | AC50: =IF(ABS(Z50)<=$R$5,"Confere",IF(Z50>0,"Sobrando","Faltando")) -> Sobrando | AD50: =COUNTIFS(Lançamentos!$A$2:$A$607,">="&$F$5,Lançamentos!$A$2:$A$607,"<="&$H$5,Lançamentos!$C$2:$C$607,$T50,Lançamentos!$D$2:$D$607,$AG50,Lançamentos!$B$2:$B$607,$R$4,Lançamentos!$G$2:$G$607,U50) -> 15 | AE50: CA MOEDAS 2,01KG/UC 10UC/CX 30CX/PAL | AF50: =IF(AND(AA50=1,AC50<>"Confere"),ABS(Z50)+ROW()/10000000,0) -> 1083.39 | AG50: 253540301 | AH50: =LARGE($AF$40:$AF$133,11) -> 273.36001 | AI50: =IF(AH50>0,MATCH(AH50,$AF$40:$AF$133,0),"") -> 15 | AJ50: =IF(AI50="","",INDEX($T$40:$T$133,AI50)&" · "&INDEX($AG$40:$AG$133,AI50)) -> 811-BR-25A · 250880301 | AK50: =IF(AI50="",0,MAX(INDEX($Z$40:$Z$133,AI50),0)) -> 273.36 | AL50: =IF(AI50="",0,MIN(INDEX($Z$40:$Z$133,AI50),0)) -> 0 | AN50: 19/09 | AO50: 46284 | AP50: =IF(AND(AO50>=$F$5,AO50<=$H$5),SUMIFS(Lançamentos!$I$2:$I$607,Lançamentos!$A$2:$A$607,$AO50,Lançamentos!$C$2:$C$607,$R$1,Lançamentos!$D$2:$D$607,$R$2,Lançamentos!$G$2:$G$607,$R$3,Lançamentos!$B$2:$B$607,$R$4),0) -> 0 | AQ50: =IF(AND(AO50>=$F$5,AO50<=$H$5),-SUMIFS(Lançamentos!$J$2:$J$607,Lançamentos!$A$2:$A$607,$AO50,Lançamentos!$C$2:$C$607,$R$1,Lançamentos!$D$2:$D$607,$R$2,Lançamentos!$G$2:$G$607,$R$3,Lançamentos!$B$2:$B$607,$R$4),0) -> -195 | AS50: W2-BR-D94 | AV50: =IFERROR(INDEX($AX$1:$AX$94,MATCH(49,$AY$1:$AY$94,0)),"") -> 251880301 | AW50: CHM-SP-Z3L-E0-U72 | AX50: 253100102 | AY50: =IF(OR($A$5="Todos",AW50=$A$5),MAX(AY$1:AY49)+1,0) -> 50
A51: =IF(IFERROR(MATCH(18,$AB$40:$AB$133,0),0)=0,"",INDEX($T$40:$T$133,IFERROR(MATCH(18,$AB$40:$AB$133,0),0))) -> 823-BR-25A | B51: =IF(IFERROR(MATCH(18,$AB$40:$AB$133,0),0)=0,"",INDEX($AG$40:$AG$133,IFERROR(MATCH(18,$AB$40:$AB$133,0),0))) -> 252900303 | C51: =IF(IFERROR(MATCH(18,$AB$40:$AB$133,0),0)=0,"",INDEX($U$40:$U$133,IFERROR(MATCH(18,$AB$40:$AB$133,0),0))) -> KG | D51: =IF(IFERROR(MATCH(18,$AB$40:$AB$133,0),0)=0,"",INDEX($V$40:$V$133,IFERROR(MATCH(18,$AB$40:$AB$133,0),0))) -> 0 | E51: =IF(IFERROR(MATCH(18,$AB$40:$AB$133,0),0)=0,"",INDEX($W$40:$W$133,IFERROR(MATCH(18,$AB$40:$AB$133,0),0))) -> 3612 | F51: =IF(IFERROR(MATCH(18,$AB$40:$AB$133,0),0)=0,"",INDEX($X$40:$X$133,IFERROR(MATCH(18,$AB$40:$AB$133,0),0))) -> 80.4 | G51: =IF(A51="","",E51-F51) -> 3531.6 | H51: =IF(IFERROR(MATCH(18,$AB$40:$AB$133,0),0)=0,"",INDEX($Y$40:$Y$133,IFERROR(MATCH(18,$AB$40:$AB$133,0),0))) -> 3612 | I51: =IF(IFERROR(MATCH(18,$AB$40:$AB$133,0),0)=0,"",INDEX($Z$40:$Z$133,IFERROR(MATCH(18,$AB$40:$AB$133,0),0))) -> 80.4 | J51: =IF(IFERROR(MATCH(18,$AB$40:$AB$133,0),0)=0,"",INDEX($AC$40:$AC$133,IFERROR(MATCH(18,$AB$40:$AB$133,0),0))) -> Sobrando | K51: =IF(IFERROR(MATCH(18,$AB$40:$AB$133,0),0)=0,"",INDEX($AD$40:$AD$133,IFERROR(MATCH(18,$AB$40:$AB$133,0),0))) -> 8 | L51: =IF(IFERROR(MATCH(18,$AB$40:$AB$133,0),0)=0,"",INDEX($AE$40:$AE$133,IFERROR(MATCH(18,$AB$40:$AB$133,0),0))&"") -> CA MOEDAS 2,01KG/UC 10UC/CX 30CX/PAL | T51: CW2-BR-25A | U51: KG | V51: =SUMIFS(Lançamentos!$H$2:$H$607,Lançamentos!$A$2:$A$607,">="&$F$5,Lançamentos!$A$2:$A$607,"<="&$H$5,Lançamentos!$C$2:$C$607,$T51,Lançamentos!$D$2:$D$607,$AG51,Lançamentos!$B$2:$B$607,"Recebido no 2008") -> 0 | W51: =SUMIFS(Lançamentos!$I$2:$I$607,Lançamentos!$A$2:$A$607,">="&$F$5,Lançamentos!$A$2:$A$607,"<="&$H$5,Lançamentos!$C$2:$C$607,$T51,Lançamentos!$D$2:$D$607,$AG51) -> 763.8 | X51: =SUMIFS(Lançamentos!$J$2:$J$607,Lançamentos!$A$2:$A$607,">="&$F$5,Lançamentos!$A$2:$A$607,"<="&$H$5,Lançamentos!$C$2:$C$607,$T51,Lançamentos!$D$2:$D$607,$AG51) -> 924.6 | Y51: =SUMIFS('Estoque físico'!$J$2:$J$229,'Estoque físico'!$A$2:$A$229,$T51,'Estoque físico'!$B$2:$B$229,$AG51) -> 763.8 | Z51: =ROUND(Y51-(W51-X51),3) -> 924.6 | AA51: =IF(AND(U51=$R$3,OR($R$1="*",T51=$R$1),OR($R$2="*",AG51=$R$2),ABS(V51)+ABS(W51)+ABS(X51)+ABS(Y51)>0),1,0) -> 1 | AB51: =IF(AA51=1,SUM(AA$40:AA51),"") -> 10 | AC51: =IF(ABS(Z51)<=$R$5,"Confere",IF(Z51>0,"Sobrando","Faltando")) -> Sobrando | AD51: =COUNTIFS(Lançamentos!$A$2:$A$607,">="&$F$5,Lançamentos!$A$2:$A$607,"<="&$H$5,Lançamentos!$C$2:$C$607,$T51,Lançamentos!$D$2:$D$607,$AG51,Lançamentos!$B$2:$B$607,$R$4,Lançamentos!$G$2:$G$607,U51) -> 12 | AE51: CA MOEDAS 2,01KG/UC 10UC/CX 30CX/PAL | AF51: =IF(AND(AA51=1,AC51<>"Confere"),ABS(Z51)+ROW()/10000000,0) -> 924.60001 | AG51: 253470301 | AH51: =LARGE($AF$40:$AF$133,12) -> 261.12 | AI51: =IF(AH51>0,MATCH(AH51,$AF$40:$AF$133,0),"") -> 2 | AJ51: =IF(AI51="","",INDEX($T$40:$T$133,AI51)&" · "&INDEX($AG$40:$AG$133,AI51)) -> CHM-TS-P23-E0-999 · 2605567696 | AK51: =IF(AI51="",0,MAX(INDEX($Z$40:$Z$133,AI51),0)) -> 0 | AL51: =IF(AI51="",0,MIN(INDEX($Z$40:$Z$133,AI51),0)) -> -261.12 | AN51: 20/09 | AO51: 46285 | AP51: =IF(AND(AO51>=$F$5,AO51<=$H$5),SUMIFS(Lançamentos!$I$2:$I$607,Lançamentos!$A$2:$A$607,$AO51,Lançamentos!$C$2:$C$607,$R$1,Lançamentos!$D$2:$D$607,$R$2,Lançamentos!$G$2:$G$607,$R$3,Lançamentos!$B$2:$B$607,$R$4),0) -> 0 | AQ51: =IF(AND(AO51>=$F$5,AO51<=$H$5),-SUMIFS(Lançamentos!$J$2:$J$607,Lançamentos!$A$2:$A$607,$AO51,Lançamentos!$C$2:$C$607,$R$1,Lançamentos!$D$2:$D$607,$R$2,Lançamentos!$G$2:$G$607,$R$3,Lançamentos!$B$2:$B$607,$R$4),0) -> -302.7 | AS51: W3-BR-25A | AV51: =IFERROR(INDEX($AX$1:$AX$94,MATCH(50,$AY$1:$AY$94,0)),"") -> 253100102 | AW51: CHM-SP-Z3L-E0-U72 | AX51: 260580101 | AY51: =IF(OR($A$5="Todos",AW51=$A$5),MAX(AY$1:AY50)+1,0) -> 51
A52: =IF(IFERROR(MATCH(19,$AB$40:$AB$133,0),0)=0,"",INDEX($T$40:$T$133,IFERROR(MATCH(19,$AB$40:$AB$133,0),0))) -> CHK-R30GOLD-E0-D94 | B52: =IF(IFERROR(MATCH(19,$AB$40:$AB$133,0),0)=0,"",INDEX($AG$40:$AG$133,IFERROR(MATCH(19,$AB$40:$AB$133,0),0))) -> 260720939 | C52: =IF(IFERROR(MATCH(19,$AB$40:$AB$133,0),0)=0,"",INDEX($U$40:$U$133,IFERROR(MATCH(19,$AB$40:$AB$133,0),0))) -> KG | D52: =IF(IFERROR(MATCH(19,$AB$40:$AB$133,0),0)=0,"",INDEX($V$40:$V$133,IFERROR(MATCH(19,$AB$40:$AB$133,0),0))) -> 0 | E52: =IF(IFERROR(MATCH(19,$AB$40:$AB$133,0),0)=0,"",INDEX($W$40:$W$133,IFERROR(MATCH(19,$AB$40:$AB$133,0),0))) -> 806.4 | F52: =IF(IFERROR(MATCH(19,$AB$40:$AB$133,0),0)=0,"",INDEX($X$40:$X$133,IFERROR(MATCH(19,$AB$40:$AB$133,0),0))) -> 53.2 | G52: =IF(A52="","",E52-F52) -> 753.2 | H52: =IF(IFERROR(MATCH(19,$AB$40:$AB$133,0),0)=0,"",INDEX($Y$40:$Y$133,IFERROR(MATCH(19,$AB$40:$AB$133,0),0))) -> 825.999 | I52: =IF(IFERROR(MATCH(19,$AB$40:$AB$133,0),0)=0,"",INDEX($Z$40:$Z$133,IFERROR(MATCH(19,$AB$40:$AB$133,0),0))) -> 72.799 | J52: =IF(IFERROR(MATCH(19,$AB$40:$AB$133,0),0)=0,"",INDEX($AC$40:$AC$133,IFERROR(MATCH(19,$AB$40:$AB$133,0),0))) -> Sobrando | K52: =IF(IFERROR(MATCH(19,$AB$40:$AB$133,0),0)=0,"",INDEX($AD$40:$AD$133,IFERROR(MATCH(19,$AB$40:$AB$133,0),0))) -> 7 | L52: =IF(IFERROR(MATCH(19,$AB$40:$AB$133,0),0)=0,"",INDEX($AE$40:$AE$133,IFERROR(MATCH(19,$AB$40:$AB$133,0),0))&"") -> CA CALLETS 0.4KG/UC 7UC/BOX 144BOX/PAL | T52: CHP-20SICHP-760 | U52: KG | V52: =SUMIFS(Lançamentos!$H$2:$H$607,Lançamentos!$A$2:$A$607,">="&$F$5,Lançamentos!$A$2:$A$607,"<="&$H$5,Lançamentos!$C$2:$C$607,$T52,Lançamentos!$D$2:$D$607,$AG52,Lançamentos!$B$2:$B$607,"Recebido no 2008") -> 0 | W52: =SUMIFS(Lançamentos!$I$2:$I$607,Lançamentos!$A$2:$A$607,">="&$F$5,Lançamentos!$A$2:$A$607,"<="&$H$5,Lançamentos!$C$2:$C$607,$T52,Lançamentos!$D$2:$D$607,$AG52) -> 918 | X52: =SUMIFS(Lançamentos!$J$2:$J$607,Lançamentos!$A$2:$A$607,">="&$F$5,Lançamentos!$A$2:$A$607,"<="&$H$5,Lançamentos!$C$2:$C$607,$T52,Lançamentos!$D$2:$D$607,$AG52) -> 186 | Y52: =SUMIFS('Estoque físico'!$J$2:$J$229,'Estoque físico'!$A$2:$A$229,$T52,'Estoque físico'!$B$2:$B$229,$AG52) -> 1272 | Z52: =ROUND(Y52-(W52-X52),3) -> 540 | AA52: =IF(AND(U52=$R$3,OR($R$1="*",T52=$R$1),OR($R$2="*",AG52=$R$2),ABS(V52)+ABS(W52)+ABS(X52)+ABS(Y52)>0),1,0) -> 1 | AB52: =IF(AA52=1,SUM(AA$40:AA52),"") -> 11 | AC52: =IF(ABS(Z52)<=$R$5,"Confere",IF(Z52>0,"Sobrando","Faltando")) -> Sobrando | AD52: =COUNTIFS(Lançamentos!$A$2:$A$607,">="&$F$5,Lançamentos!$A$2:$A$607,"<="&$H$5,Lançamentos!$C$2:$C$607,$T52,Lançamentos!$D$2:$D$607,$AG52,Lançamentos!$B$2:$B$607,$R$4,Lançamentos!$G$2:$G$607,U52) -> 13 | AE52: CA SILKY CHOCO POWDER POWDER 1KG/UC | AF52: =IF(AND(AA52=1,AC52<>"Confere"),ABS(Z52)+ROW()/10000000,0) -> 540.00001 | AG52: 252843369 | AN52: 21/09 | AO52: 46286 | AP52: =IF(AND(AO52>=$F$5,AO52<=$H$5),SUMIFS(Lançamentos!$I$2:$I$607,Lançamentos!$A$2:$A$607,$AO52,Lançamentos!$C$2:$C$607,$R$1,Lançamentos!$D$2:$D$607,$R$2,Lançamentos!$G$2:$G$607,$R$3,Lançamentos!$B$2:$B$607,$R$4),0) -> 918 | AQ52: =IF(AND(AO52>=$F$5,AO52<=$H$5),-SUMIFS(Lançamentos!$J$2:$J$607,Lançamentos!$A$2:$A$607,$AO52,Lançamentos!$C$2:$C$607,$R$1,Lançamentos!$D$2:$D$607,$R$2,Lançamentos!$G$2:$G$607,$R$3,Lançamentos!$B$2:$B$607,$R$4),0) -> -278.5 | AV52: =IFERROR(INDEX($AX$1:$AX$94,MATCH(51,$AY$1:$AY$94,0)),"") -> 260580101 | AW52: CHM-TS-22351E0-999 | AX52: 2522444420 | AY52: =IF(OR($A$5="Todos",AW52=$A$5),MAX(AY$1:AY51)+1,0) -> 52
A53: =IF(IFERROR(MATCH(20,$AB$40:$AB$133,0),0)=0,"",INDEX($T$40:$T$133,IFERROR(MATCH(20,$AB$40:$AB$133,0),0))) -> CHM-CU-7X80-E5-U70 | B53: =IF(IFERROR(MATCH(20,$AB$40:$AB$133,0),0)=0,"",INDEX($AG$40:$AG$133,IFERROR(MATCH(20,$AB$40:$AB$133,0),0))) -> 2528749307 | C53: =IF(IFERROR(MATCH(20,$AB$40:$AB$133,0),0)=0,"",INDEX($U$40:$U$133,IFERROR(MATCH(20,$AB$40:$AB$133,0),0))) -> KG | D53: =IF(IFERROR(MATCH(20,$AB$40:$AB$133,0),0)=0,"",INDEX($V$40:$V$133,IFERROR(MATCH(20,$AB$40:$AB$133,0),0))) -> 0 | E53: =IF(IFERROR(MATCH(20,$AB$40:$AB$133,0),0)=0,"",INDEX($W$40:$W$133,IFERROR(MATCH(20,$AB$40:$AB$133,0),0))) -> 10 | F53: =IF(IFERROR(MATCH(20,$AB$40:$AB$133,0),0)=0,"",INDEX($X$40:$X$133,IFERROR(MATCH(20,$AB$40:$AB$133,0),0))) -> 60 | G53: =IF(A53="","",E53-F53) -> -50 | H53: =IF(IFERROR(MATCH(20,$AB$40:$AB$133,0),0)=0,"",INDEX($Y$40:$Y$133,IFERROR(MATCH(20,$AB$40:$AB$133,0),0))) -> 10 | I53: =IF(IFERROR(MATCH(20,$AB$40:$AB$133,0),0)=0,"",INDEX($Z$40:$Z$133,IFERROR(MATCH(20,$AB$40:$AB$133,0),0))) -> 60 | J53: =IF(IFERROR(MATCH(20,$AB$40:$AB$133,0),0)=0,"",INDEX($AC$40:$AC$133,IFERROR(MATCH(20,$AB$40:$AB$133,0),0))) -> Sobrando | K53: =IF(IFERROR(MATCH(20,$AB$40:$AB$133,0),0)=0,"",INDEX($AD$40:$AD$133,IFERROR(MATCH(20,$AB$40:$AB$133,0),0))) -> 3 | L53: =IF(IFERROR(MATCH(20,$AB$40:$AB$133,0),0)=0,"",INDEX($AE$40:$AE$133,IFERROR(MATCH(20,$AB$40:$AB$133,0),0))&"") -> CA CHOCOCUBES CHUNKS 700CT/KG 2.5KG/UC | T53: 70-30-38-BR-25A | U53: KG | V53: =SUMIFS(Lançamentos!$H$2:$H$607,Lançamentos!$A$2:$A$607,">="&$F$5,Lançamentos!$A$2:$A$607,"<="&$H$5,Lançamentos!$C$2:$C$607,$T53,Lançamentos!$D$2:$D$607,$AG53,Lançamentos!$B$2:$B$607,"Recebido no 2008") -> 6633 | W53: =SUMIFS(Lançamentos!$I$2:$I$607,Lançamentos!$A$2:$A$607,">="&$F$5,Lançamentos!$A$2:$A$607,"<="&$H$5,Lançamentos!$C$2:$C$607,$T53,Lançamentos!$D$2:$D$607,$AG53) -> 603 | X53: =SUMIFS(Lançamentos!$J$2:$J$607,Lançamentos!$A$2:$A$607,">="&$F$5,Lançamentos!$A$2:$A$607,"<="&$H$5,Lançamentos!$C$2:$C$607,$T53,Lançamentos!$D$2:$D$607,$AG53) -> 321.6 | Y53: =SUMIFS('Estoque físico'!$J$2:$J$229,'Estoque físico'!$A$2:$A$229,$T53,'Estoque físico'!$B$2:$B$229,$AG53) -> 623.1 | Z53: =ROUND(Y53-(W53-X53),3) -> 341.7 | AA53: =IF(AND(U53=$R$3,OR($R$1="*",T53=$R$1),OR($R$2="*",AG53=$R$2),ABS(V53)+ABS(W53)+ABS(X53)+ABS(Y53)>0),1,0) -> 1 | AB53: =IF(AA53=1,SUM(AA$40:AA53),"") -> 12 | AC53: =IF(ABS(Z53)<=$R$5,"Confere",IF(Z53>0,"Sobrando","Faltando")) -> Sobrando | AD53: =COUNTIFS(Lançamentos!$A$2:$A$607,">="&$F$5,Lançamentos!$A$2:$A$607,"<="&$H$5,Lançamentos!$C$2:$C$607,$T53,Lançamentos!$D$2:$D$607,$AG53,Lançamentos!$B$2:$B$607,$R$4,Lançamentos!$G$2:$G$607,U53) -> 13 | AE53: CA MOEDAS 2,01KG/UC 10UC/CX 30CX/PAL | AF53: =IF(AND(AA53=1,AC53<>"Confere"),ABS(Z53)+ROW()/10000000,0) -> 341.70001 | AG53: 260370301 | AN53: 22/09 | AO53: 46287 | AP53: =IF(AND(AO53>=$F$5,AO53<=$H$5),SUMIFS(Lançamentos!$I$2:$I$607,Lançamentos!$A$2:$A$607,$AO53,Lançamentos!$C$2:$C$607,$R$1,Lançamentos!$D$2:$D$607,$R$2,Lançamentos!$G$2:$G$607,$R$3,Lançamentos!$B$2:$B$607,$R$4),0) -> 0 | AQ53: =IF(AND(AO53>=$F$5,AO53<=$H$5),-SUMIFS(Lançamentos!$J$2:$J$607,Lançamentos!$A$2:$A$607,$AO53,Lançamentos!$C$2:$C$607,$R$1,Lançamentos!$D$2:$D$607,$R$2,Lançamentos!$G$2:$G$607,$R$3,Lançamentos!$B$2:$B$607,$R$4),0) -> -120.1 | AV53: =IFERROR(INDEX($AX$1:$AX$94,MATCH(52,$AY$1:$AY$94,0)),"") -> 2522444420 | AW53: CHM-TS-22351E0-999 | AX53: 2525950306 | AY53: =IF(OR($A$5="Todos",AW53=$A$5),MAX(AY$1:AY52)+1,0) -> 53
A54: =IF(IFERROR(MATCH(21,$AB$40:$AB$133,0),0)=0,"",INDEX($T$40:$T$133,IFERROR(MATCH(21,$AB$40:$AB$133,0),0))) -> CW2-BR-25A | B54: =IF(IFERROR(MATCH(21,$AB$40:$AB$133,0),0)=0,"",INDEX($AG$40:$AG$133,IFERROR(MATCH(21,$AB$40:$AB$133,0),0))) -> 252350301 | C54: =IF(IFERROR(MATCH(21,$AB$40:$AB$133,0),0)=0,"",INDEX($U$40:$U$133,IFERROR(MATCH(21,$AB$40:$AB$133,0),0))) -> KG | D54: =IF(IFERROR(MATCH(21,$AB$40:$AB$133,0),0)=0,"",INDEX($V$40:$V$133,IFERROR(MATCH(21,$AB$40:$AB$133,0),0))) -> 0 | E54: =IF(IFERROR(MATCH(21,$AB$40:$AB$133,0),0)=0,"",INDEX($W$40:$W$133,IFERROR(MATCH(21,$AB$40:$AB$133,0),0))) -> 602.9 | F54: =IF(IFERROR(MATCH(21,$AB$40:$AB$133,0),0)=0,"",INDEX($X$40:$X$133,IFERROR(MATCH(21,$AB$40:$AB$133,0),0))) -> 301.5 | G54: =IF(A54="","",E54-F54) -> 301.4 | H54: =IF(IFERROR(MATCH(21,$AB$40:$AB$133,0),0)=0,"",INDEX($Y$40:$Y$133,IFERROR(MATCH(21,$AB$40:$AB$133,0),0))) -> 321.5 | I54: =IF(IFERROR(MATCH(21,$AB$40:$AB$133,0),0)=0,"",INDEX($Z$40:$Z$133,IFERROR(MATCH(21,$AB$40:$AB$133,0),0))) -> 20.1 | J54: =IF(IFERROR(MATCH(21,$AB$40:$AB$133,0),0)=0,"",INDEX($AC$40:$AC$133,IFERROR(MATCH(21,$AB$40:$AB$133,0),0))) -> Sobrando | K54: =IF(IFERROR(MATCH(21,$AB$40:$AB$133,0),0)=0,"",INDEX($AD$40:$AD$133,IFERROR(MATCH(21,$AB$40:$AB$133,0),0))) -> 5 | L54: =IF(IFERROR(MATCH(21,$AB$40:$AB$133,0),0)=0,"",INDEX($AE$40:$AE$133,IFERROR(MATCH(21,$AB$40:$AB$133,0),0))&"") -> CA MOEDAS 2,01KG/UC 10UC/CX 30CX/PAL | T54: 811-BR-25A | U54: KG | V54: =SUMIFS(Lançamentos!$H$2:$H$607,Lançamentos!$A$2:$A$607,">="&$F$5,Lançamentos!$A$2:$A$607,"<="&$H$5,Lançamentos!$C$2:$C$607,$T54,Lançamentos!$D$2:$D$607,$AG54,Lançamentos!$B$2:$B$607,"Recebido no 2008") -> 0 | W54: =SUMIFS(Lançamentos!$I$2:$I$607,Lançamentos!$A$2:$A$607,">="&$F$5,Lançamentos!$A$2:$A$607,"<="&$H$5,Lançamentos!$C$2:$C$607,$T54,Lançamentos!$D$2:$D$607,$AG54) -> 180.9 | X54: =SUMIFS(Lançamentos!$J$2:$J$607,Lançamentos!$A$2:$A$607,">="&$F$5,Lançamentos!$A$2:$A$607,"<="&$H$5,Lançamentos!$C$2:$C$607,$T54,Lançamentos!$D$2:$D$607,$AG54) -> 180.9 | Y54: =SUMIFS('Estoque físico'!$J$2:$J$229,'Estoque físico'!$A$2:$A$229,$T54,'Estoque físico'!$B$2:$B$229,$AG54) -> 273.36 | Z54: =ROUND(Y54-(W54-X54),3) -> 273.36 | AA54: =IF(AND(U54=$R$3,OR($R$1="*",T54=$R$1),OR($R$2="*",AG54=$R$2),ABS(V54)+ABS(W54)+ABS(X54)+ABS(Y54)>0),1,0) -> 1 | AB54: =IF(AA54=1,SUM(AA$40:AA54),"") -> 13 | AC54: =IF(ABS(Z54)<=$R$5,"Confere",IF(Z54>0,"Sobrando","Faltando")) -> Sobrando | AD54: =COUNTIFS(Lançamentos!$A$2:$A$607,">="&$F$5,Lançamentos!$A$2:$A$607,"<="&$H$5,Lançamentos!$C$2:$C$607,$T54,Lançamentos!$D$2:$D$607,$AG54,Lançamentos!$B$2:$B$607,$R$4,Lançamentos!$G$2:$G$607,U54) -> 5 | AE54: CA MOEDAS 2,01KG/UC 10UC/CX 30CX/PAL | AF54: =IF(AND(AA54=1,AC54<>"Confere"),ABS(Z54)+ROW()/10000000,0) -> 273.36001 | AG54: 250880301 | AN54: 23/09 | AO54: 46288 | AP54: =IF(AND(AO54>=$F$5,AO54<=$H$5),SUMIFS(Lançamentos!$I$2:$I$607,Lançamentos!$A$2:$A$607,$AO54,Lançamentos!$C$2:$C$607,$R$1,Lançamentos!$D$2:$D$607,$R$2,Lançamentos!$G$2:$G$607,$R$3,Lançamentos!$B$2:$B$607,$R$4),0) -> 6467.92 | AQ54: =IF(AND(AO54>=$F$5,AO54<=$H$5),-SUMIFS(Lançamentos!$J$2:$J$607,Lançamentos!$A$2:$A$607,$AO54,Lançamentos!$C$2:$C$607,$R$1,Lançamentos!$D$2:$D$607,$R$2,Lançamentos!$G$2:$G$607,$R$3,Lançamentos!$B$2:$B$607,$R$4),0) -> -134.5 | AV54: =IFERROR(INDEX($AX$1:$AX$94,MATCH(53,$AY$1:$AY$94,0)),"") -> 2525950306 | AW54: CHM-TS-22351E0-999 | AX54: 2526050307 | AY54: =IF(OR($A$5="Todos",AW54=$A$5),MAX(AY$1:AY53)+1,0) -> 54
A55: =IF(IFERROR(MATCH(22,$AB$40:$AB$133,0),0)=0,"",INDEX($T$40:$T$133,IFERROR(MATCH(22,$AB$40:$AB$133,0),0))) -> 811-BR-25A | B55: =IF(IFERROR(MATCH(22,$AB$40:$AB$133,0),0)=0,"",INDEX($AG$40:$AG$133,IFERROR(MATCH(22,$AB$40:$AB$133,0),0))) -> 252450301 | C55: =IF(IFERROR(MATCH(22,$AB$40:$AB$133,0),0)=0,"",INDEX($U$40:$U$133,IFERROR(MATCH(22,$AB$40:$AB$133,0),0))) -> KG | D55: =IF(IFERROR(MATCH(22,$AB$40:$AB$133,0),0)=0,"",INDEX($V$40:$V$133,IFERROR(MATCH(22,$AB$40:$AB$133,0),0))) -> 0 | E55: =IF(IFERROR(MATCH(22,$AB$40:$AB$133,0),0)=0,"",INDEX($W$40:$W$133,IFERROR(MATCH(22,$AB$40:$AB$133,0),0))) -> 2733.6 | F55: =IF(IFERROR(MATCH(22,$AB$40:$AB$133,0),0)=0,"",INDEX($X$40:$X$133,IFERROR(MATCH(22,$AB$40:$AB$133,0),0))) -> 1206 | G55: =IF(A55="","",E55-F55) -> 1527.6 | H55: =IF(IFERROR(MATCH(22,$AB$40:$AB$133,0),0)=0,"",INDEX($Y$40:$Y$133,IFERROR(MATCH(22,$AB$40:$AB$133,0),0))) -> 1547.7 | I55: =IF(IFERROR(MATCH(22,$AB$40:$AB$133,0),0)=0,"",INDEX($Z$40:$Z$133,IFERROR(MATCH(22,$AB$40:$AB$133,0),0))) -> 20.1 | J55: =IF(IFERROR(MATCH(22,$AB$40:$AB$133,0),0)=0,"",INDEX($AC$40:$AC$133,IFERROR(MATCH(22,$AB$40:$AB$133,0),0))) -> Sobrando | K55: =IF(IFERROR(MATCH(22,$AB$40:$AB$133,0),0)=0,"",INDEX($AD$40:$AD$133,IFERROR(MATCH(22,$AB$40:$AB$133,0),0))) -> 7 | L55: =IF(IFERROR(MATCH(22,$AB$40:$AB$133,0),0)=0,"",INDEX($AE$40:$AE$133,IFERROR(MATCH(22,$AB$40:$AB$133,0),0))&"") -> CA MOEDAS 2,01KG/UC 10UC/CX 30CX/PAL | T55: CHM-BS-9U15-E0-07B | U55: KG | V55: =SUMIFS(Lançamentos!$H$2:$H$607,Lançamentos!$A$2:$A$607,">="&$F$5,Lançamentos!$A$2:$A$607,"<="&$H$5,Lançamentos!$C$2:$C$607,$T55,Lançamentos!$D$2:$D$607,$AG55,Lançamentos!$B$2:$B$607,"Recebido no 2008") -> 1920 | W55: =SUMIFS(Lançamentos!$I$2:$I$607,Lançamentos!$A$2:$A$607,">="&$F$5,Lançamentos!$A$2:$A$607,"<="&$H$5,Lançamentos!$C$2:$C$607,$T55,Lançamentos!$D$2:$D$607,$AG55) -> 960 | X55: =SUMIFS(Lançamentos!$J$2:$J$607,Lançamentos!$A$2:$A$607,">="&$F$5,Lançamentos!$A$2:$A$607,"<="&$H$5,Lançamentos!$C$2:$C$607,$T55,Lançamentos!$D$2:$D$607,$AG55) -> 176 | Y55: =SUMIFS('Estoque físico'!$J$2:$J$229,'Estoque físico'!$A$2:$A$229,$T55,'Estoque físico'!$B$2:$B$229,$AG55) -> 1032 | Z55: =ROUND(Y55-(W55-X55),3) -> 248 | AA55: =IF(AND(U55=$R$3,OR($R$1="*",T55=$R$1),OR($R$2="*",AG55=$R$2),ABS(V55)+ABS(W55)+ABS(X55)+ABS(Y55)>0),1,0) -> 1 | AB55: =IF(AA55=1,SUM(AA$40:AA55),"") -> 14 | AC55: =IF(ABS(Z55)<=$R$5,"Confere",IF(Z55>0,"Sobrando","Faltando")) -> Sobrando | AD55: =COUNTIFS(Lançamentos!$A$2:$A$607,">="&$F$5,Lançamentos!$A$2:$A$607,"<="&$H$5,Lançamentos!$C$2:$C$607,$T55,Lançamentos!$D$2:$D$607,$AG55,Lançamentos!$B$2:$B$607,$R$4,Lançamentos!$G$2:$G$607,U55) -> 20 | AE55: CA MILK BLOSSOMS BLOSSOMS 1KG/UC 4UC/BOX | AF55: =IF(AND(AA55=1,AC55<>"Confere"),ABS(Z55)+ROW()/10000000,0) -> 248.00001 | AG55: 260701069 | AN55: 24/09 | AO55: 46289 | AP55: =IF(AND(AO55>=$F$5,AO55<=$H$5),SUMIFS(Lançamentos!$I$2:$I$607,Lançamentos!$A$2:$A$607,$AO55,Lançamentos!$C$2:$C$607,$R$1,Lançamentos!$D$2:$D$607,$R$2,Lançamentos!$G$2:$G$607,$R$3,Lançamentos!$B$2:$B$607,$R$4),0) -> 17483.8 | AQ55: =IF(AND(AO55>=$F$5,AO55<=$H$5),-SUMIFS(Lançamentos!$J$2:$J$607,Lançamentos!$A$2:$A$607,$AO55,Lançamentos!$C$2:$C$607,$R$1,Lançamentos!$D$2:$D$607,$R$2,Lançamentos!$G$2:$G$607,$R$3,Lançamentos!$B$2:$B$607,$R$4),0) -> -310.1 | AV55: =IFERROR(INDEX($AX$1:$AX$94,MATCH(54,$AY$1:$AY$94,0)),"") -> 2526050307 | AW55: CHM-TS-P23-E0-999 | AX55: 2605567696 | AY55: =IF(OR($A$5="Todos",AW55=$A$5),MAX(AY$1:AY54)+1,0) -> 55
A56: =IF(IFERROR(MATCH(23,$AB$40:$AB$133,0),0)=0,"",INDEX($T$40:$T$133,IFERROR(MATCH(23,$AB$40:$AB$133,0),0))) -> W3-BR-25A | B56: =IF(IFERROR(MATCH(23,$AB$40:$AB$133,0),0)=0,"",INDEX($AG$40:$AG$133,IFERROR(MATCH(23,$AB$40:$AB$133,0),0))) -> 261080301 | C56: =IF(IFERROR(MATCH(23,$AB$40:$AB$133,0),0)=0,"",INDEX($U$40:$U$133,IFERROR(MATCH(23,$AB$40:$AB$133,0),0))) -> KG | D56: =IF(IFERROR(MATCH(23,$AB$40:$AB$133,0),0)=0,"",INDEX($V$40:$V$133,IFERROR(MATCH(23,$AB$40:$AB$133,0),0))) -> 2995 | E56: =IF(IFERROR(MATCH(23,$AB$40:$AB$133,0),0)=0,"",INDEX($W$40:$W$133,IFERROR(MATCH(23,$AB$40:$AB$133,0),0))) -> 3025.7 | F56: =IF(IFERROR(MATCH(23,$AB$40:$AB$133,0),0)=0,"",INDEX($X$40:$X$133,IFERROR(MATCH(23,$AB$40:$AB$133,0),0))) -> 1366.8 | G56: =IF(A56="","",E56-F56) -> 1658.9 | H56: =IF(IFERROR(MATCH(23,$AB$40:$AB$133,0),0)=0,"",INDEX($Y$40:$Y$133,IFERROR(MATCH(23,$AB$40:$AB$133,0),0))) -> 1679 | I56: =IF(IFERROR(MATCH(23,$AB$40:$AB$133,0),0)=0,"",INDEX($Z$40:$Z$133,IFERROR(MATCH(23,$AB$40:$AB$133,0),0))) -> 20.1 | J56: =IF(IFERROR(MATCH(23,$AB$40:$AB$133,0),0)=0,"",INDEX($AC$40:$AC$133,IFERROR(MATCH(23,$AB$40:$AB$133,0),0))) -> Sobrando | K56: =IF(IFERROR(MATCH(23,$AB$40:$AB$133,0),0)=0,"",INDEX($AD$40:$AD$133,IFERROR(MATCH(23,$AB$40:$AB$133,0),0))) -> 18 | L56: =IF(IFERROR(MATCH(23,$AB$40:$AB$133,0),0)=0,"",INDEX($AE$40:$AE$133,IFERROR(MATCH(23,$AB$40:$AB$133,0),0))&"") -> CA MOEDAS 2,01KG/UC 10UC/CX 30CX/PAL | T56: 70-30-38-BR-D94 | U56: KG | V56: =SUMIFS(Lançamentos!$H$2:$H$607,Lançamentos!$A$2:$A$607,">="&$F$5,Lançamentos!$A$2:$A$607,"<="&$H$5,Lançamentos!$C$2:$C$607,$T56,Lançamentos!$D$2:$D$607,$AG56,Lançamentos!$B$2:$B$607,"Recebido no 2008") -> 0 | W56: =SUMIFS(Lançamentos!$I$2:$I$607,Lançamentos!$A$2:$A$607,">="&$F$5,Lançamentos!$A$2:$A$607,"<="&$H$5,Lançamentos!$C$2:$C$607,$T56,Lançamentos!$D$2:$D$607,$AG56) -> 940.8 | X56: =SUMIFS(Lançamentos!$J$2:$J$607,Lançamentos!$A$2:$A$607,">="&$F$5,Lançamentos!$A$2:$A$607,"<="&$H$5,Lançamentos!$C$2:$C$607,$T56,Lançamentos!$D$2:$D$607,$AG56) -> 781.2 | Y56: =SUMIFS('Estoque físico'!$J$2:$J$229,'Estoque físico'!$A$2:$A$229,$T56,'Estoque físico'!$B$2:$B$229,$AG56) -> 333.2 | Z56: =ROUND(Y56-(W56-X56),3) -> 173.6 | AA56: =IF(AND(U56=$R$3,OR($R$1="*",T56=$R$1),OR($R$2="*",AG56=$R$2),ABS(V56)+ABS(W56)+ABS(X56)+ABS(Y56)>0),1,0) -> 1 | AB56: =IF(AA56=1,SUM(AA$40:AA56),"") -> 15 | AC56: =IF(ABS(Z56)<=$R$5,"Confere",IF(Z56>0,"Sobrando","Faltando")) -> Sobrando | AD56: =COUNTIFS(Lançamentos!$A$2:$A$607,">="&$F$5,Lançamentos!$A$2:$A$607,"<="&$H$5,Lançamentos!$C$2:$C$607,$T56,Lançamentos!$D$2:$D$607,$AG56,Lançamentos!$B$2:$B$607,$R$4,Lançamentos!$G$2:$G$607,U56) -> 26 | AE56: CA MOEDAS 0,4KG/UC 7UC/CX 144CX/PAL | AF56: =IF(AND(AA56=1,AC56<>"Confere"),ABS(Z56)+ROW()/10000000,0) -> 173.60001 | AG56: 253213449 | AN56: 25/09 | AO56: 46290 | AP56: =IF(AND(AO56>=$F$5,AO56<=$H$5),SUMIFS(Lançamentos!$I$2:$I$607,Lançamentos!$A$2:$A$607,$AO56,Lançamentos!$C$2:$C$607,$R$1,Lançamentos!$D$2:$D$607,$R$2,Lançamentos!$G$2:$G$607,$R$3,Lançamentos!$B$2:$B$607,$R$4),0) -> 0 | AQ56: =IF(AND(AO56>=$F$5,AO56<=$H$5),-SUMIFS(Lançamentos!$J$2:$J$607,Lançamentos!$A$2:$A$607,$AO56,Lançamentos!$C$2:$C$607,$R$1,Lançamentos!$D$2:$D$607,$R$2,Lançamentos!$G$2:$G$607,$R$3,Lançamentos!$B$2:$B$607,$R$4),0) -> -4832.1 | AV56: =IFERROR(INDEX($AX$1:$AX$94,MATCH(55,$AY$1:$AY$94,0)),"") -> 2605567696 | AW56: CHM-VR-Z3S-E0-U68 | AX56: 260400301 | AY56: =IF(OR($A$5="Todos",AW56=$A$5),MAX(AY$1:AY55)+1,0) -> 56
A57: =IF(IFERROR(MATCH(24,$AB$40:$AB$133,0),0)=0,"",INDEX($T$40:$T$133,IFERROR(MATCH(24,$AB$40:$AB$133,0),0))) -> 2665-E4-U71 | B57: =IF(IFERROR(MATCH(24,$AB$40:$AB$133,0),0)=0,"",INDEX($AG$40:$AG$133,IFERROR(MATCH(24,$AB$40:$AB$133,0),0))) -> 252800202 | C57: =IF(IFERROR(MATCH(24,$AB$40:$AB$133,0),0)=0,"",INDEX($U$40:$U$133,IFERROR(MATCH(24,$AB$40:$AB$133,0),0))) -> KG | D57: =IF(IFERROR(MATCH(24,$AB$40:$AB$133,0),0)=0,"",INDEX($V$40:$V$133,IFERROR(MATCH(24,$AB$40:$AB$133,0),0))) -> 0 | E57: =IF(IFERROR(MATCH(24,$AB$40:$AB$133,0),0)=0,"",INDEX($W$40:$W$133,IFERROR(MATCH(24,$AB$40:$AB$133,0),0))) -> 1200 | F57: =IF(IFERROR(MATCH(24,$AB$40:$AB$133,0),0)=0,"",INDEX($X$40:$X$133,IFERROR(MATCH(24,$AB$40:$AB$133,0),0))) -> 0 | G57: =IF(A57="","",E57-F57) -> 1200 | H57: =IF(IFERROR(MATCH(24,$AB$40:$AB$133,0),0)=0,"",INDEX($Y$40:$Y$133,IFERROR(MATCH(24,$AB$40:$AB$133,0),0))) -> 1200 | I57: =IF(IFERROR(MATCH(24,$AB$40:$AB$133,0),0)=0,"",INDEX($Z$40:$Z$133,IFERROR(MATCH(24,$AB$40:$AB$133,0),0))) -> 0 | J57: =IF(IFERROR(MATCH(24,$AB$40:$AB$133,0),0)=0,"",INDEX($AC$40:$AC$133,IFERROR(MATCH(24,$AB$40:$AB$133,0),0))) -> Confere | K57: =IF(IFERROR(MATCH(24,$AB$40:$AB$133,0),0)=0,"",INDEX($AD$40:$AD$133,IFERROR(MATCH(24,$AB$40:$AB$133,0),0))) -> 2 | L57: =IF(IFERROR(MATCH(24,$AB$40:$AB$133,0),0)=0,"",INDEX($AE$40:$AE$133,IFERROR(MATCH(24,$AB$40:$AB$133,0),0))&"") | T57: CW2-BR-25A | U57: KG | V57: =SUMIFS(Lançamentos!$H$2:$H$607,Lançamentos!$A$2:$A$607,">="&$F$5,Lançamentos!$A$2:$A$607,"<="&$H$5,Lançamentos!$C$2:$C$607,$T57,Lançamentos!$D$2:$D$607,$AG57,Lançamentos!$B$2:$B$607,"Recebido no 2008") -> 40 | W57: =SUMIFS(Lançamentos!$I$2:$I$607,Lançamentos!$A$2:$A$607,">="&$F$5,Lançamentos!$A$2:$A$607,"<="&$H$5,Lançamentos!$C$2:$C$607,$T57,Lançamentos!$D$2:$D$607,$AG57) -> 2271.3 | X57: =SUMIFS(Lançamentos!$J$2:$J$607,Lançamentos!$A$2:$A$607,">="&$F$5,Lançamentos!$A$2:$A$607,"<="&$H$5,Lançamentos!$C$2:$C$607,$T57,Lançamentos!$D$2:$D$607,$AG57) -> 562.8 | Y57: =SUMIFS('Estoque físico'!$J$2:$J$229,'Estoque físico'!$A$2:$A$229,$T57,'Estoque físico'!$B$2:$B$229,$AG57) -> 1829.1 | Z57: =ROUND(Y57-(W57-X57),3) -> 120.6 | AA57: =IF(AND(U57=$R$3,OR($R$1="*",T57=$R$1),OR($R$2="*",AG57=$R$2),ABS(V57)+ABS(W57)+ABS(X57)+ABS(Y57)>0),1,0) -> 1 | AB57: =IF(AA57=1,SUM(AA$40:AA57),"") -> 16 | AC57: =IF(ABS(Z57)<=$R$5,"Confere",IF(Z57>0,"Sobrando","Faltando")) -> Sobrando | AD57: =COUNTIFS(Lançamentos!$A$2:$A$607,">="&$F$5,Lançamentos!$A$2:$A$607,"<="&$H$5,Lançamentos!$C$2:$C$607,$T57,Lançamentos!$D$2:$D$607,$AG57,Lançamentos!$B$2:$B$607,$R$4,Lançamentos!$G$2:$G$607,U57) -> 15 | AE57: CA MOEDAS 2,01KG/UC 10UC/CX 30CX/PAL | AF57: =IF(AND(AA57=1,AC57<>"Confere"),ABS(Z57)+ROW()/10000000,0) -> 120.60001 | AG57: 252650301 | AN57: 26/09 | AO57: 46291 | AP57: =IF(AND(AO57>=$F$5,AO57<=$H$5),SUMIFS(Lançamentos!$I$2:$I$607,Lançamentos!$A$2:$A$607,$AO57,Lançamentos!$C$2:$C$607,$R$1,Lançamentos!$D$2:$D$607,$R$2,Lançamentos!$G$2:$G$607,$R$3,Lançamentos!$B$2:$B$607,$R$4),0) -> 9865.5 | AQ57: =IF(AND(AO57>=$F$5,AO57<=$H$5),-SUMIFS(Lançamentos!$J$2:$J$607,Lançamentos!$A$2:$A$607,$AO57,Lançamentos!$C$2:$C$607,$R$1,Lançamentos!$D$2:$D$607,$R$2,Lançamentos!$G$2:$G$607,$R$3,Lançamentos!$B$2:$B$607,$R$4),0) -> -3904.2 | AV57: =IFERROR(INDEX($AX$1:$AX$94,MATCH(56,$AY$1:$AY$94,0)),"") -> 260400301 | AW57: CHM-VR-Z3S-E0-U72 | AX57: 260600103 | AY57: =IF(OR($A$5="Todos",AW57=$A$5),MAX(AY$1:AY56)+1,0) -> 57
A58: =IF(IFERROR(MATCH(25,$AB$40:$AB$133,0),0)=0,"",INDEX($T$40:$T$133,IFERROR(MATCH(25,$AB$40:$AB$133,0),0))) -> 70-30-38-BR-25A | B58: =IF(IFERROR(MATCH(25,$AB$40:$AB$133,0),0)=0,"",INDEX($AG$40:$AG$133,IFERROR(MATCH(25,$AB$40:$AB$133,0),0))) -> 260070301 | C58: =IF(IFERROR(MATCH(25,$AB$40:$AB$133,0),0)=0,"",INDEX($U$40:$U$133,IFERROR(MATCH(25,$AB$40:$AB$133,0),0))) -> KG | D58: =IF(IFERROR(MATCH(25,$AB$40:$AB$133,0),0)=0,"",INDEX($V$40:$V$133,IFERROR(MATCH(25,$AB$40:$AB$133,0),0))) -> 0 | E58: =IF(IFERROR(MATCH(25,$AB$40:$AB$133,0),0)=0,"",INDEX($W$40:$W$133,IFERROR(MATCH(25,$AB$40:$AB$133,0),0))) -> 3015 | F58: =IF(IFERROR(MATCH(25,$AB$40:$AB$133,0),0)=0,"",INDEX($X$40:$X$133,IFERROR(MATCH(25,$AB$40:$AB$133,0),0))) -> 2673.3 | G58: =IF(A58="","",E58-F58) -> 341.7 | H58: =IF(IFERROR(MATCH(25,$AB$40:$AB$133,0),0)=0,"",INDEX($Y$40:$Y$133,IFERROR(MATCH(25,$AB$40:$AB$133,0),0))) -> 341.7 | I58: =IF(IFERROR(MATCH(25,$AB$40:$AB$133,0),0)=0,"",INDEX($Z$40:$Z$133,IFERROR(MATCH(25,$AB$40:$AB$133,0),0))) -> 0 | J58: =IF(IFERROR(MATCH(25,$AB$40:$AB$133,0),0)=0,"",INDEX($AC$40:$AC$133,IFERROR(MATCH(25,$AB$40:$AB$133,0),0))) -> Confere | K58: =IF(IFERROR(MATCH(25,$AB$40:$AB$133,0),0)=0,"",INDEX($AD$40:$AD$133,IFERROR(MATCH(25,$AB$40:$AB$133,0),0))) -> 20 | L58: =IF(IFERROR(MATCH(25,$AB$40:$AB$133,0),0)=0,"",INDEX($AE$40:$AE$133,IFERROR(MATCH(25,$AB$40:$AB$133,0),0))&"") -> CA MOEDAS 2,01KG/UC 10UC/CX 30CX/PAL | T58: NIBS-S502-X47 | U58: CX | V58: =SUMIFS(Lançamentos!$H$2:$H$607,Lançamentos!$A$2:$A$607,">="&$F$5,Lançamentos!$A$2:$A$607,"<="&$H$5,Lançamentos!$C$2:$C$607,$T58,Lançamentos!$D$2:$D$607,$AG58,Lançamentos!$B$2:$B$607,"Recebido no 2008") -> 0 | W58: =SUMIFS(Lançamentos!$I$2:$I$607,Lançamentos!$A$2:$A$607,">="&$F$5,Lançamentos!$A$2:$A$607,"<="&$H$5,Lançamentos!$C$2:$C$607,$T58,Lançamentos!$D$2:$D$607,$AG58) -> -120 | X58: =SUMIFS(Lançamentos!$J$2:$J$607,Lançamentos!$A$2:$A$607,">="&$F$5,Lançamentos!$A$2:$A$607,"<="&$H$5,Lançamentos!$C$2:$C$607,$T58,Lançamentos!$D$2:$D$607,$AG58) -> 0 | Y58: =SUMIFS('Estoque físico'!$J$2:$J$229,'Estoque físico'!$A$2:$A$229,$T58,'Estoque físico'!$B$2:$B$229,$AG58) -> 0 | Z58: =ROUND(Y58-(W58-X58),3) -> 120 | AA58: =IF(AND(U58=$R$3,OR($R$1="*",T58=$R$1),OR($R$2="*",AG58=$R$2),ABS(V58)+ABS(W58)+ABS(X58)+ABS(Y58)>0),1,0) -> 0 | AB58: =IF(AA58=1,SUM(AA$40:AA58),"") | AC58: =IF(ABS(Z58)<=$R$5,"Confere",IF(Z58>0,"Sobrando","Faltando")) -> Sobrando | AD58: =COUNTIFS(Lançamentos!$A$2:$A$607,">="&$F$5,Lançamentos!$A$2:$A$607,"<="&$H$5,Lançamentos!$C$2:$C$607,$T58,Lançamentos!$D$2:$D$607,$AG58,Lançamentos!$B$2:$B$607,$R$4,Lançamentos!$G$2:$G$607,U58) -> 1 | AE58: CA NIBS S 0.8KG/UC 4UC/BOX 120BOX/PAL | AF58: =IF(AND(AA58=1,AC58<>"Confere"),ABS(Z58)+ROW()/10000000,0) -> 0 | AG58: 242643099 | AN58: 27/09 | AO58: 46292 | AP58: =IF(AND(AO58>=$F$5,AO58<=$H$5),SUMIFS(Lançamentos!$I$2:$I$607,Lançamentos!$A$2:$A$607,$AO58,Lançamentos!$C$2:$C$607,$R$1,Lançamentos!$D$2:$D$607,$R$2,Lançamentos!$G$2:$G$607,$R$3,Lançamentos!$B$2:$B$607,$R$4),0) -> 0 | AQ58: =IF(AND(AO58>=$F$5,AO58<=$H$5),-SUMIFS(Lançamentos!$J$2:$J$607,Lançamentos!$A$2:$A$607,$AO58,Lançamentos!$C$2:$C$607,$R$1,Lançamentos!$D$2:$D$607,$R$2,Lançamentos!$G$2:$G$607,$R$3,Lançamentos!$B$2:$B$607,$R$4),0) -> -2188.2 | AV58: =IFERROR(INDEX($AX$1:$AX$94,MATCH(57,$AY$1:$AY$94,0)),"") -> 260600103 | AW58: CHP-20SICHP-760 | AX58: 252843369 | AY58: =IF(OR($A$5="Todos",AW58=$A$5),MAX(AY$1:AY57)+1,0) -> 58
A59: =IF(IFERROR(MATCH(26,$AB$40:$AB$133,0),0)=0,"",INDEX($T$40:$T$133,IFERROR(MATCH(26,$AB$40:$AB$133,0),0))) -> 805-BR-D94 | B59: =IF(IFERROR(MATCH(26,$AB$40:$AB$133,0),0)=0,"",INDEX($AG$40:$AG$133,IFERROR(MATCH(26,$AB$40:$AB$133,0),0))) -> 260130779 | C59: =IF(IFERROR(MATCH(26,$AB$40:$AB$133,0),0)=0,"",INDEX($U$40:$U$133,IFERROR(MATCH(26,$AB$40:$AB$133,0),0))) -> KG | D59: =IF(IFERROR(MATCH(26,$AB$40:$AB$133,0),0)=0,"",INDEX($V$40:$V$133,IFERROR(MATCH(26,$AB$40:$AB$133,0),0))) -> 0 | E59: =IF(IFERROR(MATCH(26,$AB$40:$AB$133,0),0)=0,"",INDEX($W$40:$W$133,IFERROR(MATCH(26,$AB$40:$AB$133,0),0))) -> 142.8 | F59: =IF(IFERROR(MATCH(26,$AB$40:$AB$133,0),0)=0,"",INDEX($X$40:$X$133,IFERROR(MATCH(26,$AB$40:$AB$133,0),0))) -> 0 | G59: =IF(A59="","",E59-F59) -> 142.8 | H59: =IF(IFERROR(MATCH(26,$AB$40:$AB$133,0),0)=0,"",INDEX($Y$40:$Y$133,IFERROR(MATCH(26,$AB$40:$AB$133,0),0))) -> 142.8 | I59: =IF(IFERROR(MATCH(26,$AB$40:$AB$133,0),0)=0,"",INDEX($Z$40:$Z$133,IFERROR(MATCH(26,$AB$40:$AB$133,0),0))) -> 0 | J59: =IF(IFERROR(MATCH(26,$AB$40:$AB$133,0),0)=0,"",INDEX($AC$40:$AC$133,IFERROR(MATCH(26,$AB$40:$AB$133,0),0))) -> Confere | K59: =IF(IFERROR(MATCH(26,$AB$40:$AB$133,0),0)=0,"",INDEX($AD$40:$AD$133,IFERROR(MATCH(26,$AB$40:$AB$133,0),0))) -> 1 | L59: =IF(IFERROR(MATCH(26,$AB$40:$AB$133,0),0)=0,"",INDEX($AE$40:$AE$133,IFERROR(MATCH(26,$AB$40:$AB$133,0),0))&"") -> CA MOEDAS 0,4KG/UC 7UC/CX 144CX/PAL | T59: CHK-R30GOLD-BR-25A | U59: KG | V59: =SUMIFS(Lançamentos!$H$2:$H$607,Lançamentos!$A$2:$A$607,">="&$F$5,Lançamentos!$A$2:$A$607,"<="&$H$5,Lançamentos!$C$2:$C$607,$T59,Lançamentos!$D$2:$D$607,$AG59,Lançamentos!$B$2:$B$607,"Recebido no 2008") -> 0 | W59: =SUMIFS(Lançamentos!$I$2:$I$607,Lançamentos!$A$2:$A$607,">="&$F$5,Lançamentos!$A$2:$A$607,"<="&$H$5,Lançamentos!$C$2:$C$607,$T59,Lançamentos!$D$2:$D$607,$AG59) -> 40.2 | X59: =SUMIFS(Lançamentos!$J$2:$J$607,Lançamentos!$A$2:$A$607,">="&$F$5,Lançamentos!$A$2:$A$607,"<="&$H$5,Lançamentos!$C$2:$C$607,$T59,Lançamentos!$D$2:$D$607,$AG59) -> 40.2 | Y59: =SUMIFS('Estoque físico'!$J$2:$J$229,'Estoque físico'!$A$2:$A$229,$T59,'Estoque físico'!$B$2:$B$229,$AG59) -> 116.58 | Z59: =ROUND(Y59-(W59-X59),3) -> 116.58 | AA59: =IF(AND(U59=$R$3,OR($R$1="*",T59=$R$1),OR($R$2="*",AG59=$R$2),ABS(V59)+ABS(W59)+ABS(X59)+ABS(Y59)>0),1,0) -> 1 | AB59: =IF(AA59=1,SUM(AA$40:AA59),"") -> 17 | AC59: =IF(ABS(Z59)<=$R$5,"Confere",IF(Z59>0,"Sobrando","Faltando")) -> Sobrando | AD59: =COUNTIFS(Lançamentos!$A$2:$A$607,">="&$F$5,Lançamentos!$A$2:$A$607,"<="&$H$5,Lançamentos!$C$2:$C$607,$T59,Lançamentos!$D$2:$D$607,$AG59,Lançamentos!$B$2:$B$607,$R$4,Lançamentos!$G$2:$G$607,U59) -> 3 | AE59: CA MOEDAS 2,01KG/UC 10UC/CX 30CX/PAL | AF59: =IF(AND(AA59=1,AC59<>"Confere"),ABS(Z59)+ROW()/10000000,0) -> 116.58001 | AG59: 253620301 | AN59: 28/09 | AO59: 46293 | AP59: =IF(AND(AO59>=$F$5,AO59<=$H$5),SUMIFS(Lançamentos!$I$2:$I$607,Lançamentos!$A$2:$A$607,$AO59,Lançamentos!$C$2:$C$607,$R$1,Lançamentos!$D$2:$D$607,$R$2,Lançamentos!$G$2:$G$607,$R$3,Lançamentos!$B$2:$B$607,$R$4),0) -> 7172.8 | AQ59: =IF(AND(AO59>=$F$5,AO59<=$H$5),-SUMIFS(Lançamentos!$J$2:$J$607,Lançamentos!$A$2:$A$607,$AO59,Lançamentos!$C$2:$C$607,$R$1,Lançamentos!$D$2:$D$607,$R$2,Lançamentos!$G$2:$G$607,$R$3,Lançamentos!$B$2:$B$607,$R$4),0) -> -179.6 | AV59: =IFERROR(INDEX($AX$1:$AX$94,MATCH(58,$AY$1:$AY$94,0)),"") -> 252843369 | AW59: CHR-Q37RB2-2B-U75 | AX59: 261320202 | AY59: =IF(OR($A$5="Todos",AW59=$A$5),MAX(AY$1:AY58)+1,0) -> 59
A60: =IF(IFERROR(MATCH(27,$AB$40:$AB$133,0),0)=0,"",INDEX($T$40:$T$133,IFERROR(MATCH(27,$AB$40:$AB$133,0),0))) -> 811NV-132 | B60: =IF(IFERROR(MATCH(27,$AB$40:$AB$133,0),0)=0,"",INDEX($AG$40:$AG$133,IFERROR(MATCH(27,$AB$40:$AB$133,0),0))) -> 252510301 | C60: =IF(IFERROR(MATCH(27,$AB$40:$AB$133,0),0)=0,"",INDEX($U$40:$U$133,IFERROR(MATCH(27,$AB$40:$AB$133,0),0))) -> KG | D60: =IF(IFERROR(MATCH(27,$AB$40:$AB$133,0),0)=0,"",INDEX($V$40:$V$133,IFERROR(MATCH(27,$AB$40:$AB$133,0),0))) -> 0 | E60: =IF(IFERROR(MATCH(27,$AB$40:$AB$133,0),0)=0,"",INDEX($W$40:$W$133,IFERROR(MATCH(27,$AB$40:$AB$133,0),0))) -> 1500 | F60: =IF(IFERROR(MATCH(27,$AB$40:$AB$133,0),0)=0,"",INDEX($X$40:$X$133,IFERROR(MATCH(27,$AB$40:$AB$133,0),0))) -> 0 | G60: =IF(A60="","",E60-F60) -> 1500 | H60: =IF(IFERROR(MATCH(27,$AB$40:$AB$133,0),0)=0,"",INDEX($Y$40:$Y$133,IFERROR(MATCH(27,$AB$40:$AB$133,0),0))) -> 1500 | I60: =IF(IFERROR(MATCH(27,$AB$40:$AB$133,0),0)=0,"",INDEX($Z$40:$Z$133,IFERROR(MATCH(27,$AB$40:$AB$133,0),0))) -> 0 | J60: =IF(IFERROR(MATCH(27,$AB$40:$AB$133,0),0)=0,"",INDEX($AC$40:$AC$133,IFERROR(MATCH(27,$AB$40:$AB$133,0),0))) -> Confere | K60: =IF(IFERROR(MATCH(27,$AB$40:$AB$133,0),0)=0,"",INDEX($AD$40:$AD$133,IFERROR(MATCH(27,$AB$40:$AB$133,0),0))) -> 4 | L60: =IF(IFERROR(MATCH(27,$AB$40:$AB$133,0),0)=0,"",INDEX($AE$40:$AE$133,IFERROR(MATCH(27,$AB$40:$AB$133,0),0))&"") -> 96_FU:811NV-50C_CA BLOCKS 5KG/UC 5UC | T60: 823-BR-25A | U60: KG | V60: =SUMIFS(Lançamentos!$H$2:$H$607,Lançamentos!$A$2:$A$607,">="&$F$5,Lançamentos!$A$2:$A$607,"<="&$H$5,Lançamentos!$C$2:$C$607,$T60,Lançamentos!$D$2:$D$607,$AG60,Lançamentos!$B$2:$B$607,"Recebido no 2008") -> 0 | W60: =SUMIFS(Lançamentos!$I$2:$I$607,Lançamentos!$A$2:$A$607,">="&$F$5,Lançamentos!$A$2:$A$607,"<="&$H$5,Lançamentos!$C$2:$C$607,$T60,Lançamentos!$D$2:$D$607,$AG60) -> 3612 | X60: =SUMIFS(Lançamentos!$J$2:$J$607,Lançamentos!$A$2:$A$607,">="&$F$5,Lançamentos!$A$2:$A$607,"<="&$H$5,Lançamentos!$C$2:$C$607,$T60,Lançamentos!$D$2:$D$607,$AG60) -> 80.4 | Y60: =SUMIFS('Estoque físico'!$J$2:$J$229,'Estoque físico'!$A$2:$A$229,$T60,'Estoque físico'!$B$2:$B$229,$AG60) -> 3612 | Z60: =ROUND(Y60-(W60-X60),3) -> 80.4 | AA60: =IF(AND(U60=$R$3,OR($R$1="*",T60=$R$1),OR($R$2="*",AG60=$R$2),ABS(V60)+ABS(W60)+ABS(X60)+ABS(Y60)>0),1,0) -> 1 | AB60: =IF(AA60=1,SUM(AA$40:AA60),"") -> 18 | AC60: =IF(ABS(Z60)<=$R$5,"Confere",IF(Z60>0,"Sobrando","Faltando")) -> Sobrando | AD60: =COUNTIFS(Lançamentos!$A$2:$A$607,">="&$F$5,Lançamentos!$A$2:$A$607,"<="&$H$5,Lançamentos!$C$2:$C$607,$T60,Lançamentos!$D$2:$D$607,$AG60,Lançamentos!$B$2:$B$607,$R$4,Lançamentos!$G$2:$G$607,U60) -> 8 | AE60: CA MOEDAS 2,01KG/UC 10UC/CX 30CX/PAL | AF60: =IF(AND(AA60=1,AC60<>"Confere"),ABS(Z60)+ROW()/10000000,0) -> 80.400006 | AG60: 252900303 | AN60: 29/09 | AO60: 46294 | AP60: =IF(AND(AO60>=$F$5,AO60<=$H$5),SUMIFS(Lançamentos!$I$2:$I$607,Lançamentos!$A$2:$A$607,$AO60,Lançamentos!$C$2:$C$607,$R$1,Lançamentos!$D$2:$D$607,$R$2,Lançamentos!$G$2:$G$607,$R$3,Lançamentos!$B$2:$B$607,$R$4),0) -> 15789.3 | AQ60: =IF(AND(AO60>=$F$5,AO60<=$H$5),-SUMIFS(Lançamentos!$J$2:$J$607,Lançamentos!$A$2:$A$607,$AO60,Lançamentos!$C$2:$C$607,$R$1,Lançamentos!$D$2:$D$607,$R$2,Lançamentos!$G$2:$G$607,$R$3,Lançamentos!$B$2:$B$607,$R$4),0) -> -2433.6 | AV60: =IFERROR(INDEX($AX$1:$AX$94,MATCH(59,$AY$1:$AY$94,0)),"") -> 261320202 | AW60: CHR-Q37RB2-2B-U75 | AX60: 261320203 | AY60: =IF(OR($A$5="Todos",AW60=$A$5),MAX(AY$1:AY59)+1,0) -> 60
A61: =IF(IFERROR(MATCH(28,$AB$40:$AB$133,0),0)=0,"",INDEX($T$40:$T$133,IFERROR(MATCH(28,$AB$40:$AB$133,0),0))) -> 811NV-132 | B61: =IF(IFERROR(MATCH(28,$AB$40:$AB$133,0),0)=0,"",INDEX($AG$40:$AG$133,IFERROR(MATCH(28,$AB$40:$AB$133,0),0))) -> 253280301 | C61: =IF(IFERROR(MATCH(28,$AB$40:$AB$133,0),0)=0,"",INDEX($U$40:$U$133,IFERROR(MATCH(28,$AB$40:$AB$133,0),0))) -> KG | D61: =IF(IFERROR(MATCH(28,$AB$40:$AB$133,0),0)=0,"",INDEX($V$40:$V$133,IFERROR(MATCH(28,$AB$40:$AB$133,0),0))) -> 0 | E61: =IF(IFERROR(MATCH(28,$AB$40:$AB$133,0),0)=0,"",INDEX($W$40:$W$133,IFERROR(MATCH(28,$AB$40:$AB$133,0),0))) -> 1750 | F61: =IF(IFERROR(MATCH(28,$AB$40:$AB$133,0),0)=0,"",INDEX($X$40:$X$133,IFERROR(MATCH(28,$AB$40:$AB$133,0),0))) -> 800 | G61: =IF(A61="","",E61-F61) -> 950 | H61: =IF(IFERROR(MATCH(28,$AB$40:$AB$133,0),0)=0,"",INDEX($Y$40:$Y$133,IFERROR(MATCH(28,$AB$40:$AB$133,0),0))) -> 950 | I61: =IF(IFERROR(MATCH(28,$AB$40:$AB$133,0),0)=0,"",INDEX($Z$40:$Z$133,IFERROR(MATCH(28,$AB$40:$AB$133,0),0))) -> 0 | J61: =IF(IFERROR(MATCH(28,$AB$40:$AB$133,0),0)=0,"",INDEX($AC$40:$AC$133,IFERROR(MATCH(28,$AB$40:$AB$133,0),0))) -> Confere | K61: =IF(IFERROR(MATCH(28,$AB$40:$AB$133,0),0)=0,"",INDEX($AD$40:$AD$133,IFERROR(MATCH(28,$AB$40:$AB$133,0),0))) -> 9 | L61: =IF(IFERROR(MATCH(28,$AB$40:$AB$133,0),0)=0,"",INDEX($AE$40:$AE$133,IFERROR(MATCH(28,$AB$40:$AB$133,0),0))&"") -> 96_FU:811NV-50C_CA BLOCKS 5KG/UC 5UC | T61: CHK-R30GOLD-E0-D94 | U61: KG | V61: =SUMIFS(Lançamentos!$H$2:$H$607,Lançamentos!$A$2:$A$607,">="&$F$5,Lançamentos!$A$2:$A$607,"<="&$H$5,Lançamentos!$C$2:$C$607,$T61,Lançamentos!$D$2:$D$607,$AG61,Lançamentos!$B$2:$B$607,"Recebido no 2008") -> 0 | W61: =SUMIFS(Lançamentos!$I$2:$I$607,Lançamentos!$A$2:$A$607,">="&$F$5,Lançamentos!$A$2:$A$607,"<="&$H$5,Lançamentos!$C$2:$C$607,$T61,Lançamentos!$D$2:$D$607,$AG61) -> 806.4 | X61: =SUMIFS(Lançamentos!$J$2:$J$607,Lançamentos!$A$2:$A$607,">="&$F$5,Lançamentos!$A$2:$A$607,"<="&$H$5,Lançamentos!$C$2:$C$607,$T61,Lançamentos!$D$2:$D$607,$AG61) -> 53.2 | Y61: =SUMIFS('Estoque físico'!$J$2:$J$229,'Estoque físico'!$A$2:$A$229,$T61,'Estoque físico'!$B$2:$B$229,$AG61) -> 825.999 | Z61: =ROUND(Y61-(W61-X61),3) -> 72.799 | AA61: =IF(AND(U61=$R$3,OR($R$1="*",T61=$R$1),OR($R$2="*",AG61=$R$2),ABS(V61)+ABS(W61)+ABS(X61)+ABS(Y61)>0),1,0) -> 1 | AB61: =IF(AA61=1,SUM(AA$40:AA61),"") -> 19 | AC61: =IF(ABS(Z61)<=$R$5,"Confere",IF(Z61>0,"Sobrando","Faltando")) -> Sobrando | AD61: =COUNTIFS(Lançamentos!$A$2:$A$607,">="&$F$5,Lançamentos!$A$2:$A$607,"<="&$H$5,Lançamentos!$C$2:$C$607,$T61,Lançamentos!$D$2:$D$607,$AG61,Lançamentos!$B$2:$B$607,$R$4,Lançamentos!$G$2:$G$607,U61) -> 7 | AE61: CA CALLETS 0.4KG/UC 7UC/BOX 144BOX/PAL | AF61: =IF(AND(AA61=1,AC61<>"Confere"),ABS(Z61)+ROW()/10000000,0) -> 72.799006 | AG61: 260720939 | AN61: 30/09 | AO61: 46295 | AP61: =IF(AND(AO61>=$F$5,AO61<=$H$5),SUMIFS(Lançamentos!$I$2:$I$607,Lançamentos!$A$2:$A$607,$AO61,Lançamentos!$C$2:$C$607,$R$1,Lançamentos!$D$2:$D$607,$R$2,Lançamentos!$G$2:$G$607,$R$3,Lançamentos!$B$2:$B$607,$R$4),0) -> 1021.1 | AQ61: =IF(AND(AO61>=$F$5,AO61<=$H$5),-SUMIFS(Lançamentos!$J$2:$J$607,Lançamentos!$A$2:$A$607,$AO61,Lançamentos!$C$2:$C$607,$R$1,Lançamentos!$D$2:$D$607,$R$2,Lançamentos!$G$2:$G$607,$R$3,Lançamentos!$B$2:$B$607,$R$4),0) -> -5962.6 | AV61: =IFERROR(INDEX($AX$1:$AX$94,MATCH(60,$AY$1:$AY$94,0)),"") -> 261320203 | AW61: CHR-Q37RB2-E0-D94 | AX61: 261301539 | AY61: =IF(OR($A$5="Todos",AW61=$A$5),MAX(AY$1:AY60)+1,0) -> 61
A62: =IF(IFERROR(MATCH(29,$AB$40:$AB$133,0),0)=0,"",INDEX($T$40:$T$133,IFERROR(MATCH(29,$AB$40:$AB$133,0),0))) -> 811NV-595 | B62: =IF(IFERROR(MATCH(29,$AB$40:$AB$133,0),0)=0,"",INDEX($AG$40:$AG$133,IFERROR(MATCH(29,$AB$40:$AB$133,0),0))) -> 260900702 | C62: =IF(IFERROR(MATCH(29,$AB$40:$AB$133,0),0)=0,"",INDEX($U$40:$U$133,IFERROR(MATCH(29,$AB$40:$AB$133,0),0))) -> KG | D62: =IF(IFERROR(MATCH(29,$AB$40:$AB$133,0),0)=0,"",INDEX($V$40:$V$133,IFERROR(MATCH(29,$AB$40:$AB$133,0),0))) -> 0 | E62: =IF(IFERROR(MATCH(29,$AB$40:$AB$133,0),0)=0,"",INDEX($W$40:$W$133,IFERROR(MATCH(29,$AB$40:$AB$133,0),0))) -> 1800 | F62: =IF(IFERROR(MATCH(29,$AB$40:$AB$133,0),0)=0,"",INDEX($X$40:$X$133,IFERROR(MATCH(29,$AB$40:$AB$133,0),0))) -> 1780 | G62: =IF(A62="","",E62-F62) -> 20 | H62: =IF(IFERROR(MATCH(29,$AB$40:$AB$133,0),0)=0,"",INDEX($Y$40:$Y$133,IFERROR(MATCH(29,$AB$40:$AB$133,0),0))) -> 20 | I62: =IF(IFERROR(MATCH(29,$AB$40:$AB$133,0),0)=0,"",INDEX($Z$40:$Z$133,IFERROR(MATCH(29,$AB$40:$AB$133,0),0))) -> 0 | J62: =IF(IFERROR(MATCH(29,$AB$40:$AB$133,0),0)=0,"",INDEX($AC$40:$AC$133,IFERROR(MATCH(29,$AB$40:$AB$133,0),0))) -> Confere | K62: =IF(IFERROR(MATCH(29,$AB$40:$AB$133,0),0)=0,"",INDEX($AD$40:$AD$133,IFERROR(MATCH(29,$AB$40:$AB$133,0),0))) -> 3 | L62: =IF(IFERROR(MATCH(29,$AB$40:$AB$133,0),0)=0,"",INDEX($AE$40:$AE$133,IFERROR(MATCH(29,$AB$40:$AB$133,0),0))&"") -> CA CALLETS 10KG/UC 2UC/BOX 30BOX/PAL | T62: CHD-BB-308BY-357 | U62: UN | V62: =SUMIFS(Lançamentos!$H$2:$H$607,Lançamentos!$A$2:$A$607,">="&$F$5,Lançamentos!$A$2:$A$607,"<="&$H$5,Lançamentos!$C$2:$C$607,$T62,Lançamentos!$D$2:$D$607,$AG62,Lançamentos!$B$2:$B$607,"Recebido no 2008") -> 0 | W62: =SUMIFS(Lançamentos!$I$2:$I$607,Lançamentos!$A$2:$A$607,">="&$F$5,Lançamentos!$A$2:$A$607,"<="&$H$5,Lançamentos!$C$2:$C$607,$T62,Lançamentos!$D$2:$D$607,$AG62) -> 450 | X62: =SUMIFS(Lançamentos!$J$2:$J$607,Lançamentos!$A$2:$A$607,">="&$F$5,Lançamentos!$A$2:$A$607,"<="&$H$5,Lançamentos!$C$2:$C$607,$T62,Lançamentos!$D$2:$D$607,$AG62) -> 510 | Y62: =SUMIFS('Estoque físico'!$J$2:$J$229,'Estoque físico'!$A$2:$A$229,$T62,'Estoque físico'!$B$2:$B$229,$AG62) -> 0 | Z62: =ROUND(Y62-(W62-X62),3) -> 60 | AA62: =IF(AND(U62=$R$3,OR($R$1="*",T62=$R$1),OR($R$2="*",AG62=$R$2),ABS(V62)+ABS(W62)+ABS(X62)+ABS(Y62)>0),1,0) -> 0 | AB62: =IF(AA62=1,SUM(AA$40:AA62),"") | AC62: =IF(ABS(Z62)<=$R$5,"Confere",IF(Z62>0,"Sobrando","Faltando")) -> Sobrando | AD62: =COUNTIFS(Lançamentos!$A$2:$A$607,">="&$F$5,Lançamentos!$A$2:$A$607,"<="&$H$5,Lançamentos!$C$2:$C$607,$T62,Lançamentos!$D$2:$D$607,$AG62,Lançamentos!$B$2:$B$607,$R$4,Lançamentos!$G$2:$G$607,U62) -> 16 | AE62: CB EXTRUDED 8CM STICKS 1.6KG/UC 15UC/BOX | AF62: =IF(AND(AA62=1,AC62<>"Confere"),ABS(Z62)+ROW()/10000000,0) -> 0 | AG62: 2529678000 | AN62: 01/10 | AO62: 46296 | AP62: =IF(AND(AO62>=$F$5,AO62<=$H$5),SUMIFS(Lançamentos!$I$2:$I$607,Lançamentos!$A$2:$A$607,$AO62,Lançamentos!$C$2:$C$607,$R$1,Lançamentos!$D$2:$D$607,$R$2,Lançamentos!$G$2:$G$607,$R$3,Lançamentos!$B$2:$B$607,$R$4),0) -> 0 | AQ62: =IF(AND(AO62>=$F$5,AO62<=$H$5),-SUMIFS(Lançamentos!$J$2:$J$607,Lançamentos!$A$2:$A$607,$AO62,Lançamentos!$C$2:$C$607,$R$1,Lançamentos!$D$2:$D$607,$R$2,Lançamentos!$G$2:$G$607,$R$3,Lançamentos!$B$2:$B$607,$R$4),0) -> -490.8 | AV62: =IFERROR(INDEX($AX$1:$AX$94,MATCH(61,$AY$1:$AY$94,0)),"") -> 261301539 | AW62: CW2-BR-25A | AX62: 252350301 | AY62: =IF(OR($A$5="Todos",AW62=$A$5),MAX(AY$1:AY61)+1,0) -> 62
A63: =IF(IFERROR(MATCH(30,$AB$40:$AB$133,0),0)=0,"",INDEX($T$40:$T$133,IFERROR(MATCH(30,$AB$40:$AB$133,0),0))) -> 811NV-595 | B63: =IF(IFERROR(MATCH(30,$AB$40:$AB$133,0),0)=0,"",INDEX($AG$40:$AG$133,IFERROR(MATCH(30,$AB$40:$AB$133,0),0))) -> 260920702 | C63: =IF(IFERROR(MATCH(30,$AB$40:$AB$133,0),0)=0,"",INDEX($U$40:$U$133,IFERROR(MATCH(30,$AB$40:$AB$133,0),0))) -> KG | D63: =IF(IFERROR(MATCH(30,$AB$40:$AB$133,0),0)=0,"",INDEX($V$40:$V$133,IFERROR(MATCH(30,$AB$40:$AB$133,0),0))) -> 0 | E63: =IF(IFERROR(MATCH(30,$AB$40:$AB$133,0),0)=0,"",INDEX($W$40:$W$133,IFERROR(MATCH(30,$AB$40:$AB$133,0),0))) -> 600 | F63: =IF(IFERROR(MATCH(30,$AB$40:$AB$133,0),0)=0,"",INDEX($X$40:$X$133,IFERROR(MATCH(30,$AB$40:$AB$133,0),0))) -> 0 | G63: =IF(A63="","",E63-F63) -> 600 | H63: =IF(IFERROR(MATCH(30,$AB$40:$AB$133,0),0)=0,"",INDEX($Y$40:$Y$133,IFERROR(MATCH(30,$AB$40:$AB$133,0),0))) -> 600 | I63: =IF(IFERROR(MATCH(30,$AB$40:$AB$133,0),0)=0,"",INDEX($Z$40:$Z$133,IFERROR(MATCH(30,$AB$40:$AB$133,0),0))) -> 0 | J63: =IF(IFERROR(MATCH(30,$AB$40:$AB$133,0),0)=0,"",INDEX($AC$40:$AC$133,IFERROR(MATCH(30,$AB$40:$AB$133,0),0))) -> Confere | K63: =IF(IFERROR(MATCH(30,$AB$40:$AB$133,0),0)=0,"",INDEX($AD$40:$AD$133,IFERROR(MATCH(30,$AB$40:$AB$133,0),0))) -> 1 | L63: =IF(IFERROR(MATCH(30,$AB$40:$AB$133,0),0)=0,"",INDEX($AE$40:$AE$133,IFERROR(MATCH(30,$AB$40:$AB$133,0),0))&"") -> CA CALLETS 10KG/UC 2UC/BOX 30BOX/PAL | T63: CHM-CU-7X80-E5-U70 | U63: KG | V63: =SUMIFS(Lançamentos!$H$2:$H$607,Lançamentos!$A$2:$A$607,">="&$F$5,Lançamentos!$A$2:$A$607,"<="&$H$5,Lançamentos!$C$2:$C$607,$T63,Lançamentos!$D$2:$D$607,$AG63,Lançamentos!$B$2:$B$607,"Recebido no 2008") -> 0 | W63: =SUMIFS(Lançamentos!$I$2:$I$607,Lançamentos!$A$2:$A$607,">="&$F$5,Lançamentos!$A$2:$A$607,"<="&$H$5,Lançamentos!$C$2:$C$607,$T63,Lançamentos!$D$2:$D$607,$AG63) -> 10 | X63: =SUMIFS(Lançamentos!$J$2:$J$607,Lançamentos!$A$2:$A$607,">="&$F$5,Lançamentos!$A$2:$A$607,"<="&$H$5,Lançamentos!$C$2:$C$607,$T63,Lançamentos!$D$2:$D$607,$AG63) -> 60 | Y63: =SUMIFS('Estoque físico'!$J$2:$J$229,'Estoque físico'!$A$2:$A$229,$T63,'Estoque físico'!$B$2:$B$229,$AG63) -> 10 | Z63: =ROUND(Y63-(W63-X63),3) -> 60 | AA63: =IF(AND(U63=$R$3,OR($R$1="*",T63=$R$1),OR($R$2="*",AG63=$R$2),ABS(V63)+ABS(W63)+ABS(X63)+ABS(Y63)>0),1,0) -> 1 | AB63: =IF(AA63=1,SUM(AA$40:AA63),"") -> 20 | AC63: =IF(ABS(Z63)<=$R$5,"Confere",IF(Z63>0,"Sobrando","Faltando")) -> Sobrando | AD63: =COUNTIFS(Lançamentos!$A$2:$A$607,">="&$F$5,Lançamentos!$A$2:$A$607,"<="&$H$5,Lançamentos!$C$2:$C$607,$T63,Lançamentos!$D$2:$D$607,$AG63,Lançamentos!$B$2:$B$607,$R$4,Lançamentos!$G$2:$G$607,U63) -> 3 | AE63: CA CHOCOCUBES CHUNKS 700CT/KG 2.5KG/UC | AF63: =IF(AND(AA63=1,AC63<>"Confere"),ABS(Z63)+ROW()/10000000,0) -> 60.000006 | AG63: 2528749307 | AV63: =IFERROR(INDEX($AX$1:$AX$94,MATCH(62,$AY$1:$AY$94,0)),"") -> 252350301 | AW63: CW2-BR-25A | AX63: 252590301 | AY63: =IF(OR($A$5="Todos",AW63=$A$5),MAX(AY$1:AY62)+1,0) -> 63
A64: =IF(IFERROR(MATCH(31,$AB$40:$AB$133,0),0)=0,"",INDEX($T$40:$T$133,IFERROR(MATCH(31,$AB$40:$AB$133,0),0))) -> 811NV-595 | B64: =IF(IFERROR(MATCH(31,$AB$40:$AB$133,0),0)=0,"",INDEX($AG$40:$AG$133,IFERROR(MATCH(31,$AB$40:$AB$133,0),0))) -> 261146101 | C64: =IF(IFERROR(MATCH(31,$AB$40:$AB$133,0),0)=0,"",INDEX($U$40:$U$133,IFERROR(MATCH(31,$AB$40:$AB$133,0),0))) -> KG | D64: =IF(IFERROR(MATCH(31,$AB$40:$AB$133,0),0)=0,"",INDEX($V$40:$V$133,IFERROR(MATCH(31,$AB$40:$AB$133,0),0))) -> 4360 | E64: =IF(IFERROR(MATCH(31,$AB$40:$AB$133,0),0)=0,"",INDEX($W$40:$W$133,IFERROR(MATCH(31,$AB$40:$AB$133,0),0))) -> 1180 | F64: =IF(IFERROR(MATCH(31,$AB$40:$AB$133,0),0)=0,"",INDEX($X$40:$X$133,IFERROR(MATCH(31,$AB$40:$AB$133,0),0))) -> 1160 | G64: =IF(A64="","",E64-F64) -> 20 | H64: =IF(IFERROR(MATCH(31,$AB$40:$AB$133,0),0)=0,"",INDEX($Y$40:$Y$133,IFERROR(MATCH(31,$AB$40:$AB$133,0),0))) -> 20 | I64: =IF(IFERROR(MATCH(31,$AB$40:$AB$133,0),0)=0,"",INDEX($Z$40:$Z$133,IFERROR(MATCH(31,$AB$40:$AB$133,0),0))) -> 0 | J64: =IF(IFERROR(MATCH(31,$AB$40:$AB$133,0),0)=0,"",INDEX($AC$40:$AC$133,IFERROR(MATCH(31,$AB$40:$AB$133,0),0))) -> Confere | K64: =IF(IFERROR(MATCH(31,$AB$40:$AB$133,0),0)=0,"",INDEX($AD$40:$AD$133,IFERROR(MATCH(31,$AB$40:$AB$133,0),0))) -> 3 | L64: =IF(IFERROR(MATCH(31,$AB$40:$AB$133,0),0)=0,"",INDEX($AE$40:$AE$133,IFERROR(MATCH(31,$AB$40:$AB$133,0),0))&"") -> CA CALLETS 10KG/UC 2UC/BOX 30BOX/PAL | T64: CHD-BB-308BY-357 | U64: UN | V64: =SUMIFS(Lançamentos!$H$2:$H$607,Lançamentos!$A$2:$A$607,">="&$F$5,Lançamentos!$A$2:$A$607,"<="&$H$5,Lançamentos!$C$2:$C$607,$T64,Lançamentos!$D$2:$D$607,$AG64,Lançamentos!$B$2:$B$607,"Recebido no 2008") -> 0 | W64: =SUMIFS(Lançamentos!$I$2:$I$607,Lançamentos!$A$2:$A$607,">="&$F$5,Lançamentos!$A$2:$A$607,"<="&$H$5,Lançamentos!$C$2:$C$607,$T64,Lançamentos!$D$2:$D$607,$AG64) -> 1320 | X64: =SUMIFS(Lançamentos!$J$2:$J$607,Lançamentos!$A$2:$A$607,">="&$F$5,Lançamentos!$A$2:$A$607,"<="&$H$5,Lançamentos!$C$2:$C$607,$T64,Lançamentos!$D$2:$D$607,$AG64) -> 330 | Y64: =SUMIFS('Estoque físico'!$J$2:$J$229,'Estoque físico'!$A$2:$A$229,$T64,'Estoque físico'!$B$2:$B$229,$AG64) -> 1020 | Z64: =ROUND(Y64-(W64-X64),3) -> 30 | AA64: =IF(AND(U64=$R$3,OR($R$1="*",T64=$R$1),OR($R$2="*",AG64=$R$2),ABS(V64)+ABS(W64)+ABS(X64)+ABS(Y64)>0),1,0) -> 0 | AB64: =IF(AA64=1,SUM(AA$40:AA64),"") | AC64: =IF(ABS(Z64)<=$R$5,"Confere",IF(Z64>0,"Sobrando","Faltando")) -> Sobrando | AD64: =COUNTIFS(Lançamentos!$A$2:$A$607,">="&$F$5,Lançamentos!$A$2:$A$607,"<="&$H$5,Lançamentos!$C$2:$C$607,$T64,Lançamentos!$D$2:$D$607,$AG64,Lançamentos!$B$2:$B$607,$R$4,Lançamentos!$G$2:$G$607,U64) -> 7 | AE64: CB EXTRUDED 8CM STICKS 1.6KG/UC 15UC/BOX | AF64: =IF(AND(AA64=1,AC64<>"Confere"),ABS(Z64)+ROW()/10000000,0) -> 0 | AG64: 2611378000 | AV64: =IFERROR(INDEX($AX$1:$AX$94,MATCH(63,$AY$1:$AY$94,0)),"") -> 252590301 | AW64: CW2-BR-25A | AX64: 252650301 | AY64: =IF(OR($A$5="Todos",AW64=$A$5),MAX(AY$1:AY63)+1,0) -> 64
A65: =IF(IFERROR(MATCH(32,$AB$40:$AB$133,0),0)=0,"",INDEX($T$40:$T$133,IFERROR(MATCH(32,$AB$40:$AB$133,0),0))) -> 811NV-595 | B65: =IF(IFERROR(MATCH(32,$AB$40:$AB$133,0),0)=0,"",INDEX($AG$40:$AG$133,IFERROR(MATCH(32,$AB$40:$AB$133,0),0))) -> 261146102 | C65: =IF(IFERROR(MATCH(32,$AB$40:$AB$133,0),0)=0,"",INDEX($U$40:$U$133,IFERROR(MATCH(32,$AB$40:$AB$133,0),0))) -> KG | D65: =IF(IFERROR(MATCH(32,$AB$40:$AB$133,0),0)=0,"",INDEX($V$40:$V$133,IFERROR(MATCH(32,$AB$40:$AB$133,0),0))) -> 5240 | E65: =IF(IFERROR(MATCH(32,$AB$40:$AB$133,0),0)=0,"",INDEX($W$40:$W$133,IFERROR(MATCH(32,$AB$40:$AB$133,0),0))) -> 1660 | F65: =IF(IFERROR(MATCH(32,$AB$40:$AB$133,0),0)=0,"",INDEX($X$40:$X$133,IFERROR(MATCH(32,$AB$40:$AB$133,0),0))) -> 580 | G65: =IF(A65="","",E65-F65) -> 1080 | H65: =IF(IFERROR(MATCH(32,$AB$40:$AB$133,0),0)=0,"",INDEX($Y$40:$Y$133,IFERROR(MATCH(32,$AB$40:$AB$133,0),0))) -> 1080 | I65: =IF(IFERROR(MATCH(32,$AB$40:$AB$133,0),0)=0,"",INDEX($Z$40:$Z$133,IFERROR(MATCH(32,$AB$40:$AB$133,0),0))) -> 0 | J65: =IF(IFERROR(MATCH(32,$AB$40:$AB$133,0),0)=0,"",INDEX($AC$40:$AC$133,IFERROR(MATCH(32,$AB$40:$AB$133,0),0))) -> Confere | K65: =IF(IFERROR(MATCH(32,$AB$40:$AB$133,0),0)=0,"",INDEX($AD$40:$AD$133,IFERROR(MATCH(32,$AB$40:$AB$133,0),0))) -> 10 | L65: =IF(IFERROR(MATCH(32,$AB$40:$AB$133,0),0)=0,"",INDEX($AE$40:$AE$133,IFERROR(MATCH(32,$AB$40:$AB$133,0),0))&"") -> CA CALLETS 10KG/UC 2UC/BOX 30BOX/PAL | T65: CW2-BR-25A | U65: KG | V65: =SUMIFS(Lançamentos!$H$2:$H$607,Lançamentos!$A$2:$A$607,">="&$F$5,Lançamentos!$A$2:$A$607,"<="&$H$5,Lançamentos!$C$2:$C$607,$T65,Lançamentos!$D$2:$D$607,$AG65,Lançamentos!$B$2:$B$607,"Recebido no 2008") -> 0 | W65: =SUMIFS(Lançamentos!$I$2:$I$607,Lançamentos!$A$2:$A$607,">="&$F$5,Lançamentos!$A$2:$A$607,"<="&$H$5,Lançamentos!$C$2:$C$607,$T65,Lançamentos!$D$2:$D$607,$AG65) -> 602.9 | X65: =SUMIFS(Lançamentos!$J$2:$J$607,Lançamentos!$A$2:$A$607,">="&$F$5,Lançamentos!$A$2:$A$607,"<="&$H$5,Lançamentos!$C$2:$C$607,$T65,Lançamentos!$D$2:$D$607,$AG65) -> 301.5 | Y65: =SUMIFS('Estoque físico'!$J$2:$J$229,'Estoque físico'!$A$2:$A$229,$T65,'Estoque físico'!$B$2:$B$229,$AG65) -> 321.5 | Z65: =ROUND(Y65-(W65-X65),3) -> 20.1 | AA65: =IF(AND(U65=$R$3,OR($R$1="*",T65=$R$1),OR($R$2="*",AG65=$R$2),ABS(V65)+ABS(W65)+ABS(X65)+ABS(Y65)>0),1,0) -> 1 | AB65: =IF(AA65=1,SUM(AA$40:AA65),"") -> 21 | AC65: =IF(ABS(Z65)<=$R$5,"Confere",IF(Z65>0,"Sobrando","Faltando")) -> Sobrando | AD65: =COUNTIFS(Lançamentos!$A$2:$A$607,">="&$F$5,Lançamentos!$A$2:$A$607,"<="&$H$5,Lançamentos!$C$2:$C$607,$T65,Lançamentos!$D$2:$D$607,$AG65,Lançamentos!$B$2:$B$607,$R$4,Lançamentos!$G$2:$G$607,U65) -> 5 | AE65: CA MOEDAS 2,01KG/UC 10UC/CX 30CX/PAL | AF65: =IF(AND(AA65=1,AC65<>"Confere"),ABS(Z65)+ROW()/10000000,0) -> 20.100006 | AG65: 252350301 | AV65: =IFERROR(INDEX($AX$1:$AX$94,MATCH(64,$AY$1:$AY$94,0)),"") -> 252650301 | AW65: CW2-BR-25A | AX65: 253470301 | AY65: =IF(OR($A$5="Todos",AW65=$A$5),MAX(AY$1:AY64)+1,0) -> 65
A66: =IF(IFERROR(MATCH(33,$AB$40:$AB$133,0),0)=0,"",INDEX($T$40:$T$133,IFERROR(MATCH(33,$AB$40:$AB$133,0),0))) -> 823-BR-25A | B66: =IF(IFERROR(MATCH(33,$AB$40:$AB$133,0),0)=0,"",INDEX($AG$40:$AG$133,IFERROR(MATCH(33,$AB$40:$AB$133,0),0))) -> 252100301 | C66: =IF(IFERROR(MATCH(33,$AB$40:$AB$133,0),0)=0,"",INDEX($U$40:$U$133,IFERROR(MATCH(33,$AB$40:$AB$133,0),0))) -> KG | D66: =IF(IFERROR(MATCH(33,$AB$40:$AB$133,0),0)=0,"",INDEX($V$40:$V$133,IFERROR(MATCH(33,$AB$40:$AB$133,0),0))) -> 0 | E66: =IF(IFERROR(MATCH(33,$AB$40:$AB$133,0),0)=0,"",INDEX($W$40:$W$133,IFERROR(MATCH(33,$AB$40:$AB$133,0),0))) -> 461.9 | F66: =IF(IFERROR(MATCH(33,$AB$40:$AB$133,0),0)=0,"",INDEX($X$40:$X$133,IFERROR(MATCH(33,$AB$40:$AB$133,0),0))) -> 442.2 | G66: =IF(A66="","",E66-F66) -> 19.7 | H66: =IF(IFERROR(MATCH(33,$AB$40:$AB$133,0),0)=0,"",INDEX($Y$40:$Y$133,IFERROR(MATCH(33,$AB$40:$AB$133,0),0))) -> 19.7 | I66: =IF(IFERROR(MATCH(33,$AB$40:$AB$133,0),0)=0,"",INDEX($Z$40:$Z$133,IFERROR(MATCH(33,$AB$40:$AB$133,0),0))) -> 0 | J66: =IF(IFERROR(MATCH(33,$AB$40:$AB$133,0),0)=0,"",INDEX($AC$40:$AC$133,IFERROR(MATCH(33,$AB$40:$AB$133,0),0))) -> Confere | K66: =IF(IFERROR(MATCH(33,$AB$40:$AB$133,0),0)=0,"",INDEX($AD$40:$AD$133,IFERROR(MATCH(33,$AB$40:$AB$133,0),0))) -> 2 | L66: =IF(IFERROR(MATCH(33,$AB$40:$AB$133,0),0)=0,"",INDEX($AE$40:$AE$133,IFERROR(MATCH(33,$AB$40:$AB$133,0),0))&"") -> CA MOEDAS 2,01KG/UC 10UC/CX 30CX/PAL | T66: 811-BR-25A | U66: KG | V66: =SUMIFS(Lançamentos!$H$2:$H$607,Lançamentos!$A$2:$A$607,">="&$F$5,Lançamentos!$A$2:$A$607,"<="&$H$5,Lançamentos!$C$2:$C$607,$T66,Lançamentos!$D$2:$D$607,$AG66,Lançamentos!$B$2:$B$607,"Recebido no 2008") -> 0 | W66: =SUMIFS(Lançamentos!$I$2:$I$607,Lançamentos!$A$2:$A$607,">="&$F$5,Lançamentos!$A$2:$A$607,"<="&$H$5,Lançamentos!$C$2:$C$607,$T66,Lançamentos!$D$2:$D$607,$AG66) -> 2733.6 | X66: =SUMIFS(Lançamentos!$J$2:$J$607,Lançamentos!$A$2:$A$607,">="&$F$5,Lançamentos!$A$2:$A$607,"<="&$H$5,Lançamentos!$C$2:$C$607,$T66,Lançamentos!$D$2:$D$607,$AG66) -> 1206 | Y66: =SUMIFS('Estoque físico'!$J$2:$J$229,'Estoque físico'!$A$2:$A$229,$T66,'Estoque físico'!$B$2:$B$229,$AG66) -> 1547.7 | Z66: =ROUND(Y66-(W66-X66),3) -> 20.1 | AA66: =IF(AND(U66=$R$3,OR($R$1="*",T66=$R$1),OR($R$2="*",AG66=$R$2),ABS(V66)+ABS(W66)+ABS(X66)+ABS(Y66)>0),1,0) -> 1 | AB66: =IF(AA66=1,SUM(AA$40:AA66),"") -> 22 | AC66: =IF(ABS(Z66)<=$R$5,"Confere",IF(Z66>0,"Sobrando","Faltando")) -> Sobrando | AD66: =COUNTIFS(Lançamentos!$A$2:$A$607,">="&$F$5,Lançamentos!$A$2:$A$607,"<="&$H$5,Lançamentos!$C$2:$C$607,$T66,Lançamentos!$D$2:$D$607,$AG66,Lançamentos!$B$2:$B$607,$R$4,Lançamentos!$G$2:$G$607,U66) -> 7 | AE66: CA MOEDAS 2,01KG/UC 10UC/CX 30CX/PAL | AF66: =IF(AND(AA66=1,AC66<>"Confere"),ABS(Z66)+ROW()/10000000,0) -> 20.100007 | AG66: 252450301 | AV66: =IFERROR(INDEX($AX$1:$AX$94,MATCH(65,$AY$1:$AY$94,0)),"") -> 253470301 | AW66: CW2-BR-25A | AX66: 261070301 | AY66: =IF(OR($A$5="Todos",AW66=$A$5),MAX(AY$1:AY65)+1,0) -> 66
A67: =IF(IFERROR(MATCH(34,$AB$40:$AB$133,0),0)=0,"",INDEX($T$40:$T$133,IFERROR(MATCH(34,$AB$40:$AB$133,0),0))) -> 823-BR-25A | B67: =IF(IFERROR(MATCH(34,$AB$40:$AB$133,0),0)=0,"",INDEX($AG$40:$AG$133,IFERROR(MATCH(34,$AB$40:$AB$133,0),0))) -> 252940301 | C67: =IF(IFERROR(MATCH(34,$AB$40:$AB$133,0),0)=0,"",INDEX($U$40:$U$133,IFERROR(MATCH(34,$AB$40:$AB$133,0),0))) -> KG | D67: =IF(IFERROR(MATCH(34,$AB$40:$AB$133,0),0)=0,"",INDEX($V$40:$V$133,IFERROR(MATCH(34,$AB$40:$AB$133,0),0))) -> 0 | E67: =IF(IFERROR(MATCH(34,$AB$40:$AB$133,0),0)=0,"",INDEX($W$40:$W$133,IFERROR(MATCH(34,$AB$40:$AB$133,0),0))) -> 1809 | F67: =IF(IFERROR(MATCH(34,$AB$40:$AB$133,0),0)=0,"",INDEX($X$40:$X$133,IFERROR(MATCH(34,$AB$40:$AB$133,0),0))) -> 1025.1 | G67: =IF(A67="","",E67-F67) -> 783.9 | H67: =IF(IFERROR(MATCH(34,$AB$40:$AB$133,0),0)=0,"",INDEX($Y$40:$Y$133,IFERROR(MATCH(34,$AB$40:$AB$133,0),0))) -> 783.9 | I67: =IF(IFERROR(MATCH(34,$AB$40:$AB$133,0),0)=0,"",INDEX($Z$40:$Z$133,IFERROR(MATCH(34,$AB$40:$AB$133,0),0))) -> 0 | J67: =IF(IFERROR(MATCH(34,$AB$40:$AB$133,0),0)=0,"",INDEX($AC$40:$AC$133,IFERROR(MATCH(34,$AB$40:$AB$133,0),0))) -> Confere | K67: =IF(IFERROR(MATCH(34,$AB$40:$AB$133,0),0)=0,"",INDEX($AD$40:$AD$133,IFERROR(MATCH(34,$AB$40:$AB$133,0),0))) -> 9 | L67: =IF(IFERROR(MATCH(34,$AB$40:$AB$133,0),0)=0,"",INDEX($AE$40:$AE$133,IFERROR(MATCH(34,$AB$40:$AB$133,0),0))&"") -> CA MOEDAS 2,01KG/UC 10UC/CX 30CX/PAL | T67: W3-BR-25A | U67: KG | V67: =SUMIFS(Lançamentos!$H$2:$H$607,Lançamentos!$A$2:$A$607,">="&$F$5,Lançamentos!$A$2:$A$607,"<="&$H$5,Lançamentos!$C$2:$C$607,$T67,Lançamentos!$D$2:$D$607,$AG67,Lançamentos!$B$2:$B$607,"Recebido no 2008") -> 2995 | W67: =SUMIFS(Lançamentos!$I$2:$I$607,Lançamentos!$A$2:$A$607,">="&$F$5,Lançamentos!$A$2:$A$607,"<="&$H$5,Lançamentos!$C$2:$C$607,$T67,Lançamentos!$D$2:$D$607,$AG67) -> 3025.7 | X67: =SUMIFS(Lançamentos!$J$2:$J$607,Lançamentos!$A$2:$A$607,">="&$F$5,Lançamentos!$A$2:$A$607,"<="&$H$5,Lançamentos!$C$2:$C$607,$T67,Lançamentos!$D$2:$D$607,$AG67) -> 1366.8 | Y67: =SUMIFS('Estoque físico'!$J$2:$J$229,'Estoque físico'!$A$2:$A$229,$T67,'Estoque físico'!$B$2:$B$229,$AG67) -> 1679 | Z67: =ROUND(Y67-(W67-X67),3) -> 20.1 | AA67: =IF(AND(U67=$R$3,OR($R$1="*",T67=$R$1),OR($R$2="*",AG67=$R$2),ABS(V67)+ABS(W67)+ABS(X67)+ABS(Y67)>0),1,0) -> 1 | AB67: =IF(AA67=1,SUM(AA$40:AA67),"") -> 23 | AC67: =IF(ABS(Z67)<=$R$5,"Confere",IF(Z67>0,"Sobrando","Faltando")) -> Sobrando | AD67: =COUNTIFS(Lançamentos!$A$2:$A$607,">="&$F$5,Lançamentos!$A$2:$A$607,"<="&$H$5,Lançamentos!$C$2:$C$607,$T67,Lançamentos!$D$2:$D$607,$AG67,Lançamentos!$B$2:$B$607,$R$4,Lançamentos!$G$2:$G$607,U67) -> 18 | AE67: CA MOEDAS 2,01KG/UC 10UC/CX 30CX/PAL | AF67: =IF(AND(AA67=1,AC67<>"Confere"),ABS(Z67)+ROW()/10000000,0) -> 20.100007 | AG67: 261080301 | AV67: =IFERROR(INDEX($AX$1:$AX$94,MATCH(66,$AY$1:$AY$94,0)),"") -> 261070301 | AW67: CW2NV-595 | AX67: 260850602 | AY67: =IF(OR($A$5="Todos",AW67=$A$5),MAX(AY$1:AY66)+1,0) -> 67
A68: =IF(IFERROR(MATCH(35,$AB$40:$AB$133,0),0)=0,"",INDEX($T$40:$T$133,IFERROR(MATCH(35,$AB$40:$AB$133,0),0))) -> 823NV-132 | B68: =IF(IFERROR(MATCH(35,$AB$40:$AB$133,0),0)=0,"",INDEX($AG$40:$AG$133,IFERROR(MATCH(35,$AB$40:$AB$133,0),0))) -> 260880201 | C68: =IF(IFERROR(MATCH(35,$AB$40:$AB$133,0),0)=0,"",INDEX($U$40:$U$133,IFERROR(MATCH(35,$AB$40:$AB$133,0),0))) -> KG | D68: =IF(IFERROR(MATCH(35,$AB$40:$AB$133,0),0)=0,"",INDEX($V$40:$V$133,IFERROR(MATCH(35,$AB$40:$AB$133,0),0))) -> 0 | E68: =IF(IFERROR(MATCH(35,$AB$40:$AB$133,0),0)=0,"",INDEX($W$40:$W$133,IFERROR(MATCH(35,$AB$40:$AB$133,0),0))) -> 1000 | F68: =IF(IFERROR(MATCH(35,$AB$40:$AB$133,0),0)=0,"",INDEX($X$40:$X$133,IFERROR(MATCH(35,$AB$40:$AB$133,0),0))) -> 0 | G68: =IF(A68="","",E68-F68) -> 1000 | H68: =IF(IFERROR(MATCH(35,$AB$40:$AB$133,0),0)=0,"",INDEX($Y$40:$Y$133,IFERROR(MATCH(35,$AB$40:$AB$133,0),0))) -> 1000 | I68: =IF(IFERROR(MATCH(35,$AB$40:$AB$133,0),0)=0,"",INDEX($Z$40:$Z$133,IFERROR(MATCH(35,$AB$40:$AB$133,0),0))) -> 0 | J68: =IF(IFERROR(MATCH(35,$AB$40:$AB$133,0),0)=0,"",INDEX($AC$40:$AC$133,IFERROR(MATCH(35,$AB$40:$AB$133,0),0))) -> Confere | K68: =IF(IFERROR(MATCH(35,$AB$40:$AB$133,0),0)=0,"",INDEX($AD$40:$AD$133,IFERROR(MATCH(35,$AB$40:$AB$133,0),0))) -> 1 | L68: =IF(IFERROR(MATCH(35,$AB$40:$AB$133,0),0)=0,"",INDEX($AE$40:$AE$133,IFERROR(MATCH(35,$AB$40:$AB$133,0),0))&"") | T68: 2665-E4-U71 | U68: KG | V68: =SUMIFS(Lançamentos!$H$2:$H$607,Lançamentos!$A$2:$A$607,">="&$F$5,Lançamentos!$A$2:$A$607,"<="&$H$5,Lançamentos!$C$2:$C$607,$T68,Lançamentos!$D$2:$D$607,$AG68,Lançamentos!$B$2:$B$607,"Recebido no 2008") -> 0 | W68: =SUMIFS(Lançamentos!$I$2:$I$607,Lançamentos!$A$2:$A$607,">="&$F$5,Lançamentos!$A$2:$A$607,"<="&$H$5,Lançamentos!$C$2:$C$607,$T68,Lançamentos!$D$2:$D$607,$AG68) -> 1200 | X68: =SUMIFS(Lançamentos!$J$2:$J$607,Lançamentos!$A$2:$A$607,">="&$F$5,Lançamentos!$A$2:$A$607,"<="&$H$5,Lançamentos!$C$2:$C$607,$T68,Lançamentos!$D$2:$D$607,$AG68) -> 0 | Y68: =SUMIFS('Estoque físico'!$J$2:$J$229,'Estoque físico'!$A$2:$A$229,$T68,'Estoque físico'!$B$2:$B$229,$AG68) -> 1200 | Z68: =ROUND(Y68-(W68-X68),3) -> 0 | AA68: =IF(AND(U68=$R$3,OR($R$1="*",T68=$R$1),OR($R$2="*",AG68=$R$2),ABS(V68)+ABS(W68)+ABS(X68)+ABS(Y68)>0),1,0) -> 1 | AB68: =IF(AA68=1,SUM(AA$40:AA68),"") -> 24 | AC68: =IF(ABS(Z68)<=$R$5,"Confere",IF(Z68>0,"Sobrando","Faltando")) -> Confere | AD68: =COUNTIFS(Lançamentos!$A$2:$A$607,">="&$F$5,Lançamentos!$A$2:$A$607,"<="&$H$5,Lançamentos!$C$2:$C$607,$T68,Lançamentos!$D$2:$D$607,$AG68,Lançamentos!$B$2:$B$607,$R$4,Lançamentos!$G$2:$G$607,U68) -> 2 | AF68: =IF(AND(AA68=1,AC68<>"Confere"),ABS(Z68)+ROW()/10000000,0) -> 0 | AG68: 252800202 | AV68: =IFERROR(INDEX($AX$1:$AX$94,MATCH(67,$AY$1:$AY$94,0)),"") -> 260850602 | AW68: CW2NV-595 | AX68: 261070601 | AY68: =IF(OR($A$5="Todos",AW68=$A$5),MAX(AY$1:AY67)+1,0) -> 68
A69: =IF(IFERROR(MATCH(36,$AB$40:$AB$133,0),0)=0,"",INDEX($T$40:$T$133,IFERROR(MATCH(36,$AB$40:$AB$133,0),0))) -> 823NV-595 | B69: =IF(IFERROR(MATCH(36,$AB$40:$AB$133,0),0)=0,"",INDEX($AG$40:$AG$133,IFERROR(MATCH(36,$AB$40:$AB$133,0),0))) -> 260416102 | C69: =IF(IFERROR(MATCH(36,$AB$40:$AB$133,0),0)=0,"",INDEX($U$40:$U$133,IFERROR(MATCH(36,$AB$40:$AB$133,0),0))) -> KG | D69: =IF(IFERROR(MATCH(36,$AB$40:$AB$133,0),0)=0,"",INDEX($V$40:$V$133,IFERROR(MATCH(36,$AB$40:$AB$133,0),0))) -> 0 | E69: =IF(IFERROR(MATCH(36,$AB$40:$AB$133,0),0)=0,"",INDEX($W$40:$W$133,IFERROR(MATCH(36,$AB$40:$AB$133,0),0))) -> 1800 | F69: =IF(IFERROR(MATCH(36,$AB$40:$AB$133,0),0)=0,"",INDEX($X$40:$X$133,IFERROR(MATCH(36,$AB$40:$AB$133,0),0))) -> 0 | G69: =IF(A69="","",E69-F69) -> 1800 | H69: =IF(IFERROR(MATCH(36,$AB$40:$AB$133,0),0)=0,"",INDEX($Y$40:$Y$133,IFERROR(MATCH(36,$AB$40:$AB$133,0),0))) -> 1800 | I69: =IF(IFERROR(MATCH(36,$AB$40:$AB$133,0),0)=0,"",INDEX($Z$40:$Z$133,IFERROR(MATCH(36,$AB$40:$AB$133,0),0))) -> 0 | J69: =IF(IFERROR(MATCH(36,$AB$40:$AB$133,0),0)=0,"",INDEX($AC$40:$AC$133,IFERROR(MATCH(36,$AB$40:$AB$133,0),0))) -> Confere | K69: =IF(IFERROR(MATCH(36,$AB$40:$AB$133,0),0)=0,"",INDEX($AD$40:$AD$133,IFERROR(MATCH(36,$AB$40:$AB$133,0),0))) -> 1 | L69: =IF(IFERROR(MATCH(36,$AB$40:$AB$133,0),0)=0,"",INDEX($AE$40:$AE$133,IFERROR(MATCH(36,$AB$40:$AB$133,0),0))&"") -> CA CALLETS 10KG/UC 2UC/BOX 30BOX/PAL | T69: 70-30-38-BR-25A | U69: KG | V69: =SUMIFS(Lançamentos!$H$2:$H$607,Lançamentos!$A$2:$A$607,">="&$F$5,Lançamentos!$A$2:$A$607,"<="&$H$5,Lançamentos!$C$2:$C$607,$T69,Lançamentos!$D$2:$D$607,$AG69,Lançamentos!$B$2:$B$607,"Recebido no 2008") -> 0 | W69: =SUMIFS(Lançamentos!$I$2:$I$607,Lançamentos!$A$2:$A$607,">="&$F$5,Lançamentos!$A$2:$A$607,"<="&$H$5,Lançamentos!$C$2:$C$607,$T69,Lançamentos!$D$2:$D$607,$AG69) -> 3015 | X69: =SUMIFS(Lançamentos!$J$2:$J$607,Lançamentos!$A$2:$A$607,">="&$F$5,Lançamentos!$A$2:$A$607,"<="&$H$5,Lançamentos!$C$2:$C$607,$T69,Lançamentos!$D$2:$D$607,$AG69) -> 2673.3 | Y69: =SUMIFS('Estoque físico'!$J$2:$J$229,'Estoque físico'!$A$2:$A$229,$T69,'Estoque físico'!$B$2:$B$229,$AG69) -> 341.7 | Z69: =ROUND(Y69-(W69-X69),3) -> 0 | AA69: =IF(AND(U69=$R$3,OR($R$1="*",T69=$R$1),OR($R$2="*",AG69=$R$2),ABS(V69)+ABS(W69)+ABS(X69)+ABS(Y69)>0),1,0) -> 1 | AB69: =IF(AA69=1,SUM(AA$40:AA69),"") -> 25 | AC69: =IF(ABS(Z69)<=$R$5,"Confere",IF(Z69>0,"Sobrando","Faltando")) -> Confere | AD69: =COUNTIFS(Lançamentos!$A$2:$A$607,">="&$F$5,Lançamentos!$A$2:$A$607,"<="&$H$5,Lançamentos!$C$2:$C$607,$T69,Lançamentos!$D$2:$D$607,$AG69,Lançamentos!$B$2:$B$607,$R$4,Lançamentos!$G$2:$G$607,U69) -> 20 | AE69: CA MOEDAS 2,01KG/UC 10UC/CX 30CX/PAL | AF69: =IF(AND(AA69=1,AC69<>"Confere"),ABS(Z69)+ROW()/10000000,0) -> 0 | AG69: 260070301 | AV69: =IFERROR(INDEX($AX$1:$AX$94,MATCH(68,$AY$1:$AY$94,0)),"") -> 261070601 | AW69: DCP-10BONOI-89B | AX69: 260778132 | AY69: =IF(OR($A$5="Todos",AW69=$A$5),MAX(AY$1:AY68)+1,0) -> 69
A70: =IF(IFERROR(MATCH(37,$AB$40:$AB$133,0),0)=0,"",INDEX($T$40:$T$133,IFERROR(MATCH(37,$AB$40:$AB$133,0),0))) -> 823NV-595 | B70: =IF(IFERROR(MATCH(37,$AB$40:$AB$133,0),0)=0,"",INDEX($AG$40:$AG$133,IFERROR(MATCH(37,$AB$40:$AB$133,0),0))) -> 261376101 | C70: =IF(IFERROR(MATCH(37,$AB$40:$AB$133,0),0)=0,"",INDEX($U$40:$U$133,IFERROR(MATCH(37,$AB$40:$AB$133,0),0))) -> KG | D70: =IF(IFERROR(MATCH(37,$AB$40:$AB$133,0),0)=0,"",INDEX($V$40:$V$133,IFERROR(MATCH(37,$AB$40:$AB$133,0),0))) -> 6000 | E70: =IF(IFERROR(MATCH(37,$AB$40:$AB$133,0),0)=0,"",INDEX($W$40:$W$133,IFERROR(MATCH(37,$AB$40:$AB$133,0),0))) -> 5940 | F70: =IF(IFERROR(MATCH(37,$AB$40:$AB$133,0),0)=0,"",INDEX($X$40:$X$133,IFERROR(MATCH(37,$AB$40:$AB$133,0),0))) -> 4940 | G70: =IF(A70="","",E70-F70) -> 1000 | H70: =IF(IFERROR(MATCH(37,$AB$40:$AB$133,0),0)=0,"",INDEX($Y$40:$Y$133,IFERROR(MATCH(37,$AB$40:$AB$133,0),0))) -> 1000 | I70: =IF(IFERROR(MATCH(37,$AB$40:$AB$133,0),0)=0,"",INDEX($Z$40:$Z$133,IFERROR(MATCH(37,$AB$40:$AB$133,0),0))) -> 0 | J70: =IF(IFERROR(MATCH(37,$AB$40:$AB$133,0),0)=0,"",INDEX($AC$40:$AC$133,IFERROR(MATCH(37,$AB$40:$AB$133,0),0))) -> Confere | K70: =IF(IFERROR(MATCH(37,$AB$40:$AB$133,0),0)=0,"",INDEX($AD$40:$AD$133,IFERROR(MATCH(37,$AB$40:$AB$133,0),0))) -> 12 | L70: =IF(IFERROR(MATCH(37,$AB$40:$AB$133,0),0)=0,"",INDEX($AE$40:$AE$133,IFERROR(MATCH(37,$AB$40:$AB$133,0),0))&"") -> CA CALLETS 10KG/UC 2UC/BOX 30BOX/PAL | T70: 805-BR-D94 | U70: KG | V70: =SUMIFS(Lançamentos!$H$2:$H$607,Lançamentos!$A$2:$A$607,">="&$F$5,Lançamentos!$A$2:$A$607,"<="&$H$5,Lançamentos!$C$2:$C$607,$T70,Lançamentos!$D$2:$D$607,$AG70,Lançamentos!$B$2:$B$607,"Recebido no 2008") -> 0 | W70: =SUMIFS(Lançamentos!$I$2:$I$607,Lançamentos!$A$2:$A$607,">="&$F$5,Lançamentos!$A$2:$A$607,"<="&$H$5,Lançamentos!$C$2:$C$607,$T70,Lançamentos!$D$2:$D$607,$AG70) -> 142.8 | X70: =SUMIFS(Lançamentos!$J$2:$J$607,Lançamentos!$A$2:$A$607,">="&$F$5,Lançamentos!$A$2:$A$607,"<="&$H$5,Lançamentos!$C$2:$C$607,$T70,Lançamentos!$D$2:$D$607,$AG70) -> 0 | Y70: =SUMIFS('Estoque físico'!$J$2:$J$229,'Estoque físico'!$A$2:$A$229,$T70,'Estoque físico'!$B$2:$B$229,$AG70) -> 142.8 | Z70: =ROUND(Y70-(W70-X70),3) -> 0 | AA70: =IF(AND(U70=$R$3,OR($R$1="*",T70=$R$1),OR($R$2="*",AG70=$R$2),ABS(V70)+ABS(W70)+ABS(X70)+ABS(Y70)>0),1,0) -> 1 | AB70: =IF(AA70=1,SUM(AA$40:AA70),"") -> 26 | AC70: =IF(ABS(Z70)<=$R$5,"Confere",IF(Z70>0,"Sobrando","Faltando")) -> Confere | AD70: =COUNTIFS(Lançamentos!$A$2:$A$607,">="&$F$5,Lançamentos!$A$2:$A$607,"<="&$H$5,Lançamentos!$C$2:$C$607,$T70,Lançamentos!$D$2:$D$607,$AG70,Lançamentos!$B$2:$B$607,$R$4,Lançamentos!$G$2:$G$607,U70) -> 1 | AE70: CA MOEDAS 0,4KG/UC 7UC/CX 144CX/PAL | AF70: =IF(AND(AA70=1,AC70<>"Confere"),ABS(Z70)+ROW()/10000000,0) -> 0 | AG70: 260130779 | AV70: =IFERROR(INDEX($AX$1:$AX$94,MATCH(69,$AY$1:$AY$94,0)),"") -> 260778132 | AW70: DCP-20BODEC-89B | AX70: 261388131 | AY70: =IF(OR($A$5="Todos",AW70=$A$5),MAX(AY$1:AY69)+1,0) -> 70
A71: =IF(IFERROR(MATCH(38,$AB$40:$AB$133,0),0)=0,"",INDEX($T$40:$T$133,IFERROR(MATCH(38,$AB$40:$AB$133,0),0))) -> BIG-PF-1BO-401 | B71: =IF(IFERROR(MATCH(38,$AB$40:$AB$133,0),0)=0,"",INDEX($AG$40:$AG$133,IFERROR(MATCH(38,$AB$40:$AB$133,0),0))) -> 26093039 | C71: =IF(IFERROR(MATCH(38,$AB$40:$AB$133,0),0)=0,"",INDEX($U$40:$U$133,IFERROR(MATCH(38,$AB$40:$AB$133,0),0))) -> KG | D71: =IF(IFERROR(MATCH(38,$AB$40:$AB$133,0),0)=0,"",INDEX($V$40:$V$133,IFERROR(MATCH(38,$AB$40:$AB$133,0),0))) -> 0 | E71: =IF(IFERROR(MATCH(38,$AB$40:$AB$133,0),0)=0,"",INDEX($W$40:$W$133,IFERROR(MATCH(38,$AB$40:$AB$133,0),0))) -> 720 | F71: =IF(IFERROR(MATCH(38,$AB$40:$AB$133,0),0)=0,"",INDEX($X$40:$X$133,IFERROR(MATCH(38,$AB$40:$AB$133,0),0))) -> 240 | G71: =IF(A71="","",E71-F71) -> 480 | H71: =IF(IFERROR(MATCH(38,$AB$40:$AB$133,0),0)=0,"",INDEX($Y$40:$Y$133,IFERROR(MATCH(38,$AB$40:$AB$133,0),0))) -> 480 | I71: =IF(IFERROR(MATCH(38,$AB$40:$AB$133,0),0)=0,"",INDEX($Z$40:$Z$133,IFERROR(MATCH(38,$AB$40:$AB$133,0),0))) -> 0 | J71: =IF(IFERROR(MATCH(38,$AB$40:$AB$133,0),0)=0,"",INDEX($AC$40:$AC$133,IFERROR(MATCH(38,$AB$40:$AB$133,0),0))) -> Confere | K71: =IF(IFERROR(MATCH(38,$AB$40:$AB$133,0),0)=0,"",INDEX($AD$40:$AD$133,IFERROR(MATCH(38,$AB$40:$AB$133,0),0))) -> 2 | L71: =IF(IFERROR(MATCH(38,$AB$40:$AB$133,0),0)=0,"",INDEX($AE$40:$AE$133,IFERROR(MATCH(38,$AB$40:$AB$133,0),0))&"") -> CB PAILLETÉ FEUILLETINE 2.5KG/UC 4UC/BOX | T71: 811NV-132 | U71: KG | V71: =SUMIFS(Lançamentos!$H$2:$H$607,Lançamentos!$A$2:$A$607,">="&$F$5,Lançamentos!$A$2:$A$607,"<="&$H$5,Lançamentos!$C$2:$C$607,$T71,Lançamentos!$D$2:$D$607,$AG71,Lançamentos!$B$2:$B$607,"Recebido no 2008") -> 0 | W71: =SUMIFS(Lançamentos!$I$2:$I$607,Lançamentos!$A$2:$A$607,">="&$F$5,Lançamentos!$A$2:$A$607,"<="&$H$5,Lançamentos!$C$2:$C$607,$T71,Lançamentos!$D$2:$D$607,$AG71) -> 1500 | X71: =SUMIFS(Lançamentos!$J$2:$J$607,Lançamentos!$A$2:$A$607,">="&$F$5,Lançamentos!$A$2:$A$607,"<="&$H$5,Lançamentos!$C$2:$C$607,$T71,Lançamentos!$D$2:$D$607,$AG71) -> 0 | Y71: =SUMIFS('Estoque físico'!$J$2:$J$229,'Estoque físico'!$A$2:$A$229,$T71,'Estoque físico'!$B$2:$B$229,$AG71) -> 1500 | Z71: =ROUND(Y71-(W71-X71),3) -> 0 | AA71: =IF(AND(U71=$R$3,OR($R$1="*",T71=$R$1),OR($R$2="*",AG71=$R$2),ABS(V71)+ABS(W71)+ABS(X71)+ABS(Y71)>0),1,0) -> 1 | AB71: =IF(AA71=1,SUM(AA$40:AA71),"") -> 27 | AC71: =IF(ABS(Z71)<=$R$5,"Confere",IF(Z71>0,"Sobrando","Faltando")) -> Confere | AD71: =COUNTIFS(Lançamentos!$A$2:$A$607,">="&$F$5,Lançamentos!$A$2:$A$607,"<="&$H$5,Lançamentos!$C$2:$C$607,$T71,Lançamentos!$D$2:$D$607,$AG71,Lançamentos!$B$2:$B$607,$R$4,Lançamentos!$G$2:$G$607,U71) -> 4 | AE71: 96_FU:811NV-50C_CA BLOCKS 5KG/UC 5UC | AF71: =IF(AND(AA71=1,AC71<>"Confere"),ABS(Z71)+ROW()/10000000,0) -> 0 | AG71: 252510301 | AV71: =IFERROR(INDEX($AX$1:$AX$94,MATCH(70,$AY$1:$AY$94,0)),"") -> 261388131 | AW71: DCP-22ZEPLA-89B | AX71: 260348131 | AY71: =IF(OR($A$5="Todos",AW71=$A$5),MAX(AY$1:AY70)+1,0) -> 71
A72: =IF(IFERROR(MATCH(39,$AB$40:$AB$133,0),0)=0,"",INDEX($T$40:$T$133,IFERROR(MATCH(39,$AB$40:$AB$133,0),0))) -> BIG-PF-1BO-401 | B72: =IF(IFERROR(MATCH(39,$AB$40:$AB$133,0),0)=0,"",INDEX($AG$40:$AG$133,IFERROR(MATCH(39,$AB$40:$AB$133,0),0))) -> 26126039 | C72: =IF(IFERROR(MATCH(39,$AB$40:$AB$133,0),0)=0,"",INDEX($U$40:$U$133,IFERROR(MATCH(39,$AB$40:$AB$133,0),0))) -> KG | D72: =IF(IFERROR(MATCH(39,$AB$40:$AB$133,0),0)=0,"",INDEX($V$40:$V$133,IFERROR(MATCH(39,$AB$40:$AB$133,0),0))) -> 2880 | E72: =IF(IFERROR(MATCH(39,$AB$40:$AB$133,0),0)=0,"",INDEX($W$40:$W$133,IFERROR(MATCH(39,$AB$40:$AB$133,0),0))) -> 40 | F72: =IF(IFERROR(MATCH(39,$AB$40:$AB$133,0),0)=0,"",INDEX($X$40:$X$133,IFERROR(MATCH(39,$AB$40:$AB$133,0),0))) -> 0 | G72: =IF(A72="","",E72-F72) -> 40 | H72: =IF(IFERROR(MATCH(39,$AB$40:$AB$133,0),0)=0,"",INDEX($Y$40:$Y$133,IFERROR(MATCH(39,$AB$40:$AB$133,0),0))) -> 40 | I72: =IF(IFERROR(MATCH(39,$AB$40:$AB$133,0),0)=0,"",INDEX($Z$40:$Z$133,IFERROR(MATCH(39,$AB$40:$AB$133,0),0))) -> 0 | J72: =IF(IFERROR(MATCH(39,$AB$40:$AB$133,0),0)=0,"",INDEX($AC$40:$AC$133,IFERROR(MATCH(39,$AB$40:$AB$133,0),0))) -> Confere | K72: =IF(IFERROR(MATCH(39,$AB$40:$AB$133,0),0)=0,"",INDEX($AD$40:$AD$133,IFERROR(MATCH(39,$AB$40:$AB$133,0),0))) -> 3 | L72: =IF(IFERROR(MATCH(39,$AB$40:$AB$133,0),0)=0,"",INDEX($AE$40:$AE$133,IFERROR(MATCH(39,$AB$40:$AB$133,0),0))&"") -> CB PAILLETÉ FEUILLETINE 2.5KG/UC 4UC/BOX | T72: 811NV-132 | U72: KG | V72: =SUMIFS(Lançamentos!$H$2:$H$607,Lançamentos!$A$2:$A$607,">="&$F$5,Lançamentos!$A$2:$A$607,"<="&$H$5,Lançamentos!$C$2:$C$607,$T72,Lançamentos!$D$2:$D$607,$AG72,Lançamentos!$B$2:$B$607,"Recebido no 2008") -> 0 | W72: =SUMIFS(Lançamentos!$I$2:$I$607,Lançamentos!$A$2:$A$607,">="&$F$5,Lançamentos!$A$2:$A$607,"<="&$H$5,Lançamentos!$C$2:$C$607,$T72,Lançamentos!$D$2:$D$607,$AG72) -> 1750 | X72: =SUMIFS(Lançamentos!$J$2:$J$607,Lançamentos!$A$2:$A$607,">="&$F$5,Lançamentos!$A$2:$A$607,"<="&$H$5,Lançamentos!$C$2:$C$607,$T72,Lançamentos!$D$2:$D$607,$AG72) -> 800 | Y72: =SUMIFS('Estoque físico'!$J$2:$J$229,'Estoque físico'!$A$2:$A$229,$T72,'Estoque físico'!$B$2:$B$229,$AG72) -> 950 | Z72: =ROUND(Y72-(W72-X72),3) -> 0 | AA72: =IF(AND(U72=$R$3,OR($R$1="*",T72=$R$1),OR($R$2="*",AG72=$R$2),ABS(V72)+ABS(W72)+ABS(X72)+ABS(Y72)>0),1,0) -> 1 | AB72: =IF(AA72=1,SUM(AA$40:AA72),"") -> 28 | AC72: =IF(ABS(Z72)<=$R$5,"Confere",IF(Z72>0,"Sobrando","Faltando")) -> Confere | AD72: =COUNTIFS(Lançamentos!$A$2:$A$607,">="&$F$5,Lançamentos!$A$2:$A$607,"<="&$H$5,Lançamentos!$C$2:$C$607,$T72,Lançamentos!$D$2:$D$607,$AG72,Lançamentos!$B$2:$B$607,$R$4,Lançamentos!$G$2:$G$607,U72) -> 9 | AE72: 96_FU:811NV-50C_CA BLOCKS 5KG/UC 5UC | AF72: =IF(AND(AA72=1,AC72<>"Confere"),ABS(Z72)+ROW()/10000000,0) -> 0 | AG72: 253280301 | AV72: =IFERROR(INDEX($AX$1:$AX$94,MATCH(71,$AY$1:$AY$94,0)),"") -> 260348131 | AW72: DCP-22ZEPLA-89B | AX72: 260358131 | AY72: =IF(OR($A$5="Todos",AW72=$A$5),MAX(AY$1:AY71)+1,0) -> 72
A73: =IF(IFERROR(MATCH(40,$AB$40:$AB$133,0),0)=0,"",INDEX($T$40:$T$133,IFERROR(MATCH(40,$AB$40:$AB$133,0),0))) -> CHD-DR-75Y5-E1-U68 | B73: =IF(IFERROR(MATCH(40,$AB$40:$AB$133,0),0)=0,"",INDEX($AG$40:$AG$133,IFERROR(MATCH(40,$AB$40:$AB$133,0),0))) -> 252810301 | C73: =IF(IFERROR(MATCH(40,$AB$40:$AB$133,0),0)=0,"",INDEX($U$40:$U$133,IFERROR(MATCH(40,$AB$40:$AB$133,0),0))) -> KG | D73: =IF(IFERROR(MATCH(40,$AB$40:$AB$133,0),0)=0,"",INDEX($V$40:$V$133,IFERROR(MATCH(40,$AB$40:$AB$133,0),0))) -> 0 | E73: =IF(IFERROR(MATCH(40,$AB$40:$AB$133,0),0)=0,"",INDEX($W$40:$W$133,IFERROR(MATCH(40,$AB$40:$AB$133,0),0))) -> 648 | F73: =IF(IFERROR(MATCH(40,$AB$40:$AB$133,0),0)=0,"",INDEX($X$40:$X$133,IFERROR(MATCH(40,$AB$40:$AB$133,0),0))) -> 54 | G73: =IF(A73="","",E73-F73) -> 594 | H73: =IF(IFERROR(MATCH(40,$AB$40:$AB$133,0),0)=0,"",INDEX($Y$40:$Y$133,IFERROR(MATCH(40,$AB$40:$AB$133,0),0))) -> 594 | I73: =IF(IFERROR(MATCH(40,$AB$40:$AB$133,0),0)=0,"",INDEX($Z$40:$Z$133,IFERROR(MATCH(40,$AB$40:$AB$133,0),0))) -> 0 | J73: =IF(IFERROR(MATCH(40,$AB$40:$AB$133,0),0)=0,"",INDEX($AC$40:$AC$133,IFERROR(MATCH(40,$AB$40:$AB$133,0),0))) -> Confere | K73: =IF(IFERROR(MATCH(40,$AB$40:$AB$133,0),0)=0,"",INDEX($AD$40:$AD$133,IFERROR(MATCH(40,$AB$40:$AB$133,0),0))) -> 5 | L73: =IF(IFERROR(MATCH(40,$AB$40:$AB$133,0),0)=0,"",INDEX($AE$40:$AE$133,IFERROR(MATCH(40,$AB$40:$AB$133,0),0))&"") -> CB CHIPS 7500CT/KG 1KG/UC 6UC/CX | T73: 811NV-595 | U73: KG | V73: =SUMIFS(Lançamentos!$H$2:$H$607,Lançamentos!$A$2:$A$607,">="&$F$5,Lançamentos!$A$2:$A$607,"<="&$H$5,Lançamentos!$C$2:$C$607,$T73,Lançamentos!$D$2:$D$607,$AG73,Lançamentos!$B$2:$B$607,"Recebido no 2008") -> 0 | W73: =SUMIFS(Lançamentos!$I$2:$I$607,Lançamentos!$A$2:$A$607,">="&$F$5,Lançamentos!$A$2:$A$607,"<="&$H$5,Lançamentos!$C$2:$C$607,$T73,Lançamentos!$D$2:$D$607,$AG73) -> 1800 | X73: =SUMIFS(Lançamentos!$J$2:$J$607,Lançamentos!$A$2:$A$607,">="&$F$5,Lançamentos!$A$2:$A$607,"<="&$H$5,Lançamentos!$C$2:$C$607,$T73,Lançamentos!$D$2:$D$607,$AG73) -> 1780 | Y73: =SUMIFS('Estoque físico'!$J$2:$J$229,'Estoque físico'!$A$2:$A$229,$T73,'Estoque físico'!$B$2:$B$229,$AG73) -> 20 | Z73: =ROUND(Y73-(W73-X73),3) -> 0 | AA73: =IF(AND(U73=$R$3,OR($R$1="*",T73=$R$1),OR($R$2="*",AG73=$R$2),ABS(V73)+ABS(W73)+ABS(X73)+ABS(Y73)>0),1,0) -> 1 | AB73: =IF(AA73=1,SUM(AA$40:AA73),"") -> 29 | AC73: =IF(ABS(Z73)<=$R$5,"Confere",IF(Z73>0,"Sobrando","Faltando")) -> Confere | AD73: =COUNTIFS(Lançamentos!$A$2:$A$607,">="&$F$5,Lançamentos!$A$2:$A$607,"<="&$H$5,Lançamentos!$C$2:$C$607,$T73,Lançamentos!$D$2:$D$607,$AG73,Lançamentos!$B$2:$B$607,$R$4,Lançamentos!$G$2:$G$607,U73) -> 3 | AE73: CA CALLETS 10KG/UC 2UC/BOX 30BOX/PAL | AF73: =IF(AND(AA73=1,AC73<>"Confere"),ABS(Z73)+ROW()/10000000,0) -> 0 | AG73: 260900702 | AV73: =IFERROR(INDEX($AX$1:$AX$94,MATCH(72,$AY$1:$AY$94,0)),"") -> 260358131 | AW73: GIA-145 | AX73: 2518442009 | AY73: =IF(OR($A$5="Todos",AW73=$A$5),MAX(AY$1:AY72)+1,0) -> 73
A74: =IF(IFERROR(MATCH(41,$AB$40:$AB$133,0),0)=0,"",INDEX($T$40:$T$133,IFERROR(MATCH(41,$AB$40:$AB$133,0),0))) -> CHD-SP-1M-2B-U77 | B74: =IF(IFERROR(MATCH(41,$AB$40:$AB$133,0),0)=0,"",INDEX($AG$40:$AG$133,IFERROR(MATCH(41,$AB$40:$AB$133,0),0))) -> 260880101 | C74: =IF(IFERROR(MATCH(41,$AB$40:$AB$133,0),0)=0,"",INDEX($U$40:$U$133,IFERROR(MATCH(41,$AB$40:$AB$133,0),0))) -> KG | D74: =IF(IFERROR(MATCH(41,$AB$40:$AB$133,0),0)=0,"",INDEX($V$40:$V$133,IFERROR(MATCH(41,$AB$40:$AB$133,0),0))) -> 2400 | E74: =IF(IFERROR(MATCH(41,$AB$40:$AB$133,0),0)=0,"",INDEX($W$40:$W$133,IFERROR(MATCH(41,$AB$40:$AB$133,0),0))) -> 0 | F74: =IF(IFERROR(MATCH(41,$AB$40:$AB$133,0),0)=0,"",INDEX($X$40:$X$133,IFERROR(MATCH(41,$AB$40:$AB$133,0),0))) -> 0 | G74: =IF(A74="","",E74-F74) -> 0 | H74: =IF(IFERROR(MATCH(41,$AB$40:$AB$133,0),0)=0,"",INDEX($Y$40:$Y$133,IFERROR(MATCH(41,$AB$40:$AB$133,0),0))) -> 0 | I74: =IF(IFERROR(MATCH(41,$AB$40:$AB$133,0),0)=0,"",INDEX($Z$40:$Z$133,IFERROR(MATCH(41,$AB$40:$AB$133,0),0))) -> 0 | J74: =IF(IFERROR(MATCH(41,$AB$40:$AB$133,0),0)=0,"",INDEX($AC$40:$AC$133,IFERROR(MATCH(41,$AB$40:$AB$133,0),0))) -> Confere | K74: =IF(IFERROR(MATCH(41,$AB$40:$AB$133,0),0)=0,"",INDEX($AD$40:$AD$133,IFERROR(MATCH(41,$AB$40:$AB$133,0),0))) -> 2 | L74: =IF(IFERROR(MATCH(41,$AB$40:$AB$133,0),0)=0,"",INDEX($AE$40:$AE$133,IFERROR(MATCH(41,$AB$40:$AB$133,0),0))&"") | T74: 811NV-595 | U74: KG | V74: =SUMIFS(Lançamentos!$H$2:$H$607,Lançamentos!$A$2:$A$607,">="&$F$5,Lançamentos!$A$2:$A$607,"<="&$H$5,Lançamentos!$C$2:$C$607,$T74,Lançamentos!$D$2:$D$607,$AG74,Lançamentos!$B$2:$B$607,"Recebido no 2008") -> 0 | W74: =SUMIFS(Lançamentos!$I$2:$I$607,Lançamentos!$A$2:$A$607,">="&$F$5,Lançamentos!$A$2:$A$607,"<="&$H$5,Lançamentos!$C$2:$C$607,$T74,Lançamentos!$D$2:$D$607,$AG74) -> 600 | X74: =SUMIFS(Lançamentos!$J$2:$J$607,Lançamentos!$A$2:$A$607,">="&$F$5,Lançamentos!$A$2:$A$607,"<="&$H$5,Lançamentos!$C$2:$C$607,$T74,Lançamentos!$D$2:$D$607,$AG74) -> 0 | Y74: =SUMIFS('Estoque físico'!$J$2:$J$229,'Estoque físico'!$A$2:$A$229,$T74,'Estoque físico'!$B$2:$B$229,$AG74) -> 600 | Z74: =ROUND(Y74-(W74-X74),3) -> 0 | AA74: =IF(AND(U74=$R$3,OR($R$1="*",T74=$R$1),OR($R$2="*",AG74=$R$2),ABS(V74)+ABS(W74)+ABS(X74)+ABS(Y74)>0),1,0) -> 1 | AB74: =IF(AA74=1,SUM(AA$40:AA74),"") -> 30 | AC74: =IF(ABS(Z74)<=$R$5,"Confere",IF(Z74>0,"Sobrando","Faltando")) -> Confere | AD74: =COUNTIFS(Lançamentos!$A$2:$A$607,">="&$F$5,Lançamentos!$A$2:$A$607,"<="&$H$5,Lançamentos!$C$2:$C$607,$T74,Lançamentos!$D$2:$D$607,$AG74,Lançamentos!$B$2:$B$607,$R$4,Lançamentos!$G$2:$G$607,U74) -> 1 | AE74: CA CALLETS 10KG/UC 2UC/BOX 30BOX/PAL | AF74: =IF(AND(AA74=1,AC74<>"Confere"),ABS(Z74)+ROW()/10000000,0) -> 0 | AG74: 260920702 | AV74: =IFERROR(INDEX($AX$1:$AX$94,MATCH(73,$AY$1:$AY$94,0)),"") -> 2518442009 | AW74: MALCHOC-D-123 | AX74: 261060203 | AY74: =IF(OR($A$5="Todos",AW74=$A$5),MAX(AY$1:AY73)+1,0) -> 74
A75: =IF(IFERROR(MATCH(42,$AB$40:$AB$133,0),0)=0,"",INDEX($T$40:$T$133,IFERROR(MATCH(42,$AB$40:$AB$133,0),0))) -> CHD-SP-1M-BR-U73 | B75: =IF(IFERROR(MATCH(42,$AB$40:$AB$133,0),0)=0,"",INDEX($AG$40:$AG$133,IFERROR(MATCH(42,$AB$40:$AB$133,0),0))) -> 260310301 | C75: =IF(IFERROR(MATCH(42,$AB$40:$AB$133,0),0)=0,"",INDEX($U$40:$U$133,IFERROR(MATCH(42,$AB$40:$AB$133,0),0))) -> KG | D75: =IF(IFERROR(MATCH(42,$AB$40:$AB$133,0),0)=0,"",INDEX($V$40:$V$133,IFERROR(MATCH(42,$AB$40:$AB$133,0),0))) -> 798 | E75: =IF(IFERROR(MATCH(42,$AB$40:$AB$133,0),0)=0,"",INDEX($W$40:$W$133,IFERROR(MATCH(42,$AB$40:$AB$133,0),0))) -> 0 | F75: =IF(IFERROR(MATCH(42,$AB$40:$AB$133,0),0)=0,"",INDEX($X$40:$X$133,IFERROR(MATCH(42,$AB$40:$AB$133,0),0))) -> 0 | G75: =IF(A75="","",E75-F75) -> 0 | H75: =IF(IFERROR(MATCH(42,$AB$40:$AB$133,0),0)=0,"",INDEX($Y$40:$Y$133,IFERROR(MATCH(42,$AB$40:$AB$133,0),0))) -> 0 | I75: =IF(IFERROR(MATCH(42,$AB$40:$AB$133,0),0)=0,"",INDEX($Z$40:$Z$133,IFERROR(MATCH(42,$AB$40:$AB$133,0),0))) -> 0 | J75: =IF(IFERROR(MATCH(42,$AB$40:$AB$133,0),0)=0,"",INDEX($AC$40:$AC$133,IFERROR(MATCH(42,$AB$40:$AB$133,0),0))) -> Confere | K75: =IF(IFERROR(MATCH(42,$AB$40:$AB$133,0),0)=0,"",INDEX($AD$40:$AD$133,IFERROR(MATCH(42,$AB$40:$AB$133,0),0))) -> 1 | L75: =IF(IFERROR(MATCH(42,$AB$40:$AB$133,0),0)=0,"",INDEX($AE$40:$AE$133,IFERROR(MATCH(42,$AB$40:$AB$133,0),0))&"") | T75: 811NV-595 | U75: KG | V75: =SUMIFS(Lançamentos!$H$2:$H$607,Lançamentos!$A$2:$A$607,">="&$F$5,Lançamentos!$A$2:$A$607,"<="&$H$5,Lançamentos!$C$2:$C$607,$T75,Lançamentos!$D$2:$D$607,$AG75,Lançamentos!$B$2:$B$607,"Recebido no 2008") -> 4360 | W75: =SUMIFS(Lançamentos!$I$2:$I$607,Lançamentos!$A$2:$A$607,">="&$F$5,Lançamentos!$A$2:$A$607,"<="&$H$5,Lançamentos!$C$2:$C$607,$T75,Lançamentos!$D$2:$D$607,$AG75) -> 1180 | X75: =SUMIFS(Lançamentos!$J$2:$J$607,Lançamentos!$A$2:$A$607,">="&$F$5,Lançamentos!$A$2:$A$607,"<="&$H$5,Lançamentos!$C$2:$C$607,$T75,Lançamentos!$D$2:$D$607,$AG75) -> 1160 | Y75: =SUMIFS('Estoque físico'!$J$2:$J$229,'Estoque físico'!$A$2:$A$229,$T75,'Estoque físico'!$B$2:$B$229,$AG75) -> 20 | Z75: =ROUND(Y75-(W75-X75),3) -> 0 | AA75: =IF(AND(U75=$R$3,OR($R$1="*",T75=$R$1),OR($R$2="*",AG75=$R$2),ABS(V75)+ABS(W75)+ABS(X75)+ABS(Y75)>0),1,0) -> 1 | AB75: =IF(AA75=1,SUM(AA$40:AA75),"") -> 31 | AC75: =IF(ABS(Z75)<=$R$5,"Confere",IF(Z75>0,"Sobrando","Faltando")) -> Confere | AD75: =COUNTIFS(Lançamentos!$A$2:$A$607,">="&$F$5,Lançamentos!$A$2:$A$607,"<="&$H$5,Lançamentos!$C$2:$C$607,$T75,Lançamentos!$D$2:$D$607,$AG75,Lançamentos!$B$2:$B$607,$R$4,Lançamentos!$G$2:$G$607,U75) -> 3 | AE75: CA CALLETS 10KG/UC 2UC/BOX 30BOX/PAL | AF75: =IF(AND(AA75=1,AC75<>"Confere"),ABS(Z75)+ROW()/10000000,0) -> 0 | AG75: 261146101 | AV75: =IFERROR(INDEX($AX$1:$AX$94,MATCH(74,$AY$1:$AY$94,0)),"") -> 261060203 | AW75: NIBS-S502-X47 | AX75: 242643099 | AY75: =IF(OR($A$5="Todos",AW75=$A$5),MAX(AY$1:AY74)+1,0) -> 75
A76: =IF(IFERROR(MATCH(43,$AB$40:$AB$133,0),0)=0,"",INDEX($T$40:$T$133,IFERROR(MATCH(43,$AB$40:$AB$133,0),0))) -> CHD-SP-1M-BR-U73 | B76: =IF(IFERROR(MATCH(43,$AB$40:$AB$133,0),0)=0,"",INDEX($AG$40:$AG$133,IFERROR(MATCH(43,$AB$40:$AB$133,0),0))) -> 260880301 | C76: =IF(IFERROR(MATCH(43,$AB$40:$AB$133,0),0)=0,"",INDEX($U$40:$U$133,IFERROR(MATCH(43,$AB$40:$AB$133,0),0))) -> KG | D76: =IF(IFERROR(MATCH(43,$AB$40:$AB$133,0),0)=0,"",INDEX($V$40:$V$133,IFERROR(MATCH(43,$AB$40:$AB$133,0),0))) -> 1122 | E76: =IF(IFERROR(MATCH(43,$AB$40:$AB$133,0),0)=0,"",INDEX($W$40:$W$133,IFERROR(MATCH(43,$AB$40:$AB$133,0),0))) -> 0 | F76: =IF(IFERROR(MATCH(43,$AB$40:$AB$133,0),0)=0,"",INDEX($X$40:$X$133,IFERROR(MATCH(43,$AB$40:$AB$133,0),0))) -> 0 | G76: =IF(A76="","",E76-F76) -> 0 | H76: =IF(IFERROR(MATCH(43,$AB$40:$AB$133,0),0)=0,"",INDEX($Y$40:$Y$133,IFERROR(MATCH(43,$AB$40:$AB$133,0),0))) -> 0 | I76: =IF(IFERROR(MATCH(43,$AB$40:$AB$133,0),0)=0,"",INDEX($Z$40:$Z$133,IFERROR(MATCH(43,$AB$40:$AB$133,0),0))) -> 0 | J76: =IF(IFERROR(MATCH(43,$AB$40:$AB$133,0),0)=0,"",INDEX($AC$40:$AC$133,IFERROR(MATCH(43,$AB$40:$AB$133,0),0))) -> Confere | K76: =IF(IFERROR(MATCH(43,$AB$40:$AB$133,0),0)=0,"",INDEX($AD$40:$AD$133,IFERROR(MATCH(43,$AB$40:$AB$133,0),0))) -> 1 | L76: =IF(IFERROR(MATCH(43,$AB$40:$AB$133,0),0)=0,"",INDEX($AE$40:$AE$133,IFERROR(MATCH(43,$AB$40:$AB$133,0),0))&"") | T76: 811NV-595 | U76: KG | V76: =SUMIFS(Lançamentos!$H$2:$H$607,Lançamentos!$A$2:$A$607,">="&$F$5,Lançamentos!$A$2:$A$607,"<="&$H$5,Lançamentos!$C$2:$C$607,$T76,Lançamentos!$D$2:$D$607,$AG76,Lançamentos!$B$2:$B$607,"Recebido no 2008") -> 5240 | W76: =SUMIFS(Lançamentos!$I$2:$I$607,Lançamentos!$A$2:$A$607,">="&$F$5,Lançamentos!$A$2:$A$607,"<="&$H$5,Lançamentos!$C$2:$C$607,$T76,Lançamentos!$D$2:$D$607,$AG76) -> 1660 | X76: =SUMIFS(Lançamentos!$J$2:$J$607,Lançamentos!$A$2:$A$607,">="&$F$5,Lançamentos!$A$2:$A$607,"<="&$H$5,Lançamentos!$C$2:$C$607,$T76,Lançamentos!$D$2:$D$607,$AG76) -> 580 | Y76: =SUMIFS('Estoque físico'!$J$2:$J$229,'Estoque físico'!$A$2:$A$229,$T76,'Estoque físico'!$B$2:$B$229,$AG76) -> 1080 | Z76: =ROUND(Y76-(W76-X76),3) -> 0 | AA76: =IF(AND(U76=$R$3,OR($R$1="*",T76=$R$1),OR($R$2="*",AG76=$R$2),ABS(V76)+ABS(W76)+ABS(X76)+ABS(Y76)>0),1,0) -> 1 | AB76: =IF(AA76=1,SUM(AA$40:AA76),"") -> 32 | AC76: =IF(ABS(Z76)<=$R$5,"Confere",IF(Z76>0,"Sobrando","Faltando")) -> Confere | AD76: =COUNTIFS(Lançamentos!$A$2:$A$607,">="&$F$5,Lançamentos!$A$2:$A$607,"<="&$H$5,Lançamentos!$C$2:$C$607,$T76,Lançamentos!$D$2:$D$607,$AG76,Lançamentos!$B$2:$B$607,$R$4,Lançamentos!$G$2:$G$607,U76) -> 10 | AE76: CA CALLETS 10KG/UC 2UC/BOX 30BOX/PAL | AF76: =IF(AND(AA76=1,AC76<>"Confere"),ABS(Z76)+ROW()/10000000,0) -> 0 | AG76: 261146102 | AV76: =IFERROR(INDEX($AX$1:$AX$94,MATCH(75,$AY$1:$AY$94,0)),"") -> 242643099 | AW76: NIBS-S502-X47 | AX76: 252643099 | AY76: =IF(OR($A$5="Todos",AW76=$A$5),MAX(AY$1:AY75)+1,0) -> 76
A77: =IF(IFERROR(MATCH(44,$AB$40:$AB$133,0),0)=0,"",INDEX($T$40:$T$133,IFERROR(MATCH(44,$AB$40:$AB$133,0),0))) -> CHD-TS-22350E0-999 | B77: =IF(IFERROR(MATCH(44,$AB$40:$AB$133,0),0)=0,"",INDEX($AG$40:$AG$133,IFERROR(MATCH(44,$AB$40:$AB$133,0),0))) -> 2520443650 | C77: =IF(IFERROR(MATCH(44,$AB$40:$AB$133,0),0)=0,"",INDEX($U$40:$U$133,IFERROR(MATCH(44,$AB$40:$AB$133,0),0))) -> KG | D77: =IF(IFERROR(MATCH(44,$AB$40:$AB$133,0),0)=0,"",INDEX($V$40:$V$133,IFERROR(MATCH(44,$AB$40:$AB$133,0),0))) -> 0 | E77: =IF(IFERROR(MATCH(44,$AB$40:$AB$133,0),0)=0,"",INDEX($W$40:$W$133,IFERROR(MATCH(44,$AB$40:$AB$133,0),0))) -> 81.6 | F77: =IF(IFERROR(MATCH(44,$AB$40:$AB$133,0),0)=0,"",INDEX($X$40:$X$133,IFERROR(MATCH(44,$AB$40:$AB$133,0),0))) -> 0 | G77: =IF(A77="","",E77-F77) -> 81.6 | H77: =IF(IFERROR(MATCH(44,$AB$40:$AB$133,0),0)=0,"",INDEX($Y$40:$Y$133,IFERROR(MATCH(44,$AB$40:$AB$133,0),0))) -> 81.6 | I77: =IF(IFERROR(MATCH(44,$AB$40:$AB$133,0),0)=0,"",INDEX($Z$40:$Z$133,IFERROR(MATCH(44,$AB$40:$AB$133,0),0))) -> 0 | J77: =IF(IFERROR(MATCH(44,$AB$40:$AB$133,0),0)=0,"",INDEX($AC$40:$AC$133,IFERROR(MATCH(44,$AB$40:$AB$133,0),0))) -> Confere | K77: =IF(IFERROR(MATCH(44,$AB$40:$AB$133,0),0)=0,"",INDEX($AD$40:$AD$133,IFERROR(MATCH(44,$AB$40:$AB$133,0),0))) -> 1 | L77: =IF(IFERROR(MATCH(44,$AB$40:$AB$133,0),0)=0,"",INDEX($AE$40:$AE$133,IFERROR(MATCH(44,$AB$40:$AB$133,0),0))&"") | T77: 823-BR-25A | U77: KG | V77: =SUMIFS(Lançamentos!$H$2:$H$607,Lançamentos!$A$2:$A$607,">="&$F$5,Lançamentos!$A$2:$A$607,"<="&$H$5,Lançamentos!$C$2:$C$607,$T77,Lançamentos!$D$2:$D$607,$AG77,Lançamentos!$B$2:$B$607,"Recebido no 2008") -> 0 | W77: =SUMIFS(Lançamentos!$I$2:$I$607,Lançamentos!$A$2:$A$607,">="&$F$5,Lançamentos!$A$2:$A$607,"<="&$H$5,Lançamentos!$C$2:$C$607,$T77,Lançamentos!$D$2:$D$607,$AG77) -> 461.9 | X77: =SUMIFS(Lançamentos!$J$2:$J$607,Lançamentos!$A$2:$A$607,">="&$F$5,Lançamentos!$A$2:$A$607,"<="&$H$5,Lançamentos!$C$2:$C$607,$T77,Lançamentos!$D$2:$D$607,$AG77) -> 442.2 | Y77: =SUMIFS('Estoque físico'!$J$2:$J$229,'Estoque físico'!$A$2:$A$229,$T77,'Estoque físico'!$B$2:$B$229,$AG77) -> 19.7 | Z77: =ROUND(Y77-(W77-X77),3) -> 0 | AA77: =IF(AND(U77=$R$3,OR($R$1="*",T77=$R$1),OR($R$2="*",AG77=$R$2),ABS(V77)+ABS(W77)+ABS(X77)+ABS(Y77)>0),1,0) -> 1 | AB77: =IF(AA77=1,SUM(AA$40:AA77),"") -> 33 | AC77: =IF(ABS(Z77)<=$R$5,"Confere",IF(Z77>0,"Sobrando","Faltando")) -> Confere | AD77: =COUNTIFS(Lançamentos!$A$2:$A$607,">="&$F$5,Lançamentos!$A$2:$A$607,"<="&$H$5,Lançamentos!$C$2:$C$607,$T77,Lançamentos!$D$2:$D$607,$AG77,Lançamentos!$B$2:$B$607,$R$4,Lançamentos!$G$2:$G$607,U77) -> 2 | AE77: CA MOEDAS 2,01KG/UC 10UC/CX 30CX/PAL | AF77: =IF(AND(AA77=1,AC77<>"Confere"),ABS(Z77)+ROW()/10000000,0) -> 0 | AG77: 252100301 | AV77: =IFERROR(INDEX($AX$1:$AX$94,MATCH(76,$AY$1:$AY$94,0)),"") -> 252643099 | AW77: NIBS-S502-X47 | AX77: 252683099 | AY77: =IF(OR($A$5="Todos",AW77=$A$5),MAX(AY$1:AY76)+1,0) -> 77
A78: =IF(IFERROR(MATCH(45,$AB$40:$AB$133,0),0)=0,"",INDEX($T$40:$T$133,IFERROR(MATCH(45,$AB$40:$AB$133,0),0))) -> CHD-VR-Z2S-E0-U68 | B78: =IF(IFERROR(MATCH(45,$AB$40:$AB$133,0),0)=0,"",INDEX($AG$40:$AG$133,IFERROR(MATCH(45,$AB$40:$AB$133,0),0))) -> 261160301 | C78: =IF(IFERROR(MATCH(45,$AB$40:$AB$133,0),0)=0,"",INDEX($U$40:$U$133,IFERROR(MATCH(45,$AB$40:$AB$133,0),0))) -> KG | D78: =IF(IFERROR(MATCH(45,$AB$40:$AB$133,0),0)=0,"",INDEX($V$40:$V$133,IFERROR(MATCH(45,$AB$40:$AB$133,0),0))) -> 1296 | E78: =IF(IFERROR(MATCH(45,$AB$40:$AB$133,0),0)=0,"",INDEX($W$40:$W$133,IFERROR(MATCH(45,$AB$40:$AB$133,0),0))) -> 0 | F78: =IF(IFERROR(MATCH(45,$AB$40:$AB$133,0),0)=0,"",INDEX($X$40:$X$133,IFERROR(MATCH(45,$AB$40:$AB$133,0),0))) -> 0 | G78: =IF(A78="","",E78-F78) -> 0 | H78: =IF(IFERROR(MATCH(45,$AB$40:$AB$133,0),0)=0,"",INDEX($Y$40:$Y$133,IFERROR(MATCH(45,$AB$40:$AB$133,0),0))) -> 0 | I78: =IF(IFERROR(MATCH(45,$AB$40:$AB$133,0),0)=0,"",INDEX($Z$40:$Z$133,IFERROR(MATCH(45,$AB$40:$AB$133,0),0))) -> 0 | J78: =IF(IFERROR(MATCH(45,$AB$40:$AB$133,0),0)=0,"",INDEX($AC$40:$AC$133,IFERROR(MATCH(45,$AB$40:$AB$133,0),0))) -> Confere | K78: =IF(IFERROR(MATCH(45,$AB$40:$AB$133,0),0)=0,"",INDEX($AD$40:$AD$133,IFERROR(MATCH(45,$AB$40:$AB$133,0),0))) -> 1 | L78: =IF(IFERROR(MATCH(45,$AB$40:$AB$133,0),0)=0,"",INDEX($AE$40:$AE$133,IFERROR(MATCH(45,$AB$40:$AB$133,0),0))&"") | T78: 823-BR-25A | U78: KG | V78: =SUMIFS(Lançamentos!$H$2:$H$607,Lançamentos!$A$2:$A$607,">="&$F$5,Lançamentos!$A$2:$A$607,"<="&$H$5,Lançamentos!$C$2:$C$607,$T78,Lançamentos!$D$2:$D$607,$AG78,Lançamentos!$B$2:$B$607,"Recebido no 2008") -> 0 | W78: =SUMIFS(Lançamentos!$I$2:$I$607,Lançamentos!$A$2:$A$607,">="&$F$5,Lançamentos!$A$2:$A$607,"<="&$H$5,Lançamentos!$C$2:$C$607,$T78,Lançamentos!$D$2:$D$607,$AG78) -> 1809 | X78: =SUMIFS(Lançamentos!$J$2:$J$607,Lançamentos!$A$2:$A$607,">="&$F$5,Lançamentos!$A$2:$A$607,"<="&$H$5,Lançamentos!$C$2:$C$607,$T78,Lançamentos!$D$2:$D$607,$AG78) -> 1025.1 | Y78: =SUMIFS('Estoque físico'!$J$2:$J$229,'Estoque físico'!$A$2:$A$229,$T78,'Estoque físico'!$B$2:$B$229,$AG78) -> 783.9 | Z78: =ROUND(Y78-(W78-X78),3) -> 0 | AA78: =IF(AND(U78=$R$3,OR($R$1="*",T78=$R$1),OR($R$2="*",AG78=$R$2),ABS(V78)+ABS(W78)+ABS(X78)+ABS(Y78)>0),1,0) -> 1 | AB78: =IF(AA78=1,SUM(AA$40:AA78),"") -> 34 | AC78: =IF(ABS(Z78)<=$R$5,"Confere",IF(Z78>0,"Sobrando","Faltando")) -> Confere | AD78: =COUNTIFS(Lançamentos!$A$2:$A$607,">="&$F$5,Lançamentos!$A$2:$A$607,"<="&$H$5,Lançamentos!$C$2:$C$607,$T78,Lançamentos!$D$2:$D$607,$AG78,Lançamentos!$B$2:$B$607,$R$4,Lançamentos!$G$2:$G$607,U78) -> 9 | AE78: CA MOEDAS 2,01KG/UC 10UC/CX 30CX/PAL | AF78: =IF(AND(AA78=1,AC78<>"Confere"),ABS(Z78)+ROW()/10000000,0) -> 0 | AG78: 252940301 | AV78: =IFERROR(INDEX($AX$1:$AX$94,MATCH(77,$AY$1:$AY$94,0)),"") -> 252683099 | AW78: NIBS-S502-X47 | AX78: 253490619 | AY78: =IF(OR($A$5="Todos",AW78=$A$5),MAX(AY$1:AY77)+1,0) -> 78
A79: =IF(IFERROR(MATCH(46,$AB$40:$AB$133,0),0)=0,"",INDEX($T$40:$T$133,IFERROR(MATCH(46,$AB$40:$AB$133,0),0))) -> CHK-D-413 | B79: =IF(IFERROR(MATCH(46,$AB$40:$AB$133,0),0)=0,"",INDEX($AG$40:$AG$133,IFERROR(MATCH(46,$AB$40:$AB$133,0),0))) -> 261756201 | C79: =IF(IFERROR(MATCH(46,$AB$40:$AB$133,0),0)=0,"",INDEX($U$40:$U$133,IFERROR(MATCH(46,$AB$40:$AB$133,0),0))) -> KG | D79: =IF(IFERROR(MATCH(46,$AB$40:$AB$133,0),0)=0,"",INDEX($V$40:$V$133,IFERROR(MATCH(46,$AB$40:$AB$133,0),0))) -> 1280 | E79: =IF(IFERROR(MATCH(46,$AB$40:$AB$133,0),0)=0,"",INDEX($W$40:$W$133,IFERROR(MATCH(46,$AB$40:$AB$133,0),0))) -> 0 | F79: =IF(IFERROR(MATCH(46,$AB$40:$AB$133,0),0)=0,"",INDEX($X$40:$X$133,IFERROR(MATCH(46,$AB$40:$AB$133,0),0))) -> 0 | G79: =IF(A79="","",E79-F79) -> 0 | H79: =IF(IFERROR(MATCH(46,$AB$40:$AB$133,0),0)=0,"",INDEX($Y$40:$Y$133,IFERROR(MATCH(46,$AB$40:$AB$133,0),0))) -> 0 | I79: =IF(IFERROR(MATCH(46,$AB$40:$AB$133,0),0)=0,"",INDEX($Z$40:$Z$133,IFERROR(MATCH(46,$AB$40:$AB$133,0),0))) -> 0 | J79: =IF(IFERROR(MATCH(46,$AB$40:$AB$133,0),0)=0,"",INDEX($AC$40:$AC$133,IFERROR(MATCH(46,$AB$40:$AB$133,0),0))) -> Confere | K79: =IF(IFERROR(MATCH(46,$AB$40:$AB$133,0),0)=0,"",INDEX($AD$40:$AD$133,IFERROR(MATCH(46,$AB$40:$AB$133,0),0))) -> 1 | L79: =IF(IFERROR(MATCH(46,$AB$40:$AB$133,0),0)=0,"",INDEX($AE$40:$AE$133,IFERROR(MATCH(46,$AB$40:$AB$133,0),0))&"") | T79: 823NV-132 | U79: KG | V79: =SUMIFS(Lançamentos!$H$2:$H$607,Lançamentos!$A$2:$A$607,">="&$F$5,Lançamentos!$A$2:$A$607,"<="&$H$5,Lançamentos!$C$2:$C$607,$T79,Lançamentos!$D$2:$D$607,$AG79,Lançamentos!$B$2:$B$607,"Recebido no 2008") -> 0 | W79: =SUMIFS(Lançamentos!$I$2:$I$607,Lançamentos!$A$2:$A$607,">="&$F$5,Lançamentos!$A$2:$A$607,"<="&$H$5,Lançamentos!$C$2:$C$607,$T79,Lançamentos!$D$2:$D$607,$AG79) -> 1000 | X79: =SUMIFS(Lançamentos!$J$2:$J$607,Lançamentos!$A$2:$A$607,">="&$F$5,Lançamentos!$A$2:$A$607,"<="&$H$5,Lançamentos!$C$2:$C$607,$T79,Lançamentos!$D$2:$D$607,$AG79) -> 0 | Y79: =SUMIFS('Estoque físico'!$J$2:$J$229,'Estoque físico'!$A$2:$A$229,$T79,'Estoque físico'!$B$2:$B$229,$AG79) -> 1000 | Z79: =ROUND(Y79-(W79-X79),3) -> 0 | AA79: =IF(AND(U79=$R$3,OR($R$1="*",T79=$R$1),OR($R$2="*",AG79=$R$2),ABS(V79)+ABS(W79)+ABS(X79)+ABS(Y79)>0),1,0) -> 1 | AB79: =IF(AA79=1,SUM(AA$40:AA79),"") -> 35 | AC79: =IF(ABS(Z79)<=$R$5,"Confere",IF(Z79>0,"Sobrando","Faltando")) -> Confere | AD79: =COUNTIFS(Lançamentos!$A$2:$A$607,">="&$F$5,Lançamentos!$A$2:$A$607,"<="&$H$5,Lançamentos!$C$2:$C$607,$T79,Lançamentos!$D$2:$D$607,$AG79,Lançamentos!$B$2:$B$607,$R$4,Lançamentos!$G$2:$G$607,U79) -> 1 | AF79: =IF(AND(AA79=1,AC79<>"Confere"),ABS(Z79)+ROW()/10000000,0) -> 0 | AG79: 260880201 | AV79: =IFERROR(INDEX($AX$1:$AX$94,MATCH(78,$AY$1:$AY$94,0)),"") -> 253490619 | AW79: NIBS-S502-X47 | AX79: 260341149 | AY79: =IF(OR($A$5="Todos",AW79=$A$5),MAX(AY$1:AY78)+1,0) -> 79
A80: =IF(IFERROR(MATCH(47,$AB$40:$AB$133,0),0)=0,"",INDEX($T$40:$T$133,IFERROR(MATCH(47,$AB$40:$AB$133,0),0))) -> CHK-R30GOLD-BR-25A | B80: =IF(IFERROR(MATCH(47,$AB$40:$AB$133,0),0)=0,"",INDEX($AG$40:$AG$133,IFERROR(MATCH(47,$AB$40:$AB$133,0),0))) -> 252750301 | C80: =IF(IFERROR(MATCH(47,$AB$40:$AB$133,0),0)=0,"",INDEX($U$40:$U$133,IFERROR(MATCH(47,$AB$40:$AB$133,0),0))) -> KG | D80: =IF(IFERROR(MATCH(47,$AB$40:$AB$133,0),0)=0,"",INDEX($V$40:$V$133,IFERROR(MATCH(47,$AB$40:$AB$133,0),0))) -> 160.8 | E80: =IF(IFERROR(MATCH(47,$AB$40:$AB$133,0),0)=0,"",INDEX($W$40:$W$133,IFERROR(MATCH(47,$AB$40:$AB$133,0),0))) -> 0 | F80: =IF(IFERROR(MATCH(47,$AB$40:$AB$133,0),0)=0,"",INDEX($X$40:$X$133,IFERROR(MATCH(47,$AB$40:$AB$133,0),0))) -> 0 | G80: =IF(A80="","",E80-F80) -> 0 | H80: =IF(IFERROR(MATCH(47,$AB$40:$AB$133,0),0)=0,"",INDEX($Y$40:$Y$133,IFERROR(MATCH(47,$AB$40:$AB$133,0),0))) -> 0 | I80: =IF(IFERROR(MATCH(47,$AB$40:$AB$133,0),0)=0,"",INDEX($Z$40:$Z$133,IFERROR(MATCH(47,$AB$40:$AB$133,0),0))) -> 0 | J80: =IF(IFERROR(MATCH(47,$AB$40:$AB$133,0),0)=0,"",INDEX($AC$40:$AC$133,IFERROR(MATCH(47,$AB$40:$AB$133,0),0))) -> Confere | K80: =IF(IFERROR(MATCH(47,$AB$40:$AB$133,0),0)=0,"",INDEX($AD$40:$AD$133,IFERROR(MATCH(47,$AB$40:$AB$133,0),0))) -> 1 | L80: =IF(IFERROR(MATCH(47,$AB$40:$AB$133,0),0)=0,"",INDEX($AE$40:$AE$133,IFERROR(MATCH(47,$AB$40:$AB$133,0),0))&"") -> CA MOEDAS 2,01KG/UC 10UC/CX 30CX/PAL | T80: 823NV-595 | U80: KG | V80: =SUMIFS(Lançamentos!$H$2:$H$607,Lançamentos!$A$2:$A$607,">="&$F$5,Lançamentos!$A$2:$A$607,"<="&$H$5,Lançamentos!$C$2:$C$607,$T80,Lançamentos!$D$2:$D$607,$AG80,Lançamentos!$B$2:$B$607,"Recebido no 2008") -> 0 | W80: =SUMIFS(Lançamentos!$I$2:$I$607,Lançamentos!$A$2:$A$607,">="&$F$5,Lançamentos!$A$2:$A$607,"<="&$H$5,Lançamentos!$C$2:$C$607,$T80,Lançamentos!$D$2:$D$607,$AG80) -> 1800 | X80: =SUMIFS(Lançamentos!$J$2:$J$607,Lançamentos!$A$2:$A$607,">="&$F$5,Lançamentos!$A$2:$A$607,"<="&$H$5,Lançamentos!$C$2:$C$607,$T80,Lançamentos!$D$2:$D$607,$AG80) -> 0 | Y80: =SUMIFS('Estoque físico'!$J$2:$J$229,'Estoque físico'!$A$2:$A$229,$T80,'Estoque físico'!$B$2:$B$229,$AG80) -> 1800 | Z80: =ROUND(Y80-(W80-X80),3) -> 0 | AA80: =IF(AND(U80=$R$3,OR($R$1="*",T80=$R$1),OR($R$2="*",AG80=$R$2),ABS(V80)+ABS(W80)+ABS(X80)+ABS(Y80)>0),1,0) -> 1 | AB80: =IF(AA80=1,SUM(AA$40:AA80),"") -> 36 | AC80: =IF(ABS(Z80)<=$R$5,"Confere",IF(Z80>0,"Sobrando","Faltando")) -> Confere | AD80: =COUNTIFS(Lançamentos!$A$2:$A$607,">="&$F$5,Lançamentos!$A$2:$A$607,"<="&$H$5,Lançamentos!$C$2:$C$607,$T80,Lançamentos!$D$2:$D$607,$AG80,Lançamentos!$B$2:$B$607,$R$4,Lançamentos!$G$2:$G$607,U80) -> 1 | AE80: CA CALLETS 10KG/UC 2UC/BOX 30BOX/PAL | AF80: =IF(AND(AA80=1,AC80<>"Confere"),ABS(Z80)+ROW()/10000000,0) -> 0 | AG80: 260416102 | AV80: =IFERROR(INDEX($AX$1:$AX$94,MATCH(79,$AY$1:$AY$94,0)),"") -> 260341149 | AW80: NIBS-S502-X47 | AX80: 260611429 | AY80: =IF(OR($A$5="Todos",AW80=$A$5),MAX(AY$1:AY79)+1,0) -> 80
A81: =IF(IFERROR(MATCH(48,$AB$40:$AB$133,0),0)=0,"",INDEX($T$40:$T$133,IFERROR(MATCH(48,$AB$40:$AB$133,0),0))) -> CHK-W-413 | B81: =IF(IFERROR(MATCH(48,$AB$40:$AB$133,0),0)=0,"",INDEX($AG$40:$AG$133,IFERROR(MATCH(48,$AB$40:$AB$133,0),0))) -> 260536201 | C81: =IF(IFERROR(MATCH(48,$AB$40:$AB$133,0),0)=0,"",INDEX($U$40:$U$133,IFERROR(MATCH(48,$AB$40:$AB$133,0),0))) -> KG | D81: =IF(IFERROR(MATCH(48,$AB$40:$AB$133,0),0)=0,"",INDEX($V$40:$V$133,IFERROR(MATCH(48,$AB$40:$AB$133,0),0))) -> 640 | E81: =IF(IFERROR(MATCH(48,$AB$40:$AB$133,0),0)=0,"",INDEX($W$40:$W$133,IFERROR(MATCH(48,$AB$40:$AB$133,0),0))) -> 0 | F81: =IF(IFERROR(MATCH(48,$AB$40:$AB$133,0),0)=0,"",INDEX($X$40:$X$133,IFERROR(MATCH(48,$AB$40:$AB$133,0),0))) -> 0 | G81: =IF(A81="","",E81-F81) -> 0 | H81: =IF(IFERROR(MATCH(48,$AB$40:$AB$133,0),0)=0,"",INDEX($Y$40:$Y$133,IFERROR(MATCH(48,$AB$40:$AB$133,0),0))) -> 0 | I81: =IF(IFERROR(MATCH(48,$AB$40:$AB$133,0),0)=0,"",INDEX($Z$40:$Z$133,IFERROR(MATCH(48,$AB$40:$AB$133,0),0))) -> 0 | J81: =IF(IFERROR(MATCH(48,$AB$40:$AB$133,0),0)=0,"",INDEX($AC$40:$AC$133,IFERROR(MATCH(48,$AB$40:$AB$133,0),0))) -> Confere | K81: =IF(IFERROR(MATCH(48,$AB$40:$AB$133,0),0)=0,"",INDEX($AD$40:$AD$133,IFERROR(MATCH(48,$AB$40:$AB$133,0),0))) -> 1 | L81: =IF(IFERROR(MATCH(48,$AB$40:$AB$133,0),0)=0,"",INDEX($AE$40:$AE$133,IFERROR(MATCH(48,$AB$40:$AB$133,0),0))&"") | T81: 823NV-595 | U81: KG | V81: =SUMIFS(Lançamentos!$H$2:$H$607,Lançamentos!$A$2:$A$607,">="&$F$5,Lançamentos!$A$2:$A$607,"<="&$H$5,Lançamentos!$C$2:$C$607,$T81,Lançamentos!$D$2:$D$607,$AG81,Lançamentos!$B$2:$B$607,"Recebido no 2008") -> 6000 | W81: =SUMIFS(Lançamentos!$I$2:$I$607,Lançamentos!$A$2:$A$607,">="&$F$5,Lançamentos!$A$2:$A$607,"<="&$H$5,Lançamentos!$C$2:$C$607,$T81,Lançamentos!$D$2:$D$607,$AG81) -> 5940 | X81: =SUMIFS(Lançamentos!$J$2:$J$607,Lançamentos!$A$2:$A$607,">="&$F$5,Lançamentos!$A$2:$A$607,"<="&$H$5,Lançamentos!$C$2:$C$607,$T81,Lançamentos!$D$2:$D$607,$AG81) -> 4940 | Y81: =SUMIFS('Estoque físico'!$J$2:$J$229,'Estoque físico'!$A$2:$A$229,$T81,'Estoque físico'!$B$2:$B$229,$AG81) -> 1000 | Z81: =ROUND(Y81-(W81-X81),3) -> 0 | AA81: =IF(AND(U81=$R$3,OR($R$1="*",T81=$R$1),OR($R$2="*",AG81=$R$2),ABS(V81)+ABS(W81)+ABS(X81)+ABS(Y81)>0),1,0) -> 1 | AB81: =IF(AA81=1,SUM(AA$40:AA81),"") -> 37 | AC81: =IF(ABS(Z81)<=$R$5,"Confere",IF(Z81>0,"Sobrando","Faltando")) -> Confere | AD81: =COUNTIFS(Lançamentos!$A$2:$A$607,">="&$F$5,Lançamentos!$A$2:$A$607,"<="&$H$5,Lançamentos!$C$2:$C$607,$T81,Lançamentos!$D$2:$D$607,$AG81,Lançamentos!$B$2:$B$607,$R$4,Lançamentos!$G$2:$G$607,U81) -> 12 | AE81: CA CALLETS 10KG/UC 2UC/BOX 30BOX/PAL | AF81: =IF(AND(AA81=1,AC81<>"Confere"),ABS(Z81)+ROW()/10000000,0) -> 0 | AG81: 261376101 | AV81: =IFERROR(INDEX($AX$1:$AX$94,MATCH(80,$AY$1:$AY$94,0)),"") -> 260611429 | AW81: NIBS-S502-X47 | AX81: 260691479 | AY81: =IF(OR($A$5="Todos",AW81=$A$5),MAX(AY$1:AY80)+1,0) -> 81
A82: =IF(IFERROR(MATCH(49,$AB$40:$AB$133,0),0)=0,"",INDEX($T$40:$T$133,IFERROR(MATCH(49,$AB$40:$AB$133,0),0))) -> CHM-Q41ALUN-2B-U73 | B82: =IF(IFERROR(MATCH(49,$AB$40:$AB$133,0),0)=0,"",INDEX($AG$40:$AG$133,IFERROR(MATCH(49,$AB$40:$AB$133,0),0))) -> 260660303 | C82: =IF(IFERROR(MATCH(49,$AB$40:$AB$133,0),0)=0,"",INDEX($U$40:$U$133,IFERROR(MATCH(49,$AB$40:$AB$133,0),0))) -> KG | D82: =IF(IFERROR(MATCH(49,$AB$40:$AB$133,0),0)=0,"",INDEX($V$40:$V$133,IFERROR(MATCH(49,$AB$40:$AB$133,0),0))) -> 384 | E82: =IF(IFERROR(MATCH(49,$AB$40:$AB$133,0),0)=0,"",INDEX($W$40:$W$133,IFERROR(MATCH(49,$AB$40:$AB$133,0),0))) -> 0 | F82: =IF(IFERROR(MATCH(49,$AB$40:$AB$133,0),0)=0,"",INDEX($X$40:$X$133,IFERROR(MATCH(49,$AB$40:$AB$133,0),0))) -> 0 | G82: =IF(A82="","",E82-F82) -> 0 | H82: =IF(IFERROR(MATCH(49,$AB$40:$AB$133,0),0)=0,"",INDEX($Y$40:$Y$133,IFERROR(MATCH(49,$AB$40:$AB$133,0),0))) -> 0 | I82: =IF(IFERROR(MATCH(49,$AB$40:$AB$133,0),0)=0,"",INDEX($Z$40:$Z$133,IFERROR(MATCH(49,$AB$40:$AB$133,0),0))) -> 0 | J82: =IF(IFERROR(MATCH(49,$AB$40:$AB$133,0),0)=0,"",INDEX($AC$40:$AC$133,IFERROR(MATCH(49,$AB$40:$AB$133,0),0))) -> Confere | K82: =IF(IFERROR(MATCH(49,$AB$40:$AB$133,0),0)=0,"",INDEX($AD$40:$AD$133,IFERROR(MATCH(49,$AB$40:$AB$133,0),0))) -> 1 | L82: =IF(IFERROR(MATCH(49,$AB$40:$AB$133,0),0)=0,"",INDEX($AE$40:$AE$133,IFERROR(MATCH(49,$AB$40:$AB$133,0),0))&"") | T82: BIG-PF-1BO-401 | U82: KG | V82: =SUMIFS(Lançamentos!$H$2:$H$607,Lançamentos!$A$2:$A$607,">="&$F$5,Lançamentos!$A$2:$A$607,"<="&$H$5,Lançamentos!$C$2:$C$607,$T82,Lançamentos!$D$2:$D$607,$AG82,Lançamentos!$B$2:$B$607,"Recebido no 2008") -> 0 | W82: =SUMIFS(Lançamentos!$I$2:$I$607,Lançamentos!$A$2:$A$607,">="&$F$5,Lançamentos!$A$2:$A$607,"<="&$H$5,Lançamentos!$C$2:$C$607,$T82,Lançamentos!$D$2:$D$607,$AG82) -> 720 | X82: =SUMIFS(Lançamentos!$J$2:$J$607,Lançamentos!$A$2:$A$607,">="&$F$5,Lançamentos!$A$2:$A$607,"<="&$H$5,Lançamentos!$C$2:$C$607,$T82,Lançamentos!$D$2:$D$607,$AG82) -> 240 | Y82: =SUMIFS('Estoque físico'!$J$2:$J$229,'Estoque físico'!$A$2:$A$229,$T82,'Estoque físico'!$B$2:$B$229,$AG82) -> 480 | Z82: =ROUND(Y82-(W82-X82),3) -> 0 | AA82: =IF(AND(U82=$R$3,OR($R$1="*",T82=$R$1),OR($R$2="*",AG82=$R$2),ABS(V82)+ABS(W82)+ABS(X82)+ABS(Y82)>0),1,0) -> 1 | AB82: =IF(AA82=1,SUM(AA$40:AA82),"") -> 38 | AC82: =IF(ABS(Z82)<=$R$5,"Confere",IF(Z82>0,"Sobrando","Faltando")) -> Confere | AD82: =COUNTIFS(Lançamentos!$A$2:$A$607,">="&$F$5,Lançamentos!$A$2:$A$607,"<="&$H$5,Lançamentos!$C$2:$C$607,$T82,Lançamentos!$D$2:$D$607,$AG82,Lançamentos!$B$2:$B$607,$R$4,Lançamentos!$G$2:$G$607,U82) -> 2 | AE82: CB PAILLETÉ FEUILLETINE 2.5KG/UC 4UC/BOX | AF82: =IF(AND(AA82=1,AC82<>"Confere"),ABS(Z82)+ROW()/10000000,0) -> 0 | AG82: 26093039 | AV82: =IFERROR(INDEX($AX$1:$AX$94,MATCH(81,$AY$1:$AY$94,0)),"") -> 260691479 | AW82: PNP-T14 | AX82: 2608294084 | AY82: =IF(OR($A$5="Todos",AW82=$A$5),MAX(AY$1:AY81)+1,0) -> 82
A83: =IF(IFERROR(MATCH(50,$AB$40:$AB$133,0),0)=0,"",INDEX($T$40:$T$133,IFERROR(MATCH(50,$AB$40:$AB$133,0),0))) -> CHM-SP-Z3L-BR-U73 | B83: =IF(IFERROR(MATCH(50,$AB$40:$AB$133,0),0)=0,"",INDEX($AG$40:$AG$133,IFERROR(MATCH(50,$AB$40:$AB$133,0),0))) -> 250880301 | C83: =IF(IFERROR(MATCH(50,$AB$40:$AB$133,0),0)=0,"",INDEX($U$40:$U$133,IFERROR(MATCH(50,$AB$40:$AB$133,0),0))) -> KG | D83: =IF(IFERROR(MATCH(50,$AB$40:$AB$133,0),0)=0,"",INDEX($V$40:$V$133,IFERROR(MATCH(50,$AB$40:$AB$133,0),0))) -> 0 | E83: =IF(IFERROR(MATCH(50,$AB$40:$AB$133,0),0)=0,"",INDEX($W$40:$W$133,IFERROR(MATCH(50,$AB$40:$AB$133,0),0))) -> 288 | F83: =IF(IFERROR(MATCH(50,$AB$40:$AB$133,0),0)=0,"",INDEX($X$40:$X$133,IFERROR(MATCH(50,$AB$40:$AB$133,0),0))) -> 0 | G83: =IF(A83="","",E83-F83) -> 288 | H83: =IF(IFERROR(MATCH(50,$AB$40:$AB$133,0),0)=0,"",INDEX($Y$40:$Y$133,IFERROR(MATCH(50,$AB$40:$AB$133,0),0))) -> 288 | I83: =IF(IFERROR(MATCH(50,$AB$40:$AB$133,0),0)=0,"",INDEX($Z$40:$Z$133,IFERROR(MATCH(50,$AB$40:$AB$133,0),0))) -> 0 | J83: =IF(IFERROR(MATCH(50,$AB$40:$AB$133,0),0)=0,"",INDEX($AC$40:$AC$133,IFERROR(MATCH(50,$AB$40:$AB$133,0),0))) -> Confere | K83: =IF(IFERROR(MATCH(50,$AB$40:$AB$133,0),0)=0,"",INDEX($AD$40:$AD$133,IFERROR(MATCH(50,$AB$40:$AB$133,0),0))) -> 1 | L83: =IF(IFERROR(MATCH(50,$AB$40:$AB$133,0),0)=0,"",INDEX($AE$40:$AE$133,IFERROR(MATCH(50,$AB$40:$AB$133,0),0))&"") -> CA MILK LARGE FLAKES SPLITTERS 1KG/UC | T83: BIG-PF-1BO-401 | U83: KG | V83: =SUMIFS(Lançamentos!$H$2:$H$607,Lançamentos!$A$2:$A$607,">="&$F$5,Lançamentos!$A$2:$A$607,"<="&$H$5,Lançamentos!$C$2:$C$607,$T83,Lançamentos!$D$2:$D$607,$AG83,Lançamentos!$B$2:$B$607,"Recebido no 2008") -> 2880 | W83: =SUMIFS(Lançamentos!$I$2:$I$607,Lançamentos!$A$2:$A$607,">="&$F$5,Lançamentos!$A$2:$A$607,"<="&$H$5,Lançamentos!$C$2:$C$607,$T83,Lançamentos!$D$2:$D$607,$AG83) -> 40 | X83: =SUMIFS(Lançamentos!$J$2:$J$607,Lançamentos!$A$2:$A$607,">="&$F$5,Lançamentos!$A$2:$A$607,"<="&$H$5,Lançamentos!$C$2:$C$607,$T83,Lançamentos!$D$2:$D$607,$AG83) -> 0 | Y83: =SUMIFS('Estoque físico'!$J$2:$J$229,'Estoque físico'!$A$2:$A$229,$T83,'Estoque físico'!$B$2:$B$229,$AG83) -> 40 | Z83: =ROUND(Y83-(W83-X83),3) -> 0 | AA83: =IF(AND(U83=$R$3,OR($R$1="*",T83=$R$1),OR($R$2="*",AG83=$R$2),ABS(V83)+ABS(W83)+ABS(X83)+ABS(Y83)>0),1,0) -> 1 | AB83: =IF(AA83=1,SUM(AA$40:AA83),"") -> 39 | AC83: =IF(ABS(Z83)<=$R$5,"Confere",IF(Z83>0,"Sobrando","Faltando")) -> Confere | AD83: =COUNTIFS(Lançamentos!$A$2:$A$607,">="&$F$5,Lançamentos!$A$2:$A$607,"<="&$H$5,Lançamentos!$C$2:$C$607,$T83,Lançamentos!$D$2:$D$607,$AG83,Lançamentos!$B$2:$B$607,$R$4,Lançamentos!$G$2:$G$607,U83) -> 3 | AE83: CB PAILLETÉ FEUILLETINE 2.5KG/UC 4UC/BOX | AF83: =IF(AND(AA83=1,AC83<>"Confere"),ABS(Z83)+ROW()/10000000,0) -> 0 | AG83: 26126039 | AV83: =IFERROR(INDEX($AX$1:$AX$94,MATCH(82,$AY$1:$AY$94,0)),"") -> 2608294084 | AW83: PNP-T14 | AX83: 2613495951 | AY83: =IF(OR($A$5="Todos",AW83=$A$5),MAX(AY$1:AY82)+1,0) -> 83
A84: =IF(IFERROR(MATCH(51,$AB$40:$AB$133,0),0)=0,"",INDEX($T$40:$T$133,IFERROR(MATCH(51,$AB$40:$AB$133,0),0))) -> CHM-SP-Z3L-E0-U72 | B84: =IF(IFERROR(MATCH(51,$AB$40:$AB$133,0),0)=0,"",INDEX($AG$40:$AG$133,IFERROR(MATCH(51,$AB$40:$AB$133,0),0))) -> 253100102 | C84: =IF(IFERROR(MATCH(51,$AB$40:$AB$133,0),0)=0,"",INDEX($U$40:$U$133,IFERROR(MATCH(51,$AB$40:$AB$133,0),0))) -> KG | D84: =IF(IFERROR(MATCH(51,$AB$40:$AB$133,0),0)=0,"",INDEX($V$40:$V$133,IFERROR(MATCH(51,$AB$40:$AB$133,0),0))) -> 1300 | E84: =IF(IFERROR(MATCH(51,$AB$40:$AB$133,0),0)=0,"",INDEX($W$40:$W$133,IFERROR(MATCH(51,$AB$40:$AB$133,0),0))) -> 0 | F84: =IF(IFERROR(MATCH(51,$AB$40:$AB$133,0),0)=0,"",INDEX($X$40:$X$133,IFERROR(MATCH(51,$AB$40:$AB$133,0),0))) -> 0 | G84: =IF(A84="","",E84-F84) -> 0 | H84: =IF(IFERROR(MATCH(51,$AB$40:$AB$133,0),0)=0,"",INDEX($Y$40:$Y$133,IFERROR(MATCH(51,$AB$40:$AB$133,0),0))) -> 0 | I84: =IF(IFERROR(MATCH(51,$AB$40:$AB$133,0),0)=0,"",INDEX($Z$40:$Z$133,IFERROR(MATCH(51,$AB$40:$AB$133,0),0))) -> 0 | J84: =IF(IFERROR(MATCH(51,$AB$40:$AB$133,0),0)=0,"",INDEX($AC$40:$AC$133,IFERROR(MATCH(51,$AB$40:$AB$133,0),0))) -> Confere | K84: =IF(IFERROR(MATCH(51,$AB$40:$AB$133,0),0)=0,"",INDEX($AD$40:$AD$133,IFERROR(MATCH(51,$AB$40:$AB$133,0),0))) -> 1 | L84: =IF(IFERROR(MATCH(51,$AB$40:$AB$133,0),0)=0,"",INDEX($AE$40:$AE$133,IFERROR(MATCH(51,$AB$40:$AB$133,0),0))&"") | T84: CHD-BB-308BY-357 | U84: UN | V84: =SUMIFS(Lançamentos!$H$2:$H$607,Lançamentos!$A$2:$A$607,">="&$F$5,Lançamentos!$A$2:$A$607,"<="&$H$5,Lançamentos!$C$2:$C$607,$T84,Lançamentos!$D$2:$D$607,$AG84,Lançamentos!$B$2:$B$607,"Recebido no 2008") -> 0 | W84: =SUMIFS(Lançamentos!$I$2:$I$607,Lançamentos!$A$2:$A$607,">="&$F$5,Lançamentos!$A$2:$A$607,"<="&$H$5,Lançamentos!$C$2:$C$607,$T84,Lançamentos!$D$2:$D$607,$AG84) -> 2250 | X84: =SUMIFS(Lançamentos!$J$2:$J$607,Lançamentos!$A$2:$A$607,">="&$F$5,Lançamentos!$A$2:$A$607,"<="&$H$5,Lançamentos!$C$2:$C$607,$T84,Lançamentos!$D$2:$D$607,$AG84) -> 885 | Y84: =SUMIFS('Estoque físico'!$J$2:$J$229,'Estoque físico'!$A$2:$A$229,$T84,'Estoque físico'!$B$2:$B$229,$AG84) -> 1365 | Z84: =ROUND(Y84-(W84-X84),3) -> 0 | AA84: =IF(AND(U84=$R$3,OR($R$1="*",T84=$R$1),OR($R$2="*",AG84=$R$2),ABS(V84)+ABS(W84)+ABS(X84)+ABS(Y84)>0),1,0) -> 0 | AB84: =IF(AA84=1,SUM(AA$40:AA84),"") | AC84: =IF(ABS(Z84)<=$R$5,"Confere",IF(Z84>0,"Sobrando","Faltando")) -> Confere | AD84: =COUNTIFS(Lançamentos!$A$2:$A$607,">="&$F$5,Lançamentos!$A$2:$A$607,"<="&$H$5,Lançamentos!$C$2:$C$607,$T84,Lançamentos!$D$2:$D$607,$AG84,Lançamentos!$B$2:$B$607,$R$4,Lançamentos!$G$2:$G$607,U84) -> 22 | AE84: CB EXTRUDED 8CM STICKS 1.6KG/UC 15UC/BOX | AF84: =IF(AND(AA84=1,AC84<>"Confere"),ABS(Z84)+ROW()/10000000,0) -> 0 | AG84: 2529778000 | AV84: =IFERROR(INDEX($AX$1:$AX$94,MATCH(83,$AY$1:$AY$94,0)),"") -> 2613495951 | AW84: PRA-T14 | AX84: 2611295089 | AY84: =IF(OR($A$5="Todos",AW84=$A$5),MAX(AY$1:AY83)+1,0) -> 84
A85: =IF(IFERROR(MATCH(52,$AB$40:$AB$133,0),0)=0,"",INDEX($T$40:$T$133,IFERROR(MATCH(52,$AB$40:$AB$133,0),0))) -> CHM-SP-Z3L-E0-U72 | B85: =IF(IFERROR(MATCH(52,$AB$40:$AB$133,0),0)=0,"",INDEX($AG$40:$AG$133,IFERROR(MATCH(52,$AB$40:$AB$133,0),0))) -> 260580101 | C85: =IF(IFERROR(MATCH(52,$AB$40:$AB$133,0),0)=0,"",INDEX($U$40:$U$133,IFERROR(MATCH(52,$AB$40:$AB$133,0),0))) -> KG | D85: =IF(IFERROR(MATCH(52,$AB$40:$AB$133,0),0)=0,"",INDEX($V$40:$V$133,IFERROR(MATCH(52,$AB$40:$AB$133,0),0))) -> 2900 | E85: =IF(IFERROR(MATCH(52,$AB$40:$AB$133,0),0)=0,"",INDEX($W$40:$W$133,IFERROR(MATCH(52,$AB$40:$AB$133,0),0))) -> 0 | F85: =IF(IFERROR(MATCH(52,$AB$40:$AB$133,0),0)=0,"",INDEX($X$40:$X$133,IFERROR(MATCH(52,$AB$40:$AB$133,0),0))) -> 0 | G85: =IF(A85="","",E85-F85) -> 0 | H85: =IF(IFERROR(MATCH(52,$AB$40:$AB$133,0),0)=0,"",INDEX($Y$40:$Y$133,IFERROR(MATCH(52,$AB$40:$AB$133,0),0))) -> 0 | I85: =IF(IFERROR(MATCH(52,$AB$40:$AB$133,0),0)=0,"",INDEX($Z$40:$Z$133,IFERROR(MATCH(52,$AB$40:$AB$133,0),0))) -> 0 | J85: =IF(IFERROR(MATCH(52,$AB$40:$AB$133,0),0)=0,"",INDEX($AC$40:$AC$133,IFERROR(MATCH(52,$AB$40:$AB$133,0),0))) -> Confere | K85: =IF(IFERROR(MATCH(52,$AB$40:$AB$133,0),0)=0,"",INDEX($AD$40:$AD$133,IFERROR(MATCH(52,$AB$40:$AB$133,0),0))) -> 1 | L85: =IF(IFERROR(MATCH(52,$AB$40:$AB$133,0),0)=0,"",INDEX($AE$40:$AE$133,IFERROR(MATCH(52,$AB$40:$AB$133,0),0))&"") | T85: CHD-BB-308BY-357 | U85: UN | V85: =SUMIFS(Lançamentos!$H$2:$H$607,Lançamentos!$A$2:$A$607,">="&$F$5,Lançamentos!$A$2:$A$607,"<="&$H$5,Lançamentos!$C$2:$C$607,$T85,Lançamentos!$D$2:$D$607,$AG85,Lançamentos!$B$2:$B$607,"Recebido no 2008") -> 0 | W85: =SUMIFS(Lançamentos!$I$2:$I$607,Lançamentos!$A$2:$A$607,">="&$F$5,Lançamentos!$A$2:$A$607,"<="&$H$5,Lançamentos!$C$2:$C$607,$T85,Lançamentos!$D$2:$D$607,$AG85) -> 450 | X85: =SUMIFS(Lançamentos!$J$2:$J$607,Lançamentos!$A$2:$A$607,">="&$F$5,Lançamentos!$A$2:$A$607,"<="&$H$5,Lançamentos!$C$2:$C$607,$T85,Lançamentos!$D$2:$D$607,$AG85) -> 450 | Y85: =SUMIFS('Estoque físico'!$J$2:$J$229,'Estoque físico'!$A$2:$A$229,$T85,'Estoque físico'!$B$2:$B$229,$AG85) -> 0 | Z85: =ROUND(Y85-(W85-X85),3) -> 0 | AA85: =IF(AND(U85=$R$3,OR($R$1="*",T85=$R$1),OR($R$2="*",AG85=$R$2),ABS(V85)+ABS(W85)+ABS(X85)+ABS(Y85)>0),1,0) -> 0 | AB85: =IF(AA85=1,SUM(AA$40:AA85),"") | AC85: =IF(ABS(Z85)<=$R$5,"Confere",IF(Z85>0,"Sobrando","Faltando")) -> Confere | AD85: =COUNTIFS(Lançamentos!$A$2:$A$607,">="&$F$5,Lançamentos!$A$2:$A$607,"<="&$H$5,Lançamentos!$C$2:$C$607,$T85,Lançamentos!$D$2:$D$607,$AG85,Lançamentos!$B$2:$B$607,$R$4,Lançamentos!$G$2:$G$607,U85) -> 2 | AE85: CB EXTRUDED 8CM STICKS 1.6KG/UC 15UC/BOX | AF85: =IF(AND(AA85=1,AC85<>"Confere"),ABS(Z85)+ROW()/10000000,0) -> 0 | AG85: 2609078000 | AV85: =IFERROR(INDEX($AX$1:$AX$94,MATCH(84,$AY$1:$AY$94,0)),"") -> 2611295089 | AW85: PRA-T14 | AX85: 2611895339 | AY85: =IF(OR($A$5="Todos",AW85=$A$5),MAX(AY$1:AY84)+1,0) -> 85
A86: =IF(IFERROR(MATCH(53,$AB$40:$AB$133,0),0)=0,"",INDEX($T$40:$T$133,IFERROR(MATCH(53,$AB$40:$AB$133,0),0))) -> CHM-TS-22351E0-999 | B86: =IF(IFERROR(MATCH(53,$AB$40:$AB$133,0),0)=0,"",INDEX($AG$40:$AG$133,IFERROR(MATCH(53,$AB$40:$AB$133,0),0))) -> 2522444420 | C86: =IF(IFERROR(MATCH(53,$AB$40:$AB$133,0),0)=0,"",INDEX($U$40:$U$133,IFERROR(MATCH(53,$AB$40:$AB$133,0),0))) -> KG | D86: =IF(IFERROR(MATCH(53,$AB$40:$AB$133,0),0)=0,"",INDEX($V$40:$V$133,IFERROR(MATCH(53,$AB$40:$AB$133,0),0))) -> 0 | E86: =IF(IFERROR(MATCH(53,$AB$40:$AB$133,0),0)=0,"",INDEX($W$40:$W$133,IFERROR(MATCH(53,$AB$40:$AB$133,0),0))) -> 108.8 | F86: =IF(IFERROR(MATCH(53,$AB$40:$AB$133,0),0)=0,"",INDEX($X$40:$X$133,IFERROR(MATCH(53,$AB$40:$AB$133,0),0))) -> 0 | G86: =IF(A86="","",E86-F86) -> 108.8 | H86: =IF(IFERROR(MATCH(53,$AB$40:$AB$133,0),0)=0,"",INDEX($Y$40:$Y$133,IFERROR(MATCH(53,$AB$40:$AB$133,0),0))) -> 108.8 | I86: =IF(IFERROR(MATCH(53,$AB$40:$AB$133,0),0)=0,"",INDEX($Z$40:$Z$133,IFERROR(MATCH(53,$AB$40:$AB$133,0),0))) -> 0 | J86: =IF(IFERROR(MATCH(53,$AB$40:$AB$133,0),0)=0,"",INDEX($AC$40:$AC$133,IFERROR(MATCH(53,$AB$40:$AB$133,0),0))) -> Confere | K86: =IF(IFERROR(MATCH(53,$AB$40:$AB$133,0),0)=0,"",INDEX($AD$40:$AD$133,IFERROR(MATCH(53,$AB$40:$AB$133,0),0))) -> 1 | L86: =IF(IFERROR(MATCH(53,$AB$40:$AB$133,0),0)=0,"",INDEX($AE$40:$AE$133,IFERROR(MATCH(53,$AB$40:$AB$133,0),0))&"") | T86: CHD-BB-308BY-357 | U86: UN | V86: =SUMIFS(Lançamentos!$H$2:$H$607,Lançamentos!$A$2:$A$607,">="&$F$5,Lançamentos!$A$2:$A$607,"<="&$H$5,Lançamentos!$C$2:$C$607,$T86,Lançamentos!$D$2:$D$607,$AG86,Lançamentos!$B$2:$B$607,"Recebido no 2008") -> 0 | W86: =SUMIFS(Lançamentos!$I$2:$I$607,Lançamentos!$A$2:$A$607,">="&$F$5,Lançamentos!$A$2:$A$607,"<="&$H$5,Lançamentos!$C$2:$C$607,$T86,Lançamentos!$D$2:$D$607,$AG86) -> 900 | X86: =SUMIFS(Lançamentos!$J$2:$J$607,Lançamentos!$A$2:$A$607,">="&$F$5,Lançamentos!$A$2:$A$607,"<="&$H$5,Lançamentos!$C$2:$C$607,$T86,Lançamentos!$D$2:$D$607,$AG86) -> 840 | Y86: =SUMIFS('Estoque físico'!$J$2:$J$229,'Estoque físico'!$A$2:$A$229,$T86,'Estoque físico'!$B$2:$B$229,$AG86) -> 60 | Z86: =ROUND(Y86-(W86-X86),3) -> 0 | AA86: =IF(AND(U86=$R$3,OR($R$1="*",T86=$R$1),OR($R$2="*",AG86=$R$2),ABS(V86)+ABS(W86)+ABS(X86)+ABS(Y86)>0),1,0) -> 0 | AB86: =IF(AA86=1,SUM(AA$40:AA86),"") | AC86: =IF(ABS(Z86)<=$R$5,"Confere",IF(Z86>0,"Sobrando","Faltando")) -> Confere | AD86: =COUNTIFS(Lançamentos!$A$2:$A$607,">="&$F$5,Lançamentos!$A$2:$A$607,"<="&$H$5,Lançamentos!$C$2:$C$607,$T86,Lançamentos!$D$2:$D$607,$AG86,Lançamentos!$B$2:$B$607,$R$4,Lançamentos!$G$2:$G$607,U86) -> 6 | AE86: CB EXTRUDED 8CM STICKS 1.6KG/UC 15UC/BOX | AF86: =IF(AND(AA86=1,AC86<>"Confere"),ABS(Z86)+ROW()/10000000,0) -> 0 | AG86: 2609178000 | AV86: =IFERROR(INDEX($AX$1:$AX$94,MATCH(85,$AY$1:$AY$94,0)),"") -> 2611895339 | AW86: SPLIT-4-D-413 | AX86: 261826201 | AY86: =IF(OR($A$5="Todos",AW86=$A$5),MAX(AY$1:AY85)+1,0) -> 86
A87: =IF(IFERROR(MATCH(54,$AB$40:$AB$133,0),0)=0,"",INDEX($T$40:$T$133,IFERROR(MATCH(54,$AB$40:$AB$133,0),0))) -> CHM-TS-22351E0-999 | B87: =IF(IFERROR(MATCH(54,$AB$40:$AB$133,0),0)=0,"",INDEX($AG$40:$AG$133,IFERROR(MATCH(54,$AB$40:$AB$133,0),0))) -> 2525950306 | C87: =IF(IFERROR(MATCH(54,$AB$40:$AB$133,0),0)=0,"",INDEX($U$40:$U$133,IFERROR(MATCH(54,$AB$40:$AB$133,0),0))) -> KG | D87: =IF(IFERROR(MATCH(54,$AB$40:$AB$133,0),0)=0,"",INDEX($V$40:$V$133,IFERROR(MATCH(54,$AB$40:$AB$133,0),0))) -> 0 | E87: =IF(IFERROR(MATCH(54,$AB$40:$AB$133,0),0)=0,"",INDEX($W$40:$W$133,IFERROR(MATCH(54,$AB$40:$AB$133,0),0))) -> 195.84 | F87: =IF(IFERROR(MATCH(54,$AB$40:$AB$133,0),0)=0,"",INDEX($X$40:$X$133,IFERROR(MATCH(54,$AB$40:$AB$133,0),0))) -> 0 | G87: =IF(A87="","",E87-F87) -> 195.84 | H87: =IF(IFERROR(MATCH(54,$AB$40:$AB$133,0),0)=0,"",INDEX($Y$40:$Y$133,IFERROR(MATCH(54,$AB$40:$AB$133,0),0))) -> 195.84 | I87: =IF(IFERROR(MATCH(54,$AB$40:$AB$133,0),0)=0,"",INDEX($Z$40:$Z$133,IFERROR(MATCH(54,$AB$40:$AB$133,0),0))) -> 0 | J87: =IF(IFERROR(MATCH(54,$AB$40:$AB$133,0),0)=0,"",INDEX($AC$40:$AC$133,IFERROR(MATCH(54,$AB$40:$AB$133,0),0))) -> Confere | K87: =IF(IFERROR(MATCH(54,$AB$40:$AB$133,0),0)=0,"",INDEX($AD$40:$AD$133,IFERROR(MATCH(54,$AB$40:$AB$133,0),0))) -> 1 | L87: =IF(IFERROR(MATCH(54,$AB$40:$AB$133,0),0)=0,"",INDEX($AE$40:$AE$133,IFERROR(MATCH(54,$AB$40:$AB$133,0),0))&"") | T87: CHD-DR-75Y5-E1-U68 | U87: KG | V87: =SUMIFS(Lançamentos!$H$2:$H$607,Lançamentos!$A$2:$A$607,">="&$F$5,Lançamentos!$A$2:$A$607,"<="&$H$5,Lançamentos!$C$2:$C$607,$T87,Lançamentos!$D$2:$D$607,$AG87,Lançamentos!$B$2:$B$607,"Recebido no 2008") -> 0 | W87: =SUMIFS(Lançamentos!$I$2:$I$607,Lançamentos!$A$2:$A$607,">="&$F$5,Lançamentos!$A$2:$A$607,"<="&$H$5,Lançamentos!$C$2:$C$607,$T87,Lançamentos!$D$2:$D$607,$AG87) -> 648 | X87: =SUMIFS(Lançamentos!$J$2:$J$607,Lançamentos!$A$2:$A$607,">="&$F$5,Lançamentos!$A$2:$A$607,"<="&$H$5,Lançamentos!$C$2:$C$607,$T87,Lançamentos!$D$2:$D$607,$AG87) -> 54 | Y87: =SUMIFS('Estoque físico'!$J$2:$J$229,'Estoque físico'!$A$2:$A$229,$T87,'Estoque físico'!$B$2:$B$229,$AG87) -> 594 | Z87: =ROUND(Y87-(W87-X87),3) -> 0 | AA87: =IF(AND(U87=$R$3,OR($R$1="*",T87=$R$1),OR($R$2="*",AG87=$R$2),ABS(V87)+ABS(W87)+ABS(X87)+ABS(Y87)>0),1,0) -> 1 | AB87: =IF(AA87=1,SUM(AA$40:AA87),"") -> 40 | AC87: =IF(ABS(Z87)<=$R$5,"Confere",IF(Z87>0,"Sobrando","Faltando")) -> Confere | AD87: =COUNTIFS(Lançamentos!$A$2:$A$607,">="&$F$5,Lançamentos!$A$2:$A$607,"<="&$H$5,Lançamentos!$C$2:$C$607,$T87,Lançamentos!$D$2:$D$607,$AG87,Lançamentos!$B$2:$B$607,$R$4,Lançamentos!$G$2:$G$607,U87) -> 5 | AE87: CB CHIPS 7500CT/KG 1KG/UC 6UC/CX | AF87: =IF(AND(AA87=1,AC87<>"Confere"),ABS(Z87)+ROW()/10000000,0) -> 0 | AG87: 252810301 | AV87: =IFERROR(INDEX($AX$1:$AX$94,MATCH(86,$AY$1:$AY$94,0)),"") -> 261826201 | AW87: SPLIT-4-M-413 | AX87: 261596201 | AY87: =IF(OR($A$5="Todos",AW87=$A$5),MAX(AY$1:AY86)+1,0) -> 87
A88: =IF(IFERROR(MATCH(55,$AB$40:$AB$133,0),0)=0,"",INDEX($T$40:$T$133,IFERROR(MATCH(55,$AB$40:$AB$133,0),0))) -> CHM-TS-22351E0-999 | B88: =IF(IFERROR(MATCH(55,$AB$40:$AB$133,0),0)=0,"",INDEX($AG$40:$AG$133,IFERROR(MATCH(55,$AB$40:$AB$133,0),0))) -> 2526050307 | C88: =IF(IFERROR(MATCH(55,$AB$40:$AB$133,0),0)=0,"",INDEX($U$40:$U$133,IFERROR(MATCH(55,$AB$40:$AB$133,0),0))) -> KG | D88: =IF(IFERROR(MATCH(55,$AB$40:$AB$133,0),0)=0,"",INDEX($V$40:$V$133,IFERROR(MATCH(55,$AB$40:$AB$133,0),0))) -> 0 | E88: =IF(IFERROR(MATCH(55,$AB$40:$AB$133,0),0)=0,"",INDEX($W$40:$W$133,IFERROR(MATCH(55,$AB$40:$AB$133,0),0))) -> 295.12 | F88: =IF(IFERROR(MATCH(55,$AB$40:$AB$133,0),0)=0,"",INDEX($X$40:$X$133,IFERROR(MATCH(55,$AB$40:$AB$133,0),0))) -> 0 | G88: =IF(A88="","",E88-F88) -> 295.12 | H88: =IF(IFERROR(MATCH(55,$AB$40:$AB$133,0),0)=0,"",INDEX($Y$40:$Y$133,IFERROR(MATCH(55,$AB$40:$AB$133,0),0))) -> 295.12 | I88: =IF(IFERROR(MATCH(55,$AB$40:$AB$133,0),0)=0,"",INDEX($Z$40:$Z$133,IFERROR(MATCH(55,$AB$40:$AB$133,0),0))) -> 0 | J88: =IF(IFERROR(MATCH(55,$AB$40:$AB$133,0),0)=0,"",INDEX($AC$40:$AC$133,IFERROR(MATCH(55,$AB$40:$AB$133,0),0))) -> Confere | K88: =IF(IFERROR(MATCH(55,$AB$40:$AB$133,0),0)=0,"",INDEX($AD$40:$AD$133,IFERROR(MATCH(55,$AB$40:$AB$133,0),0))) -> 1 | L88: =IF(IFERROR(MATCH(55,$AB$40:$AB$133,0),0)=0,"",INDEX($AE$40:$AE$133,IFERROR(MATCH(55,$AB$40:$AB$133,0),0))&"") | T88: CHD-SP-1M-2B-U77 | U88: KG | V88: =SUMIFS(Lançamentos!$H$2:$H$607,Lançamentos!$A$2:$A$607,">="&$F$5,Lançamentos!$A$2:$A$607,"<="&$H$5,Lançamentos!$C$2:$C$607,$T88,Lançamentos!$D$2:$D$607,$AG88,Lançamentos!$B$2:$B$607,"Recebido no 2008") -> 2400 | W88: =SUMIFS(Lançamentos!$I$2:$I$607,Lançamentos!$A$2:$A$607,">="&$F$5,Lançamentos!$A$2:$A$607,"<="&$H$5,Lançamentos!$C$2:$C$607,$T88,Lançamentos!$D$2:$D$607,$AG88) -> 0 | X88: =SUMIFS(Lançamentos!$J$2:$J$607,Lançamentos!$A$2:$A$607,">="&$F$5,Lançamentos!$A$2:$A$607,"<="&$H$5,Lançamentos!$C$2:$C$607,$T88,Lançamentos!$D$2:$D$607,$AG88) -> 0 | Y88: =SUMIFS('Estoque físico'!$J$2:$J$229,'Estoque físico'!$A$2:$A$229,$T88,'Estoque físico'!$B$2:$B$229,$AG88) -> 0 | Z88: =ROUND(Y88-(W88-X88),3) -> 0 | AA88: =IF(AND(U88=$R$3,OR($R$1="*",T88=$R$1),OR($R$2="*",AG88=$R$2),ABS(V88)+ABS(W88)+ABS(X88)+ABS(Y88)>0),1,0) -> 1 | AB88: =IF(AA88=1,SUM(AA$40:AA88),"") -> 41 | AC88: =IF(ABS(Z88)<=$R$5,"Confere",IF(Z88>0,"Sobrando","Faltando")) -> Confere | AD88: =COUNTIFS(Lançamentos!$A$2:$A$607,">="&$F$5,Lançamentos!$A$2:$A$607,"<="&$H$5,Lançamentos!$C$2:$C$607,$T88,Lançamentos!$D$2:$D$607,$AG88,Lançamentos!$B$2:$B$607,$R$4,Lançamentos!$G$2:$G$607,U88) -> 2 | AF88: =IF(AND(AA88=1,AC88<>"Confere"),ABS(Z88)+ROW()/10000000,0) -> 0 | AG88: 260880101 | AV88: =IFERROR(INDEX($AX$1:$AX$94,MATCH(87,$AY$1:$AY$94,0)),"") -> 261596201 | AW88: W2-BR-D94 | AX88: 252232739 | AY88: =IF(OR($A$5="Todos",AW88=$A$5),MAX(AY$1:AY87)+1,0) -> 88
A89: =IF(IFERROR(MATCH(56,$AB$40:$AB$133,0),0)=0,"",INDEX($T$40:$T$133,IFERROR(MATCH(56,$AB$40:$AB$133,0),0))) -> CHM-VR-Z3S-E0-U68 | B89: =IF(IFERROR(MATCH(56,$AB$40:$AB$133,0),0)=0,"",INDEX($AG$40:$AG$133,IFERROR(MATCH(56,$AB$40:$AB$133,0),0))) -> 260400301 | C89: =IF(IFERROR(MATCH(56,$AB$40:$AB$133,0),0)=0,"",INDEX($U$40:$U$133,IFERROR(MATCH(56,$AB$40:$AB$133,0),0))) -> KG | D89: =IF(IFERROR(MATCH(56,$AB$40:$AB$133,0),0)=0,"",INDEX($V$40:$V$133,IFERROR(MATCH(56,$AB$40:$AB$133,0),0))) -> 0 | E89: =IF(IFERROR(MATCH(56,$AB$40:$AB$133,0),0)=0,"",INDEX($W$40:$W$133,IFERROR(MATCH(56,$AB$40:$AB$133,0),0))) -> 432 | F89: =IF(IFERROR(MATCH(56,$AB$40:$AB$133,0),0)=0,"",INDEX($X$40:$X$133,IFERROR(MATCH(56,$AB$40:$AB$133,0),0))) -> 0 | G89: =IF(A89="","",E89-F89) -> 432 | H89: =IF(IFERROR(MATCH(56,$AB$40:$AB$133,0),0)=0,"",INDEX($Y$40:$Y$133,IFERROR(MATCH(56,$AB$40:$AB$133,0),0))) -> 432 | I89: =IF(IFERROR(MATCH(56,$AB$40:$AB$133,0),0)=0,"",INDEX($Z$40:$Z$133,IFERROR(MATCH(56,$AB$40:$AB$133,0),0))) -> 0 | J89: =IF(IFERROR(MATCH(56,$AB$40:$AB$133,0),0)=0,"",INDEX($AC$40:$AC$133,IFERROR(MATCH(56,$AB$40:$AB$133,0),0))) -> Confere | K89: =IF(IFERROR(MATCH(56,$AB$40:$AB$133,0),0)=0,"",INDEX($AD$40:$AD$133,IFERROR(MATCH(56,$AB$40:$AB$133,0),0))) -> 1 | L89: =IF(IFERROR(MATCH(56,$AB$40:$AB$133,0),0)=0,"",INDEX($AE$40:$AE$133,IFERROR(MATCH(56,$AB$40:$AB$133,0),0))&"") | T89: CHD-SP-1M-BR-U73 | U89: KG | V89: =SUMIFS(Lançamentos!$H$2:$H$607,Lançamentos!$A$2:$A$607,">="&$F$5,Lançamentos!$A$2:$A$607,"<="&$H$5,Lançamentos!$C$2:$C$607,$T89,Lançamentos!$D$2:$D$607,$AG89,Lançamentos!$B$2:$B$607,"Recebido no 2008") -> 798 | W89: =SUMIFS(Lançamentos!$I$2:$I$607,Lançamentos!$A$2:$A$607,">="&$F$5,Lançamentos!$A$2:$A$607,"<="&$H$5,Lançamentos!$C$2:$C$607,$T89,Lançamentos!$D$2:$D$607,$AG89) -> 0 | X89: =SUMIFS(Lançamentos!$J$2:$J$607,Lançamentos!$A$2:$A$607,">="&$F$5,Lançamentos!$A$2:$A$607,"<="&$H$5,Lançamentos!$C$2:$C$607,$T89,Lançamentos!$D$2:$D$607,$AG89) -> 0 | Y89: =SUMIFS('Estoque físico'!$J$2:$J$229,'Estoque físico'!$A$2:$A$229,$T89,'Estoque físico'!$B$2:$B$229,$AG89) -> 0 | Z89: =ROUND(Y89-(W89-X89),3) -> 0 | AA89: =IF(AND(U89=$R$3,OR($R$1="*",T89=$R$1),OR($R$2="*",AG89=$R$2),ABS(V89)+ABS(W89)+ABS(X89)+ABS(Y89)>0),1,0) -> 1 | AB89: =IF(AA89=1,SUM(AA$40:AA89),"") -> 42 | AC89: =IF(ABS(Z89)<=$R$5,"Confere",IF(Z89>0,"Sobrando","Faltando")) -> Confere | AD89: =COUNTIFS(Lançamentos!$A$2:$A$607,">="&$F$5,Lançamentos!$A$2:$A$607,"<="&$H$5,Lançamentos!$C$2:$C$607,$T89,Lançamentos!$D$2:$D$607,$AG89,Lançamentos!$B$2:$B$607,$R$4,Lançamentos!$G$2:$G$607,U89) -> 1 | AF89: =IF(AND(AA89=1,AC89<>"Confere"),ABS(Z89)+ROW()/10000000,0) -> 0 | AG89: 260310301 | AV89: =IFERROR(INDEX($AX$1:$AX$94,MATCH(88,$AY$1:$AY$94,0)),"") -> 252232739 | AW89: W2-BR-D94 | AX89: 260700919 | AY89: =IF(OR($A$5="Todos",AW89=$A$5),MAX(AY$1:AY88)+1,0) -> 89
A90: =IF(IFERROR(MATCH(57,$AB$40:$AB$133,0),0)=0,"",INDEX($T$40:$T$133,IFERROR(MATCH(57,$AB$40:$AB$133,0),0))) -> CHM-VR-Z3S-E0-U72 | B90: =IF(IFERROR(MATCH(57,$AB$40:$AB$133,0),0)=0,"",INDEX($AG$40:$AG$133,IFERROR(MATCH(57,$AB$40:$AB$133,0),0))) -> 260600103 | C90: =IF(IFERROR(MATCH(57,$AB$40:$AB$133,0),0)=0,"",INDEX($U$40:$U$133,IFERROR(MATCH(57,$AB$40:$AB$133,0),0))) -> KG | D90: =IF(IFERROR(MATCH(57,$AB$40:$AB$133,0),0)=0,"",INDEX($V$40:$V$133,IFERROR(MATCH(57,$AB$40:$AB$133,0),0))) -> 1200 | E90: =IF(IFERROR(MATCH(57,$AB$40:$AB$133,0),0)=0,"",INDEX($W$40:$W$133,IFERROR(MATCH(57,$AB$40:$AB$133,0),0))) -> 0 | F90: =IF(IFERROR(MATCH(57,$AB$40:$AB$133,0),0)=0,"",INDEX($X$40:$X$133,IFERROR(MATCH(57,$AB$40:$AB$133,0),0))) -> 0 | G90: =IF(A90="","",E90-F90) -> 0 | H90: =IF(IFERROR(MATCH(57,$AB$40:$AB$133,0),0)=0,"",INDEX($Y$40:$Y$133,IFERROR(MATCH(57,$AB$40:$AB$133,0),0))) -> 0 | I90: =IF(IFERROR(MATCH(57,$AB$40:$AB$133,0),0)=0,"",INDEX($Z$40:$Z$133,IFERROR(MATCH(57,$AB$40:$AB$133,0),0))) -> 0 | J90: =IF(IFERROR(MATCH(57,$AB$40:$AB$133,0),0)=0,"",INDEX($AC$40:$AC$133,IFERROR(MATCH(57,$AB$40:$AB$133,0),0))) -> Confere | K90: =IF(IFERROR(MATCH(57,$AB$40:$AB$133,0),0)=0,"",INDEX($AD$40:$AD$133,IFERROR(MATCH(57,$AB$40:$AB$133,0),0))) -> 1 | L90: =IF(IFERROR(MATCH(57,$AB$40:$AB$133,0),0)=0,"",INDEX($AE$40:$AE$133,IFERROR(MATCH(57,$AB$40:$AB$133,0),0))&"") | T90: CHD-SP-1M-BR-U73 | U90: KG | V90: =SUMIFS(Lançamentos!$H$2:$H$607,Lançamentos!$A$2:$A$607,">="&$F$5,Lançamentos!$A$2:$A$607,"<="&$H$5,Lançamentos!$C$2:$C$607,$T90,Lançamentos!$D$2:$D$607,$AG90,Lançamentos!$B$2:$B$607,"Recebido no 2008") -> 1122 | W90: =SUMIFS(Lançamentos!$I$2:$I$607,Lançamentos!$A$2:$A$607,">="&$F$5,Lançamentos!$A$2:$A$607,"<="&$H$5,Lançamentos!$C$2:$C$607,$T90,Lançamentos!$D$2:$D$607,$AG90) -> 0 | X90: =SUMIFS(Lançamentos!$J$2:$J$607,Lançamentos!$A$2:$A$607,">="&$F$5,Lançamentos!$A$2:$A$607,"<="&$H$5,Lançamentos!$C$2:$C$607,$T90,Lançamentos!$D$2:$D$607,$AG90) -> 0 | Y90: =SUMIFS('Estoque físico'!$J$2:$J$229,'Estoque físico'!$A$2:$A$229,$T90,'Estoque físico'!$B$2:$B$229,$AG90) -> 0 | Z90: =ROUND(Y90-(W90-X90),3) -> 0 | AA90: =IF(AND(U90=$R$3,OR($R$1="*",T90=$R$1),OR($R$2="*",AG90=$R$2),ABS(V90)+ABS(W90)+ABS(X90)+ABS(Y90)>0),1,0) -> 1 | AB90: =IF(AA90=1,SUM(AA$40:AA90),"") -> 43 | AC90: =IF(ABS(Z90)<=$R$5,"Confere",IF(Z90>0,"Sobrando","Faltando")) -> Confere | AD90: =COUNTIFS(Lançamentos!$A$2:$A$607,">="&$F$5,Lançamentos!$A$2:$A$607,"<="&$H$5,Lançamentos!$C$2:$C$607,$T90,Lançamentos!$D$2:$D$607,$AG90,Lançamentos!$B$2:$B$607,$R$4,Lançamentos!$G$2:$G$607,U90) -> 1 | AF90: =IF(AND(AA90=1,AC90<>"Confere"),ABS(Z90)+ROW()/10000000,0) -> 0 | AG90: 260880301 | AV90: =IFERROR(INDEX($AX$1:$AX$94,MATCH(89,$AY$1:$AY$94,0)),"") -> 260700919 | AW90: W2-BR-D94 | AX90: 261131599 | AY90: =IF(OR($A$5="Todos",AW90=$A$5),MAX(AY$1:AY89)+1,0) -> 90
A91: =IF(IFERROR(MATCH(58,$AB$40:$AB$133,0),0)=0,"",INDEX($T$40:$T$133,IFERROR(MATCH(58,$AB$40:$AB$133,0),0))) -> CHR-Q37RB2-2B-U75 | B91: =IF(IFERROR(MATCH(58,$AB$40:$AB$133,0),0)=0,"",INDEX($AG$40:$AG$133,IFERROR(MATCH(58,$AB$40:$AB$133,0),0))) -> 261320202 | C91: =IF(IFERROR(MATCH(58,$AB$40:$AB$133,0),0)=0,"",INDEX($U$40:$U$133,IFERROR(MATCH(58,$AB$40:$AB$133,0),0))) -> KG | D91: =IF(IFERROR(MATCH(58,$AB$40:$AB$133,0),0)=0,"",INDEX($V$40:$V$133,IFERROR(MATCH(58,$AB$40:$AB$133,0),0))) -> 0 | E91: =IF(IFERROR(MATCH(58,$AB$40:$AB$133,0),0)=0,"",INDEX($W$40:$W$133,IFERROR(MATCH(58,$AB$40:$AB$133,0),0))) -> 1860 | F91: =IF(IFERROR(MATCH(58,$AB$40:$AB$133,0),0)=0,"",INDEX($X$40:$X$133,IFERROR(MATCH(58,$AB$40:$AB$133,0),0))) -> 770 | G91: =IF(A91="","",E91-F91) -> 1090 | H91: =IF(IFERROR(MATCH(58,$AB$40:$AB$133,0),0)=0,"",INDEX($Y$40:$Y$133,IFERROR(MATCH(58,$AB$40:$AB$133,0),0))) -> 1090 | I91: =IF(IFERROR(MATCH(58,$AB$40:$AB$133,0),0)=0,"",INDEX($Z$40:$Z$133,IFERROR(MATCH(58,$AB$40:$AB$133,0),0))) -> 0 | J91: =IF(IFERROR(MATCH(58,$AB$40:$AB$133,0),0)=0,"",INDEX($AC$40:$AC$133,IFERROR(MATCH(58,$AB$40:$AB$133,0),0))) -> Confere | K91: =IF(IFERROR(MATCH(58,$AB$40:$AB$133,0),0)=0,"",INDEX($AD$40:$AD$133,IFERROR(MATCH(58,$AB$40:$AB$133,0),0))) -> 33 | L91: =IF(IFERROR(MATCH(58,$AB$40:$AB$133,0),0)=0,"",INDEX($AE$40:$AE$133,IFERROR(MATCH(58,$AB$40:$AB$133,0),0))&"") -> CA RUBY CALLETS 2.5KG/UC 4UC/BOX | T91: CHD-TS-22350E0-999 | U91: KG | V91: =SUMIFS(Lançamentos!$H$2:$H$607,Lançamentos!$A$2:$A$607,">="&$F$5,Lançamentos!$A$2:$A$607,"<="&$H$5,Lançamentos!$C$2:$C$607,$T91,Lançamentos!$D$2:$D$607,$AG91,Lançamentos!$B$2:$B$607,"Recebido no 2008") -> 0 | W91: =SUMIFS(Lançamentos!$I$2:$I$607,Lançamentos!$A$2:$A$607,">="&$F$5,Lançamentos!$A$2:$A$607,"<="&$H$5,Lançamentos!$C$2:$C$607,$T91,Lançamentos!$D$2:$D$607,$AG91) -> 81.6 | X91: =SUMIFS(Lançamentos!$J$2:$J$607,Lançamentos!$A$2:$A$607,">="&$F$5,Lançamentos!$A$2:$A$607,"<="&$H$5,Lançamentos!$C$2:$C$607,$T91,Lançamentos!$D$2:$D$607,$AG91) -> 0 | Y91: =SUMIFS('Estoque físico'!$J$2:$J$229,'Estoque físico'!$A$2:$A$229,$T91,'Estoque físico'!$B$2:$B$229,$AG91) -> 81.6 | Z91: =ROUND(Y91-(W91-X91),3) -> 0 | AA91: =IF(AND(U91=$R$3,OR($R$1="*",T91=$R$1),OR($R$2="*",AG91=$R$2),ABS(V91)+ABS(W91)+ABS(X91)+ABS(Y91)>0),1,0) -> 1 | AB91: =IF(AA91=1,SUM(AA$40:AA91),"") -> 44 | AC91: =IF(ABS(Z91)<=$R$5,"Confere",IF(Z91>0,"Sobrando","Faltando")) -> Confere | AD91: =COUNTIFS(Lançamentos!$A$2:$A$607,">="&$F$5,Lançamentos!$A$2:$A$607,"<="&$H$5,Lançamentos!$C$2:$C$607,$T91,Lançamentos!$D$2:$D$607,$AG91,Lançamentos!$B$2:$B$607,$R$4,Lançamentos!$G$2:$G$607,U91) -> 1 | AF91: =IF(AND(AA91=1,AC91<>"Confere"),ABS(Z91)+ROW()/10000000,0) -> 0 | AG91: 2520443650 | AV91: =IFERROR(INDEX($AX$1:$AX$94,MATCH(90,$AY$1:$AY$94,0)),"") -> 261131599 | AW91: W2-BR-D94 | AX91: 261181599 | AY91: =IF(OR($A$5="Todos",AW91=$A$5),MAX(AY$1:AY90)+1,0) -> 91
A92: =IF(IFERROR(MATCH(59,$AB$40:$AB$133,0),0)=0,"",INDEX($T$40:$T$133,IFERROR(MATCH(59,$AB$40:$AB$133,0),0))) -> CHR-Q37RB2-2B-U75 | B92: =IF(IFERROR(MATCH(59,$AB$40:$AB$133,0),0)=0,"",INDEX($AG$40:$AG$133,IFERROR(MATCH(59,$AB$40:$AB$133,0),0))) -> 261320203 | C92: =IF(IFERROR(MATCH(59,$AB$40:$AB$133,0),0)=0,"",INDEX($U$40:$U$133,IFERROR(MATCH(59,$AB$40:$AB$133,0),0))) -> KG | D92: =IF(IFERROR(MATCH(59,$AB$40:$AB$133,0),0)=0,"",INDEX($V$40:$V$133,IFERROR(MATCH(59,$AB$40:$AB$133,0),0))) -> 840 | E92: =IF(IFERROR(MATCH(59,$AB$40:$AB$133,0),0)=0,"",INDEX($W$40:$W$133,IFERROR(MATCH(59,$AB$40:$AB$133,0),0))) -> 1200 | F92: =IF(IFERROR(MATCH(59,$AB$40:$AB$133,0),0)=0,"",INDEX($X$40:$X$133,IFERROR(MATCH(59,$AB$40:$AB$133,0),0))) -> 0 | G92: =IF(A92="","",E92-F92) -> 1200 | H92: =IF(IFERROR(MATCH(59,$AB$40:$AB$133,0),0)=0,"",INDEX($Y$40:$Y$133,IFERROR(MATCH(59,$AB$40:$AB$133,0),0))) -> 1200 | I92: =IF(IFERROR(MATCH(59,$AB$40:$AB$133,0),0)=0,"",INDEX($Z$40:$Z$133,IFERROR(MATCH(59,$AB$40:$AB$133,0),0))) -> 0 | J92: =IF(IFERROR(MATCH(59,$AB$40:$AB$133,0),0)=0,"",INDEX($AC$40:$AC$133,IFERROR(MATCH(59,$AB$40:$AB$133,0),0))) -> Confere | K92: =IF(IFERROR(MATCH(59,$AB$40:$AB$133,0),0)=0,"",INDEX($AD$40:$AD$133,IFERROR(MATCH(59,$AB$40:$AB$133,0),0))) -> 2 | L92: =IF(IFERROR(MATCH(59,$AB$40:$AB$133,0),0)=0,"",INDEX($AE$40:$AE$133,IFERROR(MATCH(59,$AB$40:$AB$133,0),0))&"") -> CA RUBY CALLETS 2.5KG/UC 4UC/BOX | T92: CHD-VR-Z2S-E0-U68 | U92: KG | V92: =SUMIFS(Lançamentos!$H$2:$H$607,Lançamentos!$A$2:$A$607,">="&$F$5,Lançamentos!$A$2:$A$607,"<="&$H$5,Lançamentos!$C$2:$C$607,$T92,Lançamentos!$D$2:$D$607,$AG92,Lançamentos!$B$2:$B$607,"Recebido no 2008") -> 1296 | W92: =SUMIFS(Lançamentos!$I$2:$I$607,Lançamentos!$A$2:$A$607,">="&$F$5,Lançamentos!$A$2:$A$607,"<="&$H$5,Lançamentos!$C$2:$C$607,$T92,Lançamentos!$D$2:$D$607,$AG92) -> 0 | X92: =SUMIFS(Lançamentos!$J$2:$J$607,Lançamentos!$A$2:$A$607,">="&$F$5,Lançamentos!$A$2:$A$607,"<="&$H$5,Lançamentos!$C$2:$C$607,$T92,Lançamentos!$D$2:$D$607,$AG92) -> 0 | Y92: =SUMIFS('Estoque físico'!$J$2:$J$229,'Estoque físico'!$A$2:$A$229,$T92,'Estoque físico'!$B$2:$B$229,$AG92) -> 0 | Z92: =ROUND(Y92-(W92-X92),3) -> 0 | AA92: =IF(AND(U92=$R$3,OR($R$1="*",T92=$R$1),OR($R$2="*",AG92=$R$2),ABS(V92)+ABS(W92)+ABS(X92)+ABS(Y92)>0),1,0) -> 1 | AB92: =IF(AA92=1,SUM(AA$40:AA92),"") -> 45 | AC92: =IF(ABS(Z92)<=$R$5,"Confere",IF(Z92>0,"Sobrando","Faltando")) -> Confere | AD92: =COUNTIFS(Lançamentos!$A$2:$A$607,">="&$F$5,Lançamentos!$A$2:$A$607,"<="&$H$5,Lançamentos!$C$2:$C$607,$T92,Lançamentos!$D$2:$D$607,$AG92,Lançamentos!$B$2:$B$607,$R$4,Lançamentos!$G$2:$G$607,U92) -> 1 | AF92: =IF(AND(AA92=1,AC92<>"Confere"),ABS(Z92)+ROW()/10000000,0) -> 0 | AG92: 261160301 | AV92: =IFERROR(INDEX($AX$1:$AX$94,MATCH(91,$AY$1:$AY$94,0)),"") -> 261181599 | AW92: W2-BR-D94 | AX92: 261391599 | AY92: =IF(OR($A$5="Todos",AW92=$A$5),MAX(AY$1:AY91)+1,0) -> 92
A93: =IF(IFERROR(MATCH(60,$AB$40:$AB$133,0),0)=0,"",INDEX($T$40:$T$133,IFERROR(MATCH(60,$AB$40:$AB$133,0),0))) -> CHR-Q37RB2-E0-D94 | B93: =IF(IFERROR(MATCH(60,$AB$40:$AB$133,0),0)=0,"",INDEX($AG$40:$AG$133,IFERROR(MATCH(60,$AB$40:$AB$133,0),0))) -> 261301539 | C93: =IF(IFERROR(MATCH(60,$AB$40:$AB$133,0),0)=0,"",INDEX($U$40:$U$133,IFERROR(MATCH(60,$AB$40:$AB$133,0),0))) -> KG | D93: =IF(IFERROR(MATCH(60,$AB$40:$AB$133,0),0)=0,"",INDEX($V$40:$V$133,IFERROR(MATCH(60,$AB$40:$AB$133,0),0))) -> 1873.2 | E93: =IF(IFERROR(MATCH(60,$AB$40:$AB$133,0),0)=0,"",INDEX($W$40:$W$133,IFERROR(MATCH(60,$AB$40:$AB$133,0),0))) -> 313.6 | F93: =IF(IFERROR(MATCH(60,$AB$40:$AB$133,0),0)=0,"",INDEX($X$40:$X$133,IFERROR(MATCH(60,$AB$40:$AB$133,0),0))) -> 0 | G93: =IF(A93="","",E93-F93) -> 313.6 | H93: =IF(IFERROR(MATCH(60,$AB$40:$AB$133,0),0)=0,"",INDEX($Y$40:$Y$133,IFERROR(MATCH(60,$AB$40:$AB$133,0),0))) -> 313.6 | I93: =IF(IFERROR(MATCH(60,$AB$40:$AB$133,0),0)=0,"",INDEX($Z$40:$Z$133,IFERROR(MATCH(60,$AB$40:$AB$133,0),0))) -> 0 | J93: =IF(IFERROR(MATCH(60,$AB$40:$AB$133,0),0)=0,"",INDEX($AC$40:$AC$133,IFERROR(MATCH(60,$AB$40:$AB$133,0),0))) -> Confere | K93: =IF(IFERROR(MATCH(60,$AB$40:$AB$133,0),0)=0,"",INDEX($AD$40:$AD$133,IFERROR(MATCH(60,$AB$40:$AB$133,0),0))) -> 3 | L93: =IF(IFERROR(MATCH(60,$AB$40:$AB$133,0),0)=0,"",INDEX($AE$40:$AE$133,IFERROR(MATCH(60,$AB$40:$AB$133,0),0))&"") | T93: CHK-D-413 | U93: KG | V93: =SUMIFS(Lançamentos!$H$2:$H$607,Lançamentos!$A$2:$A$607,">="&$F$5,Lançamentos!$A$2:$A$607,"<="&$H$5,Lançamentos!$C$2:$C$607,$T93,Lançamentos!$D$2:$D$607,$AG93,Lançamentos!$B$2:$B$607,"Recebido no 2008") -> 1280 | W93: =SUMIFS(Lançamentos!$I$2:$I$607,Lançamentos!$A$2:$A$607,">="&$F$5,Lançamentos!$A$2:$A$607,"<="&$H$5,Lançamentos!$C$2:$C$607,$T93,Lançamentos!$D$2:$D$607,$AG93) -> 0 | X93: =SUMIFS(Lançamentos!$J$2:$J$607,Lançamentos!$A$2:$A$607,">="&$F$5,Lançamentos!$A$2:$A$607,"<="&$H$5,Lançamentos!$C$2:$C$607,$T93,Lançamentos!$D$2:$D$607,$AG93) -> 0 | Y93: =SUMIFS('Estoque físico'!$J$2:$J$229,'Estoque físico'!$A$2:$A$229,$T93,'Estoque físico'!$B$2:$B$229,$AG93) -> 0 | Z93: =ROUND(Y93-(W93-X93),3) -> 0 | AA93: =IF(AND(U93=$R$3,OR($R$1="*",T93=$R$1),OR($R$2="*",AG93=$R$2),ABS(V93)+ABS(W93)+ABS(X93)+ABS(Y93)>0),1,0) -> 1 | AB93: =IF(AA93=1,SUM(AA$40:AA93),"") -> 46 | AC93: =IF(ABS(Z93)<=$R$5,"Confere",IF(Z93>0,"Sobrando","Faltando")) -> Confere | AD93: =COUNTIFS(Lançamentos!$A$2:$A$607,">="&$F$5,Lançamentos!$A$2:$A$607,"<="&$H$5,Lançamentos!$C$2:$C$607,$T93,Lançamentos!$D$2:$D$607,$AG93,Lançamentos!$B$2:$B$607,$R$4,Lançamentos!$G$2:$G$607,U93) -> 1 | AF93: =IF(AND(AA93=1,AC93<>"Confere"),ABS(Z93)+ROW()/10000000,0) -> 0 | AG93: 261756201 | AV93: =IFERROR(INDEX($AX$1:$AX$94,MATCH(92,$AY$1:$AY$94,0)),"") -> 261391599 | AW93: W3-BR-25A | AX93: 253540301 | AY93: =IF(OR($A$5="Todos",AW93=$A$5),MAX(AY$1:AY92)+1,0) -> 93
A94: =IF(IFERROR(MATCH(61,$AB$40:$AB$133,0),0)=0,"",INDEX($T$40:$T$133,IFERROR(MATCH(61,$AB$40:$AB$133,0),0))) -> CW2-BR-25A | B94: =IF(IFERROR(MATCH(61,$AB$40:$AB$133,0),0)=0,"",INDEX($AG$40:$AG$133,IFERROR(MATCH(61,$AB$40:$AB$133,0),0))) -> 252590301 | C94: =IF(IFERROR(MATCH(61,$AB$40:$AB$133,0),0)=0,"",INDEX($U$40:$U$133,IFERROR(MATCH(61,$AB$40:$AB$133,0),0))) -> KG | D94: =IF(IFERROR(MATCH(61,$AB$40:$AB$133,0),0)=0,"",INDEX($V$40:$V$133,IFERROR(MATCH(61,$AB$40:$AB$133,0),0))) -> 0 | E94: =IF(IFERROR(MATCH(61,$AB$40:$AB$133,0),0)=0,"",INDEX($W$40:$W$133,IFERROR(MATCH(61,$AB$40:$AB$133,0),0))) -> 603 | F94: =IF(IFERROR(MATCH(61,$AB$40:$AB$133,0),0)=0,"",INDEX($X$40:$X$133,IFERROR(MATCH(61,$AB$40:$AB$133,0),0))) -> 0 | G94: =IF(A94="","",E94-F94) -> 603 | H94: =IF(IFERROR(MATCH(61,$AB$40:$AB$133,0),0)=0,"",INDEX($Y$40:$Y$133,IFERROR(MATCH(61,$AB$40:$AB$133,0),0))) -> 603 | I94: =IF(IFERROR(MATCH(61,$AB$40:$AB$133,0),0)=0,"",INDEX($Z$40:$Z$133,IFERROR(MATCH(61,$AB$40:$AB$133,0),0))) -> 0 | J94: =IF(IFERROR(MATCH(61,$AB$40:$AB$133,0),0)=0,"",INDEX($AC$40:$AC$133,IFERROR(MATCH(61,$AB$40:$AB$133,0),0))) -> Confere | K94: =IF(IFERROR(MATCH(61,$AB$40:$AB$133,0),0)=0,"",INDEX($AD$40:$AD$133,IFERROR(MATCH(61,$AB$40:$AB$133,0),0))) -> 1 | L94: =IF(IFERROR(MATCH(61,$AB$40:$AB$133,0),0)=0,"",INDEX($AE$40:$AE$133,IFERROR(MATCH(61,$AB$40:$AB$133,0),0))&"") -> CA MOEDAS 2,01KG/UC 10UC/CX 30CX/PAL | T94: CHK-R30GOLD-BR-25A | U94: KG | V94: =SUMIFS(Lançamentos!$H$2:$H$607,Lançamentos!$A$2:$A$607,">="&$F$5,Lançamentos!$A$2:$A$607,"<="&$H$5,Lançamentos!$C$2:$C$607,$T94,Lançamentos!$D$2:$D$607,$AG94,Lançamentos!$B$2:$B$607,"Recebido no 2008") -> 160.8 | W94: =SUMIFS(Lançamentos!$I$2:$I$607,Lançamentos!$A$2:$A$607,">="&$F$5,Lançamentos!$A$2:$A$607,"<="&$H$5,Lançamentos!$C$2:$C$607,$T94,Lançamentos!$D$2:$D$607,$AG94) -> 0 | X94: =SUMIFS(Lançamentos!$J$2:$J$607,Lançamentos!$A$2:$A$607,">="&$F$5,Lançamentos!$A$2:$A$607,"<="&$H$5,Lançamentos!$C$2:$C$607,$T94,Lançamentos!$D$2:$D$607,$AG94) -> 0 | Y94: =SUMIFS('Estoque físico'!$J$2:$J$229,'Estoque físico'!$A$2:$A$229,$T94,'Estoque físico'!$B$2:$B$229,$AG94) -> 0 | Z94: =ROUND(Y94-(W94-X94),3) -> 0 | AA94: =IF(AND(U94=$R$3,OR($R$1="*",T94=$R$1),OR($R$2="*",AG94=$R$2),ABS(V94)+ABS(W94)+ABS(X94)+ABS(Y94)>0),1,0) -> 1 | AB94: =IF(AA94=1,SUM(AA$40:AA94),"") -> 47 | AC94: =IF(ABS(Z94)<=$R$5,"Confere",IF(Z94>0,"Sobrando","Faltando")) -> Confere | AD94: =COUNTIFS(Lançamentos!$A$2:$A$607,">="&$F$5,Lançamentos!$A$2:$A$607,"<="&$H$5,Lançamentos!$C$2:$C$607,$T94,Lançamentos!$D$2:$D$607,$AG94,Lançamentos!$B$2:$B$607,$R$4,Lançamentos!$G$2:$G$607,U94) -> 1 | AE94: CA MOEDAS 2,01KG/UC 10UC/CX 30CX/PAL | AF94: =IF(AND(AA94=1,AC94<>"Confere"),ABS(Z94)+ROW()/10000000,0) -> 0 | AG94: 252750301 | AV94: =IFERROR(INDEX($AX$1:$AX$94,MATCH(93,$AY$1:$AY$94,0)),"") -> 253540301 | AW94: W3-BR-25A | AX94: 261080301 | AY94: =IF(OR($A$5="Todos",AW94=$A$5),MAX(AY$1:AY93)+1,0) -> 94
A95: =IF(IFERROR(MATCH(62,$AB$40:$AB$133,0),0)=0,"",INDEX($T$40:$T$133,IFERROR(MATCH(62,$AB$40:$AB$133,0),0))) -> CW2-BR-25A | B95: =IF(IFERROR(MATCH(62,$AB$40:$AB$133,0),0)=0,"",INDEX($AG$40:$AG$133,IFERROR(MATCH(62,$AB$40:$AB$133,0),0))) -> 261070301 | C95: =IF(IFERROR(MATCH(62,$AB$40:$AB$133,0),0)=0,"",INDEX($U$40:$U$133,IFERROR(MATCH(62,$AB$40:$AB$133,0),0))) -> KG | D95: =IF(IFERROR(MATCH(62,$AB$40:$AB$133,0),0)=0,"",INDEX($V$40:$V$133,IFERROR(MATCH(62,$AB$40:$AB$133,0),0))) -> 1166 | E95: =IF(IFERROR(MATCH(62,$AB$40:$AB$133,0),0)=0,"",INDEX($W$40:$W$133,IFERROR(MATCH(62,$AB$40:$AB$133,0),0))) -> 603 | F95: =IF(IFERROR(MATCH(62,$AB$40:$AB$133,0),0)=0,"",INDEX($X$40:$X$133,IFERROR(MATCH(62,$AB$40:$AB$133,0),0))) -> 422.1 | G95: =IF(A95="","",E95-F95) -> 180.9 | H95: =IF(IFERROR(MATCH(62,$AB$40:$AB$133,0),0)=0,"",INDEX($Y$40:$Y$133,IFERROR(MATCH(62,$AB$40:$AB$133,0),0))) -> 180.9 | I95: =IF(IFERROR(MATCH(62,$AB$40:$AB$133,0),0)=0,"",INDEX($Z$40:$Z$133,IFERROR(MATCH(62,$AB$40:$AB$133,0),0))) -> 0 | J95: =IF(IFERROR(MATCH(62,$AB$40:$AB$133,0),0)=0,"",INDEX($AC$40:$AC$133,IFERROR(MATCH(62,$AB$40:$AB$133,0),0))) -> Confere | K95: =IF(IFERROR(MATCH(62,$AB$40:$AB$133,0),0)=0,"",INDEX($AD$40:$AD$133,IFERROR(MATCH(62,$AB$40:$AB$133,0),0))) -> 4 | L95: =IF(IFERROR(MATCH(62,$AB$40:$AB$133,0),0)=0,"",INDEX($AE$40:$AE$133,IFERROR(MATCH(62,$AB$40:$AB$133,0),0))&"") -> CA MOEDAS 2,01KG/UC 10UC/CX 30CX/PAL | T95: CHK-W-413 | U95: KG | V95: =SUMIFS(Lançamentos!$H$2:$H$607,Lançamentos!$A$2:$A$607,">="&$F$5,Lançamentos!$A$2:$A$607,"<="&$H$5,Lançamentos!$C$2:$C$607,$T95,Lançamentos!$D$2:$D$607,$AG95,Lançamentos!$B$2:$B$607,"Recebido no 2008") -> 640 | W95: =SUMIFS(Lançamentos!$I$2:$I$607,Lançamentos!$A$2:$A$607,">="&$F$5,Lançamentos!$A$2:$A$607,"<="&$H$5,Lançamentos!$C$2:$C$607,$T95,Lançamentos!$D$2:$D$607,$AG95) -> 0 | X95: =SUMIFS(Lançamentos!$J$2:$J$607,Lançamentos!$A$2:$A$607,">="&$F$5,Lançamentos!$A$2:$A$607,"<="&$H$5,Lançamentos!$C$2:$C$607,$T95,Lançamentos!$D$2:$D$607,$AG95) -> 0 | Y95: =SUMIFS('Estoque físico'!$J$2:$J$229,'Estoque físico'!$A$2:$A$229,$T95,'Estoque físico'!$B$2:$B$229,$AG95) -> 0 | Z95: =ROUND(Y95-(W95-X95),3) -> 0 | AA95: =IF(AND(U95=$R$3,OR($R$1="*",T95=$R$1),OR($R$2="*",AG95=$R$2),ABS(V95)+ABS(W95)+ABS(X95)+ABS(Y95)>0),1,0) -> 1 | AB95: =IF(AA95=1,SUM(AA$40:AA95),"") -> 48 | AC95: =IF(ABS(Z95)<=$R$5,"Confere",IF(Z95>0,"Sobrando","Faltando")) -> Confere | AD95: =COUNTIFS(Lançamentos!$A$2:$A$607,">="&$F$5,Lançamentos!$A$2:$A$607,"<="&$H$5,Lançamentos!$C$2:$C$607,$T95,Lançamentos!$D$2:$D$607,$AG95,Lançamentos!$B$2:$B$607,$R$4,Lançamentos!$G$2:$G$607,U95) -> 1 | AF95: =IF(AND(AA95=1,AC95<>"Confere"),ABS(Z95)+ROW()/10000000,0) -> 0 | AG95: 260536201 | AV95: =IFERROR(INDEX($AX$1:$AX$94,MATCH(94,$AY$1:$AY$94,0)),"") -> 261080301
