Workbook

Sheet MENU
B2: ZBR IMPORTADO
B3: Relatório de Gestão de Estoque
B4: Entradas, saídas, estoque físico, conciliação e plano de ação · Centro BR01
B7: Fonte dos dados | C7: Exportação SAP "Analise_ZBR_importado.XLSX" (abas Entrada, Saida, Estoque atual)
B8: Período dos movimentos | C8: 09/09/2026 a 01/10/2026
B9: Gerado em | C9: =Parâmetros!K9 -> 46297
B11: RESULTADO EM 1 MINUTO
B12: ="Conferem: "&'2 Resumo Gerencial'!D19&" de "&'2 Resumo Gerencial'!C19&" SKU·lote ("&FIXED('2 Resumo Gerencial'!F19*100,1)&"%)." -> Conferem: 66 de 94 SKU·lote (70.2%).
B13: ="Com diferença: "&'2 Resumo Gerencial'!E19&" SKU·lote — "&'2 Resumo Gerencial'!C34&" críticos, tratar primeiro (ver 6 Plano de Ação)." -> Com diferença: 28 SKU·lote — 3 críticos, tratar primeiro (ver 6 Plano de Ação).
B14: ="Parado no depósito 2008: "&FIXED('2 Resumo Gerencial'!C54,1)&" KG de importação em "&'2 Resumo Gerencial'!C53&" lotes, aguardando transferência." -> Parado no depósito 2008: 54,295.8 KG de importação em 33 lotes, aguardando transferência.
B15: =IF(SUM('3 Base Saldo Inicial 08-09'!$E$2:$E$5000)=0,"Saldo inicial de 08/09: ainda não informado — preencha a aba 3 Base Saldo Inicial (ou use o Power Query).","Saldo inicial de 08/09: informado e já considerado nas diferenças.") -> Saldo inicial de 08/09: ainda não informado — preencha a aba 3 Base Saldo Inicial (ou use o Power Query).
B16: ="Plano de ação: "&('2 Resumo Gerencial'!C58-'2 Resumo Gerencial'!C61)&" ações em aberto, "&'2 Resumo Gerencial'!C64&" sem responsável." -> Plano de ação: 61 ações em aberto, 61 sem responsável.
B18: NAVEGAÇÃO
B19: ABA | C19: PARA QUE SERVE | D19: ABRIR
B20: 1 Dashboard | C20: Visão executiva: indicadores, gráficos e filtros | D20: Abrir →
B21: 2 Resumo Gerencial | C21: O que aconteceu, em poucas linhas e números | D21: Abrir →
B22: 3 Base Entrada 2008 | C22: Dados do SAP: movimentos do depósito 2008 | D22: Abrir →
B23: 3 Base Saídas | C23: Dados do SAP: saídas 601 | D23: Abrir →
B24: 3 Base Estoque Físico | C24: Dados do SAP: posições de estoque | D24: Abrir →
B25: 3 Base Saldo Inicial 08-09 | C25: Estoque de 08/09 (preencher) — melhora a precisão das diferenças | D25: Abrir →
B26: 3 Base Movimentos | C26: Entradas e saídas juntas, para consulta | D26: Abrir →
B27: 4 Análise ZBR | C27: Por SKU·lote: deveria ter × tem, diferença, motivo e solução | D27: Abrir →
B28: 4 Análise Depósito 2008 | C28: Importação recebida, transferida e parada no 2008 | D28: Abrir →
B29: 5 Conciliação | C29: Todas as diferenças com motivo, categoria e criticidade | D29: Abrir →
B30: 6 Plano de Ação | C30: O que fazer, quem, até quando e status | D30: Abrir →
... B33: Parâmetros | C33: Datas, tolerância, limites e caminho do arquivo SAP | D33: Abrir →
B35: COMO USAR
B36: 1. Leia o "Resultado em 1 minuto" acima.
B37: 2. No 1 Dashboard, escolha período, SKU, lote, unidade e status nas células azul-claras (seta ▼).
B38: 3. Para saber o porquê de uma diferença, veja Motivo e Solução no 4 Análise ZBR.
B39: 4. Registre responsável, prazo e status no 6 Plano de Ação.
B40: 5. Nova extração do SAP: aba 8 Atualizar Dados (Power Query) — inclua o saldo de 08/09.
B42: CORES
B43: Verde: confere / concluído
B44: Amarelo: atenção / em andamento
B45: Vermelho: crítico / vencido / faltando
B46: Cinza: não iniciado / sem informação
B47: Azul-claro: célula para escolher ou preencher

Sheet 1 Dashboard
A1: Dashboard Executivo — ZBR Importado | P1: ◄ MENU
A2: Centro BR01 · movimentos de 09/09 a 01/10/2026 · fonte: exportação SAP "Analise_ZBR_importado.XLSX" · relatório gerado em 02/10/2026
A4: DATA INICIAL | C4: DATA FINAL | E4: SKU (CATEGORIA) | H4: LOTE | J4: UNIDADE | K4: TIPO DE MOVIMENTAÇÃO | N4: STATUS (SITUAÇÃO)
A5: 46274 | C5: 46296 | E5: Todos | H5: Todos | J5: KG | K5: Todas | N5: Todos
A6: ='4 Análise ZBR'!A7&IF(N5="Todos",""," · status "&N5) -> Mostrando: todos os SKUs · 9/9/2026 a 1/10/2026 · unidade KG | K6: Clique numa célula azul-clara e use a seta ▼. Os filtros valem para todas as análises.
A7: INDICADORES PRINCIPAIS
A8: ="VOLUME ANALISADO · "&'4 Análise ZBR'!$R$3 -> VOLUME ANALISADO · KG | C8: SKU·LOTE ANALISADOS | E8: MOVIMENTAÇÕES | G8: DIVERGÊNCIAS | I8: % CONFORMIDADE | K8: PENDÊNCIAS EM ABERTO | M8: OCORRÊNCIAS CRÍTICAS | O8: % CONCLUSÃO DAS AÇÕES
A9: =SUMPRODUCT('4 Análise ZBR'!$AA$40:$AA$133,'4 Análise ZBR'!$W$40:$W$133)+SUMPRODUCT('4 Análise ZBR'!$AA$40:$AA$133,'4 Análise ZBR'!$X$40:$X$133) -> 92199.08 | C9: =SUM('4 Análise ZBR'!$AA$40:$AA$133) -> 81 | E9: =SUMPRODUCT('4 Análise ZBR'!$AA$40:$AA$133,'4 Análise ZBR'!$AD$40:$AD$133) -> 526 | G9: =COUNTIFS('4 Análise ZBR'!$AA$40:$AA$133,1,'4 Análise ZBR'!$AC$40:$AC$133,"<>Confere") -> 23 | I9: =IF(SUM('4 Análise ZBR'!$AA$40:$AA$133)=0,0,COUNTIFS('4 Análise ZBR'!$AA$40:$AA$133,1,'4 Análise ZBR'!$AC$40:$AC$133,"Confere")/SUM('4 Análise ZBR'!$AA$40:$AA$133)) -> 0.71604938 | K9: =COUNTIFS('6 Plano de Ação'!$A$8:$A$507,"OC-*",'6 Plano de Ação'!$O$8:$O$507,"<>Concluído",'6 Plano de Ação'!$O$8:$O$507,"<>Cancelado") -> 61 | M9: =COUNTIFS('4 Análise ZBR'!$AA$40:$AA$133,1,'4 Análise ZBR'!$BF$40:$BF$133,"Crítica") -> 3 | O9: =IF(COUNTIF('6 Plano de Ação'!$A$8:$A$507,"OC-*")=0,0,COUNTIF('6 Plano de Ação'!$O$8:$O$507,"Concluído")/COUNTIF('6 Plano de Ação'!$A$8:$A$507,"OC-*")) -> 0
A10: entrou + saiu no ZBR | C10: registros no filtro | E10: lançamentos no filtro | G10: SKU·lote com diferença | I10: SKU·lote que conferem | K10: ações do plano (geral) | M10: criticidade proposta | O10: plano de ação (geral)
A12: ="QUANTIDADES · "&'4 Análise ZBR'!$R$3 -> QUANTIDADES · KG
A13: ENTROU NO ZBR | D13: SAIU | G13: DEVERIA TER | J13: ESTOQUE FÍSICO | M13: DIFERENÇA | O13: AGUARDANDO NO 2008
A14: =SUMPRODUCT('4 Análise ZBR'!$AA$40:$AA$133,'4 Análise ZBR'!$W$40:$W$133) -> 65930.28 | D14: =SUMPRODUCT('4 Análise ZBR'!$AA$40:$AA$133,'4 Análise ZBR'!$X$40:$X$133) -> 26268.8 | G14: =SUMPRODUCT('4 Análise ZBR'!$AA$40:$AA$133,'4 Análise ZBR'!$BH$40:$BH$133)+A14-D14 -> 39661.48 | J14: =SUMPRODUCT('4 Análise ZBR'!$AA$40:$AA$133,'4 Análise ZBR'!$Y$40:$Y$133) -> 59270.487 | M14: =ROUND(J14-G14,3) -> 19609.007 | O14: =SUMPRODUCT('4 Análise Depósito 2008'!$Z$40:$Z$133*('4 Análise Depósito 2008'!$Y$40:$Y$133>0)*'4 Análise Depósito 2008'!$Y$40:$Y$133) -> 54295.8
A15: transferido do 2008 | D15: vendas e entregas (601) | G15: saldo inicial + entrou − saiu | J15: posição atual no depósito | M15: físico − deveria ter | O15: importação não transferida
A17: GRÁFICOS GERENCIAIS
T19: Categoria da causa | U19: Ocorrências
T20: Falta sem explicação | U20: =COUNTIFS('4 Análise ZBR'!$AA$40:$AA$133,1,'4 Análise ZBR'!$BE$40:$BE$133,T20) -> 2
T21: Não localizado no estoque | U21: =COUNTIFS('4 Análise ZBR'!$AA$40:$AA$133,1,'4 Análise ZBR'!$BE$40:$BE$133,T21) -> 1
T22: Saída sem baixa no estoque | U22: =COUNTIFS('4 Análise ZBR'!$AA$40:$AA$133,1,'4 Análise ZBR'!$BE$40:$BE$133,T22) -> 8
T23: Doca/transferência pendente | U23: =COUNTIFS('4 Análise ZBR'!$AA$40:$AA$133,1,'4 Análise ZBR'!$BE$40:$BE$133,T23) -> 1
T24: Estoque anterior a 09/09 | U24: =COUNTIFS('4 Análise ZBR'!$AA$40:$AA$133,1,'4 Análise ZBR'!$BE$40:$BE$133,T24) -> 3
T25: Troca de lote | U25: =COUNTIFS('4 Análise ZBR'!$AA$40:$AA$133,1,'4 Análise ZBR'!$BE$40:$BE$133,T25) -> 0
T26: Sobra parcialmente explicada | U26: =COUNTIFS('4 Análise ZBR'!$AA$40:$AA$133,1,'4 Análise ZBR'!$BE$40:$BE$133,T26) -> 7
T27: Sobra sem explicação | U27: =COUNTIFS('4 Análise ZBR'!$AA$40:$AA$133,1,'4 Análise ZBR'!$BE$40:$BE$133,T27) -> 1
T30: Situação | U30: SKU·lote
T31: Confere | U31: =COUNTIFS('4 Análise ZBR'!$AA$40:$AA$133,1,'4 Análise ZBR'!$AC$40:$AC$133,T31) -> 58
T32: Sobrando | U32: =COUNTIFS('4 Análise ZBR'!$AA$40:$AA$133,1,'4 Análise ZBR'!$AC$40:$AC$133,T32) -> 20
T33: Faltando | U33: =COUNTIFS('4 Análise ZBR'!$AA$40:$AA$133,1,'4 Análise ZBR'!$AC$40:$AC$133,T33) -> 3
T36: Criticidade | U36: Ocorrências
T37: Crítica | U37: =COUNTIFS('4 Análise ZBR'!$AA$40:$AA$133,1,'4 Análise ZBR'!$BF$40:$BF$133,T37) -> 3
T38: Alta | U38: =COUNTIFS('4 Análise ZBR'!$AA$40:$AA$133,1,'4 Análise ZBR'!$BF$40:$BF$133,T38) -> 4
T39: Média | U39: =COUNTIFS('4 Análise ZBR'!$AA$40:$AA$133,1,'4 Análise ZBR'!$BF$40:$BF$133,T39) -> 4
T40: Baixa | U40: =COUNTIFS('4 Análise ZBR'!$AA$40:$AA$133,1,'4 Análise ZBR'!$BF$40:$BF$133,T40) -> 12
T43: Status do plano | U43: Ações
T44: Não iniciado | U44: =COUNTIF('6 Plano de Ação'!$O$8:$O$507,T44) -> 61
T45: Em andamento | U45: =COUNTIF('6 Plano de Ação'!$O$8:$O$507,T45) -> 0
T46: Concluído | U46: =COUNTIF('6 Plano de Ação'!$O$8:$O$507,T46) -> 0
T47: Cancelado | U47: =COUNTIF('6 Plano de Ação'!$O$8:$O$507,T47) -> 0
I73: Leitura rápida
I74: • Azul = entrou no ZBR · azul-claro = saiu. Verde = regular · amarelo = atenção · vermelho = crítico.
I75: • Todos os números seguem os filtros do topo, exceto Pendências e % Conclusão (plano de ação geral).
I76: • Detalhe por SKU·lote: abas "4 Análise ZBR" e "5 Conciliação". Ações: aba "6 Plano de Ação".
I77: • Critérios de cálculo de cada indicador: aba "7 Dicionário de Dados".

Sheet 2 Resumo Gerencial
A1: Resumo Gerencial | I1: ◄ MENU
A2: Síntese das análises, principais ocorrências e conclusões · visão geral (sem filtros)
B5: 1. Escopo da análise
B6: Item | C6: Valor
B7: Primeira data de movimento | C7: =MIN(MIN('3 Base Entrada 2008'!$F$2:$F$5000),MIN('3 Base Saídas'!$G$2:$G$5000)) -> 46274
B8: Última data de movimento | C8: =MAX(MAX('3 Base Entrada 2008'!$F$2:$F$5000),MAX('3 Base Saídas'!$G$2:$G$5000)) -> 46296
B9: SKU·lote conciliados | C9: =COUNTA('5 Conciliação'!$A$14:$A$107) -> 94
B10: Lançamentos no depósito 2008 (base Entrada) | C10: =COUNTA('3 Base Entrada 2008'!$A$2:$A$5000) -> 201
B11: Lançamentos de saída 601 (base Saídas) | C11: =COUNTA('3 Base Saídas'!$A$2:$A$5000) -> 405
B12: Posições de estoque físico (base Estoque) | C12: =COUNTA('3 Base Estoque Físico'!$A$2:$A$5000) -> 228
B14: 2. Resultado da conciliação por unidade de medida
B15: Unidade | C15: SKU·lote | D15: Conferem | E15: Divergentes | F15: % conformidade | G15: Diferença líquida | H15: Sem explicação
B16: KG | C16: =COUNTIFS('5 Conciliação'!$D$14:$D$107,"KG") -> 81 | D16: =COUNTIFS('5 Conciliação'!$D$14:$D$107,"KG",'5 Conciliação'!$J$14:$J$107,"Confere") -> 58 | E16: =C16-D16 -> 23 | F16: =IF(C16=0,0,D16/C16) -> 0.71604938 | G16: =SUMIFS('5 Conciliação'!$I$14:$I$107,'5 Conciliação'!$D$14:$D$107,"KG") -> 19609.01 | H16: =SUMIFS('5 Conciliação'!$O$14:$O$107,'5 Conciliação'!$D$14:$D$107,"KG") -> 4630.78
B17: UN | C17: =COUNTIFS('5 Conciliação'!$D$14:$D$107,"UN") -> 6 | D17: =COUNTIFS('5 Conciliação'!$D$14:$D$107,"UN",'5 Conciliação'!$J$14:$J$107,"Confere") -> 3 | E17: =C17-D17 -> 3 | F17: =IF(C17=0,0,D17/C17) -> 0.5 | G17: =SUMIFS('5 Conciliação'!$I$14:$I$107,'5 Conciliação'!$D$14:$D$107,"UN") -> 64.22 | H17: =SUMIFS('5 Conciliação'!$O$14:$O$107,'5 Conciliação'!$D$14:$D$107,"UN") -> 4.22
B18: CX | C18: =COUNTIFS('5 Conciliação'!$D$14:$D$107,"CX") -> 7 | D18: =COUNTIFS('5 Conciliação'!$D$14:$D$107,"CX",'5 Conciliação'!$J$14:$J$107,"Confere") -> 5 | E18: =C18-D18 -> 2 | F18: =IF(C18=0,0,D18/C18) -> 0.71428571 | G18: =SUMIFS('5 Conciliação'!$I$14:$I$107,'5 Conciliação'!$D$14:$D$107,"CX") -> 0 | H18: =SUMIFS('5 Conciliação'!$O$14:$O$107,'5 Conciliação'!$D$14:$D$107,"CX") -> 0
B19: Total | C19: =SUM(C16:C18) -> 94 | D19: =SUM(D16:D18) -> 66 | E19: =SUM(E16:E18) -> 28 | F19: =IF(C19=0,0,D19/C19) -> 0.70212766
B21: 3. Divergências por categoria de causa
B22: Categoria | C22: Ocorrências | D22: Diferença (KG)
B23: Falta sem explicação | C23: =COUNTIFS('5 Conciliação'!$Q$14:$Q$107,B23) -> 3 | D23: =SUMIFS('5 Conciliação'!$I$14:$I$107,'5 Conciliação'!$Q$14:$Q$107,B23,'5 Conciliação'!$D$14:$D$107,"KG") -> -652.2
B24: Não localizado no estoque | C24: =COUNTIFS('5 Conciliação'!$Q$14:$Q$107,B24) -> 1 | D24: =SUMIFS('5 Conciliação'!$I$14:$I$107,'5 Conciliação'!$Q$14:$Q$107,B24,'5 Conciliação'!$D$14:$D$107,"KG") -> -261.12
B25: Saída sem baixa no estoque | C25: =COUNTIFS('5 Conciliação'!$Q$14:$Q$107,B25) -> 9 | D25: =SUMIFS('5 Conciliação'!$I$14:$I$107,'5 Conciliação'!$Q$14:$Q$107,B25,'5 Conciliação'!$D$14:$D$107,"KG") -> 2941.6
B26: Doca/transferência pendente | C26: =COUNTIFS('5 Conciliação'!$Q$14:$Q$107,B26) -> 1 | D26: =SUMIFS('5 Conciliação'!$I$14:$I$107,'5 Conciliação'!$Q$14:$Q$107,B26,'5 Conciliação'!$D$14:$D$107,"KG") -> 20.1
B27: Estoque anterior a 09/09 | C27: =COUNTIFS('5 Conciliação'!$Q$14:$Q$107,B27) -> 3 | D27: =SUMIFS('5 Conciliação'!$I$14:$I$107,'5 Conciliação'!$Q$14:$Q$107,B27,'5 Conciliação'!$D$14:$D$107,"KG") -> 410.04
B28: Troca de lote | C28: =COUNTIFS('5 Conciliação'!$Q$14:$Q$107,B28) -> 2 | D28: =SUMIFS('5 Conciliação'!$I$14:$I$107,'5 Conciliação'!$Q$14:$Q$107,B28,'5 Conciliação'!$D$14:$D$107,"KG") -> 0
B29: Sobra parcialmente explicada | C29: =COUNTIFS('5 Conciliação'!$Q$14:$Q$107,B29) -> 7 | D29: =SUMIFS('5 Conciliação'!$I$14:$I$107,'5 Conciliação'!$Q$14:$Q$107,B29,'5 Conciliação'!$D$14:$D$107,"KG") -> 16902.59
B30: Sobra sem explicação | C30: =COUNTIFS('5 Conciliação'!$Q$14:$Q$107,B30) -> 2 | D30: =SUMIFS('5 Conciliação'!$I$14:$I$107,'5 Conciliação'!$Q$14:$Q$107,B30,'5 Conciliação'!$D$14:$D$107,"KG") -> 248
B32: 4. Ocorrências por criticidade (proposta para validação)
B33: Criticidade | C33: Ocorrências | D33: Critério
B34: Crítica | C34: =COUNTIF('5 Conciliação'!$R$14:$R$107,"Crítica") -> 3 | D34: ="Não localizado no estoque, ou falta sem explicação ≥ "&Parâmetros!$K$6 -> Não localizado no estoque, ou falta sem explicação ≥ 200
B35: Alta | C35: =COUNTIF('5 Conciliação'!$R$14:$R$107,"Alta") -> 5 | D35: ="Outras faltas sem explicação, ou sobra sem explicação ≥ "&Parâmetros!$K$7 -> Outras faltas sem explicação, ou sobra sem explicação ≥ 500
B36: Média | C36: =COUNTIF('5 Conciliação'!$R$14:$R$107,"Média") -> 5 | D36: Sobra com parte sem explicação abaixo do limite
B37: Baixa | C37: =COUNTIF('5 Conciliação'!$R$14:$R$107,"Baixa") -> 15 | D37: Diferença totalmente explicada pelos dados
B39: 5. Cinco maiores ocorrências (diferença sem explicação)
B40: SKU | C40: Lote | D40: UM | E40: Diferença | F40: Sem explicação | G40: Categoria | H40: Criticidade
B41: =IFERROR(INDEX('5 Conciliação'!$A$14:$A$107,MATCH(LARGE('5 Conciliação'!$T$14:$T$107,1),'5 Conciliação'!$T$14:$T$107,0)),"") -> CHM-SP-Z3L-BR-U73 | C41: =IFERROR(INDEX('5 Conciliação'!$B$14:$B$107,MATCH(LARGE('5 Conciliação'!$T$14:$T$107,1),'5 Conciliação'!$T$14:$T$107,0)),"") -> 251880301 | D41: =IFERROR(INDEX('5 Conciliação'!$D$14:$D$107,MATCH(LARGE('5 Conciliação'!$T$14:$T$107,1),'5 Conciliação'!$T$14:$T$107,0)),"") -> KG | E41: =IFERROR(INDEX('5 Conciliação'!$I$14:$I$107,MATCH(LARGE('5 Conciliação'!$T$14:$T$107,1),'5 Conciliação'!$T$14:$T$107,0)),"") -> 3695 | F41: =IFERROR(INDEX('5 Conciliação'!$O$14:$O$107,MATCH(LARGE('5 Conciliação'!$T$14:$T$107,1),'5 Conciliação'!$T$14:$T$107,0)),"") -> 2148 | G41: =IFERROR(INDEX('5 Conciliação'!$Q$14:$Q$107,MATCH(LARGE('5 Conciliação'!$T$14:$T$107,1),'5 Conciliação'!$T$14:$T$107,0)),"") -> Sobra parcialmente explicada | H41: =IFERROR(INDEX('5 Conciliação'!$R$14:$R$107,MATCH(LARGE('5 Conciliação'!$T$14:$T$107,1),'5 Conciliação'!$T$14:$T$107,0)),"") -> Alta
B42: =IFERROR(INDEX('5 Conciliação'!$A$14:$A$107,MATCH(LARGE('5 Conciliação'!$T$14:$T$107,2),'5 Conciliação'!$T$14:$T$107,0)),"") -> 823-BR-D94 | C42: =IFERROR(INDEX('5 Conciliação'!$B$14:$B$107,MATCH(LARGE('5 Conciliação'!$T$14:$T$107,2),'5 Conciliação'!$T$14:$T$107,0)),"") -> 252103049 | D42: =IFERROR(INDEX('5 Conciliação'!$D$14:$D$107,MATCH(LARGE('5 Conciliação'!$T$14:$T$107,2),'5 Conciliação'!$T$14:$T$107,0)),"") -> KG | E42: =IFERROR(INDEX('5 Conciliação'!$I$14:$I$107,MATCH(LARGE('5 Conciliação'!$T$14:$T$107,2),'5 Conciliação'!$T$14:$T$107,0)),"") -> 2528.4 | F42: =IFERROR(INDEX('5 Conciliação'!$O$14:$O$107,MATCH(LARGE('5 Conciliação'!$T$14:$T$107,2),'5 Conciliação'!$T$14:$T$107,0)),"") -> 1260 | G42: =IFERROR(INDEX('5 Conciliação'!$Q$14:$Q$107,MATCH(LARGE('5 Conciliação'!$T$14:$T$107,2),'5 Conciliação'!$T$14:$T$107,0)),"") -> Sobra parcialmente explicada | H42: =IFERROR(INDEX('5 Conciliação'!$R$14:$R$107,MATCH(LARGE('5 Conciliação'!$T$14:$T$107,2),'5 Conciliação'!$T$14:$T$107,0)),"") -> Alta
B43: =IFERROR(INDEX('5 Conciliação'!$A$14:$A$107,MATCH(LARGE('5 Conciliação'!$T$14:$T$107,3),'5 Conciliação'!$T$14:$T$107,0)),"") -> W3-BR-25A | C43: =IFERROR(INDEX('5 Conciliação'!$B$14:$B$107,MATCH(LARGE('5 Conciliação'!$T$14:$T$107,3),'5 Conciliação'!$T$14:$T$107,0)),"") -> 253540301 | D43: =IFERROR(INDEX('5 Conciliação'!$D$14:$D$107,MATCH(LARGE('5 Conciliação'!$T$14:$T$107,3),'5 Conciliação'!$T$14:$T$107,0)),"") -> KG | E43: =IFERROR(INDEX('5 Conciliação'!$I$14:$I$107,MATCH(LARGE('5 Conciliação'!$T$14:$T$107,3),'5 Conciliação'!$T$14:$T$107,0)),"") -> 1083.39 | F43: =IFERROR(INDEX('5 Conciliação'!$O$14:$O$107,MATCH(LARGE('5 Conciliação'!$T$14:$T$107,3),'5 Conciliação'!$T$14:$T$107,0)),"") -> 562.8 | G43: =IFERROR(INDEX('5 Conciliação'!$Q$14:$Q$107,MATCH(LARGE('5 Conciliação'!$T$14:$T$107,3),'5 Conciliação'!$T$14:$T$107,0)),"") -> Sobra parcialmente explicada | H43: =IFERROR(INDEX('5 Conciliação'!$R$14:$R$107,MATCH(LARGE('5 Conciliação'!$T$14:$T$107,3),'5 Conciliação'!$T$14:$T$107,0)),"") -> Alta
B44: =IFERROR(INDEX('5 Conciliação'!$A$14:$A$107,MATCH(LARGE('5 Conciliação'!$T$14:$T$107,4),'5 Conciliação'!$T$14:$T$107,0)),"") -> CHP-20SICHP-760 | C44: =IFERROR(INDEX('5 Conciliação'!$B$14:$B$107,MATCH(LARGE('5 Conciliação'!$T$14:$T$107,4),'5 Conciliação'!$T$14:$T$107,0)),"") -> 252843369 | D44: =IFERROR(INDEX('5 Conciliação'!$D$14:$D$107,MATCH(LARGE('5 Conciliação'!$T$14:$T$107,4),'5 Conciliação'!$T$14:$T$107,0)),"") -> KG | E44: =IFERROR(INDEX('5 Conciliação'!$I$14:$I$107,MATCH(LARGE('5 Conciliação'!$T$14:$T$107,4),'5 Conciliação'!$T$14:$T$107,0)),"") -> 540 | F44: =IFERROR(INDEX('5 Conciliação'!$O$14:$O$107,MATCH(LARGE('5 Conciliação'!$T$14:$T$107,4),'5 Conciliação'!$T$14:$T$107,0)),"") -> 516 | G44: =IFERROR(INDEX('5 Conciliação'!$Q$14:$Q$107,MATCH(LARGE('5 Conciliação'!$T$14:$T$107,4),'5 Conciliação'!$T$14:$T$107,0)),"") -> Sobra parcialmente explicada | H44: =IFERROR(INDEX('5 Conciliação'!$R$14:$R$107,MATCH(LARGE('5 Conciliação'!$T$14:$T$107,4),'5 Conciliação'!$T$14:$T$107,0)),"") -> Alta
B45: =IFERROR(INDEX('5 Conciliação'!$A$14:$A$107,MATCH(LARGE('5 Conciliação'!$T$14:$T$107,5),'5 Conciliação'!$T$14:$T$107,0)),"") -> CHK-R30GOLD-BR-25A | C45: =IFERROR(INDEX('5 Conciliação'!$B$14:$B$107,MATCH(LARGE('5 Conciliação'!$T$14:$T$107,5),'5 Conciliação'!$T$14:$T$107,0)),"") -> 261130301 | D45: =IFERROR(INDEX('5 Conciliação'!$D$14:$D$107,MATCH(LARGE('5 Conciliação'!$T$14:$T$107,5),'5 Conciliação'!$T$14:$T$107,0)),"") -> KG | E45: =IFERROR(INDEX('5 Conciliação'!$I$14:$I$107,MATCH(LARGE('5 Conciliação'!$T$14:$T$107,5),'5 Conciliação'!$T$14:$T$107,0)),"") -> -442.2 | F45: =IFERROR(INDEX('5 Conciliação'!$O$14:$O$107,MATCH(LARGE('5 Conciliação'!$T$14:$T$107,5),'5 Conciliação'!$T$14:$T$107,0)),"") -> -442.2 | G45: =IFERROR(INDEX('5 Conciliação'!$Q$14:$Q$107,MATCH(LARGE('5 Conciliação'!$T$14:$T$107,5),'5 Conciliação'!$T$14:$T$107,0)),"") -> Falta sem explicação | H45: =IFERROR(INDEX('5 Conciliação'!$R$14:$R$107,MATCH(LARGE('5 Conciliação'!$T$14:$T$107,5),'5 Conciliação'!$T$14:$T$107,0)),"") -> Crítica
B47: 6. Depósito 2008 (importação) · KG
B48: Indicador | C48: Valor
B49: Recebido no 2008 | C49: =SUMIFS('3 Base Entrada 2008'!$G$2:$G$5000,'3 Base Entrada 2008'!$K$2:$K$5000,"Recebido no 2008",'3 Base Entrada 2008'!$H$2:$H$5000,"KG") -> 77159.5
B50: Transferido ao ZBR | C50: =-SUMIFS('3 Base Entrada 2008'!$G$2:$G$5000,'3 Base Entrada 2008'!$K$2:$K$5000,"Entrada",'3 Base Entrada 2008'!$H$2:$H$5000,"KG") -> 67865.28
B51: Estornos (voltou ao 2008) | C51: =SUMIFS('3 Base Entrada 2008'!$G$2:$G$5000,'3 Base Entrada 2008'!$K$2:$K$5000,"Estorno",'3 Base Entrada 2008'!$H$2:$H$5000,"KG") -> 1935
B52: Saldo do período no 2008 | C52: =C49-C50+C51 -> 11229.22
B53: Lotes aguardando transferência (todas as unidades) | C53: =COUNTIF('6 Plano de Ação'!$B$8:$B$507,"Depósito 2008") -> 33
B54: Volume aguardando transferência (KG) | C54: =SUMIFS('6 Plano de Ação'!$I$8:$I$507,'6 Plano de Ação'!$B$8:$B$507,"Depósito 2008",'6 Plano de Ação'!$E$8:$E$507,"KG") -> 54295.8
B56: 7. Plano de ação
B57: Indicador | C57: Valor
B58: Ocorrências no plano | C58: =COUNTIF('6 Plano de Ação'!$A$8:$A$507,"OC-*") -> 61
B59: Não iniciadas | C59: =COUNTIF('6 Plano de Ação'!$O$8:$O$507,"Não iniciado") -> 61
B60: Em andamento | C60: =COUNTIF('6 Plano de Ação'!$O$8:$O$507,"Em andamento") -> 0
B61: Concluídas | C61: =COUNTIF('6 Plano de Ação'!$O$8:$O$507,"Concluído") -> 0
B62: % concluído | C62: =IF(C58=0,0,C61/C58) -> 0
B63: Vencidas | C63: =COUNTIF('6 Plano de Ação'!$P$8:$P$507,"Vencida") -> 0
B64: Sem responsável definido | C64: =COUNTIF('6 Plano de Ação'!$K$8:$K$507,"Pendente de preenchimento") -> 61
B66: 8. Conclusões (geradas a partir dos números acima)
B67: ="Conformidade: "&D19&" de "&C19&" SKU·lote conferem ("&FIXED(F19*100,1)&"%); "&E19&" apresentam diferença." -> Conformidade: 66 de 94 SKU·lote conferem (70.2%); 28 apresentam diferença.
B68: ="Principal causa: "&INDEX(B23:B30,MATCH(MAX(C23:C30),C23:C30,0))&" ("&MAX(C23:C30)&" ocorrências)." -> Principal causa: Saída sem baixa no estoque (9 ocorrências).
B69: ="Ocorrências críticas: "&C34&" (faltas relevantes ou mercadoria não localizada) — tratar antes das sobras." -> Ocorrências críticas: 3 (faltas relevantes ou mercadoria não localizada) — tratar antes das sobras.
B70: ="Maior ocorrência: SKU "&B41&" lote "&C41&", "&FIXED(F41,1)&" "&D41&" sem explicação ("&G41&")." -> Maior ocorrência: SKU CHM-SP-Z3L-BR-U73 lote 251880301, 2,148.0 KG sem explicação (Sobra parcialmente explicada).
B71: ="Depósito 2008: "&FIXED(C54,1)&" KG de importação aguardam transferência para o ZBR em "&C53&" lotes." -> Depósito 2008: 54,295.8 KG de importação aguardam transferência para o ZBR em 33 lotes.
B72: ="Plano de ação: "&(C58-C61)&" ações em aberto; "&C64&" sem responsável definido." -> Plano de ação: 61 ações em aberto; 61 sem responsável definido.
B73: =IF(SUM('3 Base Saldo Inicial 08-09'!$E$2:$E$5000)=0,"Saldo inicial de 08/09 ainda não informado: as sobras podem ser estoque anterior a 09/09. Preencha a aba 3 Base Saldo Inicial 08-09 (ou carregue pelo Power Query) para refinar as diferenças.","Saldo inicial de 08/09 informado ("&FIXED(SUM('3 Base Saldo Inicial 08-09'!$E$2:$E$5000),1)&") e já considerado no Deveria ter.") -> Saldo inicial de 08/09 ainda não informado: as sobras podem ser estoque anterior a 09/09. Preencha a aba 3 Base Saldo Inicial 08-09 (ou carregue pelo Power Query) para refinar as diferenças.

Sheet 3 Base Entrada 2008
A1: DOC.MATERIAL | B1: SKU | C1: LOTE | D1: DEPÓSITO | E1: CENTRO | F1: DATA DE LANÇAMENTO | G1: QUANTIDADE | H1: UM | I1: DATA DE ENTRADA | J1: HORA DO REGISTRO | K1: MOVIMENTAÇÃO | L1: ENTROU NO ZBR
A2: 4904083265 | B2: 2665-E4-U71 | C2: 252800202 | D2: 2008 | E2: BR01 | F2: 46289 | G2: -600 | H2: KG | I2: 46289 | J2: 0.87827546 | K2: =IF(AND(G2>0,F2<=Parâmetros!$C$6),"Recebido no 2008",IF(G2<0,"Entrada","Estorno")) -> Entrada | L2: =IF(K2="Recebido no 2008",0,-G2) -> 600
A3: 4904083324 | B3: 2665-E4-U71 | C3: 252800202 | D3: 2008 | E3: BR01 | F3: 46289 | G3: -600 | H3: KG | I3: 46289 | J3: 0.88203704 | K3: =IF(AND(G3>0,F3<=Parâmetros!$C$6),"Recebido no 2008",IF(G3<0,"Entrada","Estorno")) -> Entrada | L3: =IF(K3="Recebido no 2008",0,-G3) -> 600
A4: 4904153691 | B4: 70-30-38-BR-25A | C4: 260370301 | D4: 2008 | E4: BR01 | F4: 46294 | G4: -603 | H4: KG | I4: 46294 | J4: 0.68579861 | K4: =IF(AND(G4>0,F4<=Parâmetros!$C$6),"Recebido no 2008",IF(G4<0,"Entrada","Estorno")) -> Entrada | L4: =IF(K4="Recebido no 2008",0,-G4) -> 603
A5: 4904053448 | B5: 70-30-38-BR-25A | C5: 260070301 | D5: 2008 | E5: BR01 | F5: 46288 | G5: -2412 | H5: KG | I5: 46288 | J5: 0.26028935 | K5: =IF(AND(G5>0,F5<=Parâmetros!$C$6),"Recebido no 2008",IF(G5<0,"Entrada","Estorno")) -> Entrada | L5: =IF(K5="Recebido no 2008",0,-G5) -> 2412
A6: 4904053657 | B6: 70-30-38-BR-25A | C6: 260070301 | D6: 2008 | E6: BR01 | F6: 46288 | G6: -603 | H6: KG | I6: 46288 | J6: 0.27048611 | K6: =IF(AND(G6>0,F6<=Parâmetros!$C$6),"Recebido no 2008",IF(G6<0,"Entrada","Estorno")) -> Entrada | L6: =IF(K6="Recebido no 2008",0,-G6) -> 603
A7: 4904053653 | B7: 70-30-38-BR-D94 | C7: 253213449 | D7: 2008 | E7: BR01 | F7: 46288 | G7: -940.8 | H7: KG | I7: 46288 | J7: 0.26896991 | K7: =IF(AND(G7>0,F7<=Parâmetros!$C$6),"Recebido no 2008",IF(G7<0,"Entrada","Estorno")) -> Entrada | L7: =IF(K7="Recebido no 2008",0,-G7) -> 940.8
A8: 4904151607 | B8: 805-BR-D94 | C8: 251633359 | D8: 2008 | E8: BR01 | F8: 46294 | G8: -313.6 | H8: KG | I8: 46294 | J8: 0.61137731 | K8: =IF(AND(G8>0,F8<=Parâmetros!$C$6),"Recebido no 2008",IF(G8<0,"Entrada","Estorno")) -> Entrada | L8: =IF(K8="Recebido no 2008",0,-G8) -> 313.6
A9: 4904151607 | B9: 805-BR-D94 | C9: 260130779 | D9: 2008 | E9: BR01 | F9: 46294 | G9: -142.8 | H9: KG | I9: 46294 | J9: 0.61137731 | K9: =IF(AND(G9>0,F9<=Parâmetros!$C$6),"Recebido no 2008",IF(G9<0,"Entrada","Estorno")) -> Entrada | L9: =IF(K9="Recebido no 2008",0,-G9) -> 142.8
A10: 4904175204 | B10: 811-BR-25A | C10: 252450301 | D10: 2008 | E10: BR01 | F10: 46295 | G10: -221.1 | H10: KG | I10: 46295 | J10: 0.74815972 | K10: =IF(AND(G10>0,F10<=Parâmetros!$C$6),"Recebido no 2008",IF(G10<0,"Entrada","Estorno")) -> Entrada | L10: =IF(K10="Recebido no 2008",0,-G10) -> 221.1
A11: 4904153935 | B11: 811-BR-25A | C11: 252450301 | D11: 2008 | E11: BR01 | F11: 46294 | G11: -482.4 | H11: KG | I11: 46294 | J11: 0.69373843 | K11: =IF(AND(G11>0,F11<=Parâmetros!$C$6),"Recebido no 2008",IF(G11<0,"Entrada","Estorno")) -> Entrada | L11: =IF(K11="Recebido no 2008",0,-G11) -> 482.4
A12: 4904153935 | B12: 811-BR-25A | C12: 252450301 | D12: 2008 | E12: BR01 | F12: 46294 | G12: -221.1 | H12: KG | I12: 46294 | J12: 0.69373843 | K12: =IF(AND(G12>0,F12<=Parâmetros!$C$6),"Recebido no 2008",IF(G12<0,"Entrada","Estorno")) -> Entrada | L12: =IF(K12="Recebido no 2008",0,-G12) -> 221.1
A13: 4904153935 | B13: 811-BR-25A | C13: 252450301 | D13: 2008 | E13: BR01 | F13: 46294 | G13: -603 | H13: KG | I13: 46294 | J13: 0.69373843 | K13: =IF(AND(G13>0,F13<=Parâmetros!$C$6),"Recebido no 2008",IF(G13<0,"Entrada","Estorno")) -> Entrada | L13: =IF(K13="Recebido no 2008",0,-G13) -> 603
... A202: 4903864964 | B202: W3-BR-25A | C202: 261080301 | D202: 2008 | E202: BR01 | F202: 46275 | G202: 2995 | H202: KG | I202: 46275 | J202: 0.79055556 | K202: =IF(AND(G202>0,F202<=Parâmetros!$C$6),"Recebido no 2008",IF(G202<0,"Entrada","Estorno")) -> Recebido no 2008 | L202: =IF(K202="Recebido no 2008",0,-G202) -> 0

Sheet 3 Base Saídas
A1: DOC.MATERIAL | B1: SKU | C1: LOTE | D1: DESCRIÇÃO | E1: DEPÓSITO | F1: CENTRO | G1: DATA DE LANÇAMENTO | H1: QUANTIDADE | I1: UM | J1: DATA DE ENTRADA | K1: TIPO DE MOVIMENTO | L1: MOTIVO DO MOVIMENTO | M1: HORA DO REGISTRO | N1: NOME DO USUÁRIO | O1: REFERÊNCIA | P1: CLIENTE | Q1: NOME 1 | R1: SAIU
A2: 4904167047 | B2: 70-30-38-BR-25A | C2: 260070301 | D2: CA MOEDAS 2,01KG/UC 10UC/CX 30CX/PAL | E2: 9999 | F2: BR01 | G2: 46295 | H2: -40.2 | I2: KG | J2: 46295 | K2: 601 | L2: 0 | M2: 0.43071759 | N2: BC140676 | O2: 0017883533 | P2: 50643 | Q2: PRODUPAN - PRODUTOS PARA PANIFICACA | R2: =-H2 -> 40.2
A3: 4904165495 | B3: 70-30-38-BR-25A | C3: 260070301 | D3: CA MOEDAS 2,01KG/UC 10UC/CX 30CX/PAL | E3: 9999 | F3: BR01 | G3: 46295 | H3: -60.3 | I3: KG | J3: 46295 | K3: 601 | L3: 0 | M3: 0.3559838 | N3: BC140676 | O3: 0017883681 | P3: 218096 | Q3: T & F ALIMENTOS LTDA | R3: =-H3 -> 60.3
A4: 4904175148 | B4: 70-30-38-BR-25A | C4: 260370301 | D4: CA MOEDAS 2,01KG/UC 10UC/CX 30CX/PAL | E4: 0355 | F4: BR01 | G4: 46295 | H4: -20.1 | I4: KG | J4: 46295 | K4: 601 | L4: 0 | M4: 0.74501157 | N4: BC025150 | O4: 0017883735 | P4: 218814 | Q4: ANGELA PRATI FAVARO . LTDA | R4: =-H4 -> 20.1
A5: 4904159986 | B5: 70-30-38-BR-25A | C5: 260070301 | D5: CA MOEDAS 2,01KG/UC 10UC/CX 30CX/PAL | E5: 9999 | F5: BR01 | G5: 46294 | H5: -80.4 | I5: KG | J5: 46295 | K5: 601 | L5: 0 | M5: 0.0053935185 | N5: BC140676 | O5: 0017884035 | P5: 50588 | Q5: DISTRIBUIDORA E IMPORTADORA IRMAOS | R5: =-H5 -> 80.4
A6: 4904134037 | B6: 70-30-38-BR-25A | C6: 260370301 | D6: CA MOEDAS 2,01KG/UC 10UC/CX 30CX/PAL | E6: 0355 | F6: BR01 | G6: 46293 | H6: -20.1 | I6: KG | J6: 46293 | K6: 601 | L6: 0 | M6: 0.68363426 | N6: BC025148 | O6: 0017878206 | P6: 78892 | Q6: TANGARA DESENV IMOBIL | R6: =-H6 -> 20.1
A7: 4904119924 | B7: 70-30-38-BR-25A | C7: 260070301 | D7: CA MOEDAS 2,01KG/UC 10UC/CX 30CX/PAL | E7: 9999 | F7: BR01 | G7: 46292 | H7: -201 | I7: KG | J7: 46292 | K7: 601 | L7: 0 | M7: 0.82452546 | N7: BC147417 | O7: 0017871992 | P7: 73161 | Q7: LARGO DO CONFEITEIRO | R7: =-H7 -> 201
A8: 4904118269 | B8: 70-30-38-BR-25A | C8: 260070301 | D8: CA MOEDAS 2,01KG/UC 10UC/CX 30CX/PAL | E8: 9999 | F8: BR01 | G8: 46292 | H8: -20.1 | I8: KG | J8: 46292 | K8: 601 | L8: 0 | M8: 0.6312963 | N8: BC147417 | O8: 0017883375 | P8: 91915 | Q8: CHOCOLANDIA SOBELA LTDA | R8: =-H8 -> 20.1
A9: 4904119956 | B9: 70-30-38-BR-25A | C9: 260070301 | D9: CA MOEDAS 2,01KG/UC 10UC/CX 30CX/PAL | E9: 9999 | F9: BR01 | G9: 46292 | H9: -40.2 | I9: KG | J9: 46292 | K9: 601 | L9: 0 | M9: 0.82537037 | N9: BC147417 | O9: 0017878161 | P9: 99526 | Q9: BRUNO MENEGATTE COMERCIO LTDA | R9: =-H9 -> 40.2
A10: 4904122562 | B10: 70-30-38-BR-25A | C10: 260070301 | D10: CA MOEDAS 2,01KG/UC 10UC/CX 30CX/PAL | E10: 9999 | F10: BR01 | G10: 46292 | H10: -261.3 | I10: KG | J10: 46293 | K10: 601 | L10: 0 | M10: 0.12189815 | N10: BC116065 | O10: 0017871957 | P10: 68094 | Q10: NOVA GERACAO COMESTIVEIS LTDA | R10: =-H10 -> 261.3
A11: 4904119981 | B11: 70-30-38-BR-25A | C11: 260070301 | D11: CA MOEDAS 2,01KG/UC 10UC/CX 30CX/PAL | E11: 9999 | F11: BR01 | G11: 46292 | H11: -40.2 | I11: KG | J11: 46292 | K11: 601 | L11: 0 | M11: 0.82577546 | N11: BC147417 | O11: 0017881061 | P11: 218044 | Q11: GELATERIA PIEMONTE LTDA | R11: =-H11 -> 40.2
A12: 4904119985 | B12: 70-30-38-BR-25A | C12: 260070301 | D12: CA MOEDAS 2,01KG/UC 10UC/CX 30CX/PAL | E12: 9999 | F12: BR01 | G12: 46292 | H12: -20.1 | I12: KG | J12: 46292 | K12: 601 | L12: 0 | M12: 0.82583333 | N12: BC147417 | O12: 0017881065 | P12: 216990 | Q12: PANIFICACAO IPANEMA LTDA | R12: =-H12 -> 20.1
A13: 4904119988 | B13: 70-30-38-BR-25A | C13: 260070301 | D13: CA MOEDAS 2,01KG/UC 10UC/CX 30CX/PAL | E13: 9999 | F13: BR01 | G13: 46292 | H13: -40.2 | I13: KG | J13: 46292 | K13: 601 | L13: 0 | M13: 0.82590278 | N13: BC147417 | O13: 0017881171 | P13: 218068 | Q13: ABSURDINHA CONFEITARIA LTDA | R13: =-H13 -> 40.2
... A406: 4903864174 | B406: W3-BR-25A | C406: 253540301 | D406: CA MOEDAS 2,01KG/UC 10UC/CX 30CX/PAL | E406: 9999 | F406: BR01 | G406: 46275 | H406: -20.1 | I406: KG | J406: 46275 | K406: 601 | L406: 0 | M406: 0.74628472 | N406: BC129357 | O406: 0017854540 | P406: 94517 | Q406: JANE'S APPLE FACTORY LTDA | R406: =-H406 -> 20.1

Sheet 3 Base Estoque Físico
A1: SKU | B1: LOTE | C1: TIPO DE DEPÓSITO | D1: POSIÇÃO NO DEPÓSITO | E1: Nº DE QUANTOS | F1: TIPO DE ESTOQUE | G1: UNIDADE DE DEPÓSITO | H1: ESTOQUE DISPONÍVEL | I1: ÚLTIMO MOVIMENTO | J1: ESTOQUE FÍSICO | K1: UM | L1: DURAÇÃO | M1: DEPÓSITO | N1: DATA DO VENCIMENTO | O1: CENTRO
A2: CHK-R30GOLD-BR-25A | B2: 261130301 | C2: 922 | D2: TR-ZONE | E2: 55 | H2: 603 | I2: 46293 | J2: 603 | K2: KG | L2: 3 | M2: 0355 | O2: BR01
A3: CHK-R30GOLD-BR-25A | B3: 261130301 | C3: 922 | D3: TR-ZONE | E3: 55 | H3: -603 | I3: 46293 | J3: -603 | K3: KG | L3: 0 | M3: 9999 | O3: BR01
A4: W3-BR-25A | B4: 253540301 | C4: 922 | D4: U-ZONE | E4: 54 | H4: 281.4 | I4: 46280 | J4: 281.4 | K4: KG | L4: 54 | M4: 0355 | O4: BR01
A5: W3-BR-25A | B5: 253540301 | C5: DCK | D5: 0017854245 | E5: 1 | H5: -20.1 | I5: 46275 | J5: -20.1 | K5: KG | L5: 0 | M5: 9999 | O5: BR01
A6: 70-30-38-BR-25A | B6: 260370301 | C6: DCK | D6: 0017854263 | E6: 3 | H6: 20.1 | I6: 46279 | J6: 20.1 | K6: KG | L6: 17 | M6: 0355 | N6: 46789 | O6: BR01
A7: W3-BR-25A | B7: 253540301 | C7: DCK | D7: 0017854540 | E7: 1 | H7: -20.1 | I7: 46275 | J7: -20.1 | K7: KG | L7: 0 | M7: 9999 | O7: BR01
A8: W3-BR-25A | B8: 253540301 | C8: DCK | D8: 0017854808 | E8: 2 | H8: -20.1 | I8: 46275 | J8: -20.1 | K8: KG | L8: 0 | M8: 9999 | N8: 46558 | O8: BR01
A9: CHK-R30GOLD-E0-D94 | B9: 260720939 | C9: DCK | D9: 0017871931 | E9: 1 | H9: 19.599 | I9: 46287 | J9: 19.599 | K9: KG | L9: 9 | M9: 0355 | N9: 46459 | O9: BR01
A10: CHM-SP-Z3L-BR-U73 | B10: 251880301 | C10: DCK | D10: 0017872245 | E10: 1 | H10: 144 | I10: 46293 | J10: 144 | K10: KG | L10: 9 | M10: 9999 | N10: 46394 | O10: BR01
A11: CHK-R30GOLD-BR-25A | B11: 261130301 | C11: DCK | D11: 0017882892 | E11: 1 | H11: 804 | I11: 46291 | J11: 804 | K11: KG | L11: 5 | M11: 9999 | N11: 46683 | O11: BR01
A12: CHK-R30GOLD-BR-25A | B12: 261130301 | C12: DCK | D12: 0017883414 | E12: 2 | H12: 60.3 | I12: 46291 | J12: 60.3 | K12: KG | L12: 5 | M12: 9999 | N12: 46683 | O12: BR01
A13: CHR-Q37RB2-2B-U75 | B13: 261320202 | C13: DCK | D13: 0017883414 | E13: 2 | H13: 40 | I13: 46291 | J13: 40 | K13: KG | L13: 5 | M13: 9999 | N13: 46703 | O13: BR01
A14: 805-BR-D94 | B14: 251633359 | C14: DIF | D14: PICKLINE | E14: 40 | H14: 2.8 | I14: 46291 | J14: 2.8 | K14: KG | L14: 5 | M14: 9999 | N14: 46550 | O14: BR01
A15: 823NV-595 | B15: 261376101 | C15: DIF | D15: PICKLINE | E15: 40 | H15: 20 | I15: 46294 | J15: 20 | K15: KG | L15: 2 | M15: 9999 | O15: BR01
A16: CW2-BR-25A | B16: 252650301 | C16: DIF | D16: PICKLINE | E16: 40 | H16: 20.1 | I16: 46293 | J16: 20.1 | K16: KG | L16: 3 | M16: 9999 | N16: 46468 | O16: BR01
A17: CW2-BR-25A | B17: 253470301 | C17: FGF | D17: 06-18-E | E17: 1 | G17: 1021977000 | H17: 603 | I17: 46291 | J17: 603 | K17: KG | L17: 5 | M17: 9999 | N17: 46551 | O17: BR01
A18: CW2-BR-25A | B18: 252590301 | C18: FGF | D18: 06-20-E | E18: 1 | G18: 1021976000 | H18: 603 | I18: 46291 | J18: 603 | K18: KG | L18: 5 | M18: 9999 | N18: 46462 | O18: BR01
A19: NIBS-S502-X47 | B19: 252643099 | C19: FGF | D19: 06-87-E | E19: 1 | G19: 1021970000 | H19: 120 | I19: 46291 | J19: 120 | K19: CX | L19: 5 | M19: 9999 | N19: 46651 | O19: BR01
A20: CW2-BR-25A | B20: 261070301 | C20: FGF | D20: 07-107-E | E20: 1 | G20: 1021963000 | H20: 180.9 | I20: 46291 | J20: 180.9 | K20: KG | L20: 8 | M20: 9999 | N20: 46677 | O20: BR01
A21: 823-BR-25A | B21: 252100301 | C21: FGF | D21: 07-78-C | E21: 1 | G21: 1021970000 | H21: 19.7 | I21: 46291 | J21: 19.7 | K21: KG | L21: 5 | M21: 9999 | N21: 46416 | O21: BR01
A22: NIBS-S502-X47 | B22: 253490619 | C22: FGF | D22: 07-85-E | E22: 1 | G22: 1021970000 | H22: 120 | I22: 46291 | J22: 120 | K22: CX | L22: 5 | M22: 9999 | N22: 46736 | O22: BR01
A23: PRA-T14 | B23: 2611895339 | C23: FLR | D23: 0007939602 | E23: 1 | G23: 1021969000 | H23: 40 | I23: 46289 | J23: 40 | K23: KG | L23: 7 | M23: 9999 | N23: 46505 | O23: BR01
A24: NIBS-S502-X47 | B24: 242643099 | C24: FLR | D24: 0007940118 | E24: 1 | G24: 1021970000 | H24: 120 | I24: 46289 | J24: 120 | K24: CX | L24: 7 | M24: 9999 | N24: 46736 | O24: BR01
A25: PNP-T14 | B25: 2613495951 | C25: FLR | D25: 0007950573 | E25: 1 | G25: 1021986000 | H25: 300 | I25: 46294 | J25: 300 | K25: KG | L25: 2 | M25: 9999 | N25: 46521 | O25: BR01
A26: PNP-T14 | B26: 2613495951 | C26: FLR | D26: 0007950576 | E26: 1 | G26: 1021986000 | H26: 500 | I26: 46294 | J26: 500 | K26: KG | L26: 2 | M26: 9999 | N26: 46521 | O26: BR01
A27: DCP-10BONOI-89B | B27: 260778132 | C27: FLR | D27: 0007950581 | E27: 1 | G27: 1021986000 | H27: 126 | I27: 46295 | J27: 126 | K27: KG | L27: 2 | M27: 9999 | N27: 46830 | O27: BR01
A28: 811-BR-25A | B28: 252450301 | C28: FLR | D28: 0007950649 | E28: 1 | G28: 1021986000 | H28: 221.1 | I28: 46294 | J28: 221.1 | K28: KG | L28: 2 | M28: 9999 | N28: 46632 | O28: BR01
... A34: 811NV-132 | B34: 252510301 | C34: FLR | D34: AREA | E34: 44 | G34: 1021983000 | H34: 500 | I34: 46293 | J34: 500 | K34: KG | L34: 3 | M34: 9999 | N34: 46638 | O34: BR01
A35: 811NV-595 | B35: 260920702 | C35: FLR | D35: AREA | E35: 44 | F35: S | G35: 1021917000 | H35: 600 | I35: 46276 | J35: 600 | K35: KG | L35: 20 | M35: 9999 | N35: 46845 | O35: BR01
A36: BIG-PF-1BO-401 | B36: 26126039 | C36: FLR | D36: AREA | E36: 44 | F36: S | G36: 1021917000 | H36: 40 | I36: 46276 | J36: 40 | K36: KG | L36: 20 | M36: 9999 | N36: 46568 | O36: BR01
A37: CHM-TS-22351E0-999 | B37: 2526050307 | C37: FLR | D37: AREA | E37: 44 | F37: Q | G37: 1021907000 | H37: 1.36 | I37: 46274 | J37: 1.36 | K37: KG | L37: 22 | M37: 9999 | N37: 46463 | O37: BR01
A38: 70-30-38-BR-D94 | B38: 253213449 | C38: FLR | D38: D2 | E38: 530 | F38: R | G38: 1021981000 | H38: 11.2 | I38: 46293 | J38: 11.2 | K38: KG | L38: 3 | M38: 0355 | N38: 46708 | O38: BR01
A39: 823-BR-D94 | B39: 252103049 | C39: FLR | D39: D2 | E39: 530 | F39: R | G39: 1021981000 | H39: 14 | I39: 46293 | J39: 14 | K39: KG | L39: 3 | M39: 0355 | N39: 46416 | O39: BR01
A40: CHK-R30GOLD-BR-25A | B40: 253620301 | C40: FLR | D40: D2 | E40: 530 | F40: R | G40: 1021956000 | H40: 80.4 | I40: 46286 | J40: 80.4 | K40: KG | L40: 10 | M40: 9999 | N40: 46566 | O40: BR01
A41: CW2-BR-25A | B41: 252350301 | C41: FLR | D41: D2 | E41: 530 | F41: R | G41: 1021956000 | H41: 20.1 | I41: 46286 | J41: 20.1 | K41: KG | L41: 10 | M41: 9999 | N41: 46441 | O41: BR01
A42: 811-BR-25A | B42: 250880301 | C42: FLR | D42: DESCARTE | E42: 519 | F42: R | G42: 1021773000 | H42: 20.1 | I42: 46240 | J42: 20.1 | K42: KG | L42: 56 | M42: 9999 | N42: 46475 | O42: BR01
A43: CHM-SP-Z3L-BR-U73 | B43: 251880301 | C43: FLR | D43: DESCARTE | E43: 519 | F43: R | G43: 1021929000 | H43: 60 | I43: 46279 | J43: 60 | K43: KG | L43: 17 | M43: 9999 | N43: 46394 | O43: BR01
A44: CHD-SP-9Z4-BR-U73 | B44: 250500301 | C44: FLR | D44: DEVOLUÇÃO | E44: 397 | F44: S | G44: 1021640000 | H44: 30 | I44: 46241 | J44: 30 | K44: KG | L44: 55 | M44: 9999 | N44: 46437 | O44: BR01
A45: CHM-SP-Z3L-BR-U73 | B45: 251880301 | C45: FM1 | D45: 10-002-F | E45: 1 | G45: 1021182000 | H45: 384 | I45: 46289 | J45: 384 | K45: KG | L45: 7 | M45: 9999 | N45: 46394 | O45: BR01
A46: 805-BR-D94 | B46: 251633359 | C46: FM1 | D46: 10-031-B | E46: 1 | G46: 1021888000 | H46: 103.6 | I46: 46270 | J46: 103.6 | K46: KG | L46: 26 | M46: 9999 | N46: 46550 | O46: BR01
A47: 70-30-38-BR-25A | B47: 260370301 | C47: FM1 | D47: 10-036-G | E47: 1 | G47: 1021986000 | H47: 603 | I47: 46294 | J47: 603 | K47: KG | L47: 2 | M47: 9999 | N47: 46789 | O47: BR01
A48: 823-BR-25A | B48: 252900303 | C48: FM1 | D48: 10-038-G | E48: 1 | G48: 1021986000 | H48: 603 | I48: 46294 | J48: 603 | K48: KG | L48: 2 | M48: 9999 | N48: 46494 | O48: BR01
A49: 823-BR-25A | B49: 252900303 | C49: FM1 | D49: 10-042-G | E49: 1 | G49: 1021986000 | H49: 603 | I49: 46294 | J49: 603 | K49: KG | L49: 2 | M49: 9999 | N49: 46494 | O49: BR01
A50: W3-BR-25A | B50: 253540301 | C50: FM1 | D50: 10-051-B | E50: 1 | G50: 1021889000 | H50: 20.1 | I50: 46286 | J50: 20.1 | K50: KG | L50: 26 | M50: 9999 | N50: 46558 | O50: BR01
A51: 823-BR-25A | B51: 252900303 | C51: FM1 | D51: 10-060-B | E51: 1 | G51: 1021986000 | H51: 482.4 | I51: 46294 | J51: 482.4 | K51: KG | L51: 2 | M51: 9999 | N51: 46494 | O51: BR01
A52: CHM-SP-Z3L-BR-U73 | B52: 251880301 | C52: FM1 | D52: 10-065-C | E52: 1 | G52: 1021346000 | H52: 30 | I52: 46291 | J52: 30 | K52: KG | L52: 57 | M52: 9999 | N52: 46394 | O52: BR01
A53: CHP-20SICHP-760 | B53: 252843369 | C53: FM1 | D53: 10-065-D | E53: 1 | G53: 1021763000 | H53: 24 | I53: 46261 | J53: 24 | K53: KG | L53: 57 | M53: 9999 | N53: 46671 | O53: BR01
A54: 811NV-595 | B54: 261146102 | C54: FM1 | D54: 10-074-C | E54: 1 | G54: 1021986000 | H54: 600 | I54: 46294 | J54: 600 | K54: KG | L54: 2 | M54: 9999 | N54: 46867 | O54: BR01
A55: 823-BR-25A | B55: 252900303 | C55: FM1 | D55: 10-078-D | E55: 1 | G55: 1021986000 | H55: 120.6 | I55: 46294 | J55: 120.6 | K55: KG | L55: 2 | M55: 9999 | N55: 46494 | O55: BR01
A56: CHK-R30GOLD-BR-25A | B56: 261130301 | C56: FM1 | D56: 10-080-B | E56: 1 | G56: 1021986000 | H56: 301.5 | I56: 46295 | J56: 301.5 | K56: KG | L56: 2 | M56: 9999 | N56: 46683 | O56: BR01
... A73: CHM-SP-Z3L-BR-U73 | B73: 251880301 | C73: FM1 | D73: 11-006-C | E73: 1 | G73: 1021996000 | H73: 360 | I73: 46296 | J73: 360 | K73: KG | L73: 0 | M73: 9999 | N73: 46394 | O73: BR01
A74: 823-BR-D94 | B74: 252103049 | C74: FM1 | D74: 11-018-C | E74: 1 | F74: S | G74: 1021996000 | H74: 313.6 | I74: 46296 | J74: 313.6 | K74: KG | L74: 0 | M74: 9999 | N74: 46416 | O74: BR01
A75: CHD-SP-9Z4-BR-U73 | B75: 250500301 | C75: FM1 | D75: 11-084-B | E75: 1 | G75: 1020120000 | H75: 144 | I75: 46235 | J75: 144 | K75: KG | L75: 61 | M75: 9999 | N75: 46437 | O75: BR01
A76: 811-BR-D94 | B76: 251643289 | C76: FM1 | D76: 12-059-D | E76: 1 | G76: 1021414000 | H76: 313.6 | I76: 46183 | J76: 313.6 | K76: KG | L76: 113 | M76: 9999 | N76: 46551 | O76: BR01
A77: 811NV-595 | B77: 260900702 | C77: FM1 | D77: 12-072-B | E77: 1 | G77: 1021918000 | H77: 20 | I77: 46292 | J77: 20 | K77: KG | L77: 9 | M77: 9999 | O77: BR01
A78: CHM-TS-22351E0-999 | B78: 2525950306 | C78: FM1 | D78: 12-100-C | E78: 1 | F78: Q | G78: 1021907000 | H78: 50.32 | I78: 46274 | J78: 50.32 | K78: KG | L78: 22 | M78: 9999 | N78: 46462 | O78: BR01
A79: CHM-TS-22351E0-999 | B79: 2525950306 | C79: FM1 | D79: 12-102-C | E79: 1 | F79: Q | G79: 1021907000 | H79: 145.52 | I79: 46274 | J79: 145.52 | K79: KG | L79: 22 | M79: 9999 | N79: 46462 | O79: BR01
A80: CHM-TS-22351E0-999 | B80: 2526050307 | C80: FM1 | D80: 12-104-C | E80: 1 | F80: Q | G80: 1021907000 | H80: 146.88 | I80: 46274 | J80: 146.88 | K80: KG | L80: 22 | M80: 9999 | N80: 46463 | O80: BR01
A81: CHM-TS-22351E0-999 | B81: 2526050307 | C81: FM1 | D81: 12-106-C | E81: 1 | F81: Q | G81: 1021907000 | H81: 146.88 | I81: 46274 | J81: 146.88 | K81: KG | L81: 22 | M81: 9999 | N81: 46463 | O81: BR01
A82: 811-BR-D94 | B82: 251643289 | C82: FM1 | D82: 13-00E-C | E82: 1 | G82: 1021414000 | H82: 313.6 | I82: 46183 | J82: 313.6 | K82: KG | L82: 113 | M82: 9999 | N82: 46551 | O82: BR01
A83: CHR-Q37RB2-E0-D94 | B83: 261301539 | C83: FM1 | D83: 13-020-B | E83: 1 | G83: 1021977000 | H83: 313.6 | I83: 46291 | J83: 313.6 | K83: KG | L83: 5 | M83: 9999 | N83: 46517 | O83: BR01
A84: CHM-SP-Z3L-BR-U73 | B84: 251880301 | C84: FM1 | D84: 13-020-F | E84: 1 | G84: 1021153000 | H84: 384 | I84: 46289 | J84: 384 | K84: KG | L84: 7 | M84: 9999 | N84: 46394 | O84: BR01
A85: CHM-SP-Z3L-BR-U73 | B85: 251880301 | C85: FM1 | D85: 13-022-G | E85: 1 | G85: 1021478000 | H85: 384 | I85: 46169 | J85: 384 | K85: KG | L85: 127 | M85: 9999 | N85: 46394 | O85: BR01
A86: BIG-PF-1BO-401 | B86: 26093039 | C86: FM1 | D86: 13-032-C | E86: 1 | G86: 1021977000 | H86: 240 | I86: 46291 | J86: 240 | K86: KG | L86: 5 | M86: 9999 | N86: 46535 | O86: BR01
A87: MALCHOC-D-123 | B87: 261060203 | C87: FM1 | D87: 13-032-E | E87: 1 | G87: 1021963000 | H87: 1000 | I87: 46288 | J87: 1000 | K87: KG | L87: 8 | M87: 9999 | N87: 46859 | O87: BR01
A88: CHD-SP-9Z4-BR-U73 | B88: 250500301 | C88: FM1 | D88: 13-034-G | E88: 1 | G88: 1020164000 | H88: 384 | I88: 45881 | J88: 384 | K88: KG | L88: 415 | M88: 9999 | N88: 46437 | O88: BR01
A89: CHD-TS-22350E0-999 | B89: 2520443650 | C89: FM1 | D89: 13-036-D | E89: 1 | G89: 1021977000 | H89: 81.6 | I89: 46291 | J89: 81.6 | K89: KG | L89: 5 | M89: 9999 | N89: 46591 | O89: BR01
A90: 811-BR-D94 | B90: 251643289 | C90: FM1 | D90: 13-061-F | E90: 1 | G90: 1021414000 | H90: 310.8 | I90: 46183 | J90: 310.8 | K90: KG | L90: 113 | M90: 9999 | N90: 46551 | O90: BR01
A91: BIG-PF-1BO-401 | B91: 26093039 | C91: FM1 | D91: 13-066-C | E91: 1 | G91: 1021977000 | H91: 240 | I91: 46291 | J91: 240 | K91: KG | L91: 5 | M91: 9999 | N91: 46535 | O91: BR01
A92: 811-BR-D94 | B92: 251643289 | C92: FM1 | D92: 13-067-B | E92: 1 | G92: 1021414000 | H92: 313.6 | I92: 46183 | J92: 313.6 | K92: KG | L92: 113 | M92: 9999 | N92: 46551 | O92: BR01
A93: CHD-SP-9Z4-BR-U73 | B93: 250500301 | C93: FM1 | D93: 13-072-C | E93: 1 | G93: 1020163000 | H93: 384 | I93: 46235 | J93: 384 | K93: KG | L93: 61 | M93: 9999 | N93: 46437 | O93: BR01
... A98: 811-BR-D94 | B98: 251643289 | C98: FM1 | D98: 13-086-D | E98: 1 | G98: 1021414000 | H98: 313.6 | I98: 46183 | J98: 313.6 | K98: KG | L98: 113 | M98: 9999 | N98: 46551 | O98: BR01
A99: CHM-SP-Z3L-BR-U73 | B99: 251880301 | C99: FM1 | D99: 13-088-G | E99: 1 | F99: Q | G99: 1021182000 | H99: 186 | I99: 46095 | J99: 186 | K99: KG | L99: 201 | M99: 9999 | N99: 46394 | O99: BR01
A100: 805-BR-D94 | B100: 251633359 | C100: FM1 | D100: 13-093-E | E100: 1 | G100: 1021613000 | H100: 313.6 | I100: 46201 | J100: 313.6 | K100: KG | L100: 95 | M100: 9999 | N100: 46550 | O100: BR01
A101: 811-BR-D94 | B101: 251643289 | C101: FM1 | D101: 13-097-C | E101: 1 | G101: 1021414000 | H101: 313.6 | I101: 46183 | J101: 313.6 | K101: KG | L101: 113 | M101: 9999 | N101: 46551 | O101: BR01
A102: 823-BR-D94 | B102: 252103049 | C102: FM1 | D102: 13-098-F | E102: 1 | G102: 1021493000 | H102: 313.6 | I102: 46173 | J102: 313.6 | K102: KG | L102: 123 | M102: 9999 | N102: 46416 | O102: BR01
A103: 811-BR-D94 | B103: 251643289 | C103: FM1 | D103: 13-099-D | E103: 1 | G103: 1021414000 | H103: 313.6 | I103: 46183 | J103: 313.6 | K103: KG | L103: 113 | M103: 9999 | N103: 46551 | O103: BR01
A104: 811-BR-D94 | B104: 251643289 | C104: FM1 | D104: 13-101-D | E104: 1 | G104: 1021414000 | H104: 313.6 | I104: 46183 | J104: 313.6 | K104: KG | L104: 113 | M104: 9999 | N104: 46551 | O104: BR01
A105: 811-BR-D94 | B105: 251643289 | C105: FM1 | D105: 13-103-C | E105: 1 | G105: 1021414000 | H105: 313.6 | I105: 46183 | J105: 313.6 | K105: KG | L105: 113 | M105: 9999 | N105: 46551 | O105: BR01
A106: 811-BR-D94 | B106: 251643289 | C106: FM1 | D106: 13-103-D | E106: 1 | G106: 1021414000 | H106: 313.6 | I106: 46183 | J106: 313.6 | K106: KG | L106: 113 | M106: 9999 | N106: 46551 | O106: BR01
A107: 823-BR-D94 | B107: 252103049 | C107: FM1 | D107: 13-120-B | E107: 1 | G107: 1021450000 | H107: 313.6 | I107: 46170 | J107: 313.6 | K107: KG | L107: 126 | M107: 9999 | N107: 46416 | O107: BR01
A108: CHD-SP-9Z4-BR-U73 | B108: 250500301 | C108: FM1 | D108: 13-123-B | E108: 1 | G108: 1020164000 | H108: 384 | I108: 45881 | J108: 384 | K108: KG | L108: 415 | M108: 9999 | N108: 46437 | O108: BR01
A109: 811-BR-D94 | B109: 251643289 | C109: FM1 | D109: 13-123-D | E109: 1 | G109: 1021414000 | H109: 313.6 | I109: 46183 | J109: 313.6 | K109: KG | L109: 113 | M109: 9999 | N109: 46551 | O109: BR01
A110: CHD-SP-9Z4-BR-U73 | B110: 250500301 | C110: FM1 | D110: 14-031-D | E110: 1 | G110: 1020164000 | H110: 378 | I110: 46235 | J110: 378 | K110: KG | L110: 61 | M110: 9999 | N110: 46437 | O110: BR01
A111: 811-BR-D94 | B111: 251643289 | C111: FM1 | D111: 14-035-B | E111: 1 | G111: 1021425000 | H111: 313.6 | I111: 46183 | J111: 313.6 | K111: KG | L111: 113 | M111: 9999 | N111: 46551 | O111: BR01
... A133: W2-BR-D94 | B133: 260700919 | C133: FM1 | D133: 14-079-E | E133: 1 | G133: 1021976000 | H133: 313.6 | I133: 46291 | J133: 313.6 | K133: KG | L133: 5 | M133: 9999 | N133: 46457 | O133: BR01
A134: 823NV-595 | B134: 261376101 | C134: FM1 | D134: 14-080-B | E134: 1 | G134: 1021977000 | H134: 20 | I134: 46291 | J134: 20 | K134: KG | L134: 5 | M134: 9999 | O134: BR01
A135: NIBS-S502-X47 | B135: 253490619 | C135: FM1 | D135: 14-083-E | E135: 1 | G135: 1021977000 | H135: 120 | I135: 46293 | J135: 120 | K135: CX | L135: 3 | M135: 9999 | N135: 46736 | O135: BR01
A136: NIBS-S502-X47 | B136: 260691479 | C136: FM1 | D136: 14-086-C | E136: 1 | G136: 1021985000 | H136: 120 | I136: 46294 | J136: 120 | K136: CX | L136: 2 | M136: 9999 | N136: 46822 | O136: BR01
A137: CHR-Q37RB2-2B-U75 | B137: 261320203 | C137: FM1 | D137: 14-087-B | E137: 1 | G137: 1021983000 | H137: 360 | I137: 46293 | J137: 360 | K137: KG | L137: 3 | M137: 9999 | N137: 46703 | O137: BR01
A138: CHM-SP-Z3L-BR-U73 | B138: 251880301 | C138: FM1 | D138: 14-089-B | E138: 1 | G138: 1021977000 | H138: 198 | I138: 46291 | J138: 198 | K138: KG | L138: 5 | M138: 9999 | N138: 46394 | O138: BR01
A139: 811-BR-D94 | B139: 251643289 | C139: FM1 | D139: 14-089-C | E139: 1 | G139: 1021425000 | H139: 313.6 | I139: 46183 | J139: 313.6 | K139: KG | L139: 113 | M139: 9999 | N139: 46551 | O139: BR01
A140: 811NV-595 | B140: 261146101 | C140: FM1 | D140: 14-090-B | E140: 1 | G140: 1021918000 | H140: 20 | I140: 46290 | J140: 20 | K140: KG | L140: 6 | M140: 9999 | O140: BR01
A141: CHM-BS-9U15-E0-07B | B141: 260701069 | C141: FM1 | D141: 14-090-C | E141: 1 | G141: 1021969000 | H141: 240 | I141: 46290 | J141: 240 | K141: KG | L141: 6 | M141: 9999 | N141: 46641 | O141: BR01
A142: 805-BR-D94 | B142: 260130779 | C142: FM1 | D142: 14-090-D | E142: 1 | G142: 1021985000 | H142: 142.8 | I142: 46294 | J142: 142.8 | K142: KG | L142: 2 | M142: 9999 | N142: 46765 | O142: BR01
A143: W3-BR-25A | B143: 261080301 | C143: FM1 | D143: 14-092-C | E143: 1 | G143: 1021969000 | H143: 482.4 | I143: 46290 | J143: 482.4 | K143: KG | L143: 6 | M143: 9999 | N143: 46678 | O143: BR01
A144: 823NV-595 | B144: 261376101 | C144: FM1 | D144: 14-094-B | E144: 1 | G144: 1021969000 | H144: 360 | I144: 46295 | J144: 360 | K144: KG | L144: 6 | M144: 9999 | N144: 46708 | O144: BR01
A145: 805-BR-D94 | B145: 251633359 | C145: FM1 | D145: 14-094-D | E145: 1 | G145: 1021985000 | H145: 313.6 | I145: 46294 | J145: 313.6 | K145: KG | L145: 2 | M145: 9999 | N145: 46550 | O145: BR01
A146: 823NV-595 | B146: 261376101 | C146: FM1 | D146: 14-096-B | E146: 1 | G146: 1021969000 | H146: 600 | I146: 46290 | J146: 600 | K146: KG | L146: 6 | M146: 9999 | N146: 46708 | O146: BR01
...

Sheet 3 Base Saldo Inicial 08-09
A1: SKU | B1: LOTE | C1: DEPÓSITO | D1: UM | E1: QUANTIDADE | F1: OBSERVAÇÃO | H1: COMO PREENCHER
H2: Cole aqui o estoque de cada SKU + lote + depósito em 08/09/2026 (dia anterior ao primeiro movimento).
H3: Fonte sugerida no SAP: estoque por data (ex.: MB5B) por material, lote e depósito, ou carregue pela consulta qSaldoInicial (aba 8 Atualizar Dados).
H4: Depósito 2008 → entra no saldo do 4 Análise Depósito 2008. Demais depósitos (9999, 0355…) → entram no Deveria ter do ZBR.
H5: Enquanto estiver vazia, a análise funciona como antes (sem saldo inicial).
H6: ="Saldo inicial informado: "&FIXED(SUM(E2:E5000),1)&" (somando todas as unidades) em "&COUNTA(A2:A5000)&" linhas." -> Saldo inicial informado: 0.0 (somando todas as unidades) em 0 linhas.

Sheet 3 Base Movimentos
A1: DATA | B1: MOVIMENTAÇÃO | C1: SKU | D1: LOTE | E1: DESCRIÇÃO | F1: DEPÓSITO | G1: UM | H1: QTD NO SAP | I1: ENTROU | J1: SAIU | K1: SALDO (±) | L1: DOCUMENTO | M1: CÓD. CLIENTE | N1: CLIENTE | O1: USUÁRIO
A2: 46274 | B2: Saída | C2: 805-BR-D94 | D2: 251633359 | E2: CA MOEDAS 0,4KG/UC 7UC/CX 144CX/PAL | F2: 9999 | G2: KG | H2: ='3 Base Saídas'!H80 -> -5.6 | I2: 0 | J2: ='3 Base Saídas'!R80 -> 5.6 | K2: =I2-J2 -> -5.6 | L2: 4903838325 | M2: 51879 | N2: TRANSELPE LTDA. - EPP | O2: BC140676
A3: 46274 | B3: Saída | C3: 823-BR-D94 | D3: 252103049 | E3: CA MOEDAS 0,4KG/UC 7UC/CX 144CX/PAL | F3: 9999 | G3: KG | H3: ='3 Base Saídas'!H177 -> -5.6 | I3: 0 | J3: ='3 Base Saídas'!R177 -> 5.6 | K3: =I3-J3 -> -5.6 | L3: 4903838325 | M3: 51879 | N3: TRANSELPE LTDA. - EPP | O3: BC140676
A4: 46274 | B4: ='3 Base Entrada 2008'!K156 -> Entrada | C4: CHM-TS-22351E0-999 | D4: 2525950306 | F4: 2008 | G4: KG | H4: ='3 Base Entrada 2008'!G156 -> -195.84 | I4: ='3 Base Entrada 2008'!L156 -> 195.84 | J4: 0 | K4: =I4-J4 -> 195.84 | L4: 4903843886
A5: 46274 | B5: ='3 Base Entrada 2008'!K157 -> Entrada | C5: CHM-TS-22351E0-999 | D5: 2526050307 | F5: 2008 | G5: KG | H5: ='3 Base Entrada 2008'!G157 -> -295.12 | I5: ='3 Base Entrada 2008'!L157 -> 295.12 | J5: 0 | K5: =I5-J5 -> 295.12 | L5: 4903843886
A6: 46275 | B6: ='3 Base Entrada 2008'!K117 -> Recebido no 2008 | C6: 70-30-38-BR-25A | D6: 260370301 | E6: CA MOEDAS 2,01KG/UC 10UC/CX 30CX/PAL | F6: 2008 | G6: KG | H6: ='3 Base Entrada 2008'!G117 -> 6633 | I6: ='3 Base Entrada 2008'!L117 -> 0 | J6: 0 | K6: =I6-J6 -> 0 | L6: 4903864964
A7: 46275 | B7: Saída | C7: 70-30-38-BR-25A | D7: 260370301 | E7: CA MOEDAS 2,01KG/UC 10UC/CX 30CX/PAL | F7: 0355 | G7: KG | H7: ='3 Base Saídas'!H29 -> -20.1 | I7: 0 | J7: ='3 Base Saídas'!R29 -> 20.1 | K7: =I7-J7 -> -20.1 | L7: 4903867283 | M7: 78892 | N7: TANGARA DESENV IMOBIL | O7: BC025148
A8: 46275 | B8: Saída | C8: 70-30-38-BR-25A | D8: 260370301 | E8: CA MOEDAS 2,01KG/UC 10UC/CX 30CX/PAL | F8: 0355 | G8: KG | H8: ='3 Base Saídas'!H30 -> -40.2 | I8: 0 | J8: ='3 Base Saídas'!R30 -> 40.2 | K8: =I8-J8 -> -40.2 | L8: 4903867234 | M8: 94669 | N8: ARTISANO GELATO LTDA | O8: BC025148
A9: 46275 | B9: Saída | C9: 70-30-38-BR-D94 | D9: 253213449 | E9: CA MOEDAS 0,4KG/UC 7UC/CX 144CX/PAL | F9: 0355 | G9: KG | H9: ='3 Base Saídas'!H55 -> -11.2 | I9: 0 | J9: ='3 Base Saídas'!R55 -> 11.2 | K9: =I9-J9 -> -11.2 | L9: 4903867892 | M9: 43229 | N9: VIMEG COMERCIO DE CHOCOLATES LTDA | O9: BC025148
A10: 46275 | B10: ='3 Base Entrada 2008'!K124 -> Recebido no 2008 | C10: 811NV-595 | D10: 261146101 | E10: CA CALLETS 10KG/UC 2UC/BOX 30BOX/PAL | F10: 2008 | G10: KG | H10: ='3 Base Entrada 2008'!G124 -> 4360 | I10: ='3 Base Entrada 2008'!L124 -> 0 | J10: 0 | K10: =I10-J10 -> 0 | L10: 4903865743
A11: 46275 | B11: ='3 Base Entrada 2008'!K123 -> Recebido no 2008 | C11: 811NV-595 | D11: 261146102 | E11: CA CALLETS 10KG/UC 2UC/BOX 30BOX/PAL | F11: 2008 | G11: KG | H11: ='3 Base Entrada 2008'!G123 -> 5240 | I11: ='3 Base Entrada 2008'!L123 -> 0 | J11: 0 | K11: =I11-J11 -> 0 | L11: 4903865743
A12: 46275 | B12: Saída | C12: 823-BR-D94 | D12: 252103049 | E12: CA MOEDAS 0,4KG/UC 7UC/CX 144CX/PAL | F12: 9999 | G12: KG | H12: ='3 Base Saídas'!H175 -> -28 | I12: 0 | J12: ='3 Base Saídas'!R175 -> 28 | K12: =I12-J12 -> -28 | L12: 4903869423 | M12: 48470 | N12: MARIA CHOCOLATE LTDA | O12: BC116065
A13: 46275 | B13: Saída | C13: 823-BR-D94 | D13: 252103049 | E13: CA MOEDAS 0,4KG/UC 7UC/CX 144CX/PAL | F13: 0355 | G13: KG | H13: ='3 Base Saídas'!H176 -> -14 | I13: 0 | J13: ='3 Base Saídas'!R176 -> 14 | K13: =I13-J13 -> -14 | L13: 4903867892 | M13: 43229 | N13: VIMEG COMERCIO DE CHOCOLATES LTDA | O13: BC025148
A14: 46275 | B14: ='3 Base Entrada 2008'!K128 -> Recebido no 2008 | C14: 823NV-595 | D14: 261376101 | E14: CA CALLETS 10KG/UC 2UC/BOX 30BOX/PAL | F14: 2008 | G14: KG | H14: ='3 Base Entrada 2008'!G128 -> 2400 | I14: ='3 Base Entrada 2008'!L128 -> 0 | J14: 0 | K14: =I14-J14 -> 0 | L14: 4903867530
A15: 46275 | B15: ='3 Base Entrada 2008'!K129 -> Recebido no 2008 | C15: 823NV-595 | D15: 261376101 | E15: CA CALLETS 10KG/UC 2UC/BOX 30BOX/PAL | F15: 2008 | G15: KG | H15: ='3 Base Entrada 2008'!G129 -> 3600 | I15: ='3 Base Entrada 2008'!L129 -> 0 | J15: 0 | K15: =I15-J15 -> 0 | L15: 4903867183
A16: 46275 | B16: Saída | C16: BIG-PF-1BO-401 | D16: 26044019 | E16: CB PAILLETÉ FEUILLETINE 2.5KG/UC 4UC/BOX | F16: 9999 | G16: KG | H16: ='3 Base Saídas'!H188 -> -10 | I16: 0 | J16: ='3 Base Saídas'!R188 -> 10 | K16: =I16-J16 -> -10 | L16: 4903859705 | M16: 90486 | N16: GI CARVALHO DOCERIA UBERABA LTDA | O16: BC147417
A17: 46275 | B17: ='3 Base Entrada 2008'!K133 -> Recebido no 2008 | C17: BIG-PF-1BO-401 | D17: 26126039 | E17: CB PAILLETÉ FEUILLETINE 2.5KG/UC 4UC/BOX | F17: 2008 | G17: KG | H17: ='3 Base Entrada 2008'!G133 -> 960 | I17: ='3 Base Entrada 2008'!L133 -> 0 | J17: 0 | K17: =I17-J17 -> 0 | L17: 4903866106
A18: 46275 | B18: ='3 Base Entrada 2008'!K134 -> Recebido no 2008 | C18: BIG-PF-1BO-401 | D18: 26126039 | E18: CB PAILLETÉ FEUILLETINE 2.5KG/UC 4UC/BOX | F18: 2008 | G18: KG | H18: ='3 Base Entrada 2008'!G134 -> 1920 | I18: ='3 Base Entrada 2008'!L134 -> 0 | J18: 0 | K18: =I18-J18 -> 0 | L18: 4903863360
A19: 46275 | B19: ='3 Base Entrada 2008'!K137 -> Recebido no 2008 | C19: CHD-SP-1M-2B-U77 | D19: 260880101 | F19: 2008 | G19: KG | H19: ='3 Base Entrada 2008'!G137 -> 600 | I19: ='3 Base Entrada 2008'!L137 -> 0 | J19: 0 | K19: =I19-J19 -> 0 | L19: 4903864964
A20: 46275 | B20: ='3 Base Entrada 2008'!K138 -> Recebido no 2008 | C20: CHD-SP-1M-2B-U77 | D20: 260880101 | F20: 2008 | G20: KG | H20: ='3 Base Entrada 2008'!G138 -> 1800 | I20: ='3 Base Entrada 2008'!L138 -> 0 | J20: 0 | K20: =I20-J20 -> 0 | L20: 4903863360
A21: 46275 | B21: ='3 Base Entrada 2008'!K140 -> Recebido no 2008 | C21: CHD-SP-1M-BR-U73 | D21: 260310301 | F21: 2008 | G21: KG | H21: ='3 Base Entrada 2008'!G140 -> 798 | I21: ='3 Base Entrada 2008'!L140 -> 0 | J21: 0 | K21: =I21-J21 -> 0 | L21: 4903864964
A22: 46275 | B22: ='3 Base Entrada 2008'!K139 -> Recebido no 2008 | C22: CHD-SP-1M-BR-U73 | D22: 260880301 | F22: 2008 | G22: KG | H22: ='3 Base Entrada 2008'!G139 -> 1122 | I22: ='3 Base Entrada 2008'!L139 -> 0 | J22: 0 | K22: =I22-J22 -> 0 | L22: 4903864964
A23: 46275 | B23: ='3 Base Entrada 2008'!K142 -> Recebido no 2008 | C23: CHD-VR-Z2S-E0-U68 | D23: 261160301 | F23: 2008 | G23: KG | H23: ='3 Base Entrada 2008'!G142 -> 1296 | I23: ='3 Base Entrada 2008'!L142 -> 0 | J23: 0 | K23: =I23-J23 -> 0 | L23: 4903863360
A24: 46275 | B24: ='3 Base Entrada 2008'!K146 -> Recebido no 2008 | C24: CHK-R30GOLD-BR-25A | D24: 252750301 | E24: CA MOEDAS 2,01KG/UC 10UC/CX 30CX/PAL | F24: 2008 | G24: KG | H24: ='3 Base Entrada 2008'!G146 -> 160.8 | I24: ='3 Base Entrada 2008'!L146 -> 0 | J24: 0 | K24: =I24-J24 -> 0 | L24: 4903865743
A25: 46275 | B25: ='3 Base Entrada 2008'!K147 -> Recebido no 2008 | C25: CHK-R30GOLD-BR-25A | D25: 261130301 | E25: CA MOEDAS 2,01KG/UC 10UC/CX 30CX/PAL | F25: 2008 | G25: KG | H25: ='3 Base Entrada 2008'!G147 -> 1025.1 | I25: ='3 Base Entrada 2008'!L147 -> 0 | J25: 0 | K25: =I25-J25 -> 0 | L25: 4903865743
A26: 46275 | B26: ='3 Base Entrada 2008'!K149 -> Recebido no 2008 | C26: CHM-BS-9U15-E0-07B | D26: 260701069 | E26: CA MILK BLOSSOMS BLOSSOMS 1KG/UC 4UC/BOX | F26: 2008 | G26: KG | H26: ='3 Base Entrada 2008'!G149 -> 1920 | I26: ='3 Base Entrada 2008'!L149 -> 0 | J26: 0 | K26: =I26-J26 -> 0 | L26: 4903864617
A27: 46275 | B27: ='3 Base Entrada 2008'!K151 -> Recebido no 2008 | C27: CHM-Q41ALUN-2B-U73 | D27: 260660303 | F27: 2008 | G27: KG | H27: ='3 Base Entrada 2008'!G151 -> 384 | I27: ='3 Base Entrada 2008'!L151 -> 0 | J27: 0 | K27: =I27-J27 -> 0 | L27: 4903864964
A28: 46275 | B28: Saída | C28: CHM-SP-Z3L-BR-U73 | D28: 251880301 | E28: CA MILK LARGE FLAKES SPLITTERS 1KG/UC | F28: 9999 | G28: KG | H28: ='3 Base Saídas'!H292 -> -42 | I28: 0 | J28: ='3 Base Saídas'!R292 -> 42 | K28: =I28-J28 -> -42 | L28: 4903869423 | M28: 48470 | N28: MARIA CHOCOLATE LTDA | O28: BC116065
A29: 46275 | B29: Saída | C29: CHP-20SICHP-760 | D29: 252843369 | E29: CA SILKY CHOCO POWDER POWDER 1KG/UC | F29: 9999 | G29: KG | H29: ='3 Base Saídas'!H302 -> -12 | I29: 0 | J29: ='3 Base Saídas'!R302 -> 12 | K29: =I29-J29 -> -12 | L29: 4903869423 | M29: 48470 | N29: MARIA CHOCOLATE LTDA | O29: BC116065
A30: 46275 | B30: ='3 Base Entrada 2008'!K161 -> Recebido no 2008 | C30: CHR-Q37RB2-2B-U75 | D30: 261320203 | E30: CA RUBY CALLETS 2.5KG/UC 4UC/BOX | F30: 2008 | G30: KG | H30: ='3 Base Entrada 2008'!G161 -> 840 | I30: ='3 Base Entrada 2008'!L161 -> 0 | J30: 0 | K30: =I30-J30 -> 0 | L30: 4903863360
A31: 46275 | B31: ='3 Base Entrada 2008'!K163 -> Recebido no 2008 | C31: CHR-Q37RB2-E0-D94 | D31: 261301539 | F31: 2008 | G31: KG | H31: ='3 Base Entrada 2008'!G163 -> 940.8 | I31: ='3 Base Entrada 2008'!L163 -> 0 | J31: 0 | K31: =I31-J31 -> 0 | L31: 4903863360
A32: 46275 | B32: ='3 Base Entrada 2008'!K164 -> Recebido no 2008 | C32: CHR-Q37RB2-E0-D94 | D32: 261301539 | F32: 2008 | G32: KG | H32: ='3 Base Entrada 2008'!G164 -> 932.4 | I32: ='3 Base Entrada 2008'!L164 -> 0 | J32: 0 | K32: =I32-J32 -> 0 | L32: 4903867530
A33: 46275 | B33: ='3 Base Entrada 2008'!K170 -> Recebido no 2008 | C33: CW2-BR-25A | D33: 252650301 | E33: CA MOEDAS 2,01KG/UC 10UC/CX 30CX/PAL | F33: 2008 | G33: KG | H33: ='3 Base Entrada 2008'!G170 -> 40 | I33: ='3 Base Entrada 2008'!L170 -> 0 | J33: 0 | K33: =I33-J33 -> 0 | L33: 4903864964
A34: 46275 | B34: Saída | C34: CW2-BR-25A | D34: 252650301 | E34: CA MOEDAS 2,01KG/UC 10UC/CX 30CX/PAL | F34: 9999 | G34: KG | H34: ='3 Base Saídas'!H354 -> -40.2 | I34: 0 | J34: ='3 Base Saídas'!R354 -> 40.2 | K34: =I34-J34 -> -40.2 | L34: 4903868815 | M34: 94605 | N34: BAKERY LTDA | O34: BC116065
A35: 46275 | B35: Saída | C35: CW2-BR-25A | D35: 253470301 | E35: CA MOEDAS 2,01KG/UC 10UC/CX 30CX/PAL | F35: 0355 | G35: KG | H35: ='3 Base Saídas'!H355 -> -60.3 | I35: 0 | J35: ='3 Base Saídas'!R355 -> 60.3 | K35: =I35-J35 -> -60.3 | L35: 4903867802 | M35: 42925 | N35: MORUMBY HOTEIS LTDA | O35: BC025148
A36: 46275 | B36: Saída | C36: CW2-BR-25A | D36: 253470301 | E36: CA MOEDAS 2,01KG/UC 10UC/CX 30CX/PAL | F36: 0355 | G36: KG | H36: ='3 Base Saídas'!H356 -> -80.4 | I36: 0 | J36: ='3 Base Saídas'!R356 -> 80.4 | K36: =I36-J36 -> -80.4 | L36: 4903867287 | M36: 75158 | N36: ATELIE MJ COMERCIO | O36: BC025148
A37: 46275 | B37: ='3 Base Entrada 2008'!K169 -> Recebido no 2008 | C37: CW2-BR-25A | D37: 261070301 | E37: CA MOEDAS 2,01KG/UC 10UC/CX 30CX/PAL | F37: 2008 | G37: KG | H37: ='3 Base Entrada 2008'!G169 -> 1166 | I37: ='3 Base Entrada 2008'!L169 -> 0 | J37: 0 | K37: =I37-J37 -> 0 | L37: 4903864964
A38: 46275 | B38: ='3 Base Entrada 2008'!K172 -> Recebido no 2008 | C38: CW2NV-595 | D38: 261070601 | F38: 2008 | G38: KG | H38: ='3 Base Entrada 2008'!G172 -> 600 | I38: ='3 Base Entrada 2008'!L172 -> 0 | J38: 0 | K38: =I38-J38 -> 0 | L38: 4903864964
A39: 46275 | B39: ='3 Base Entrada 2008'!K173 -> Recebido no 2008 | C39: CW2NV-595 | D39: 261070601 | F39: 2008 | G39: KG | H39: ='3 Base Entrada 2008'!G173 -> 1800 | I39: ='3 Base Entrada 2008'!L173 -> 0 | J39: 0 | K39: =I39-J39 -> 0 | L39: 4903864617
A40: 46275 | B40: ='3 Base Entrada 2008'!K174 -> Recebido no 2008 | C40: DCP-10BONOI-89B | D40: 260778132 | E40: CA BOTANICAL NOIR INTENSE 1KG/UC 6UC/BOX | F40: 2008 | G40: KG | H40: ='3 Base Entrada 2008'!G174 -> 864 | I40: ='3 Base Entrada 2008'!L174 -> 0 | J40: 0 | K40: =I40-J40 -> 0 | L40: 4903867530
A41: 46275 | B41: ='3 Base Entrada 2008'!K175 -> Recebido no 2008 | C41: DCP-20BODEC-89B | D41: 261388131 | F41: 2008 | G41: KG | H41: ='3 Base Entrada 2008'!G175 -> 432 | I41: ='3 Base Entrada 2008'!L175 -> 0 | J41: 0 | K41: =I41-J41 -> 0 | L41: 4903863360
A42: 46275 | B42: ='3 Base Entrada 2008'!K176 -> Recebido no 2008 | C42: DCP-22ZEPLA-89B | D42: 260348131 | F42: 2008 | G42: KG | H42: ='3 Base Entrada 2008'!G176 -> 4296 | I42: ='3 Base Entrada 2008'!L176 -> 0 | J42: 0 | K42: =I42-J42 -> 0 | L42: 4903864617
A43: 46275 | B43: ='3 Base Entrada 2008'!K177 -> Recebido no 2008 | C43: DCP-22ZEPLA-89B | D43: 260358131 | F43: 2008 | G43: KG | H43: ='3 Base Entrada 2008'!G177 -> 5592 | I43: ='3 Base Entrada 2008'!L177 -> 0 | J43: 0 | K43: =I43-J43 -> 0 | L43: 4903866106
A44: 46275 | B44: ='3 Base Entrada 2008'!K178 -> Recebido no 2008 | C44: DCP-22ZEPLA-89B | D44: 260358131 | F44: 2008 | G44: KG | H44: ='3 Base Entrada 2008'!G178 -> 1320 | I44: ='3 Base Entrada 2008'!L178 -> 0 | J44: 0 | K44: =I44-J44 -> 0 | L44: 4903864617
A45: 46275 | B45: ='3 Base Entrada 2008'!K184 -> Recebido no 2008 | C45: NIBS-S502-X47 | D45: 260341149 | E45: CA NIBS S 0.8KG/UC 4UC/BOX 120BOX/PAL | F45: 2008 | G45: CX | H45: ='3 Base Entrada 2008'!G184 -> 600 | I45: ='3 Base Entrada 2008'!L184 -> 0 | J45: 0 | K45: =I45-J45 -> 0 | L45: 4903867183
A46: 46275 | B46: ='3 Base Entrada 2008'!K185 -> Recebido no 2008 | C46: NIBS-S502-X47 | D46: 260341149 | E46: CA NIBS S 0.8KG/UC 4UC/BOX 120BOX/PAL | F46: 2008 | G46: CX | H46: ='3 Base Entrada 2008'!G185 -> 300 | I46: ='3 Base Entrada 2008'!L185 -> 0 | J46: 0 | K46: =I46-J46 -> 0 | L46: 4903867530
A47: 46275 | B47: ='3 Base Entrada 2008'!K186 -> Recebido no 2008 | C47: NIBS-S502-X47 | D47: 260611429 | E47: CA NIBS S 0.8KG/UC 4UC/BOX 120BOX/PAL | F47: 2008 | G47: CX | H47: ='3 Base Entrada 2008'!G186 -> 300 | I47: ='3 Base Entrada 2008'!L186 -> 0 | J47: 0 | K47: =I47-J47 -> 0 | L47: 4903867530
A48: 46275 | B48: ='3 Base Entrada 2008'!K187 -> Recebido no 2008 | C48: NIBS-S502-X47 | D48: 260691479 | E48: CA NIBS S 0.8KG/UC 4UC/BOX 120BOX/PAL | F48: 2008 | G48: CX | H48: ='3 Base Entrada 2008'!G187 -> 240 | I48: ='3 Base Entrada 2008'!L187 -> 0 | J48: 0 | K48: =I48-J48 -> 0 | L48: 4903866106
A49: 46275 | B49: ='3 Base Entrada 2008'!K189 -> Recebido no 2008 | C49: PNP-T14 | D49: 2613495951 | E49: CA 5KG/UC 2UC/BOX 50BOX/PAL | F49: 2008 | G49: KG | H49: ='3 Base Entrada 2008'!G189 -> 4000 | I49: ='3 Base Entrada 2008'!L189 -> 0 | J49: 0 | K49: =I49-J49 -> 0 | L49: 4903867183
A50: 46275 | B50: ='3 Base Entrada 2008'!K190 -> Recebido no 2008 | C50: PNP-T14 | D50: 2613495951 | E50: CA 5KG/UC 2UC/BOX 50BOX/PAL | F50: 2008 | G50: KG | H50: ='3 Base Entrada 2008'!G190 -> 800 | I50: ='3 Base Entrada 2008'!L190 -> 0 | J50: 0 | K50: =I50-J50 -> 0 | L50: 4903863360
A51: 46275 | B51: ='3 Base Entrada 2008'!K191 -> Recebido no 2008 | C51: PRA-T14 | D51: 2611295089 | E51: CA 5KG/UC 2UC/BOX 50BOX/PAL | F51: 2008 | G51: KG | H51: ='3 Base Entrada 2008'!G191 -> 400 | I51: ='3 Base Entrada 2008'!L191 -> 0 | J51: 0 | K51: =I51-J51 -> 0 | L51: 4903863360
A52: 46275 | B52: ='3 Base Entrada 2008'!K199 -> Recebido no 2008 | C52: W2-BR-D94 | D52: 261131599 | E52: CA CALLETS 0.4KG/UC 7UC/BOX 144BOX/PAL | F52: 2008 | G52: KG | H52: ='3 Base Entrada 2008'!G199 -> 204.4 | I52: ='3 Base Entrada 2008'!L199 -> 0 | J52: 0 | K52: =I52-J52 -> 0 | L52: 4903863360
A53: 46275 | B53: ='3 Base Entrada 2008'!K198 -> Recebido no 2008 | C53: W2-BR-D94 | D53: 261181599 | E53: CA CALLETS 0.4KG/UC 7UC/BOX 144BOX/PAL | F53: 2008 | G53: KG | H53: ='3 Base Entrada 2008'!G198 -> 109.2 | I53: ='3 Base Entrada 2008'!L198 -> 0 | J53: 0 | K53: =I53-J53 -> 0 | L53: 4903863360
A54: 46275 | B54: ='3 Base Entrada 2008'!K200 -> Recebido no 2008 | C54: W2-BR-D94 | D54: 261181599 | E54: CA CALLETS 0.4KG/UC 7UC/BOX 144BOX/PAL | F54: 2008 | G54: KG | H54: ='3 Base Entrada 2008'!G200 -> 529.2 | I54: ='3 Base Entrada 2008'!L200 -> 0 | J54: 0 | K54: =I54-J54 -> 0 | L54: 4903865743
A55: 46275 | B55: ='3 Base Entrada 2008'!K196 -> Recebido no 2008 | C55: W2-BR-D94 | D55: 261391599 | E55: CA CALLETS 0.4KG/UC 7UC/BOX 144BOX/PAL | F55: 2008 | G55: KG | H55: ='3 Base Entrada 2008'!G196 -> 725.2 | I55: ='3 Base Entrada 2008'!L196 -> 0 | J55: 0 | K55: =I55-J55 -> 0 | L55: 4903865743
A56: 46275 | B56: ='3 Base Entrada 2008'!K197 -> Recebido no 2008 | C56: W2-BR-D94 | D56: 261391599 | E56: CA CALLETS 0.4KG/UC 7UC/BOX 144BOX/PAL | F56: 2008 | G56: KG | H56: ='3 Base Entrada 2008'!G197 -> 1254.4 | I56: ='3 Base Entrada 2008'!L197 -> 0 | J56: 0 | K56: =I56-J56 -> 0 | L56: 4903866106
A57: 46275 | B57: ='3 Base Entrada 2008'!K201 -> Recebido no 2008 | C57: W3-BR-25A | D57: 253540301 | E57: CA MOEDAS 2,01KG/UC 10UC/CX 30CX/PAL | F57: 2008 | G57: KG | H57: ='3 Base Entrada 2008'!G201 -> 20 | I57: ='3 Base Entrada 2008'!L201 -> 0 | J57: 0 | K57: =I57-J57 -> 0 | L57: 4903864964
A58: 46275 | B58: Saída | C58: W3-BR-25A | D58: 253540301 | E58: CA MOEDAS 2,01KG/UC 10UC/CX 30CX/PAL | F58: 9999 | G58: KG | H58: ='3 Base Saídas'!H402 -> -20.1 | I58: 0 | J58: ='3 Base Saídas'!R402 -> 20.1 | K58: =I58-J58 -> -20.1 | L58: 4903868311 | M58: 207971 | N58: ALICE DE ANDRADE COUTINHO | O58: BC025148
A59: 46275 | B59: Saída | C59: W3-BR-25A | D59: 253540301 | E59: CA MOEDAS 2,01KG/UC 10UC/CX 30CX/PAL | F59: 9999 | G59: KG | H59: ='3 Base Saídas'!H403 -> -100.5 | I59: 0 | J59: ='3 Base Saídas'!R403 -> 100.5 | K59: =I59-J59 -> -100.5 | L59: 4903869423 | M59: 48470 | N59: MARIA CHOCOLATE LTDA | O59: BC116065
A60: 46275 | B60: Saída | C60: W3-BR-25A | D60: 253540301 | E60: CA MOEDAS 2,01KG/UC 10UC/CX 30CX/PAL | F60: 9999 | G60: KG | H60: ='3 Base Saídas'!H404 -> -40.2 | I60: 0 | J60: ='3 Base Saídas'!R404 -> 40.2 | K60: =I60-J60 -> -40.2 | L60: 4903867293 | M60: 217745 | N60: HBR 66 - INVESTIMENTOS IMOBILIARIOS | O60: BC025148
A61: 46275 | B61: Saída | C61: W3-BR-25A | D61: 253540301 | E61: CA MOEDAS 2,01KG/UC 10UC/CX 30CX/PAL | F61: 9999 | G61: KG | H61: ='3 Base Saídas'!H405 -> -20.1 | I61: 0 | J61: ='3 Base Saídas'!R405 -> 20.1 | K61: =I61-J61 -> -20.1 | L61: 4903867283 | M61: 78892 | N61: TANGARA DESENV IMOBIL | O61: BC025148
A62: 46275 | B62: Saída | C62: W3-BR-25A | D62: 253540301 | E62: CA MOEDAS 2,01KG/UC 10UC/CX 30CX/PAL | F62: 9999 | G62: KG | H62: ='3 Base Saídas'!H406 -> -20.1 | I62: 0 | J62: ='3 Base Saídas'!R406 -> 20.1 | K62: =I62-J62 -> -20.1 | L62: 4903864174 | M62: 94517 | N62: JANE'S APPLE FACTORY LTDA | O62: BC129357
A63: 46275 | B63: ='3 Base Entrada 2008'!K202 -> Recebido no 2008 | C63: W3-BR-25A | D63: 261080301 | E63: CA MOEDAS 2,01KG/UC 10UC/CX 30CX/PAL | F63: 2008 | G63: KG | H63: ='3 Base Entrada 2008'!G202 -> 2995 | I63: ='3 Base Entrada 2008'!L202 -> 0 | J63: 0 | K63: =I63-J63 -> 0 | L63: 4903864964
A64: 46276 | B64: ='3 Base Entrada 2008'!K16 -> Entrada | C64: 811-BR-25A | D64: 250880301 | E64: CA MOEDAS 2,01KG/UC 10UC/CX 30CX/PAL | F64: 2008 | G64: KG | H64: ='3 Base Entrada 2008'!G16 -> -180.9 | I64: ='3 Base Entrada 2008'!L16 -> 180.9 | J64: 0 | K64: =I64-J64 -> 180.9 | L64: 4903881852
A65: 46276 | B65: ='3 Base Entrada 2008'!K119 -> Entrada | C65: 811NV-595 | D65: 260900702 | E65: CA CALLETS 10KG/UC 2UC/BOX 30BOX/PAL | F65: 2008 | G65: KG | H65: ='3 Base Entrada 2008'!G119 -> -1800 | I65: ='3 Base Entrada 2008'!L119 -> 1800 | J65: 0 | K65: =I65-J65 -> 1800 | L65: 4903880733
A66: 46276 | B66: ='3 Base Entrada 2008'!K120 -> Entrada | C66: 811NV-595 | D66: 260920702 | E66: CA CALLETS 10KG/UC 2UC/BOX 30BOX/PAL | F66: 2008 | G66: KG | H66: ='3 Base Entrada 2008'!G120 -> -600 | I66: ='3 Base Entrada 2008'!L120 -> 600 | J66: 0 | K66: =I66-J66 -> 600 | L66: 4903880733
A67: 46276 | B67: ='3 Base Entrada 2008'!K122 -> Entrada | C67: 811NV-595 | D67: 261146101 | E67: CA CALLETS 10KG/UC 2UC/BOX 30BOX/PAL | F67: 2008 | G67: KG | H67: ='3 Base Entrada 2008'!G122 -> -1180 | I67: ='3 Base Entrada 2008'!L122 -> 1180 | J67: 0 | K67: =I67-J67 -> 1180 | L67: 4903880733
A68: 46276 | B68: ='3 Base Entrada 2008'!K121 -> Entrada | C68: 811NV-595 | D68: 261146102 | E68: CA CALLETS 10KG/UC 2UC/BOX 30BOX/PAL | F68: 2008 | G68: KG | H68: ='3 Base Entrada 2008'!G121 -> -520 | I68: ='3 Base Entrada 2008'!L121 -> 520 | J68: 0 | K68: =I68-J68 -> 520 | L68: 4903880733
A69: 46276 | B69: Saída | C69: 823-BR-D94 | D69: 252103049 | E69: CA MOEDAS 0,4KG/UC 7UC/CX 144CX/PAL | F69: 9999 | G69: KG | H69: ='3 Base Saídas'!H172 -> -8.4 | I69: 0 | J69: ='3 Base Saídas'!R172 -> 8.4 | K69: =I69-J69 -> -8.4 | L69: 4903872001 | M69: 208132 | N69: CASA DO SORVETEIRO CIDADE NOVA LTDA | O69: BC116065
A70: 46276 | B70: Saída | C70: 823-BR-D94 | D70: 252103049 | E70: CA MOEDAS 0,4KG/UC 7UC/CX 144CX/PAL | F70: 9999 | G70: KG | H70: ='3 Base Saídas'!H173 -> -2.8 | I70: 0 | J70: ='3 Base Saídas'!R173 -> 2.8 | K70: =I70-J70 -> -2.8 | L70: 4903872462 | M70: 204826 | N70: OESTE PRODUTOS PARA FESTAS LTDA | O70: BC116065
A71: 46276 | B71: Saída | C71: 823-BR-D94 | D71: 252103049 | E71: CA MOEDAS 0,4KG/UC 7UC/CX 144CX/PAL | F71: 9999 | G71: KG | H71: ='3 Base Saídas'!H174 -> -2.8 | I71: 0 | J71: ='3 Base Saídas'!R174 -> 2.8 | K71: =I71-J71 -> -2.8 | L71: 4903872484 | M71: 52011 | N71: CHOCOMEL DOCES E BOMBONIERES LTDA E | O71: BC116065
A72: 46276 | B72: ='3 Base Entrada 2008'!K127 -> Entrada | C72: 823NV-595 | D72: 261376101 | E72: CA CALLETS 10KG/UC 2UC/BOX 30BOX/PAL | F72: 2008 | G72: KG | H72: ='3 Base Entrada 2008'!G127 -> -2400 | I72: ='3 Base Entrada 2008'!L127 -> 2400 | J72: 0 | K72: =I72-J72 -> 2400 | L72: 4903880733
A73: 46276 | B73: Saída | C73: 823NV-595 | D73: 261376101 | E73: CA CALLETS 10KG/UC 2UC/BOX 30BOX/PAL | F73: 9999 | G73: KG | H73: ='3 Base Saídas'!H183 -> -2300 | I73: 0 | J73: ='3 Base Saídas'!R183 -> 2300 | K73: =I73-J73 -> -2300 | L73: 4903881998 | M73: 212392 | N73: MILANO COMERCIO VAREJISTA | O73: BC105440
A74: 46276 | B74: ='3 Base Entrada 2008'!K132 -> Entrada | C74: BIG-PF-1BO-401 | D74: 26126039 | E74: CB PAILLETÉ FEUILLETINE 2.5KG/UC 4UC/BOX | F74: 2008 | G74: KG | H74: ='3 Base Entrada 2008'!G132 -> -40 | I74: ='3 Base Entrada 2008'!L132 -> 40 | J74: 0 | K74: =I74-J74 -> 40 | L74: 4903880733
A75: 46276 | B75: Saída | C75: CHM-BS-9U15-E0-07B | D75: 260701069 | E75: CA MILK BLOSSOMS BLOSSOMS 1KG/UC 4UC/BOX | F75: 9999 | G75: KG | H75: ='3 Base Saídas'!H265 -> -40 | I75: 0 | J75: ='3 Base Saídas'!R265 -> 40 | K75: =I75-J75 -> -40 | L75: 4903887109 | M75: 56938 | N75: CUNHAPAN DISTRIBUIDORA DE | O75: BC116065
A76: 46276 | B76: Saída | C76: CW2-BR-25A | D76: 253470301 | E76: CA MOEDAS 2,01KG/UC 10UC/CX 30CX/PAL | F76: 0355 | G76: KG | H76: ='3 Base Saídas'!H352 -> -241.2 | I76: 0 | J76: ='3 Base Saídas'!R352 -> 241.2 | K76: =I76-J76 -> -241.2 | L76: 4903883571 | M76: 219957 | N76: BRUXELAS DOCES LTDA | O76: BC025150
A77: 46276 | B77: Saída | C77: CW2-BR-25A | D77: 253470301 | E77: CA MOEDAS 2,01KG/UC 10UC/CX 30CX/PAL | F77: 0355 | G77: KG | H77: ='3 Base Saídas'!H353 -> -241.2 | I77: 0 | J77: ='3 Base Saídas'!R353 -> 241.2 | K77: =I77-J77 -> -241.2 | L77: 4903883571 | M77: 219957 | N77: BRUXELAS DOCES LTDA | O77: BC025150
A78: 46277 | B78: Saída | C78: 823-BR-25A | D78: 252900303 | E78: CA MOEDAS 2,01KG/UC 10UC/CX 30CX/PAL | F78: 9999 | G78: KG | H78: ='3 Base Saídas'!H124 -> -40.2 | I78: 0 | J78: ='3 Base Saídas'!R124 -> 40.2 | K78: =I78-J78 -> -40.2 | L78: 4903897767 | M78: 54480 | N78: BARRY CALLEBAUT BRASIL INDUSTRIA E | O78: BC140676
A79: 46277 | B79: Saída | C79: 823-BR-25A | D79: 252900303 | E79: CA MOEDAS 2,01KG/UC 10UC/CX 30CX/PAL | F79: 9999 | G79: KG | H79: ='3 Base Saídas'!H125 -> -40.2 | I79: 0 | J79: ='3 Base Saídas'!R125 -> 40.2 | K79: =I79-J79 -> -40.2 | L79: 4903897880 | M79: 218057 | N79: GELATO ARTESANAL AMERICANA LTDA | O79: BC140676
A80: 46277 | B80: Saída | C80: 823-BR-D94 | D80: 252103049 | E80: CA MOEDAS 0,4KG/UC 7UC/CX 144CX/PAL | F80: 9999 | G80: KG | H80: ='3 Base Saídas'!H171 -> -8.4 | I80: 0 | J80: ='3 Base Saídas'!R171 -> 8.4 | K80: =I80-J80 -> -8.4 | L80: 4903897716 | M80: 220705 | N80: CLUBE DO CONFEITEIRO LTDA | O80: BC140676
A81: 46277 | B81: Saída | C81: CHM-SP-Z3L-BR-U73 | D81: 251880301 | E81: CA MILK LARGE FLAKES SPLITTERS 1KG/UC | F81: 9999 | G81: KG | H81: ='3 Base Saídas'!H290 -> -6 | I81: 0 | J81: ='3 Base Saídas'!R290 -> 6 | K81: =I81-J81 -> -6 | L81: 4903897760 | M81: 221221 | N81: SWEET HOUSE CHOCOLATEIRA | O81: BC140676
A82: 46277 | B82: Saída | C82: CHM-SP-Z3L-BR-U73 | D82: 251880301 | E82: CA MILK LARGE FLAKES SPLITTERS 1KG/UC | F82: 9999 | G82: KG | H82: ='3 Base Saídas'!H291 -> -18 | I82: 0 | J82: ='3 Base Saídas'!R291 -> 18 | K82: =I82-J82 -> -18 | L82: 4903897716 | M82: 220705 | N82: CLUBE DO CONFEITEIRO LTDA | O82: BC140676
A83: 46277 | B83: Saída | C83: CW2-BR-25A | D83: 252650301 | E83: CA MOEDAS 2,01KG/UC 10UC/CX 30CX/PAL | F83: 9999 | G83: KG | H83: ='3 Base Saídas'!H350 -> -20.1 | I83: 0 | J83: ='3 Base Saídas'!R350 -> 20.1 | K83: =I83-J83 -> -20.1 | L83: 4903897766 | M83: 207381 | N83: DIO MIO COM DE SORVETES LTDA | O83: BC140676
A84: 46277 | B84: Saída | C84: CW2-BR-25A | D84: 252650301 | E84: CA MOEDAS 2,01KG/UC 10UC/CX 30CX/PAL | F84: 9999 | G84: KG | H84: ='3 Base Saídas'!H351 -> -20.1 | I84: 0 | J84: ='3 Base Saídas'!R351 -> 20.1 | K84: =I84-J84 -> -20.1 | L84: 4903897767 | M84: 54480 | N84: BARRY CALLEBAUT BRASIL INDUSTRIA E | O84: BC140676
A85: 46277 | B85: Saída | C85: W3-BR-25A | D85: 253540301 | E85: CA MOEDAS 2,01KG/UC 10UC/CX 30CX/PAL | F85: 9999 | G85: KG | H85: ='3 Base Saídas'!H401 -> -20.1 | I85: 0 | J85: ='3 Base Saídas'!R401 -> 20.1 | K85: =I85-J85 -> -20.1 | L85: 4903897767 | M85: 54480 | N85: BARRY CALLEBAUT BRASIL INDUSTRIA E | O85: BC140676
A86: 46278 | B86: Saída | C86: 805-BR-D94 | D86: 251633359 | E86: CA MOEDAS 0,4KG/UC 7UC/CX 144CX/PAL | F86: 9999 | G86: KG | H86: ='3 Base Saídas'!H76 -> -8.4 | I86: 0 | J86: ='3 Base Saídas'!R76 -> 8.4 | K86: =I86-J86 -> -8.4 | L86: 4903903473 | M86: 48664 | N86: ORGANIZACOES FARINHA PURA LTDA | O86: BC130327
A87: 46278 | B87: Saída | C87: 805-BR-D94 | D87: 251633359 | E87: CA MOEDAS 0,4KG/UC 7UC/CX 144CX/PAL | F87: 9999 | G87: KG | H87: ='3 Base Saídas'!H77 -> -2.8 | I87: 0 | J87: ='3 Base Saídas'!R77 -> 2.8 | K87: =I87-J87 -> -2.8 | L87: 4903905036 | M87: 93527 | N87: BRIGADEIRIA E ALGO MAIS LTDA - ME | O87: BC130327
A88: 46278 | B88: Saída | C88: 805-BR-D94 | D88: 251633359 | E88: CA MOEDAS 0,4KG/UC 7UC/CX 144CX/PAL | F88: 9999 | G88: KG | H88: ='3 Base Saídas'!H78 -> -11.2 | I88: 0 | J88: ='3 Base Saídas'!R78 -> 11.2 | K88: =I88-J88 -> -11.2 | L88: 4903906285 | M88: 206193 | N88: SUPERMERCADOS MAMBO LTDA. | O88: BC140676
A89: 46278 | B89: Saída | C89: 805-BR-D94 | D89: 251633359 | E89: CA MOEDAS 0,4KG/UC 7UC/CX 144CX/PAL | F89: 9999 | G89: KG | H89: ='3 Base Saídas'!H79 -> -14 | I89: 0 | J89: ='3 Base Saídas'!R79 -> 14 | K89: =I89-J89 -> -14 | L89: 4903906286 | M89: 206193 | N89: SUPERMERCADOS MAMBO LTDA. | O89: BC140676
A90: 46278 | B90: Saída | C90: 823-BR-D94 | D90: 252103049 | E90: CA MOEDAS 0,4KG/UC 7UC/CX 144CX/PAL | F90: 9999 | G90: KG | H90: ='3 Base Saídas'!H167 -> -19.6 | I90: 0 | J90: ='3 Base Saídas'!R167 -> 19.6 | K90: =I90-J90 -> -19.6 | L90: 4903906286 | M90: 206193 | N90: SUPERMERCADOS MAMBO LTDA. | O90: BC140676
A91: 46278 | B91: Saída | C91: 823-BR-D94 | D91: 252103049 | E91: CA MOEDAS 0,4KG/UC 7UC/CX 144CX/PAL | F91: 9999 | G91: KG | H91: ='3 Base Saídas'!H168 -> -28 | I91: 0 | J91: ='3 Base Saídas'!R168 -> 28 | K91: =I91-J91 -> -28 | L91: 4903906285 | M91: 206193 | N91: SUPERMERCADOS MAMBO LTDA. | O91: BC140676
A92: 46278 | B92: Saída | C92: 823-BR-D94 | D92: 252103049 | E92: CA MOEDAS 0,4KG/UC 7UC/CX 144CX/PAL | F92: 9999 | G92: KG | H92: ='3 Base Saídas'!H169 -> -14 | I92: 0 | J92: ='3 Base Saídas'!R169 -> 14 | K92: =I92-J92 -> -14 | L92: 4903903473 | M92: 48664 | N92: ORGANIZACOES FARINHA PURA LTDA | O92: BC130327
A93: 46278 | B93: Saída | C93: 823-BR-D94 | D93: 252103049 | E93: CA MOEDAS 0,4KG/UC 7UC/CX 144CX/PAL | F93: 9999 | G93: KG | H93: ='3 Base Saídas'!H170 -> -64.4 | I93: 0 | J93: ='3 Base Saídas'!R170 -> 64.4 | K93: =I93-J93 -> -64.4 | L93: 4903899689 | M93: 219760 | N93: 64.216.627 PATRICIA DE BIANCHI | O93: BC140676
A94: 46278 | B94: Saída | C94: CHM-SP-Z3L-BR-U73 | D94: 251880301 | E94: CA MILK LARGE FLAKES SPLITTERS 1KG/UC | F94: 9999 | G94: KG | H94: ='3 Base Saídas'!H288 -> -150 | I94: 0 | J94: ='3 Base Saídas'!R288 -> 150 | K94: =I94-J94 -> -150 | L94: 4903899082 | M94: 95872 | N94: QUALIDADE RIO CLARO COMERCIO | O94: BC140676
A95: 46278 | B95: Saída | C95: CHM-SP-Z3L-BR-U73 | D95: 251880301 | E95: CA MILK LARGE FLAKES SPLITTERS 1KG/UC | F95: 9999 | G95: KG | H95: ='3 Base Saídas'!H289 -> -18 | I95: 0 | J95: ='3 Base Saídas'!R289 -> 18 | K95: =I95-J95 -> -18 | L95: 4903903473 | M95: 48664 | N95: ORGANIZACOES FARINHA PURA LTDA | O95: BC130327
A96: 46278 | B96: Saída | C96: W3-BR-25A | D96: 253540301 | E96: CA MOEDAS 2,01KG/UC 10UC/CX 30CX/PAL | F96: 9999 | G96: KG | H96: ='3 Base Saídas'!H398 -> -40.2 | I96: 0 | J96: ='3 Base Saídas'!R398 -> 40.2 | K96: =I96-J96 -> -40.2 | L96: 4903902650 | M96: 98914 | N96: TALHO DELICATESSEN PAD E CONF LTDA | O96: BC130327
A97: 46278 | B97: Saída | C97: W3-BR-25A | D97: 253540301 | E97: CA MOEDAS 2,01KG/UC 10UC/CX 30CX/PAL | F97: 9999 | G97: KG | H97: ='3 Base Saídas'!H399 -> -20.1 | I97: 0 | J97: ='3 Base Saídas'!R399 -> 20.1 | K97: =I97-J97 -> -20.1 | L97: 4903902668 | M97: 216990 | N97: PANIFICACAO IPANEMA LTDA | O97: BC130327
A98: 46278 | B98: Saída | C98: W3-BR-25A | D98: 253540301 | E98: CA MOEDAS 2,01KG/UC 10UC/CX 30CX/PAL | F98: 9999 | G98: KG | H98: ='3 Base Saídas'!H400 -> -20.1 | I98: 0 | J98: ='3 Base Saídas'!R400 -> 20.1 | K98: =I98-J98 -> -20.1 | L98: 4903903474 | M98: 91111 | N98: MERCEARIA 1928 ALIMENTOS | O98: BC130327
A99: 46279 | B99: Saída | C99: 805-BR-D94 | D99: 251633359 | E99: CA MOEDAS 0,4KG/UC 7UC/CX 144CX/PAL | F99: 9999 | G99: KG | H99: ='3 Base Saídas'!H74 -> -2.8 | I99: 0 | J99: ='3 Base Saídas'!R74 -> 2.8 | K99: =I99-J99 -> -2.8 | L99: 4903916921 | M99: 92235 | N99: FERMISUL FERMENTOS E PRODUTOS | O99: BC147417
A100: 46279 | B100: Saída | C100: 805-BR-D94 | D100: 251633359 | E100: CA MOEDAS 0,4KG/UC 7UC/CX 144CX/PAL | F100: 9999 | G100: KG | H100: ='3 Base Saídas'!H75 -> -2.8 | I100: 0 | J100: ='3 Base Saídas'!R75 -> 2.8 | K100: =I100-J100 -> -2.8 | L100: 4903924349 | M100: 91915 | N100: CHOCOLANDIA SOBELA LTDA | O100: BC116065
...

Sheet 4 Análise ZBR
A1: Análise ZBR — por SKU e lote | O1: ◄ MENU | R1: =IF(A5="Todos","*",A5) -> * | AS1: Todos | AU1: 46274 | AV1: Todos | AW1: 2665-E4-U71 | AX1: 252800202 | AY1: =IF(OR($A$5="Todos",AW1=$A$5),1,0) -> 1 | AZ1: KG | BA1: Todas | BG1: Todos
A2: Entradas, saídas, estoque físico, diferença, motivo e solução por SKU e lote · filtros definidos no Dashboard | R2: =IF(OR(D5="Todos",D5=""),"*",D5) -> * | AS2: 2665-E4-U71 | AU2: 46275 | AV2: =IFERROR(INDEX($AX$1:$AX$94,MATCH(1,$AY$1:$AY$94,0)),"") -> 252800202 | AW2: 70-30-38-BR-25A | AX2: 260070301 | AY2: =IF(OR($A$5="Todos",AW2=$A$5),MAX(AY$1:AY1)+1,0) -> 2 | AZ2: UN | BA2: Entrada | BG2: Confere
R3: =IF(A5="Todos",J5,IFERROR(INDEX($U$40:$U$133,MATCH(A5,$T$40:$T$133,0)),J5)) -> KG | AS3: 70-30-38-BR-25A | AU3: 46276 | AV3: =IFERROR(INDEX($AX$1:$AX$94,MATCH(2,$AY$1:$AY$94,0)),"") -> 260070301 | AW3: 70-30-38-BR-25A | AX3: 260370301 | AY3: =IF(OR($A$5="Todos",AW3=$A$5),MAX(AY$1:AY2)+1,0) -> 3 | AZ3: CX | BA3: Saída | BG3: Sobrando
A4: SKU | D4: LOTE | F4: DATA INICIAL | H4: DATA FINAL | J4: UNIDADE | K4: MOVIMENTAÇÃO | R4: =IF(K5="Entrada","Entrada",IF(K5="Saída","Saída",IF(K5="Recebido no 2008","Recebido no 2008",IF(K5="Estorno","Estorno","*")))) -> * | AS4: 70-30-38-BR-D94 | AU4: 46277 | AV4: =IFERROR(INDEX($AX$1:$AX$94,MATCH(3,$AY$1:$AY$94,0)),"") -> 260370301 | AW4: 70-30-38-BR-D94 | AX4: 253213449 | AY4: =IF(OR($A$5="Todos",AW4=$A$5),MAX(AY$1:AY3)+1,0) -> 4 | BA4: Recebido no 2008 | BG4: Faltando
A5: ='1 Dashboard'!E5 -> Todos | D5: ='1 Dashboard'!H5 -> Todos | F5: ='1 Dashboard'!A5 -> 46274 | H5: ='1 Dashboard'!C5 -> 46296 | J5: ='1 Dashboard'!J5 -> KG | K5: ='1 Dashboard'!K5 -> Todas | R5: =Parâmetros!$C$7 -> 0.01 | AS5: 805-BR-D94 | AU5: 46278 | AV5: =IFERROR(INDEX($AX$1:$AX$94,MATCH(4,$AY$1:$AY$94,0)),"") -> 253213449 | AW5: 805-BR-D94 | AX5: 251633359 | AY5: =IF(OR($A$5="Todos",AW5=$A$5),MAX(AY$1:AY4)+1,0) -> 5 | BA5: Estorno
A6: Filtros definidos no Dashboard (fonte única para todas as análises). Para filtrar só esta tabela, use as setas do cabeçalho. | R6: =IF('1 Dashboard'!$N$5="Todos","*",'1 Dashboard'!$N$5) -> * | AS6: 811-BR-25A | AU6: 46279 | AV6: =IFERROR(INDEX($AX$1:$AX$94,MATCH(5,$AY$1:$AY$94,0)),"") -> 251633359 | AW6: 805-BR-D94 | AX6: 260130779 | AY6: =IF(OR($A$5="Todos",AW6=$A$5),MAX(AY$1:AY5)+1,0) -> 6
A7: ="Mostrando: "&IF(A5="Todos","todos os SKUs",A5)&IF(D5="Todos",""," · lote "&D5)&" · "&DAY(F5)&"/"&MONTH(F5)&"/"&YEAR(F5)&" a "&DAY(H5)&"/"&MONTH(H5)&"/"&YEAR(H5)&" · unidade "&$R$3&IF(K5="Todas",""," · movimentação "&K5) -> Mostrando: todos os SKUs · 9/9/2026 a 1/10/2026 · unidade KG | AS7: 811-BR-D94 | AU7: 46280 | AV7: =IFERROR(INDEX($AX$1:$AX$94,MATCH(6,$AY$1:$AY$94,0)),"") -> 260130779 | AW7: 811-BR-25A | AX7: 250880301 | AY7: =IF(OR($A$5="Todos",AW7=$A$5),MAX(AY$1:AY6)+1,0) -> 7
AS8: 811NV-132 | AU8: 46281 | AV8: =IFERROR(INDEX($AX$1:$AX$94,MATCH(7,$AY$1:$AY$94,0)),"") -> 250880301 | AW8: 811-BR-25A | AX8: 252450301 | AY8: =IF(OR($A$5="Todos",AW8=$A$5),MAX(AY$1:AY7)+1,0) -> 8
A9: ="ENTROU · "&$R$3 -> ENTROU · KG | C9: ="SAIU · "&$R$3 -> SAIU · KG | F9: ="DEVERIA TER · "&$R$3 -> DEVERIA TER · KG | H9: ="ESTOQUE FÍSICO · "&$R$3 -> ESTOQUE FÍSICO · KG | J9: ="DIFERENÇA · "&$R$3 -> DIFERENÇA · KG | L9: ="Confere: "&COUNTIFS($AA$40:$AA$133,1,$AC$40:$AC$133,"Confere")&" SKU·lote" -> Confere: 58 SKU·lote | N9: Indicadores e gráficos: aba Dashboard → | AS9: 811NV-595 | AU9: 46282 | AV9: =IFERROR(INDEX($AX$1:$AX$94,MATCH(8,$AY$1:$AY$94,0)),"") -> 252450301 | AW9: 811-BR-D94 | AX9: 251643289 | AY9: =IF(OR($A$5="Todos",AW9=$A$5),MAX(AY$1:AY8)+1,0) -> 9
A10: =SUMPRODUCT($AA$40:$AA$133,$W$40:$W$133) -> 65930.28 | C10: =SUMPRODUCT($AA$40:$AA$133,$X$40:$X$133) -> 26268.8 | F10: =SUMPRODUCT($AA$40:$AA$133,$BH$40:$BH$133)+A10-C10 -> 39661.48 | H10: =SUMPRODUCT($AA$40:$AA$133,$Y$40:$Y$133) -> 59270.487 | J10: =ROUND(H10-F10,3) -> 19609.007 | L10: ="Sobrando: "&COUNTIFS($AA$40:$AA$133,1,$AC$40:$AC$133,"Sobrando")&" SKU·lote" -> Sobrando: 20 SKU·lote | AS10: 823-BR-25A | AU10: 46283 | AV10: =IFERROR(INDEX($AX$1:$AX$94,MATCH(9,$AY$1:$AY$94,0)),"") -> 251643289 | AW10: 811NV-132 | AX10: 252510301 | AY10: =IF(OR($A$5="Todos",AW10=$A$5),MAX(AY$1:AY9)+1,0) -> 10
A11: transferido do 2008 para o ZBR | C11: vendas e entregas | F11: saldo inicial + entrou − saiu | H11: o que tem no depósito hoje | J11: =IF(OR(F5<>DATE(2026,9,9),H5<>DATE(2026,10,1)),"período parcial: compare com cuidado",IF(ABS(J10)<=$R$5,"tudo confere",IF(J10>0,"sobrando no estoque","faltando no estoque"))) -> sobrando no estoque | L11: ="Faltando: "&COUNTIFS($AA$40:$AA$133,1,$AC$40:$AC$133,"Faltando")&" SKU·lote" -> Faltando: 3 SKU·lote | AS11: 823-BR-D94 | AU11: 46284 | AV11: =IFERROR(INDEX($AX$1:$AX$94,MATCH(10,$AY$1:$AY$94,0)),"") -> 252510301 | AW11: 811NV-132 | AX11: 253280301 | AY11: =IF(OR($A$5="Todos",AW11=$A$5),MAX(AY$1:AY10)+1,0) -> 11
AS12: 823NV-132 | AU12: 46285 | AV12: =IFERROR(INDEX($AX$1:$AX$94,MATCH(11,$AY$1:$AY$94,0)),"") -> 253280301 | AW12: 811NV-595 | AX12: 260900702 | AY12: =IF(OR($A$5="Todos",AW12=$A$5),MAX(AY$1:AY11)+1,0) -> 12
A13: SKU | B13: LOTE | C13: UM | D13: SALDO INICIAL 08/09 | E13: ENTROU | F13: SAIU | G13: DEVERIA TER | H13: ESTOQUE FÍSICO | I13: DIFERENÇA | J13: SITUAÇÃO | K13: LANÇAMENTOS | L13: 1º LANÇAMENTO | M13: ÚLTIMO LANÇAMENTO | N13: MOTIVO DA DIFERENÇA | O13: SOLUÇÃO DE AJUSTE (SUGESTÃO) | AS13: 823NV-595 | AU13: 46286 | AV13: =IFERROR(INDEX($AX$1:$AX$94,MATCH(12,$AY$1:$AY$94,0)),"") -> 260900702 | AW13: 811NV-595 | AX13: 260920702 | AY13: =IF(OR($A$5="Todos",AW13=$A$5),MAX(AY$1:AY12)+1,0) -> 13
A14: =IF(IFERROR(MATCH(1,$AB$40:$AB$133,0),0)=0,"",INDEX($T$40:$T$133,IFERROR(MATCH(1,$AB$40:$AB$133,0),0))) -> CHK-R30GOLD-BR-25A | B14: =IF(IFERROR(MATCH(1,$AB$40:$AB$133,0),0)=0,"",INDEX($AG$40:$AG$133,IFERROR(MATCH(1,$AB$40:$AB$133,0),0))) -> 261130301 | C14: =IF(IFERROR(MATCH(1,$AB$40:$AB$133,0),0)=0,"",INDEX($U$40:$U$133,IFERROR(MATCH(1,$AB$40:$AB$133,0),0))) -> KG | D14: =IF(IFERROR(MATCH(1,$AB$40:$AB$133,0),0)=0,"",INDEX($BH$40:$BH$133,IFERROR(MATCH(1,$AB$40:$AB$133,0),0))) -> 0 | E14: =IF(IFERROR(MATCH(1,$AB$40:$AB$133,0),0)=0,"",INDEX($W$40:$W$133,IFERROR(MATCH(1,$AB$40:$AB$133,0),0))) -> 2673.3 | F14: =IF(IFERROR(MATCH(1,$AB$40:$AB$133,0),0)=0,"",INDEX($X$40:$X$133,IFERROR(MATCH(1,$AB$40:$AB$133,0),0))) -> 1005 | G14: =IF(A14="","",D14+E14-F14) -> 1668.3 | H14: =IF(IFERROR(MATCH(1,$AB$40:$AB$133,0),0)=0,"",INDEX($Y$40:$Y$133,IFERROR(MATCH(1,$AB$40:$AB$133,0),0))) -> 1226.1 | I14: =IF(IFERROR(MATCH(1,$AB$40:$AB$133,0),0)=0,"",INDEX($Z$40:$Z$133,IFERROR(MATCH(1,$AB$40:$AB$133,0),0))) -> -442.2 | J14: =IF(IFERROR(MATCH(1,$AB$40:$AB$133,0),0)=0,"",INDEX($AC$40:$AC$133,IFERROR(MATCH(1,$AB$40:$AB$133,0),0))) -> Faltando | K14: =IF(IFERROR(MATCH(1,$AB$40:$AB$133,0),0)=0,"",INDEX($AD$40:$AD$133,IFERROR(MATCH(1,$AB$40:$AB$133,0),0))) -> 17 | L14: =IF(IFERROR(MATCH(1,$AB$40:$AB$133,0),0)=0,"",IF(INDEX($BB$40:$BB$133,IFERROR(MATCH(1,$AB$40:$AB$133,0),0))>=99999,"",INDEX($BB$40:$BB$133,IFERROR(MATCH(1,$AB$40:$AB$133,0),0)))) -> 46275 | M14: =IF(IFERROR(MATCH(1,$AB$40:$AB$133,0),0)=0,"",IF(INDEX($BC$40:$BC$133,IFERROR(MATCH(1,$AB$40:$AB$133,0),0))=0,"",INDEX($BC$40:$BC$133,IFERROR(MATCH(1,$AB$40:$AB$133,0),0)))) -> 46295 | N14: =IF(IFERROR(MATCH(1,$AB$40:$AB$133,0),0)=0,"",INDEX($AE$40:$AE$133,IFERROR(MATCH(1,$AB$40:$AB$133,0),0))&"") -> Estoque físico menor que o esperado: saída, ajuste ou perda não lançada no período | O14: =IF(IFERROR(MATCH(1,$AB$40:$AB$133,0),0)=0,"",INDEX($BD$40:$BD$133,IFERROR(MATCH(1,$AB$40:$AB$133,0),0))&"") -> Contar o lote. Se a falta se confirmar: lançar a saída esquecida (601) ou ajuste de inventário de −442.2 KG | AS14: BIG-PF-1BO-401 | AU14: 46287 | AV14: =IFERROR(INDEX($AX$1:$AX$94,MATCH(13,$AY$1:$AY$94,0)),"") -> 260920702 | AW14: 811NV-595 | AX14: 261146101 | AY14: =IF(OR($A$5="Todos",AW14=$A$5),MAX(AY$1:AY13)+1,0) -> 14
A15: =IF(IFERROR(MATCH(2,$AB$40:$AB$133,0),0)=0,"",INDEX($T$40:$T$133,IFERROR(MATCH(2,$AB$40:$AB$133,0),0))) -> CHM-TS-P23-E0-999 | B15: =IF(IFERROR(MATCH(2,$AB$40:$AB$133,0),0)=0,"",INDEX($AG$40:$AG$133,IFERROR(MATCH(2,$AB$40:$AB$133,0),0))) -> 2605567696 | C15: =IF(IFERROR(MATCH(2,$AB$40:$AB$133,0),0)=0,"",INDEX($U$40:$U$133,IFERROR(MATCH(2,$AB$40:$AB$133,0),0))) -> KG | D15: =IF(IFERROR(MATCH(2,$AB$40:$AB$133,0),0)=0,"",INDEX($BH$40:$BH$133,IFERROR(MATCH(2,$AB$40:$AB$133,0),0))) -> 0 | E15: =IF(IFERROR(MATCH(2,$AB$40:$AB$133,0),0)=0,"",INDEX($W$40:$W$133,IFERROR(MATCH(2,$AB$40:$AB$133,0),0))) -> 261.12 | F15: =IF(IFERROR(MATCH(2,$AB$40:$AB$133,0),0)=0,"",INDEX($X$40:$X$133,IFERROR(MATCH(2,$AB$40:$AB$133,0),0))) -> 0 | G15: =IF(A15="","",D15+E15-F15) -> 261.12 | H15: =IF(IFERROR(MATCH(2,$AB$40:$AB$133,0),0)=0,"",INDEX($Y$40:$Y$133,IFERROR(MATCH(2,$AB$40:$AB$133,0),0))) -> 0 | I15: =IF(IFERROR(MATCH(2,$AB$40:$AB$133,0),0)=0,"",INDEX($Z$40:$Z$133,IFERROR(MATCH(2,$AB$40:$AB$133,0),0))) -> -261.12 | J15: =IF(IFERROR(MATCH(2,$AB$40:$AB$133,0),0)=0,"",INDEX($AC$40:$AC$133,IFERROR(MATCH(2,$AB$40:$AB$133,0),0))) -> Faltando | K15: =IF(IFERROR(MATCH(2,$AB$40:$AB$133,0),0)=0,"",INDEX($AD$40:$AD$133,IFERROR(MATCH(2,$AB$40:$AB$133,0),0))) -> 1 | L15: =IF(IFERROR(MATCH(2,$AB$40:$AB$133,0),0)=0,"",IF(INDEX($BB$40:$BB$133,IFERROR(MATCH(2,$AB$40:$AB$133,0),0))>=99999,"",INDEX($BB$40:$BB$133,IFERROR(MATCH(2,$AB$40:$AB$133,0),0)))) -> 46288 | M15: =IF(IFERROR(MATCH(2,$AB$40:$AB$133,0),0)=0,"",IF(INDEX($BC$40:$BC$133,IFERROR(MATCH(2,$AB$40:$AB$133,0),0))=0,"",INDEX($BC$40:$BC$133,IFERROR(MATCH(2,$AB$40:$AB$133,0),0)))) -> 46288 | N15: =IF(IFERROR(MATCH(2,$AB$40:$AB$133,0),0)=0,"",INDEX($AE$40:$AE$133,IFERROR(MATCH(2,$AB$40:$AB$133,0),0))&"") -> Entrou no ZBR, mas não está no estoque físico: não chegou ou foi guardado em outro lote | O15: =IF(IFERROR(MATCH(2,$AB$40:$AB$133,0),0)=0,"",INDEX($BD$40:$BD$133,IFERROR(MATCH(2,$AB$40:$AB$133,0),0))&"") -> Procurar a OT de armazenagem pendente no ZBR. Se não achar: contar e lançar ajuste de inventário de −261.1 KG | AS15: CHD-BB-308BY-357 | AU15: 46288 | AV15: =IFERROR(INDEX($AX$1:$AX$94,MATCH(14,$AY$1:$AY$94,0)),"") -> 261146101 | AW15: 811NV-595 | AX15: 261146102 | AY15: =IF(OR($A$5="Todos",AW15=$A$5),MAX(AY$1:AY14)+1,0) -> 15
A16: =IF(IFERROR(MATCH(3,$AB$40:$AB$133,0),0)=0,"",INDEX($T$40:$T$133,IFERROR(MATCH(3,$AB$40:$AB$133,0),0))) -> BIG-PF-1BO-401 | B16: =IF(IFERROR(MATCH(3,$AB$40:$AB$133,0),0)=0,"",INDEX($AG$40:$AG$133,IFERROR(MATCH(3,$AB$40:$AB$133,0),0))) -> 26044019 | C16: =IF(IFERROR(MATCH(3,$AB$40:$AB$133,0),0)=0,"",INDEX($U$40:$U$133,IFERROR(MATCH(3,$AB$40:$AB$133,0),0))) -> KG | D16: =IF(IFERROR(MATCH(3,$AB$40:$AB$133,0),0)=0,"",INDEX($BH$40:$BH$133,IFERROR(MATCH(3,$AB$40:$AB$133,0),0))) -> 0 | E16: =IF(IFERROR(MATCH(3,$AB$40:$AB$133,0),0)=0,"",INDEX($W$40:$W$133,IFERROR(MATCH(3,$AB$40:$AB$133,0),0))) -> 480 | F16: =IF(IFERROR(MATCH(3,$AB$40:$AB$133,0),0)=0,"",INDEX($X$40:$X$133,IFERROR(MATCH(3,$AB$40:$AB$133,0),0))) -> 60 | G16: =IF(A16="","",D16+E16-F16) -> 420 | H16: =IF(IFERROR(MATCH(3,$AB$40:$AB$133,0),0)=0,"",INDEX($Y$40:$Y$133,IFERROR(MATCH(3,$AB$40:$AB$133,0),0))) -> 210 | I16: =IF(IFERROR(MATCH(3,$AB$40:$AB$133,0),0)=0,"",INDEX($Z$40:$Z$133,IFERROR(MATCH(3,$AB$40:$AB$133,0),0))) -> -210 | J16: =IF(IFERROR(MATCH(3,$AB$40:$AB$133,0),0)=0,"",INDEX($AC$40:$AC$133,IFERROR(MATCH(3,$AB$40:$AB$133,0),0))) -> Faltando | K16: =IF(IFERROR(MATCH(3,$AB$40:$AB$133,0),0)=0,"",INDEX($AD$40:$AD$133,IFERROR(MATCH(3,$AB$40:$AB$133,0),0))) -> 5 | L16: =IF(IFERROR(MATCH(3,$AB$40:$AB$133,0),0)=0,"",IF(INDEX($BB$40:$BB$133,IFERROR(MATCH(3,$AB$40:$AB$133,0),0))>=99999,"",INDEX($BB$40:$BB$133,IFERROR(MATCH(3,$AB$40:$AB$133,0),0)))) -> 46275 | M16: =IF(IFERROR(MATCH(3,$AB$40:$AB$133,0),0)=0,"",IF(INDEX($BC$40:$BC$133,IFERROR(MATCH(3,$AB$40:$AB$133,0),0))=0,"",INDEX($BC$40:$BC$133,IFERROR(MATCH(3,$AB$40:$AB$133,0),0)))) -> 46295 | N16: =IF(IFERROR(MATCH(3,$AB$40:$AB$133,0),0)=0,"",INDEX($AE$40:$AE$133,IFERROR(MATCH(3,$AB$40:$AB$133,0),0))&"") -> Estoque físico menor que o esperado: saída, ajuste ou perda não lançada no período | O16: =IF(IFERROR(MATCH(3,$AB$40:$AB$133,0),0)=0,"",INDEX($BD$40:$BD$133,IFERROR(MATCH(3,$AB$40:$AB$133,0),0))&"") -> Contar o lote. Se a falta se confirmar: lançar a saída esquecida (601) ou ajuste de inventário de −210.0 KG | AS16: CHD-DR-75Y5-E1-U68 | AU16: 46289 | AV16: =IFERROR(INDEX($AX$1:$AX$94,MATCH(15,$AY$1:$AY$94,0)),"") -> 261146102 | AW16: 823-BR-25A | AX16: 252100301 | AY16: =IF(OR($A$5="Todos",AW16=$A$5),MAX(AY$1:AY15)+1,0) -> 16
A17: =IF(IFERROR(MATCH(4,$AB$40:$AB$133,0),0)=0,"",INDEX($T$40:$T$133,IFERROR(MATCH(4,$AB$40:$AB$133,0),0))) -> 811-BR-D94 | B17: =IF(IFERROR(MATCH(4,$AB$40:$AB$133,0),0)=0,"",INDEX($AG$40:$AG$133,IFERROR(MATCH(4,$AB$40:$AB$133,0),0))) -> 251643289 | C17: =IF(IFERROR(MATCH(4,$AB$40:$AB$133,0),0)=0,"",INDEX($U$40:$U$133,IFERROR(MATCH(4,$AB$40:$AB$133,0),0))) -> KG | D17: =IF(IFERROR(MATCH(4,$AB$40:$AB$133,0),0)=0,"",INDEX($BH$40:$BH$133,IFERROR(MATCH(4,$AB$40:$AB$133,0),0))) -> 0 | E17: =IF(IFERROR(MATCH(4,$AB$40:$AB$133,0),0)=0,"",INDEX($W$40:$W$133,IFERROR(MATCH(4,$AB$40:$AB$133,0),0))) -> 2.8 | F17: =IF(IFERROR(MATCH(4,$AB$40:$AB$133,0),0)=0,"",INDEX($X$40:$X$133,IFERROR(MATCH(4,$AB$40:$AB$133,0),0))) -> 226.8 | G17: =IF(A17="","",D17+E17-F17) -> -224 | H17: =IF(IFERROR(MATCH(4,$AB$40:$AB$133,0),0)=0,"",INDEX($Y$40:$Y$133,IFERROR(MATCH(4,$AB$40:$AB$133,0),0))) -> 5513.2 | I17: =IF(IFERROR(MATCH(4,$AB$40:$AB$133,0),0)=0,"",INDEX($Z$40:$Z$133,IFERROR(MATCH(4,$AB$40:$AB$133,0),0))) -> 5737.2 | J17: =IF(IFERROR(MATCH(4,$AB$40:$AB$133,0),0)=0,"",INDEX($AC$40:$AC$133,IFERROR(MATCH(4,$AB$40:$AB$133,0),0))) -> Sobrando | K17: =IF(IFERROR(MATCH(4,$AB$40:$AB$133,0),0)=0,"",INDEX($AD$40:$AD$133,IFERROR(MATCH(4,$AB$40:$AB$133,0),0))) -> 17 | L17: =IF(IFERROR(MATCH(4,$AB$40:$AB$133,0),0)=0,"",IF(INDEX($BB$40:$BB$133,IFERROR(MATCH(4,$AB$40:$AB$133,0),0))>=99999,"",INDEX($BB$40:$BB$133,IFERROR(MATCH(4,$AB$40:$AB$133,0),0)))) -> 46284 | M17: =IF(IFERROR(MATCH(4,$AB$40:$AB$133,0),0)=0,"",IF(INDEX($BC$40:$BC$133,IFERROR(MATCH(4,$AB$40:$AB$133,0),0))=0,"",INDEX($BC$40:$BC$133,IFERROR(MATCH(4,$AB$40:$AB$133,0),0)))) -> 46295 | N17: =IF(IFERROR(MATCH(4,$AB$40:$AB$133,0),0)=0,"",INDEX($AE$40:$AE$133,IFERROR(MATCH(4,$AB$40:$AB$133,0),0))&"") -> Explica em parte: estoque antigo 5,328.4 + doca/transferência 0.0; faltam 408.8 a explicar | O17: =IF(IFERROR(MATCH(4,$AB$40:$AB$133,0),0)=0,"",INDEX($BD$40:$BD$133,IFERROR(MATCH(4,$AB$40:$AB$133,0),0))&"") -> Confirmar saldo de 08/09 e OTs de doca; contar o lote para os 408.8 KG restantes e ajustar a sobra se confirmada | AS17: CHD-SP-1M-2B-U77 | AU17: 46290 | AV17: =IFERROR(INDEX($AX$1:$AX$94,MATCH(16,$AY$1:$AY$94,0)),"") -> 252100301 | AW17: 823-BR-25A | AX17: 252900303 | AY17: =IF(OR($A$5="Todos",AW17=$A$5),MAX(AY$1:AY16)+1,0) -> 17
A18: =IF(IFERROR(MATCH(5,$AB$40:$AB$133,0),0)=0,"",INDEX($T$40:$T$133,IFERROR(MATCH(5,$AB$40:$AB$133,0),0))) -> CHM-SP-Z3L-BR-U73 | B18: =IF(IFERROR(MATCH(5,$AB$40:$AB$133,0),0)=0,"",INDEX($AG$40:$AG$133,IFERROR(MATCH(5,$AB$40:$AB$133,0),0))) -> 251880301 | C18: =IF(IFERROR(MATCH(5,$AB$40:$AB$133,0),0)=0,"",INDEX($U$40:$U$133,IFERROR(MATCH(5,$AB$40:$AB$133,0),0))) -> KG | D18: =IF(IFERROR(MATCH(5,$AB$40:$AB$133,0),0)=0,"",INDEX($BH$40:$BH$133,IFERROR(MATCH(5,$AB$40:$AB$133,0),0))) -> 0 | E18: =IF(IFERROR(MATCH(5,$AB$40:$AB$133,0),0)=0,"",INDEX($W$40:$W$133,IFERROR(MATCH(5,$AB$40:$AB$133,0),0))) -> 966 | F18: =IF(IFERROR(MATCH(5,$AB$40:$AB$133,0),0)=0,"",INDEX($X$40:$X$133,IFERROR(MATCH(5,$AB$40:$AB$133,0),0))) -> 906 | G18: =IF(A18="","",D18+E18-F18) -> 60 | H18: =IF(IFERROR(MATCH(5,$AB$40:$AB$133,0),0)=0,"",INDEX($Y$40:$Y$133,IFERROR(MATCH(5,$AB$40:$AB$133,0),0))) -> 3754.998 | I18: =IF(IFERROR(MATCH(5,$AB$40:$AB$133,0),0)=0,"",INDEX($Z$40:$Z$133,IFERROR(MATCH(5,$AB$40:$AB$133,0),0))) -> 3694.998 | J18: =IF(IFERROR(MATCH(5,$AB$40:$AB$133,0),0)=0,"",INDEX($AC$40:$AC$133,IFERROR(MATCH(5,$AB$40:$AB$133,0),0))) -> Sobrando | K18: =IF(IFERROR(MATCH(5,$AB$40:$AB$133,0),0)=0,"",INDEX($AD$40:$AD$133,IFERROR(MATCH(5,$AB$40:$AB$133,0),0))) -> 30 | L18: =IF(IFERROR(MATCH(5,$AB$40:$AB$133,0),0)=0,"",IF(INDEX($BB$40:$BB$133,IFERROR(MATCH(5,$AB$40:$AB$133,0),0))>=99999,"",INDEX($BB$40:$BB$133,IFERROR(MATCH(5,$AB$40:$AB$133,0),0)))) -> 46275 | M18: =IF(IFERROR(MATCH(5,$AB$40:$AB$133,0),0)=0,"",IF(INDEX($BC$40:$BC$133,IFERROR(MATCH(5,$AB$40:$AB$133,0),0))=0,"",INDEX($BC$40:$BC$133,IFERROR(MATCH(5,$AB$40:$AB$133,0),0)))) -> 46293 | N18: =IF(IFERROR(MATCH(5,$AB$40:$AB$133,0),0)=0,"",INDEX($AE$40:$AE$133,IFERROR(MATCH(5,$AB$40:$AB$133,0),0))&"") -> Explica em parte: estoque antigo 1,343.0 + doca/transferência 204.0; faltam 2,148.0 a explicar | O18: =IF(IFERROR(MATCH(5,$AB$40:$AB$133,0),0)=0,"",INDEX($BD$40:$BD$133,IFERROR(MATCH(5,$AB$40:$AB$133,0),0))&"") -> Confirmar saldo de 08/09 e OTs de doca; contar o lote para os 2,148.0 KG restantes e ajustar a sobra se confirmada | AS18: CHD-SP-1M-BR-U73 | AU18: 46291 | AV18: =IFERROR(INDEX($AX$1:$AX$94,MATCH(17,$AY$1:$AY$94,0)),"") -> 252900303 | AW18: 823-BR-25A | AX18: 252940301 | AY18: =IF(OR($A$5="Todos",AW18=$A$5),MAX(AY$1:AY17)+1,0) -> 18
A19: =IF(IFERROR(MATCH(6,$AB$40:$AB$133,0),0)=0,"",INDEX($T$40:$T$133,IFERROR(MATCH(6,$AB$40:$AB$133,0),0))) -> CHD-SP-9Z4-BR-U73 | B19: =IF(IFERROR(MATCH(6,$AB$40:$AB$133,0),0)=0,"",INDEX($AG$40:$AG$133,IFERROR(MATCH(6,$AB$40:$AB$133,0),0))) -> 250500301 | C19: =IF(IFERROR(MATCH(6,$AB$40:$AB$133,0),0)=0,"",INDEX($U$40:$U$133,IFERROR(MATCH(6,$AB$40:$AB$133,0),0))) -> KG | D19: =IF(IFERROR(MATCH(6,$AB$40:$AB$133,0),0)=0,"",INDEX($BH$40:$BH$133,IFERROR(MATCH(6,$AB$40:$AB$133,0),0))) -> 0 | E19: =IF(IFERROR(MATCH(6,$AB$40:$AB$133,0),0)=0,"",INDEX($W$40:$W$133,IFERROR(MATCH(6,$AB$40:$AB$133,0),0))) -> 240 | F19: =IF(IFERROR(MATCH(6,$AB$40:$AB$133,0),0)=0,"",INDEX($X$40:$X$133,IFERROR(MATCH(6,$AB$40:$AB$133,0),0))) -> 6 | G19: =IF(A19="","",D19+E19-F19) -> 234 | H19: =IF(IFERROR(MATCH(6,$AB$40:$AB$133,0),0)=0,"",INDEX($Y$40:$Y$133,IFERROR(MATCH(6,$AB$40:$AB$133,0),0))) -> 3432 | I19: =IF(IFERROR(MATCH(6,$AB$40:$AB$133,0),0)=0,"",INDEX($Z$40:$Z$133,IFERROR(MATCH(6,$AB$40:$AB$133,0),0))) -> 3198 | J19: =IF(IFERROR(MATCH(6,$AB$40:$AB$133,0),0)=0,"",INDEX($AC$40:$AC$133,IFERROR(MATCH(6,$AB$40:$AB$133,0),0))) -> Sobrando | K19: =IF(IFERROR(MATCH(6,$AB$40:$AB$133,0),0)=0,"",INDEX($AD$40:$AD$133,IFERROR(MATCH(6,$AB$40:$AB$133,0),0))) -> 2 | L19: =IF(IFERROR(MATCH(6,$AB$40:$AB$133,0),0)=0,"",IF(INDEX($BB$40:$BB$133,IFERROR(MATCH(6,$AB$40:$AB$133,0),0))>=99999,"",INDEX($BB$40:$BB$133,IFERROR(MATCH(6,$AB$40:$AB$133,0),0)))) -> 46279 | M19: =IF(IFERROR(MATCH(6,$AB$40:$AB$133,0),0)=0,"",IF(INDEX($BC$40:$BC$133,IFERROR(MATCH(6,$AB$40:$AB$133,0),0))=0,"",INDEX($BC$40:$BC$133,IFERROR(MATCH(6,$AB$40:$AB$133,0),0)))) -> 46294 | N19: =IF(IFERROR(MATCH(6,$AB$40:$AB$133,0),0)=0,"",INDEX($AE$40:$AE$133,IFERROR(MATCH(6,$AB$40:$AB$133,0),0))&"") -> Explica em parte: estoque antigo 2,898.0 + doca/transferência 0.0; faltam 300.0 a explicar | O19: =IF(IFERROR(MATCH(6,$AB$40:$AB$133,0),0)=0,"",INDEX($BD$40:$BD$133,IFERROR(MATCH(6,$AB$40:$AB$133,0),0))&"") -> Confirmar saldo de 08/09 e OTs de doca; contar o lote para os 300.0 KG restantes e ajustar a sobra se confirmada | AS19: CHD-SP-9Z4-BR-U73 | AU19: 46292 | AV19: =IFERROR(INDEX($AX$1:$AX$94,MATCH(18,$AY$1:$AY$94,0)),"") -> 252940301 | AW19: 823-BR-D94 | AX19: 252103049 | AY19: =IF(OR($A$5="Todos",AW19=$A$5),MAX(AY$1:AY18)+1,0) -> 19
A20: =IF(IFERROR(MATCH(7,$AB$40:$AB$133,0),0)=0,"",INDEX($T$40:$T$133,IFERROR(MATCH(7,$AB$40:$AB$133,0),0))) -> 823-BR-D94 | B20: =IF(IFERROR(MATCH(7,$AB$40:$AB$133,0),0)=0,"",INDEX($AG$40:$AG$133,IFERROR(MATCH(7,$AB$40:$AB$133,0),0))) -> 252103049 | C20: =IF(IFERROR(MATCH(7,$AB$40:$AB$133,0),0)=0,"",INDEX($U$40:$U$133,IFERROR(MATCH(7,$AB$40:$AB$133,0),0))) -> KG | D20: =IF(IFERROR(MATCH(7,$AB$40:$AB$133,0),0)=0,"",INDEX($BH$40:$BH$133,IFERROR(MATCH(7,$AB$40:$AB$133,0),0))) -> 0 | E20: =IF(IFERROR(MATCH(7,$AB$40:$AB$133,0),0)=0,"",INDEX($W$40:$W$133,IFERROR(MATCH(7,$AB$40:$AB$133,0),0))) -> 2.8 | F20: =IF(IFERROR(MATCH(7,$AB$40:$AB$133,0),0)=0,"",INDEX($X$40:$X$133,IFERROR(MATCH(7,$AB$40:$AB$133,0),0))) -> 677.6 | G20: =IF(A20="","",D20+E20-F20) -> -674.8 | H20: =IF(IFERROR(MATCH(7,$AB$40:$AB$133,0),0)=0,"",INDEX($Y$40:$Y$133,IFERROR(MATCH(7,$AB$40:$AB$133,0),0))) -> 1853.6 | I20: =IF(IFERROR(MATCH(7,$AB$40:$AB$133,0),0)=0,"",INDEX($Z$40:$Z$133,IFERROR(MATCH(7,$AB$40:$AB$133,0),0))) -> 2528.4 | J20: =IF(IFERROR(MATCH(7,$AB$40:$AB$133,0),0)=0,"",INDEX($AC$40:$AC$133,IFERROR(MATCH(7,$AB$40:$AB$133,0),0))) -> Sobrando | K20: =IF(IFERROR(MATCH(7,$AB$40:$AB$133,0),0)=0,"",INDEX($AD$40:$AD$133,IFERROR(MATCH(7,$AB$40:$AB$133,0),0))) -> 53 | L20: =IF(IFERROR(MATCH(7,$AB$40:$AB$133,0),0)=0,"",IF(INDEX($BB$40:$BB$133,IFERROR(MATCH(7,$AB$40:$AB$133,0),0))>=99999,"",INDEX($BB$40:$BB$133,IFERROR(MATCH(7,$AB$40:$AB$133,0),0)))) -> 46274 | M20: =IF(IFERROR(MATCH(7,$AB$40:$AB$133,0),0)=0,"",IF(INDEX($BC$40:$BC$133,IFERROR(MATCH(7,$AB$40:$AB$133,0),0))=0,"",INDEX($BC$40:$BC$133,IFERROR(MATCH(7,$AB$40:$AB$133,0),0)))) -> 46296 | N20: =IF(IFERROR(MATCH(7,$AB$40:$AB$133,0),0)=0,"",INDEX($AE$40:$AE$133,IFERROR(MATCH(7,$AB$40:$AB$133,0),0))&"") -> Explica em parte: estoque antigo 1,254.4 + doca/transferência 14.0; faltam 1,260.0 a explicar | O20: =IF(IFERROR(MATCH(7,$AB$40:$AB$133,0),0)=0,"",INDEX($BD$40:$BD$133,IFERROR(MATCH(7,$AB$40:$AB$133,0),0))&"") -> Confirmar saldo de 08/09 e OTs de doca; contar o lote para os 1,260.0 KG restantes e ajustar a sobra se confirmada | AS20: CHD-TS-22350E0-999 | AU20: 46293 | AV20: =IFERROR(INDEX($AX$1:$AX$94,MATCH(19,$AY$1:$AY$94,0)),"") -> 252103049 | AW20: 823NV-132 | AX20: 260880201 | AY20: =IF(OR($A$5="Todos",AW20=$A$5),MAX(AY$1:AY19)+1,0) -> 20
A21: =IF(IFERROR(MATCH(8,$AB$40:$AB$133,0),0)=0,"",INDEX($T$40:$T$133,IFERROR(MATCH(8,$AB$40:$AB$133,0),0))) -> 805-BR-D94 | B21: =IF(IFERROR(MATCH(8,$AB$40:$AB$133,0),0)=0,"",INDEX($AG$40:$AG$133,IFERROR(MATCH(8,$AB$40:$AB$133,0),0))) -> 251633359 | C21: =IF(IFERROR(MATCH(8,$AB$40:$AB$133,0),0)=0,"",INDEX($U$40:$U$133,IFERROR(MATCH(8,$AB$40:$AB$133,0),0))) -> KG | D21: =IF(IFERROR(MATCH(8,$AB$40:$AB$133,0),0)=0,"",INDEX($BH$40:$BH$133,IFERROR(MATCH(8,$AB$40:$AB$133,0),0))) -> 0 | E21: =IF(IFERROR(MATCH(8,$AB$40:$AB$133,0),0)=0,"",INDEX($W$40:$W$133,IFERROR(MATCH(8,$AB$40:$AB$133,0),0))) -> 313.6 | F21: =IF(IFERROR(MATCH(8,$AB$40:$AB$133,0),0)=0,"",INDEX($X$40:$X$133,IFERROR(MATCH(8,$AB$40:$AB$133,0),0))) -> 221.2 | G21: =IF(A21="","",D21+E21-F21) -> 92.4 | H21: =IF(IFERROR(MATCH(8,$AB$40:$AB$133,0),0)=0,"",INDEX($Y$40:$Y$133,IFERROR(MATCH(8,$AB$40:$AB$133,0),0))) -> 1360.8 | I21: =IF(IFERROR(MATCH(8,$AB$40:$AB$133,0),0)=0,"",INDEX($Z$40:$Z$133,IFERROR(MATCH(8,$AB$40:$AB$133,0),0))) -> 1268.4 | J21: =IF(IFERROR(MATCH(8,$AB$40:$AB$133,0),0)=0,"",INDEX($AC$40:$AC$133,IFERROR(MATCH(8,$AB$40:$AB$133,0),0))) -> Sobrando | K21: =IF(IFERROR(MATCH(8,$AB$40:$AB$133,0),0)=0,"",INDEX($AD$40:$AD$133,IFERROR(MATCH(8,$AB$40:$AB$133,0),0))) -> 26 | L21: =IF(IFERROR(MATCH(8,$AB$40:$AB$133,0),0)=0,"",IF(INDEX($BB$40:$BB$133,IFERROR(MATCH(8,$AB$40:$AB$133,0),0))>=99999,"",INDEX($BB$40:$BB$133,IFERROR(MATCH(8,$AB$40:$AB$133,0),0)))) -> 46274 | M21: =IF(IFERROR(MATCH(8,$AB$40:$AB$133,0),0)=0,"",IF(INDEX($BC$40:$BC$133,IFERROR(MATCH(8,$AB$40:$AB$133,0),0))=0,"",INDEX($BC$40:$BC$133,IFERROR(MATCH(8,$AB$40:$AB$133,0),0)))) -> 46294 | N21: =IF(IFERROR(MATCH(8,$AB$40:$AB$133,0),0)=0,"",INDEX($AE$40:$AE$133,IFERROR(MATCH(8,$AB$40:$AB$133,0),0))&"") -> Estoque antigo/doca + saídas do período que não baixaram o estoque físico | O21: =IF(IFERROR(MATCH(8,$AB$40:$AB$133,0),0)=0,"",INDEX($BD$40:$BD$133,IFERROR(MATCH(8,$AB$40:$AB$133,0),0))&"") -> Confirmar a OT de saída (picking) das remessas para baixar 221.2 KG do estoque físico; conferir também estoque antigo/doca | AS21: CHD-VR-Z2S-E0-U68 | AU21: 46294 | AV21: =IFERROR(INDEX($AX$1:$AX$94,MATCH(20,$AY$1:$AY$94,0)),"") -> 260880201 | AW21: 823NV-595 | AX21: 260416102 | AY21: =IF(OR($A$5="Todos",AW21=$A$5),MAX(AY$1:AY20)+1,0) -> 21
A22: =IF(IFERROR(MATCH(9,$AB$40:$AB$133,0),0)=0,"",INDEX($T$40:$T$133,IFERROR(MATCH(9,$AB$40:$AB$133,0),0))) -> W3-BR-25A | B22: =IF(IFERROR(MATCH(9,$AB$40:$AB$133,0),0)=0,"",INDEX($AG$40:$AG$133,IFERROR(MATCH(9,$AB$40:$AB$133,0),0))) -> 253540301 | C22: =IF(IFERROR(MATCH(9,$AB$40:$AB$133,0),0)=0,"",INDEX($U$40:$U$133,IFERROR(MATCH(9,$AB$40:$AB$133,0),0))) -> KG | D22: =IF(IFERROR(MATCH(9,$AB$40:$AB$133,0),0)=0,"",INDEX($BH$40:$BH$133,IFERROR(MATCH(9,$AB$40:$AB$133,0),0))) -> 0 | E22: =IF(IFERROR(MATCH(9,$AB$40:$AB$133,0),0)=0,"",INDEX($W$40:$W$133,IFERROR(MATCH(9,$AB$40:$AB$133,0),0))) -> 0 | F22: =IF(IFERROR(MATCH(9,$AB$40:$AB$133,0),0)=0,"",INDEX($X$40:$X$133,IFERROR(MATCH(9,$AB$40:$AB$133,0),0))) -> 542.7 | G22: =IF(A22="","",D22+E22-F22) -> -542.7 | H22: =IF(IFERROR(MATCH(9,$AB$40:$AB$133,0),0)=0,"",INDEX($Y$40:$Y$133,IFERROR(MATCH(9,$AB$40:$AB$133,0),0))) -> 540.69 | I22: =IF(IFERROR(MATCH(9,$AB$40:$AB$133,0),0)=0,"",INDEX($Z$40:$Z$133,IFERROR(MATCH(9,$AB$40:$AB$133,0),0))) -> 1083.39 | J22: =IF(IFERROR(MATCH(9,$AB$40:$AB$133,0),0)=0,"",INDEX($AC$40:$AC$133,IFERROR(MATCH(9,$AB$40:$AB$133,0),0))) -> Sobrando | K22: =IF(IFERROR(MATCH(9,$AB$40:$AB$133,0),0)=0,"",INDEX($AD$40:$AD$133,IFERROR(MATCH(9,$AB$40:$AB$133,0),0))) -> 15 | L22: =IF(IFERROR(MATCH(9,$AB$40:$AB$133,0),0)=0,"",IF(INDEX($BB$40:$BB$133,IFERROR(MATCH(9,$AB$40:$AB$133,0),0))>=99999,"",INDEX($BB$40:$BB$133,IFERROR(MATCH(9,$AB$40:$AB$133,0),0)))) -> 46275 | M22: =IF(IFERROR(MATCH(9,$AB$40:$AB$133,0),0)=0,"",IF(INDEX($BC$40:$BC$133,IFERROR(MATCH(9,$AB$40:$AB$133,0),0))=0,"",INDEX($BC$40:$BC$133,IFERROR(MATCH(9,$AB$40:$AB$133,0),0)))) -> 46286 | N22: =IF(IFERROR(MATCH(9,$AB$40:$AB$133,0),0)=0,"",INDEX($AE$40:$AE$133,IFERROR(MATCH(9,$AB$40:$AB$133,0),0))&"") -> Explica em parte: estoque antigo 18.1 + doca/transferência 502.5; faltam 562.8 a explicar | O22: =IF(IFERROR(MATCH(9,$AB$40:$AB$133,0),0)=0,"",INDEX($BD$40:$BD$133,IFERROR(MATCH(9,$AB$40:$AB$133,0),0))&"") -> Confirmar saldo de 08/09 e OTs de doca; contar o lote para os 562.8 KG restantes e ajustar a sobra se confirmada | AS22: CHK-D-413 | AU22: 46295 | AV22: =IFERROR(INDEX($AX$1:$AX$94,MATCH(21,$AY$1:$AY$94,0)),"") -> 260416102 | AW22: 823NV-595 | AX22: 261376101 | AY22: =IF(OR($A$5="Todos",AW22=$A$5),MAX(AY$1:AY21)+1,0) -> 22
A23: =IF(IFERROR(MATCH(10,$AB$40:$AB$133,0),0)=0,"",INDEX($T$40:$T$133,IFERROR(MATCH(10,$AB$40:$AB$133,0),0))) -> CW2-BR-25A | B23: =IF(IFERROR(MATCH(10,$AB$40:$AB$133,0),0)=0,"",INDEX($AG$40:$AG$133,IFERROR(MATCH(10,$AB$40:$AB$133,0),0))) -> 253470301 | C23: =IF(IFERROR(MATCH(10,$AB$40:$AB$133,0),0)=0,"",INDEX($U$40:$U$133,IFERROR(MATCH(10,$AB$40:$AB$133,0),0))) -> KG | D23: =IF(IFERROR(MATCH(10,$AB$40:$AB$133,0),0)=0,"",INDEX($BH$40:$BH$133,IFERROR(MATCH(10,$AB$40:$AB$133,0),0))) -> 0 | E23: =IF(IFERROR(MATCH(10,$AB$40:$AB$133,0),0)=0,"",INDEX($W$40:$W$133,IFERROR(MATCH(10,$AB$40:$AB$133,0),0))) -> 763.8 | F23: =IF(IFERROR(MATCH(10,$AB$40:$AB$133,0),0)=0,"",INDEX($X$40:$X$133,IFERROR(MATCH(10,$AB$40:$AB$133,0),0))) -> 924.6 | G23: =IF(A23="","",D23+E23-F23) -> -160.8 | H23: =IF(IFERROR(MATCH(10,$AB$40:$AB$133,0),0)=0,"",INDEX($Y$40:$Y$133,IFERROR(MATCH(10,$AB$40:$AB$133,0),0))) -> 763.8 | I23: =IF(IFERROR(MATCH(10,$AB$40:$AB$133,0),0)=0,"",INDEX($Z$40:$Z$133,IFERROR(MATCH(10,$AB$40:$AB$133,0),0))) -> 924.6 | J23: =IF(IFERROR(MATCH(10,$AB$40:$AB$133,0),0)=0,"",INDEX($AC$40:$AC$133,IFERROR(MATCH(10,$AB$40:$AB$133,0),0))) -> Sobrando | K23: =IF(IFERROR(MATCH(10,$AB$40:$AB$133,0),0)=0,"",INDEX($AD$40:$AD$133,IFERROR(MATCH(10,$AB$40:$AB$133,0),0))) -> 12 | L23: =IF(IFERROR(MATCH(10,$AB$40:$AB$133,0),0)=0,"",IF(INDEX($BB$40:$BB$133,IFERROR(MATCH(10,$AB$40:$AB$133,0),0))>=99999,"",INDEX($BB$40:$BB$133,IFERROR(MATCH(10,$AB$40:$AB$133,0),0)))) -> 46275 | M23: =IF(IFERROR(MATCH(10,$AB$40:$AB$133,0),0)=0,"",IF(INDEX($BC$40:$BC$133,IFERROR(MATCH(10,$AB$40:$AB$133,0),0))=0,"",INDEX($BC$40:$BC$133,IFERROR(MATCH(10,$AB$40:$AB$133,0),0)))) -> 46293 | N23: =IF(IFERROR(MATCH(10,$AB$40:$AB$133,0),0)=0,"",INDEX($AE$40:$AE$133,IFERROR(MATCH(10,$AB$40:$AB$133,0),0))&"") -> As saídas do período não baixaram o estoque físico | O23: =IF(IFERROR(MATCH(10,$AB$40:$AB$133,0),0)=0,"",INDEX($BD$40:$BD$133,IFERROR(MATCH(10,$AB$40:$AB$133,0),0))&"") -> Confirmar a OT de saída (picking) das remessas para baixar 924.6 KG do estoque físico | AS23: CHK-R30GOLD-BR-25A | AU23: 46296 | AV23: =IFERROR(INDEX($AX$1:$AX$94,MATCH(22,$AY$1:$AY$94,0)),"") -> 261376101 | AW23: BIG-PF-1BO-401 | AX23: 26044019 | AY23: =IF(OR($A$5="Todos",AW23=$A$5),MAX(AY$1:AY22)+1,0) -> 23
A24: =IF(IFERROR(MATCH(11,$AB$40:$AB$133,0),0)=0,"",INDEX($T$40:$T$133,IFERROR(MATCH(11,$AB$40:$AB$133,0),0))) -> CHP-20SICHP-760 | B24: =IF(IFERROR(MATCH(11,$AB$40:$AB$133,0),0)=0,"",INDEX($AG$40:$AG$133,IFERROR(MATCH(11,$AB$40:$AB$133,0),0))) -> 252843369 | C24: =IF(IFERROR(MATCH(11,$AB$40:$AB$133,0),0)=0,"",INDEX($U$40:$U$133,IFERROR(MATCH(11,$AB$40:$AB$133,0),0))) -> KG | D24: =IF(IFERROR(MATCH(11,$AB$40:$AB$133,0),0)=0,"",INDEX($BH$40:$BH$133,IFERROR(MATCH(11,$AB$40:$AB$133,0),0))) -> 0 | E24: =IF(IFERROR(MATCH(11,$AB$40:$AB$133,0),0)=0,"",INDEX($W$40:$W$133,IFERROR(MATCH(11,$AB$40:$AB$133,0),0))) -> 918 | F24: =IF(IFERROR(MATCH(11,$AB$40:$AB$133,0),0)=0,"",INDEX($X$40:$X$133,IFERROR(MATCH(11,$AB$40:$AB$133,0),0))) -> 186 | G24: =IF(A24="","",D24+E24-F24) -> 732 | H24: =IF(IFERROR(MATCH(11,$AB$40:$AB$133,0),0)=0,"",INDEX($Y$40:$Y$133,IFERROR(MATCH(11,$AB$40:$AB$133,0),0))) -> 1272 | I24: =IF(IFERROR(MATCH(11,$AB$40:$AB$133,0),0)=0,"",INDEX($Z$40:$Z$133,IFERROR(MATCH(11,$AB$40:$AB$133,0),0))) -> 540 | J24: =IF(IFERROR(MATCH(11,$AB$40:$AB$133,0),0)=0,"",INDEX($AC$40:$AC$133,IFERROR(MATCH(11,$AB$40:$AB$133,0),0))) -> Sobrando | K24: =IF(IFERROR(MATCH(11,$AB$40:$AB$133,0),0)=0,"",INDEX($AD$40:$AD$133,IFERROR(MATCH(11,$AB$40:$AB$133,0),0))) -> 13 | L24: =IF(IFERROR(MATCH(11,$AB$40:$AB$133,0),0)=0,"",IF(INDEX($BB$40:$BB$133,IFERROR(MATCH(11,$AB$40:$AB$133,0),0))>=99999,"",INDEX($BB$40:$BB$133,IFERROR(MATCH(11,$AB$40:$AB$133,0),0)))) -> 46275 | M24: =IF(IFERROR(MATCH(11,$AB$40:$AB$133,0),0)=0,"",IF(INDEX($BC$40:$BC$133,IFERROR(MATCH(11,$AB$40:$AB$133,0),0))=0,"",INDEX($BC$40:$BC$133,IFERROR(MATCH(11,$AB$40:$AB$133,0),0)))) -> 46294 | N24: =IF(IFERROR(MATCH(11,$AB$40:$AB$133,0),0)=0,"",INDEX($AE$40:$AE$133,IFERROR(MATCH(11,$AB$40:$AB$133,0),0))&"") -> Explica em parte: estoque antigo 24.0 + doca/transferência 0.0; faltam 516.0 a explicar | O24: =IF(IFERROR(MATCH(11,$AB$40:$AB$133,0),0)=0,"",INDEX($BD$40:$BD$133,IFERROR(MATCH(11,$AB$40:$AB$133,0),0))&"") -> Confirmar saldo de 08/09 e OTs de doca; contar o lote para os 516.0 KG restantes e ajustar a sobra se confirmada | AS24: CHK-R30GOLD-E0-D94 | AV24: =IFERROR(INDEX($AX$1:$AX$94,MATCH(23,$AY$1:$AY$94,0)),"") -> 26044019 | AW24: BIG-PF-1BO-401 | AX24: 26093039 | AY24: =IF(OR($A$5="Todos",AW24=$A$5),MAX(AY$1:AY23)+1,0) -> 24
A25: =IF(IFERROR(MATCH(12,$AB$40:$AB$133,0),0)=0,"",INDEX($T$40:$T$133,IFERROR(MATCH(12,$AB$40:$AB$133,0),0))) -> 70-30-38-BR-25A | B25: =IF(IFERROR(MATCH(12,$AB$40:$AB$133,0),0)=0,"",INDEX($AG$40:$AG$133,IFERROR(MATCH(12,$AB$40:$AB$133,0),0))) -> 260370301 | C25: =IF(IFERROR(MATCH(12,$AB$40:$AB$133,0),0)=0,"",INDEX($U$40:$U$133,IFERROR(MATCH(12,$AB$40:$AB$133,0),0))) -> KG | D25: =IF(IFERROR(MATCH(12,$AB$40:$AB$133,0),0)=0,"",INDEX($BH$40:$BH$133,IFERROR(MATCH(12,$AB$40:$AB$133,0),0))) -> 0 | E25: =IF(IFERROR(MATCH(12,$AB$40:$AB$133,0),0)=0,"",INDEX($W$40:$W$133,IFERROR(MATCH(12,$AB$40:$AB$133,0),0))) -> 603 | F25: =IF(IFERROR(MATCH(12,$AB$40:$AB$133,0),0)=0,"",INDEX($X$40:$X$133,IFERROR(MATCH(12,$AB$40:$AB$133,0),0))) -> 321.6 | G25: =IF(A25="","",D25+E25-F25) -> 281.4 | H25: =IF(IFERROR(MATCH(12,$AB$40:$AB$133,0),0)=0,"",INDEX($Y$40:$Y$133,IFERROR(MATCH(12,$AB$40:$AB$133,0),0))) -> 623.1 | I25: =IF(IFERROR(MATCH(12,$AB$40:$AB$133,0),0)=0,"",INDEX($Z$40:$Z$133,IFERROR(MATCH(12,$AB$40:$AB$133,0),0))) -> 341.7 | J25: =IF(IFERROR(MATCH(12,$AB$40:$AB$133,0),0)=0,"",INDEX($AC$40:$AC$133,IFERROR(MATCH(12,$AB$40:$AB$133,0),0))) -> Sobrando | K25: =IF(IFERROR(MATCH(12,$AB$40:$AB$133,0),0)=0,"",INDEX($AD$40:$AD$133,IFERROR(MATCH(12,$AB$40:$AB$133,0),0))) -> 13 | L25: =IF(IFERROR(MATCH(12,$AB$40:$AB$133,0),0)=0,"",IF(INDEX($BB$40:$BB$133,IFERROR(MATCH(12,$AB$40:$AB$133,0),0))>=99999,"",INDEX($BB$40:$BB$133,IFERROR(MATCH(12,$AB$40:$AB$133,0),0)))) -> 46275 | M25: =IF(IFERROR(MATCH(12,$AB$40:$AB$133,0),0)=0,"",IF(INDEX($BC$40:$BC$133,IFERROR(MATCH(12,$AB$40:$AB$133,0),0))=0,"",INDEX($BC$40:$BC$133,IFERROR(MATCH(12,$AB$40:$AB$133,0),0)))) -> 46295 | N25: =IF(IFERROR(MATCH(12,$AB$40:$AB$133,0),0)=0,"",INDEX($AE$40:$AE$133,IFERROR(MATCH(12,$AB$40:$AB$133,0),0))&"") -> Estoque antigo/doca + saídas do período que não baixaram o estoque físico | O25: =IF(IFERROR(MATCH(12,$AB$40:$AB$133,0),0)=0,"",INDEX($BD$40:$BD$133,IFERROR(MATCH(12,$AB$40:$AB$133,0),0))&"") -> Confirmar a OT de saída (picking) das remessas para baixar 321.6 KG do estoque físico; conferir também estoque antigo/doca | AS25: CHK-W-413 | AV25: =IFERROR(INDEX($AX$1:$AX$94,MATCH(24,$AY$1:$AY$94,0)),"") -> 26093039 | AW25: BIG-PF-1BO-401 | AX25: 26126039 | AY25: =IF(OR($A$5="Todos",AW25=$A$5),MAX(AY$1:AY24)+1,0) -> 25
A26: =IF(IFERROR(MATCH(13,$AB$40:$AB$133,0),0)=0,"",INDEX($T$40:$T$133,IFERROR(MATCH(13,$AB$40:$AB$133,0),0))) -> 811-BR-25A | B26: =IF(IFERROR(MATCH(13,$AB$40:$AB$133,0),0)=0,"",INDEX($AG$40:$AG$133,IFERROR(MATCH(13,$AB$40:$AB$133,0),0))) -> 250880301 | C26: =IF(IFERROR(MATCH(13,$AB$40:$AB$133,0),0)=0,"",INDEX($U$40:$U$133,IFERROR(MATCH(13,$AB$40:$AB$133,0),0))) -> KG | D26: =IF(IFERROR(MATCH(13,$AB$40:$AB$133,0),0)=0,"",INDEX($BH$40:$BH$133,IFERROR(MATCH(13,$AB$40:$AB$133,0),0))) -> 0 | E26: =IF(IFERROR(MATCH(13,$AB$40:$AB$133,0),0)=0,"",INDEX($W$40:$W$133,IFERROR(MATCH(13,$AB$40:$AB$133,0),0))) -> 180.9 | F26: =IF(IFERROR(MATCH(13,$AB$40:$AB$133,0),0)=0,"",INDEX($X$40:$X$133,IFERROR(MATCH(13,$AB$40:$AB$133,0),0))) -> 180.9 | G26: =IF(A26="","",D26+E26-F26) -> 0 | H26: =IF(IFERROR(MATCH(13,$AB$40:$AB$133,0),0)=0,"",INDEX($Y$40:$Y$133,IFERROR(MATCH(13,$AB$40:$AB$133,0),0))) -> 273.36 | I26: =IF(IFERROR(MATCH(13,$AB$40:$AB$133,0),0)=0,"",INDEX($Z$40:$Z$133,IFERROR(MATCH(13,$AB$40:$AB$133,0),0))) -> 273.36 | J26: =IF(IFERROR(MATCH(13,$AB$40:$AB$133,0),0)=0,"",INDEX($AC$40:$AC$133,IFERROR(MATCH(13,$AB$40:$AB$133,0),0))) -> Sobrando | K26: =IF(IFERROR(MATCH(13,$AB$40:$AB$133,0),0)=0,"",INDEX($AD$40:$AD$133,IFERROR(MATCH(13,$AB$40:$AB$133,0),0))) -> 5 | L26: =IF(IFERROR(MATCH(13,$AB$40:$AB$133,0),0)=0,"",IF(INDEX($BB$40:$BB$133,IFERROR(MATCH(13,$AB$40:$AB$133,0),0))>=99999,"",INDEX($BB$40:$BB$133,IFERROR(MATCH(13,$AB$40:$AB$133,0),0)))) -> 46276 | M26: =IF(IFERROR(MATCH(13,$AB$40:$AB$133,0),0)=0,"",IF(INDEX($BC$40:$BC$133,IFERROR(MATCH(13,$AB$40:$AB$133,0),0))=0,"",INDEX($BC$40:$BC$133,IFERROR(MATCH(13,$AB$40:$AB$133,0),0)))) -> 46288 | N26: =IF(IFERROR(MATCH(13,$AB$40:$AB$133,0),0)=0,"",INDEX($AE$40:$AE$133,IFERROR(MATCH(13,$AB$40:$AB$133,0),0))&"") -> Estoque antigo: toda a sobra está em posições sem movimento desde antes de 09/09 | O26: =IF(IFERROR(MATCH(13,$AB$40:$AB$133,0),0)=0,"",INDEX($BD$40:$BD$133,IFERROR(MATCH(13,$AB$40:$AB$133,0),0))&"") -> Confirmar no SAP o saldo de 08/09 (273.4 KG). Se estiver certo, não há ajuste | AS26: CHM-BS-9U15-E0-07B | AV26: =IFERROR(INDEX($AX$1:$AX$94,MATCH(25,$AY$1:$AY$94,0)),"") -> 26126039 | AW26: CHD-BB-308BY-357 | AX26: 250827800 | AY26: =IF(OR($A$5="Todos",AW26=$A$5),MAX(AY$1:AY25)+1,0) -> 26
A27: =IF(IFERROR(MATCH(14,$AB$40:$AB$133,0),0)=0,"",INDEX($T$40:$T$133,IFERROR(MATCH(14,$AB$40:$AB$133,0),0))) -> CHM-BS-9U15-E0-07B | B27: =IF(IFERROR(MATCH(14,$AB$40:$AB$133,0),0)=0,"",INDEX($AG$40:$AG$133,IFERROR(MATCH(14,$AB$40:$AB$133,0),0))) -> 260701069 | C27: =IF(IFERROR(MATCH(14,$AB$40:$AB$133,0),0)=0,"",INDEX($U$40:$U$133,IFERROR(MATCH(14,$AB$40:$AB$133,0),0))) -> KG | D27: =IF(IFERROR(MATCH(14,$AB$40:$AB$133,0),0)=0,"",INDEX($BH$40:$BH$133,IFERROR(MATCH(14,$AB$40:$AB$133,0),0))) -> 0 | E27: =IF(IFERROR(MATCH(14,$AB$40:$AB$133,0),0)=0,"",INDEX($W$40:$W$133,IFERROR(MATCH(14,$AB$40:$AB$133,0),0))) -> 960 | F27: =IF(IFERROR(MATCH(14,$AB$40:$AB$133,0),0)=0,"",INDEX($X$40:$X$133,IFERROR(MATCH(14,$AB$40:$AB$133,0),0))) -> 176 | G27: =IF(A27="","",D27+E27-F27) -> 784 | H27: =IF(IFERROR(MATCH(14,$AB$40:$AB$133,0),0)=0,"",INDEX($Y$40:$Y$133,IFERROR(MATCH(14,$AB$40:$AB$133,0),0))) -> 1032 | I27: =IF(IFERROR(MATCH(14,$AB$40:$AB$133,0),0)=0,"",INDEX($Z$40:$Z$133,IFERROR(MATCH(14,$AB$40:$AB$133,0),0))) -> 248 | J27: =IF(IFERROR(MATCH(14,$AB$40:$AB$133,0),0)=0,"",INDEX($AC$40:$AC$133,IFERROR(MATCH(14,$AB$40:$AB$133,0),0))) -> Sobrando | K27: =IF(IFERROR(MATCH(14,$AB$40:$AB$133,0),0)=0,"",INDEX($AD$40:$AD$133,IFERROR(MATCH(14,$AB$40:$AB$133,0),0))) -> 20 | L27: =IF(IFERROR(MATCH(14,$AB$40:$AB$133,0),0)=0,"",IF(INDEX($BB$40:$BB$133,IFERROR(MATCH(14,$AB$40:$AB$133,0),0))>=99999,"",INDEX($BB$40:$BB$133,IFERROR(MATCH(14,$AB$40:$AB$133,0),0)))) -> 46275 | M27: =IF(IFERROR(MATCH(14,$AB$40:$AB$133,0),0)=0,"",IF(INDEX($BC$40:$BC$133,IFERROR(MATCH(14,$AB$40:$AB$133,0),0))=0,"",INDEX($BC$40:$BC$133,IFERROR(MATCH(14,$AB$40:$AB$133,0),0)))) -> 46295 | N27: =IF(IFERROR(MATCH(14,$AB$40:$AB$133,0),0)=0,"",INDEX($AE$40:$AE$133,IFERROR(MATCH(14,$AB$40:$AB$133,0),0))&"") -> Estoque acima do esperado: entrada não lançada ou saldo anterior ao período | O27: =IF(IFERROR(MATCH(14,$AB$40:$AB$133,0),0)=0,"",INDEX($BD$40:$BD$133,IFERROR(MATCH(14,$AB$40:$AB$133,0),0))&"") -> Confirmar saldo de 08/09; se não existir, contar o lote e lançar ajuste de inventário de +248.0 KG | AS27: CHM-CU-7X80-E5-U70 | AV27: =IFERROR(INDEX($AX$1:$AX$94,MATCH(26,$AY$1:$AY$94,0)),"") -> 250827800 | AW27: CHD-BB-308BY-357 | AX27: 2529678000 | AY27: =IF(OR($A$5="Todos",AW27=$A$5),MAX(AY$1:AY26)+1,0) -> 27
A28: =IF(IFERROR(MATCH(15,$AB$40:$AB$133,0),0)=0,"",INDEX($T$40:$T$133,IFERROR(MATCH(15,$AB$40:$AB$133,0),0))) -> 70-30-38-BR-D94 | B28: =IF(IFERROR(MATCH(15,$AB$40:$AB$133,0),0)=0,"",INDEX($AG$40:$AG$133,IFERROR(MATCH(15,$AB$40:$AB$133,0),0))) -> 253213449 | C28: =IF(IFERROR(MATCH(15,$AB$40:$AB$133,0),0)=0,"",INDEX($U$40:$U$133,IFERROR(MATCH(15,$AB$40:$AB$133,0),0))) -> KG | D28: =IF(IFERROR(MATCH(15,$AB$40:$AB$133,0),0)=0,"",INDEX($BH$40:$BH$133,IFERROR(MATCH(15,$AB$40:$AB$133,0),0))) -> 0 | E28: =IF(IFERROR(MATCH(15,$AB$40:$AB$133,0),0)=0,"",INDEX($W$40:$W$133,IFERROR(MATCH(15,$AB$40:$AB$133,0),0))) -> 940.8 | F28: =IF(IFERROR(MATCH(15,$AB$40:$AB$133,0),0)=0,"",INDEX($X$40:$X$133,IFERROR(MATCH(15,$AB$40:$AB$133,0),0))) -> 781.2 | G28: =IF(A28="","",D28+E28-F28) -> 159.6 | H28: =IF(IFERROR(MATCH(15,$AB$40:$AB$133,0),0)=0,"",INDEX($Y$40:$Y$133,IFERROR(MATCH(15,$AB$40:$AB$133,0),0))) -> 333.2 | I28: =IF(IFERROR(MATCH(15,$AB$40:$AB$133,0),0)=0,"",INDEX($Z$40:$Z$133,IFERROR(MATCH(15,$AB$40:$AB$133,0),0))) -> 173.6 | J28: =IF(IFERROR(MATCH(15,$AB$40:$AB$133,0),0)=0,"",INDEX($AC$40:$AC$133,IFERROR(MATCH(15,$AB$40:$AB$133,0),0))) -> Sobrando | K28: =IF(IFERROR(MATCH(15,$AB$40:$AB$133,0),0)=0,"",INDEX($AD$40:$AD$133,IFERROR(MATCH(15,$AB$40:$AB$133,0),0))) -> 26 | L28: =IF(IFERROR(MATCH(15,$AB$40:$AB$133,0),0)=0,"",IF(INDEX($BB$40:$BB$133,IFERROR(MATCH(15,$AB$40:$AB$133,0),0))>=99999,"",INDEX($BB$40:$BB$133,IFERROR(MATCH(15,$AB$40:$AB$133,0),0)))) -> 46275 | M28: =IF(IFERROR(MATCH(15,$AB$40:$AB$133,0),0)=0,"",IF(INDEX($BC$40:$BC$133,IFERROR(MATCH(15,$AB$40:$AB$133,0),0))=0,"",INDEX($BC$40:$BC$133,IFERROR(MATCH(15,$AB$40:$AB$133,0),0)))) -> 46296 | N28: =IF(IFERROR(MATCH(15,$AB$40:$AB$133,0),0)=0,"",INDEX($AE$40:$AE$133,IFERROR(MATCH(15,$AB$40:$AB$133,0),0))&"") -> Estoque antigo/doca + saídas pelo depósito 0355 que não baixaram o estoque físico | O28: =IF(IFERROR(MATCH(15,$AB$40:$AB$133,0),0)=0,"",INDEX($BD$40:$BD$133,IFERROR(MATCH(15,$AB$40:$AB$133,0),0))&"") -> Confirmar a OT de saída (picking) das remessas para baixar 162.4 KG do estoque físico; conferir também estoque antigo/doca | AS28: CHM-Q41ALUN-2B-U73 | AV28: =IFERROR(INDEX($AX$1:$AX$94,MATCH(27,$AY$1:$AY$94,0)),"") -> 2529678000 | AW28: CHD-BB-308BY-357 | AX28: 2529778000 | AY28: =IF(OR($A$5="Todos",AW28=$A$5),MAX(AY$1:AY27)+1,0) -> 28
A29: =IF(IFERROR(MATCH(16,$AB$40:$AB$133,0),0)=0,"",INDEX($T$40:$T$133,IFERROR(MATCH(16,$AB$40:$AB$133,0),0))) -> CW2-BR-25A | B29: =IF(IFERROR(MATCH(16,$AB$40:$AB$133,0),0)=0,"",INDEX($AG$40:$AG$133,IFERROR(MATCH(16,$AB$40:$AB$133,0),0))) -> 252650301 | C29: =IF(IFERROR(MATCH(16,$AB$40:$AB$133,0),0)=0,"",INDEX($U$40:$U$133,IFERROR(MATCH(16,$AB$40:$AB$133,0),0))) -> KG | D29: =IF(IFERROR(MATCH(16,$AB$40:$AB$133,0),0)=0,"",INDEX($BH$40:$BH$133,IFERROR(MATCH(16,$AB$40:$AB$133,0),0))) -> 0 | E29: =IF(IFERROR(MATCH(16,$AB$40:$AB$133,0),0)=0,"",INDEX($W$40:$W$133,IFERROR(MATCH(16,$AB$40:$AB$133,0),0))) -> 2271.3 | F29: =IF(IFERROR(MATCH(16,$AB$40:$AB$133,0),0)=0,"",INDEX($X$40:$X$133,IFERROR(MATCH(16,$AB$40:$AB$133,0),0))) -> 562.8 | G29: =IF(A29="","",D29+E29-F29) -> 1708.5 | H29: =IF(IFERROR(MATCH(16,$AB$40:$AB$133,0),0)=0,"",INDEX($Y$40:$Y$133,IFERROR(MATCH(16,$AB$40:$AB$133,0),0))) -> 1829.1 | I29: =IF(IFERROR(MATCH(16,$AB$40:$AB$133,0),0)=0,"",INDEX($Z$40:$Z$133,IFERROR(MATCH(16,$AB$40:$AB$133,0),0))) -> 120.6 | J29: =IF(IFERROR(MATCH(16,$AB$40:$AB$133,0),0)=0,"",INDEX($AC$40:$AC$133,IFERROR(MATCH(16,$AB$40:$AB$133,0),0))) -> Sobrando | K29: =IF(IFERROR(MATCH(16,$AB$40:$AB$133,0),0)=0,"",INDEX($AD$40:$AD$133,IFERROR(MATCH(16,$AB$40:$AB$133,0),0))) -> 15 | L29: =IF(IFERROR(MATCH(16,$AB$40:$AB$133,0),0)=0,"",IF(INDEX($BB$40:$BB$133,IFERROR(MATCH(16,$AB$40:$AB$133,0),0))>=99999,"",INDEX($BB$40:$BB$133,IFERROR(MATCH(16,$AB$40:$AB$133,0),0)))) -> 46275 | M29: =IF(IFERROR(MATCH(16,$AB$40:$AB$133,0),0)=0,"",IF(INDEX($BC$40:$BC$133,IFERROR(MATCH(16,$AB$40:$AB$133,0),0))=0,"",INDEX($BC$40:$BC$133,IFERROR(MATCH(16,$AB$40:$AB$133,0),0)))) -> 46295 | N29: =IF(IFERROR(MATCH(16,$AB$40:$AB$133,0),0)=0,"",INDEX($AE$40:$AE$133,IFERROR(MATCH(16,$AB$40:$AB$133,0),0))&"") -> Explica em parte: estoque antigo 0.0 + doca/transferência 20.1; faltam 100.5 a explicar | O29: =IF(IFERROR(MATCH(16,$AB$40:$AB$133,0),0)=0,"",INDEX($BD$40:$BD$133,IFERROR(MATCH(16,$AB$40:$AB$133,0),0))&"") -> Confirmar saldo de 08/09 e OTs de doca; contar o lote para os 100.5 KG restantes e ajustar a sobra se confirmada | AS29: CHM-SP-Z3L-BR-U73 | AV29: =IFERROR(INDEX($AX$1:$AX$94,MATCH(28,$AY$1:$AY$94,0)),"") -> 2529778000 | AW29: CHD-BB-308BY-357 | AX29: 2609078000 | AY29: =IF(OR($A$5="Todos",AW29=$A$5),MAX(AY$1:AY28)+1,0) -> 29
A30: =IF(IFERROR(MATCH(17,$AB$40:$AB$133,0),0)=0,"",INDEX($T$40:$T$133,IFERROR(MATCH(17,$AB$40:$AB$133,0),0))) -> CHK-R30GOLD-BR-25A | B30: =IF(IFERROR(MATCH(17,$AB$40:$AB$133,0),0)=0,"",INDEX($AG$40:$AG$133,IFERROR(MATCH(17,$AB$40:$AB$133,0),0))) -> 253620301 | C30: =IF(IFERROR(MATCH(17,$AB$40:$AB$133,0),0)=0,"",INDEX($U$40:$U$133,IFERROR(MATCH(17,$AB$40:$AB$133,0),0))) -> KG | D30: =IF(IFERROR(MATCH(17,$AB$40:$AB$133,0),0)=0,"",INDEX($BH$40:$BH$133,IFERROR(MATCH(17,$AB$40:$AB$133,0),0))) -> 0 | E30: =IF(IFERROR(MATCH(17,$AB$40:$AB$133,0),0)=0,"",INDEX($W$40:$W$133,IFERROR(MATCH(17,$AB$40:$AB$133,0),0))) -> 40.2 | F30: =IF(IFERROR(MATCH(17,$AB$40:$AB$133,0),0)=0,"",INDEX($X$40:$X$133,IFERROR(MATCH(17,$AB$40:$AB$133,0),0))) -> 40.2 | G30: =IF(A30="","",D30+E30-F30) -> 0 | H30: =IF(IFERROR(MATCH(17,$AB$40:$AB$133,0),0)=0,"",INDEX($Y$40:$Y$133,IFERROR(MATCH(17,$AB$40:$AB$133,0),0))) -> 116.58 | I30: =IF(IFERROR(MATCH(17,$AB$40:$AB$133,0),0)=0,"",INDEX($Z$40:$Z$133,IFERROR(MATCH(17,$AB$40:$AB$133,0),0))) -> 116.58 | J30: =IF(IFERROR(MATCH(17,$AB$40:$AB$133,0),0)=0,"",INDEX($AC$40:$AC$133,IFERROR(MATCH(17,$AB$40:$AB$133,0),0))) -> Sobrando | K30: =IF(IFERROR(MATCH(17,$AB$40:$AB$133,0),0)=0,"",INDEX($AD$40:$AD$133,IFERROR(MATCH(17,$AB$40:$AB$133,0),0))) -> 3 | L30: =IF(IFERROR(MATCH(17,$AB$40:$AB$133,0),0)=0,"",IF(INDEX($BB$40:$BB$133,IFERROR(MATCH(17,$AB$40:$AB$133,0),0))>=99999,"",INDEX($BB$40:$BB$133,IFERROR(MATCH(17,$AB$40:$AB$133,0),0)))) -> 46291 | M30: =IF(IFERROR(MATCH(17,$AB$40:$AB$133,0),0)=0,"",IF(INDEX($BC$40:$BC$133,IFERROR(MATCH(17,$AB$40:$AB$133,0),0))=0,"",INDEX($BC$40:$BC$133,IFERROR(MATCH(17,$AB$40:$AB$133,0),0)))) -> 46294 | N30: =IF(IFERROR(MATCH(17,$AB$40:$AB$133,0),0)=0,"",INDEX($AE$40:$AE$133,IFERROR(MATCH(17,$AB$40:$AB$133,0),0))&"") -> Estoque antigo + quantidade em doca/chão/transferência | O30: =IF(IFERROR(MATCH(17,$AB$40:$AB$133,0),0)=0,"",INDEX($BD$40:$BD$133,IFERROR(MATCH(17,$AB$40:$AB$133,0),0))&"") -> Confirmar saldo de 08/09 (36.2 KG) e tratar as OTs em doca/transferência (80.4 KG) | AS30: CHM-SP-Z3L-E0-U72 | AV30: =IFERROR(INDEX($AX$1:$AX$94,MATCH(29,$AY$1:$AY$94,0)),"") -> 2609078000 | AW30: CHD-BB-308BY-357 | AX30: 2609178000 | AY30: =IF(OR($A$5="Todos",AW30=$A$5),MAX(AY$1:AY29)+1,0) -> 30
A31: =IF(IFERROR(MATCH(18,$AB$40:$AB$133,0),0)=0,"",INDEX($T$40:$T$133,IFERROR(MATCH(18,$AB$40:$AB$133,0),0))) -> 823-BR-25A | B31: =IF(IFERROR(MATCH(18,$AB$40:$AB$133,0),0)=0,"",INDEX($AG$40:$AG$133,IFERROR(MATCH(18,$AB$40:$AB$133,0),0))) -> 252900303 | C31: =IF(IFERROR(MATCH(18,$AB$40:$AB$133,0),0)=0,"",INDEX($U$40:$U$133,IFERROR(MATCH(18,$AB$40:$AB$133,0),0))) -> KG | D31: =IF(IFERROR(MATCH(18,$AB$40:$AB$133,0),0)=0,"",INDEX($BH$40:$BH$133,IFERROR(MATCH(18,$AB$40:$AB$133,0),0))) -> 0 | E31: =IF(IFERROR(MATCH(18,$AB$40:$AB$133,0),0)=0,"",INDEX($W$40:$W$133,IFERROR(MATCH(18,$AB$40:$AB$133,0),0))) -> 3612 | F31: =IF(IFERROR(MATCH(18,$AB$40:$AB$133,0),0)=0,"",INDEX($X$40:$X$133,IFERROR(MATCH(18,$AB$40:$AB$133,0),0))) -> 80.4 | G31: =IF(A31="","",D31+E31-F31) -> 3531.6 | H31: =IF(IFERROR(MATCH(18,$AB$40:$AB$133,0),0)=0,"",INDEX($Y$40:$Y$133,IFERROR(MATCH(18,$AB$40:$AB$133,0),0))) -> 3612 | I31: =IF(IFERROR(MATCH(18,$AB$40:$AB$133,0),0)=0,"",INDEX($Z$40:$Z$133,IFERROR(MATCH(18,$AB$40:$AB$133,0),0))) -> 80.4 | J31: =IF(IFERROR(MATCH(18,$AB$40:$AB$133,0),0)=0,"",INDEX($AC$40:$AC$133,IFERROR(MATCH(18,$AB$40:$AB$133,0),0))) -> Sobrando | K31: =IF(IFERROR(MATCH(18,$AB$40:$AB$133,0),0)=0,"",INDEX($AD$40:$AD$133,IFERROR(MATCH(18,$AB$40:$AB$133,0),0))) -> 8 | L31: =IF(IFERROR(MATCH(18,$AB$40:$AB$133,0),0)=0,"",IF(INDEX($BB$40:$BB$133,IFERROR(MATCH(18,$AB$40:$AB$133,0),0))>=99999,"",INDEX($BB$40:$BB$133,IFERROR(MATCH(18,$AB$40:$AB$133,0),0)))) -> 46277 | M31: =IF(IFERROR(MATCH(18,$AB$40:$AB$133,0),0)=0,"",IF(INDEX($BC$40:$BC$133,IFERROR(MATCH(18,$AB$40:$AB$133,0),0))=0,"",INDEX($BC$40:$BC$133,IFERROR(MATCH(18,$AB$40:$AB$133,0),0)))) -> 46294 | N31: =IF(IFERROR(MATCH(18,$AB$40:$AB$133,0),0)=0,"",INDEX($AE$40:$AE$133,IFERROR(MATCH(18,$AB$40:$AB$133,0),0))&"") -> As saídas do período não baixaram o estoque físico | O31: =IF(IFERROR(MATCH(18,$AB$40:$AB$133,0),0)=0,"",INDEX($BD$40:$BD$133,IFERROR(MATCH(18,$AB$40:$AB$133,0),0))&"") -> Confirmar a OT de saída (picking) das remessas para baixar 1,119.6 KG do estoque físico; conferir também estoque antigo/doca | AS31: CHM-TS-22351E0-999 | AV31: =IFERROR(INDEX($AX$1:$AX$94,MATCH(30,$AY$1:$AY$94,0)),"") -> 2609178000 | AW31: CHD-BB-308BY-357 | AX31: 2611378000 | AY31: =IF(OR($A$5="Todos",AW31=$A$5),MAX(AY$1:AY30)+1,0) -> 31
A32: =IF(IFERROR(MATCH(19,$AB$40:$AB$133,0),0)=0,"",INDEX($T$40:$T$133,IFERROR(MATCH(19,$AB$40:$AB$133,0),0))) -> CHK-R30GOLD-E0-D94 | B32: =IF(IFERROR(MATCH(19,$AB$40:$AB$133,0),0)=0,"",INDEX($AG$40:$AG$133,IFERROR(MATCH(19,$AB$40:$AB$133,0),0))) -> 260720939 | C32: =IF(IFERROR(MATCH(19,$AB$40:$AB$133,0),0)=0,"",INDEX($U$40:$U$133,IFERROR(MATCH(19,$AB$40:$AB$133,0),0))) -> KG | D32: =IF(IFERROR(MATCH(19,$AB$40:$AB$133,0),0)=0,"",INDEX($BH$40:$BH$133,IFERROR(MATCH(19,$AB$40:$AB$133,0),0))) -> 0 | E32: =IF(IFERROR(MATCH(19,$AB$40:$AB$133,0),0)=0,"",INDEX($W$40:$W$133,IFERROR(MATCH(19,$AB$40:$AB$133,0),0))) -> 806.4 | F32: =IF(IFERROR(MATCH(19,$AB$40:$AB$133,0),0)=0,"",INDEX($X$40:$X$133,IFERROR(MATCH(19,$AB$40:$AB$133,0),0))) -> 53.2 | G32: =IF(A32="","",D32+E32-F32) -> 753.2 | H32: =IF(IFERROR(MATCH(19,$AB$40:$AB$133,0),0)=0,"",INDEX($Y$40:$Y$133,IFERROR(MATCH(19,$AB$40:$AB$133,0),0))) -> 825.999 | I32: =IF(IFERROR(MATCH(19,$AB$40:$AB$133,0),0)=0,"",INDEX($Z$40:$Z$133,IFERROR(MATCH(19,$AB$40:$AB$133,0),0))) -> 72.799 | J32: =IF(IFERROR(MATCH(19,$AB$40:$AB$133,0),0)=0,"",INDEX($AC$40:$AC$133,IFERROR(MATCH(19,$AB$40:$AB$133,0),0))) -> Sobrando | K32: =IF(IFERROR(MATCH(19,$AB$40:$AB$133,0),0)=0,"",INDEX($AD$40:$AD$133,IFERROR(MATCH(19,$AB$40:$AB$133,0),0))) -> 7 | L32: =IF(IFERROR(MATCH(19,$AB$40:$AB$133,0),0)=0,"",IF(INDEX($BB$40:$BB$133,IFERROR(MATCH(19,$AB$40:$AB$133,0),0))>=99999,"",INDEX($BB$40:$BB$133,IFERROR(MATCH(19,$AB$40:$AB$133,0),0)))) -> 46282 | M32: =IF(IFERROR(MATCH(19,$AB$40:$AB$133,0),0)=0,"",IF(INDEX($BC$40:$BC$133,IFERROR(MATCH(19,$AB$40:$AB$133,0),0))=0,"",INDEX($BC$40:$BC$133,IFERROR(MATCH(19,$AB$40:$AB$133,0),0)))) -> 46294 | N32: =IF(IFERROR(MATCH(19,$AB$40:$AB$133,0),0)=0,"",INDEX($AE$40:$AE$133,IFERROR(MATCH(19,$AB$40:$AB$133,0),0))&"") -> Estoque antigo/doca + saídas do período que não baixaram o estoque físico | O32: =IF(IFERROR(MATCH(19,$AB$40:$AB$133,0),0)=0,"",INDEX($BD$40:$BD$133,IFERROR(MATCH(19,$AB$40:$AB$133,0),0))&"") -> Confirmar a OT de saída (picking) das remessas para baixar 53.2 KG do estoque físico; conferir também estoque antigo/doca | AS32: CHM-TS-P23-E0-999 | AV32: =IFERROR(INDEX($AX$1:$AX$94,MATCH(31,$AY$1:$AY$94,0)),"") -> 2611378000 | AW32: CHD-DR-75Y5-E1-U68 | AX32: 252810301 | AY32: =IF(OR($A$5="Todos",AW32=$A$5),MAX(AY$1:AY31)+1,0) -> 32
A33: =IF(IFERROR(MATCH(20,$AB$40:$AB$133,0),0)=0,"",INDEX($T$40:$T$133,IFERROR(MATCH(20,$AB$40:$AB$133,0),0))) -> CHM-CU-7X80-E5-U70 | B33: =IF(IFERROR(MATCH(20,$AB$40:$AB$133,0),0)=0,"",INDEX($AG$40:$AG$133,IFERROR(MATCH(20,$AB$40:$AB$133,0),0))) -> 2528749307 | C33: =IF(IFERROR(MATCH(20,$AB$40:$AB$133,0),0)=0,"",INDEX($U$40:$U$133,IFERROR(MATCH(20,$AB$40:$AB$133,0),0))) -> KG | D33: =IF(IFERROR(MATCH(20,$AB$40:$AB$133,0),0)=0,"",INDEX($BH$40:$BH$133,IFERROR(MATCH(20,$AB$40:$AB$133,0),0))) -> 0 | E33: =IF(IFERROR(MATCH(20,$AB$40:$AB$133,0),0)=0,"",INDEX($W$40:$W$133,IFERROR(MATCH(20,$AB$40:$AB$133,0),0))) -> 10 | F33: =IF(IFERROR(MATCH(20,$AB$40:$AB$133,0),0)=0,"",INDEX($X$40:$X$133,IFERROR(MATCH(20,$AB$40:$AB$133,0),0))) -> 60 | G33: =IF(A33="","",D33+E33-F33) -> -50 | H33: =IF(IFERROR(MATCH(20,$AB$40:$AB$133,0),0)=0,"",INDEX($Y$40:$Y$133,IFERROR(MATCH(20,$AB$40:$AB$133,0),0))) -> 10 | I33: =IF(IFERROR(MATCH(20,$AB$40:$AB$133,0),0)=0,"",INDEX($Z$40:$Z$133,IFERROR(MATCH(20,$AB$40:$AB$133,0),0))) -> 60 | J33: =IF(IFERROR(MATCH(20,$AB$40:$AB$133,0),0)=0,"",INDEX($AC$40:$AC$133,IFERROR(MATCH(20,$AB$40:$AB$133,0),0))) -> Sobrando | K33: =IF(IFERROR(MATCH(20,$AB$40:$AB$133,0),0)=0,"",INDEX($AD$40:$AD$133,IFERROR(MATCH(20,$AB$40:$AB$133,0),0))) -> 3 | L33: =IF(IFERROR(MATCH(20,$AB$40:$AB$133,0),0)=0,"",IF(INDEX($BB$40:$BB$133,IFERROR(MATCH(20,$AB$40:$AB$133,0),0))>=99999,"",INDEX($BB$40:$BB$133,IFERROR(MATCH(20,$AB$40:$AB$133,0),0)))) -> 46291 | M33: =IF(IFERROR(MATCH(20,$AB$40:$AB$133,0),0)=0,"",IF(INDEX($BC$40:$BC$133,IFERROR(MATCH(20,$AB$40:$AB$133,0),0))=0,"",INDEX($BC$40:$BC$133,IFERROR(MATCH(20,$AB$40:$AB$133,0),0)))) -> 46295 | N33: =IF(IFERROR(MATCH(20,$AB$40:$AB$133,0),0)=0,"",INDEX($AE$40:$AE$133,IFERROR(MATCH(20,$AB$40:$AB$133,0),0))&"") -> As saídas do período não baixaram o estoque físico | O33: =IF(IFERROR(MATCH(20,$AB$40:$AB$133,0),0)=0,"",INDEX($BD$40:$BD$133,IFERROR(MATCH(20,$AB$40:$AB$133,0),0))&"") -> Confirmar a OT de saída (picking) das remessas para baixar 50.0 KG do estoque físico; conferir também estoque antigo/doca | AS33: CHM-VR-Z3S-E0-U68 | AV33: =IFERROR(INDEX($AX$1:$AX$94,MATCH(32,$AY$1:$AY$94,0)),"") -> 252810301 | AW33: CHD-SP-1M-2B-U77 | AX33: 260880101 | AY33: =IF(OR($A$5="Todos",AW33=$A$5),MAX(AY$1:AY32)+1,0) -> 33
A34: =IF(IFERROR(MATCH(21,$AB$40:$AB$133,0),0)=0,"",INDEX($T$40:$T$133,IFERROR(MATCH(21,$AB$40:$AB$133,0),0))) -> CW2-BR-25A | B34: =IF(IFERROR(MATCH(21,$AB$40:$AB$133,0),0)=0,"",INDEX($AG$40:$AG$133,IFERROR(MATCH(21,$AB$40:$AB$133,0),0))) -> 252350301 | C34: =IF(IFERROR(MATCH(21,$AB$40:$AB$133,0),0)=0,"",INDEX($U$40:$U$133,IFERROR(MATCH(21,$AB$40:$AB$133,0),0))) -> KG | D34: =IF(IFERROR(MATCH(21,$AB$40:$AB$133,0),0)=0,"",INDEX($BH$40:$BH$133,IFERROR(MATCH(21,$AB$40:$AB$133,0),0))) -> 0 | E34: =IF(IFERROR(MATCH(21,$AB$40:$AB$133,0),0)=0,"",INDEX($W$40:$W$133,IFERROR(MATCH(21,$AB$40:$AB$133,0),0))) -> 602.9 | F34: =IF(IFERROR(MATCH(21,$AB$40:$AB$133,0),0)=0,"",INDEX($X$40:$X$133,IFERROR(MATCH(21,$AB$40:$AB$133,0),0))) -> 301.5 | G34: =IF(A34="","",D34+E34-F34) -> 301.4 | H34: =IF(IFERROR(MATCH(21,$AB$40:$AB$133,0),0)=0,"",INDEX($Y$40:$Y$133,IFERROR(MATCH(21,$AB$40:$AB$133,0),0))) -> 321.5 | I34: =IF(IFERROR(MATCH(21,$AB$40:$AB$133,0),0)=0,"",INDEX($Z$40:$Z$133,IFERROR(MATCH(21,$AB$40:$AB$133,0),0))) -> 20.1 | J34: =IF(IFERROR(MATCH(21,$AB$40:$AB$133,0),0)=0,"",INDEX($AC$40:$AC$133,IFERROR(MATCH(21,$AB$40:$AB$133,0),0))) -> Sobrando | K34: =IF(IFERROR(MATCH(21,$AB$40:$AB$133,0),0)=0,"",INDEX($AD$40:$AD$133,IFERROR(MATCH(21,$AB$40:$AB$133,0),0))) -> 5 | L34: =IF(IFERROR(MATCH(21,$AB$40:$AB$133,0),0)=0,"",IF(INDEX($BB$40:$BB$133,IFERROR(MATCH(21,$AB$40:$AB$133,0),0))>=99999,"",INDEX($BB$40:$BB$133,IFERROR(MATCH(21,$AB$40:$AB$133,0),0)))) -> 46289 | M34: =IF(IFERROR(MATCH(21,$AB$40:$AB$133,0),0)=0,"",IF(INDEX($BC$40:$BC$133,IFERROR(MATCH(21,$AB$40:$AB$133,0),0))=0,"",INDEX($BC$40:$BC$133,IFERROR(MATCH(21,$AB$40:$AB$133,0),0)))) -> 46294 | N34: =IF(IFERROR(MATCH(21,$AB$40:$AB$133,0),0)=0,"",INDEX($AE$40:$AE$133,IFERROR(MATCH(21,$AB$40:$AB$133,0),0))&"") -> Quantidade parada em doca, chão ou transferência: entrega ou devolução não baixada | O34: =IF(IFERROR(MATCH(21,$AB$40:$AB$133,0),0)=0,"",INDEX($BD$40:$BD$133,IFERROR(MATCH(21,$AB$40:$AB$133,0),0))&"") -> Confirmar ou estornar as OTs em doca/transferência (20.1 KG): guardar na posição ou baixar a entrega | AS34: CHM-VR-Z3S-E0-U72 | AV34: =IFERROR(INDEX($AX$1:$AX$94,MATCH(33,$AY$1:$AY$94,0)),"") -> 260880101 | AW34: CHD-SP-1M-BR-U73 | AX34: 260310301 | AY34: =IF(OR($A$5="Todos",AW34=$A$5),MAX(AY$1:AY33)+1,0) -> 34
A35: =IF(IFERROR(MATCH(22,$AB$40:$AB$133,0),0)=0,"",INDEX($T$40:$T$133,IFERROR(MATCH(22,$AB$40:$AB$133,0),0))) -> 811-BR-25A | B35: =IF(IFERROR(MATCH(22,$AB$40:$AB$133,0),0)=0,"",INDEX($AG$40:$AG$133,IFERROR(MATCH(22,$AB$40:$AB$133,0),0))) -> 252450301 | C35: =IF(IFERROR(MATCH(22,$AB$40:$AB$133,0),0)=0,"",INDEX($U$40:$U$133,IFERROR(MATCH(22,$AB$40:$AB$133,0),0))) -> KG | D35: =IF(IFERROR(MATCH(22,$AB$40:$AB$133,0),0)=0,"",INDEX($BH$40:$BH$133,IFERROR(MATCH(22,$AB$40:$AB$133,0),0))) -> 0 | E35: =IF(IFERROR(MATCH(22,$AB$40:$AB$133,0),0)=0,"",INDEX($W$40:$W$133,IFERROR(MATCH(22,$AB$40:$AB$133,0),0))) -> 2733.6 | F35: =IF(IFERROR(MATCH(22,$AB$40:$AB$133,0),0)=0,"",INDEX($X$40:$X$133,IFERROR(MATCH(22,$AB$40:$AB$133,0),0))) -> 1206 | G35: =IF(A35="","",D35+E35-F35) -> 1527.6 | H35: =IF(IFERROR(MATCH(22,$AB$40:$AB$133,0),0)=0,"",INDEX($Y$40:$Y$133,IFERROR(MATCH(22,$AB$40:$AB$133,0),0))) -> 1547.7 | I35: =IF(IFERROR(MATCH(22,$AB$40:$AB$133,0),0)=0,"",INDEX($Z$40:$Z$133,IFERROR(MATCH(22,$AB$40:$AB$133,0),0))) -> 20.1 | J35: =IF(IFERROR(MATCH(22,$AB$40:$AB$133,0),0)=0,"",INDEX($AC$40:$AC$133,IFERROR(MATCH(22,$AB$40:$AB$133,0),0))) -> Sobrando | K35: =IF(IFERROR(MATCH(22,$AB$40:$AB$133,0),0)=0,"",INDEX($AD$40:$AD$133,IFERROR(MATCH(22,$AB$40:$AB$133,0),0))) -> 7 | L35: =IF(IFERROR(MATCH(22,$AB$40:$AB$133,0),0)=0,"",IF(INDEX($BB$40:$BB$133,IFERROR(MATCH(22,$AB$40:$AB$133,0),0))>=99999,"",INDEX($BB$40:$BB$133,IFERROR(MATCH(22,$AB$40:$AB$133,0),0)))) -> 46294 | M35: =IF(IFERROR(MATCH(22,$AB$40:$AB$133,0),0)=0,"",IF(INDEX($BC$40:$BC$133,IFERROR(MATCH(22,$AB$40:$AB$133,0),0))=0,"",INDEX($BC$40:$BC$133,IFERROR(MATCH(22,$AB$40:$AB$133,0),0)))) -> 46295 | N35: =IF(IFERROR(MATCH(22,$AB$40:$AB$133,0),0)=0,"",INDEX($AE$40:$AE$133,IFERROR(MATCH(22,$AB$40:$AB$133,0),0))&"") -> Estoque antigo: toda a sobra está em posições sem movimento desde antes de 09/09 | O35: =IF(IFERROR(MATCH(22,$AB$40:$AB$133,0),0)=0,"",INDEX($BD$40:$BD$133,IFERROR(MATCH(22,$AB$40:$AB$133,0),0))&"") -> Confirmar no SAP o saldo de 08/09 (20.1 KG). Se estiver certo, não há ajuste | AS35: CHP-20SICHP-760 | AV35: =IFERROR(INDEX($AX$1:$AX$94,MATCH(34,$AY$1:$AY$94,0)),"") -> 260310301 | AW35: CHD-SP-1M-BR-U73 | AX35: 260880301 | AY35: =IF(OR($A$5="Todos",AW35=$A$5),MAX(AY$1:AY34)+1,0) -> 35
A36: =IF(IFERROR(MATCH(23,$AB$40:$AB$133,0),0)=0,"",INDEX($T$40:$T$133,IFERROR(MATCH(23,$AB$40:$AB$133,0),0))) -> W3-BR-25A | B36: =IF(IFERROR(MATCH(23,$AB$40:$AB$133,0),0)=0,"",INDEX($AG$40:$AG$133,IFERROR(MATCH(23,$AB$40:$AB$133,0),0))) -> 261080301 | C36: =IF(IFERROR(MATCH(23,$AB$40:$AB$133,0),0)=0,"",INDEX($U$40:$U$133,IFERROR(MATCH(23,$AB$40:$AB$133,0),0))) -> KG | D36: =IF(IFERROR(MATCH(23,$AB$40:$AB$133,0),0)=0,"",INDEX($BH$40:$BH$133,IFERROR(MATCH(23,$AB$40:$AB$133,0),0))) -> 0 | E36: =IF(IFERROR(MATCH(23,$AB$40:$AB$133,0),0)=0,"",INDEX($W$40:$W$133,IFERROR(MATCH(23,$AB$40:$AB$133,0),0))) -> 3025.7 | F36: =IF(IFERROR(MATCH(23,$AB$40:$AB$133,0),0)=0,"",INDEX($X$40:$X$133,IFERROR(MATCH(23,$AB$40:$AB$133,0),0))) -> 1366.8 | G36: =IF(A36="","",D36+E36-F36) -> 1658.9 | H36: =IF(IFERROR(MATCH(23,$AB$40:$AB$133,0),0)=0,"",INDEX($Y$40:$Y$133,IFERROR(MATCH(23,$AB$40:$AB$133,0),0))) -> 1679 | I36: =IF(IFERROR(MATCH(23,$AB$40:$AB$133,0),0)=0,"",INDEX($Z$40:$Z$133,IFERROR(MATCH(23,$AB$40:$AB$133,0),0))) -> 20.1 | J36: =IF(IFERROR(MATCH(23,$AB$40:$AB$133,0),0)=0,"",INDEX($AC$40:$AC$133,IFERROR(MATCH(23,$AB$40:$AB$133,0),0))) -> Sobrando | K36: =IF(IFERROR(MATCH(23,$AB$40:$AB$133,0),0)=0,"",INDEX($AD$40:$AD$133,IFERROR(MATCH(23,$AB$40:$AB$133,0),0))) -> 18 | L36: =IF(IFERROR(MATCH(23,$AB$40:$AB$133,0),0)=0,"",IF(INDEX($BB$40:$BB$133,IFERROR(MATCH(23,$AB$40:$AB$133,0),0))>=99999,"",INDEX($BB$40:$BB$133,IFERROR(MATCH(23,$AB$40:$AB$133,0),0)))) -> 46275 | M36: =IF(IFERROR(MATCH(23,$AB$40:$AB$133,0),0)=0,"",IF(INDEX($BC$40:$BC$133,IFERROR(MATCH(23,$AB$40:$AB$133,0),0))=0,"",INDEX($BC$40:$BC$133,IFERROR(MATCH(23,$AB$40:$AB$133,0),0)))) -> 46295 | N36: =IF(IFERROR(MATCH(23,$AB$40:$AB$133,0),0)=0,"",INDEX($AE$40:$AE$133,IFERROR(MATCH(23,$AB$40:$AB$133,0),0))&"") -> Saídas pelo depósito 0355 que não baixaram o estoque físico | O36: =IF(IFERROR(MATCH(23,$AB$40:$AB$133,0),0)=0,"",INDEX($BD$40:$BD$133,IFERROR(MATCH(23,$AB$40:$AB$133,0),0))&"") -> Confirmar a OT de saída (picking) das remessas para baixar 20.1 KG do estoque físico | AS36: CHR-Q37RB2-2B-U75 | AV36: =IFERROR(INDEX($AX$1:$AX$94,MATCH(35,$AY$1:$AY$94,0)),"") -> 260880301 | AW36: CHD-SP-9Z4-BR-U73 | AX36: 250500301 | AY36: =IF(OR($A$5="Todos",AW36=$A$5),MAX(AY$1:AY35)+1,0) -> 36
A37: =IF(IFERROR(MATCH(24,$AB$40:$AB$133,0),0)=0,"",INDEX($T$40:$T$133,IFERROR(MATCH(24,$AB$40:$AB$133,0),0))) -> 2665-E4-U71 | B37: =IF(IFERROR(MATCH(24,$AB$40:$AB$133,0),0)=0,"",INDEX($AG$40:$AG$133,IFERROR(MATCH(24,$AB$40:$AB$133,0),0))) -> 252800202 | C37: =IF(IFERROR(MATCH(24,$AB$40:$AB$133,0),0)=0,"",INDEX($U$40:$U$133,IFERROR(MATCH(24,$AB$40:$AB$133,0),0))) -> KG | D37: =IF(IFERROR(MATCH(24,$AB$40:$AB$133,0),0)=0,"",INDEX($BH$40:$BH$133,IFERROR(MATCH(24,$AB$40:$AB$133,0),0))) -> 0 | E37: =IF(IFERROR(MATCH(24,$AB$40:$AB$133,0),0)=0,"",INDEX($W$40:$W$133,IFERROR(MATCH(24,$AB$40:$AB$133,0),0))) -> 1200 | F37: =IF(IFERROR(MATCH(24,$AB$40:$AB$133,0),0)=0,"",INDEX($X$40:$X$133,IFERROR(MATCH(24,$AB$40:$AB$133,0),0))) -> 0 | G37: =IF(A37="","",D37+E37-F37) -> 1200 | H37: =IF(IFERROR(MATCH(24,$AB$40:$AB$133,0),0)=0,"",INDEX($Y$40:$Y$133,IFERROR(MATCH(24,$AB$40:$AB$133,0),0))) -> 1200 | I37: =IF(IFERROR(MATCH(24,$AB$40:$AB$133,0),0)=0,"",INDEX($Z$40:$Z$133,IFERROR(MATCH(24,$AB$40:$AB$133,0),0))) -> 0 | J37: =IF(IFERROR(MATCH(24,$AB$40:$AB$133,0),0)=0,"",INDEX($AC$40:$AC$133,IFERROR(MATCH(24,$AB$40:$AB$133,0),0))) -> Confere | K37: =IF(IFERROR(MATCH(24,$AB$40:$AB$133,0),0)=0,"",INDEX($AD$40:$AD$133,IFERROR(MATCH(24,$AB$40:$AB$133,0),0))) -> 2 | L37: =IF(IFERROR(MATCH(24,$AB$40:$AB$133,0),0)=0,"",IF(INDEX($BB$40:$BB$133,IFERROR(MATCH(24,$AB$40:$AB$133,0),0))>=99999,"",INDEX($BB$40:$BB$133,IFERROR(MATCH(24,$AB$40:$AB$133,0),0)))) -> 46289 | M37: =IF(IFERROR(MATCH(24,$AB$40:$AB$133,0),0)=0,"",IF(INDEX($BC$40:$BC$133,IFERROR(MATCH(24,$AB$40:$AB$133,0),0))=0,"",INDEX($BC$40:$BC$133,IFERROR(MATCH(24,$AB$40:$AB$133,0),0)))) -> 46289 | N37: =IF(IFERROR(MATCH(24,$AB$40:$AB$133,0),0)=0,"",INDEX($AE$40:$AE$133,IFERROR(MATCH(24,$AB$40:$AB$133,0),0))&"") -> Sem diferença | O37: =IF(IFERROR(MATCH(24,$AB$40:$AB$133,0),0)=0,"",INDEX($BD$40:$BD$133,IFERROR(MATCH(24,$AB$40:$AB$133,0),0))&"") -> Nenhum ajuste necessário | AS37: CHR-Q37RB2-E0-D94 | AV37: =IFERROR(INDEX($AX$1:$AX$94,MATCH(36,$AY$1:$AY$94,0)),"") -> 250500301 | AW37: CHD-TS-22350E0-999 | AX37: 2520443650 | AY37: =IF(OR($A$5="Todos",AW37=$A$5),MAX(AY$1:AY36)+1,0) -> 37
A38: =IF(IFERROR(MATCH(25,$AB$40:$AB$133,0),0)=0,"",INDEX($T$40:$T$133,IFERROR(MATCH(25,$AB$40:$AB$133,0),0))) -> 70-30-38-BR-25A | B38: =IF(IFERROR(MATCH(25,$AB$40:$AB$133,0),0)=0,"",INDEX($AG$40:$AG$133,IFERROR(MATCH(25,$AB$40:$AB$133,0),0))) -> 260070301 | C38: =IF(IFERROR(MATCH(25,$AB$40:$AB$133,0),0)=0,"",INDEX($U$40:$U$133,IFERROR(MATCH(25,$AB$40:$AB$133,0),0))) -> KG | D38: =IF(IFERROR(MATCH(25,$AB$40:$AB$133,0),0)=0,"",INDEX($BH$40:$BH$133,IFERROR(MATCH(25,$AB$40:$AB$133,0),0))) -> 0 | E38: =IF(IFERROR(MATCH(25,$AB$40:$AB$133,0),0)=0,"",INDEX($W$40:$W$133,IFERROR(MATCH(25,$AB$40:$AB$133,0),0))) -> 3015 | F38: =IF(IFERROR(MATCH(25,$AB$40:$AB$133,0),0)=0,"",INDEX($X$40:$X$133,IFERROR(MATCH(25,$AB$40:$AB$133,0),0))) -> 2673.3 | G38: =IF(A38="","",D38+E38-F38) -> 341.7 | H38: =IF(IFERROR(MATCH(25,$AB$40:$AB$133,0),0)=0,"",INDEX($Y$40:$Y$133,IFERROR(MATCH(25,$AB$40:$AB$133,0),0))) -> 341.7 | I38: =IF(IFERROR(MATCH(25,$AB$40:$AB$133,0),0)=0,"",INDEX($Z$40:$Z$133,IFERROR(MATCH(25,$AB$40:$AB$133,0),0))) -> 0 | J38: =IF(IFERROR(MATCH(25,$AB$40:$AB$133,0),0)=0,"",INDEX($AC$40:$AC$133,IFERROR(MATCH(25,$AB$40:$AB$133,0),0))) -> Confere | K38: =IF(IFERROR(MATCH(25,$AB$40:$AB$133,0),0)=0,"",INDEX($AD$40:$AD$133,IFERROR(MATCH(25,$AB$40:$AB$133,0),0))) -> 20 | L38: =IF(IFERROR(MATCH(25,$AB$40:$AB$133,0),0)=0,"",IF(INDEX($BB$40:$BB$133,IFERROR(MATCH(25,$AB$40:$AB$133,0),0))>=99999,"",INDEX($BB$40:$BB$133,IFERROR(MATCH(25,$AB$40:$AB$133,0),0)))) -> 46288 | M38: =IF(IFERROR(MATCH(25,$AB$40:$AB$133,0),0)=0,"",IF(INDEX($BC$40:$BC$133,IFERROR(MATCH(25,$AB$40:$AB$133,0),0))=0,"",INDEX($BC$40:$BC$133,IFERROR(MATCH(25,$AB$40:$AB$133,0),0)))) -> 46295 | N38: =IF(IFERROR(MATCH(25,$AB$40:$AB$133,0),0)=0,"",INDEX($AE$40:$AE$133,IFERROR(MATCH(25,$AB$40:$AB$133,0),0))&"") -> Sem diferença | O38: =IF(IFERROR(MATCH(25,$AB$40:$AB$133,0),0)=0,"",INDEX($BD$40:$BD$133,IFERROR(MATCH(25,$AB$40:$AB$133,0),0))&"") -> Nenhum ajuste necessário | AS38: CW2-BR-25A | AV38: =IFERROR(INDEX($AX$1:$AX$94,MATCH(37,$AY$1:$AY$94,0)),"") -> 2520443650 | AW38: CHD-VR-Z2S-E0-U68 | AX38: 261160301 | AY38: =IF(OR($A$5="Todos",AW38=$A$5),MAX(AY$1:AY37)+1,0) -> 38
A39: =IF(IFERROR(MATCH(26,$AB$40:$AB$133,0),0)=0,"",INDEX($T$40:$T$133,IFERROR(MATCH(26,$AB$40:$AB$133,0),0))) -> 805-BR-D94 | B39: =IF(IFERROR(MATCH(26,$AB$40:$AB$133,0),0)=0,"",INDEX($AG$40:$AG$133,IFERROR(MATCH(26,$AB$40:$AB$133,0),0))) -> 260130779 | C39: =IF(IFERROR(MATCH(26,$AB$40:$AB$133,0),0)=0,"",INDEX($U$40:$U$133,IFERROR(MATCH(26,$AB$40:$AB$133,0),0))) -> KG | D39: =IF(IFERROR(MATCH(26,$AB$40:$AB$133,0),0)=0,"",INDEX($BH$40:$BH$133,IFERROR(MATCH(26,$AB$40:$AB$133,0),0))) -> 0 | E39: =IF(IFERROR(MATCH(26,$AB$40:$AB$133,0),0)=0,"",INDEX($W$40:$W$133,IFERROR(MATCH(26,$AB$40:$AB$133,0),0))) -> 142.8 | F39: =IF(IFERROR(MATCH(26,$AB$40:$AB$133,0),0)=0,"",INDEX($X$40:$X$133,IFERROR(MATCH(26,$AB$40:$AB$133,0),0))) -> 0 | G39: =IF(A39="","",D39+E39-F39) -> 142.8 | H39: =IF(IFERROR(MATCH(26,$AB$40:$AB$133,0),0)=0,"",INDEX($Y$40:$Y$133,IFERROR(MATCH(26,$AB$40:$AB$133,0),0))) -> 142.8 | I39: =IF(IFERROR(MATCH(26,$AB$40:$AB$133,0),0)=0,"",INDEX($Z$40:$Z$133,IFERROR(MATCH(26,$AB$40:$AB$133,0),0))) -> 0 | J39: =IF(IFERROR(MATCH(26,$AB$40:$AB$133,0),0)=0,"",INDEX($AC$40:$AC$133,IFERROR(MATCH(26,$AB$40:$AB$133,0),0))) -> Confere | K39: =IF(IFERROR(MATCH(26,$AB$40:$AB$133,0),0)=0,"",INDEX($AD$40:$AD$133,IFERROR(MATCH(26,$AB$40:$AB$133,0),0))) -> 1 | L39: =IF(IFERROR(MATCH(26,$AB$40:$AB$133,0),0)=0,"",IF(INDEX($BB$40:$BB$133,IFERROR(MATCH(26,$AB$40:$AB$133,0),0))>=99999,"",INDEX($BB$40:$BB$133,IFERROR(MATCH(26,$AB$40:$AB$133,0),0)))) -> 46294 | M39: =IF(IFERROR(MATCH(26,$AB$40:$AB$133,0),0)=0,"",IF(INDEX($BC$40:$BC$133,IFERROR(MATCH(26,$AB$40:$AB$133,0),0))=0,"",INDEX($BC$40:$BC$133,IFERROR(MATCH(26,$AB$40:$AB$133,0),0)))) -> 46294 | N39: =IF(IFERROR(MATCH(26,$AB$40:$AB$133,0),0)=0,"",INDEX($AE$40:$AE$133,IFERROR(MATCH(26,$AB$40:$AB$133,0),0))&"") -> Sem diferença | O39: =IF(IFERROR(MATCH(26,$AB$40:$AB$133,0),0)=0,"",INDEX($BD$40:$BD$133,IFERROR(MATCH(26,$AB$40:$AB$133,0),0))&"") -> Nenhum ajuste necessário | AJ39: SKU · lote | AK39: Sobrando | AL39: Faltando | AP39: Entrou no ZBR | AQ39: Saiu | AR39: Saldo acumulado (entrou − saiu) | AS39: CW2NV-595 | AV39: =IFERROR(INDEX($AX$1:$AX$94,MATCH(38,$AY$1:$AY$94,0)),"") -> 261160301 | AW39: CHK-D-413 | AX39: 261756201 | AY39: =IF(OR($A$5="Todos",AW39=$A$5),MAX(AY$1:AY38)+1,0) -> 39
A40: =IF(IFERROR(MATCH(27,$AB$40:$AB$133,0),0)=0,"",INDEX($T$40:$T$133,IFERROR(MATCH(27,$AB$40:$AB$133,0),0))) -> 811NV-132 | B40: =IF(IFERROR(MATCH(27,$AB$40:$AB$133,0),0)=0,"",INDEX($AG$40:$AG$133,IFERROR(MATCH(27,$AB$40:$AB$133,0),0))) -> 252510301 | C40: =IF(IFERROR(MATCH(27,$AB$40:$AB$133,0),0)=0,"",INDEX($U$40:$U$133,IFERROR(MATCH(27,$AB$40:$AB$133,0),0))) -> KG | D40: =IF(IFERROR(MATCH(27,$AB$40:$AB$133,0),0)=0,"",INDEX($BH$40:$BH$133,IFERROR(MATCH(27,$AB$40:$AB$133,0),0))) -> 0 | E40: =IF(IFERROR(MATCH(27,$AB$40:$AB$133,0),0)=0,"",INDEX($W$40:$W$133,IFERROR(MATCH(27,$AB$40:$AB$133,0),0))) -> 1500 | F40: =IF(IFERROR(MATCH(27,$AB$40:$AB$133,0),0)=0,"",INDEX($X$40:$X$133,IFERROR(MATCH(27,$AB$40:$AB$133,0),0))) -> 0 | G40: =IF(A40="","",D40+E40-F40) -> 1500 | H40: =IF(IFERROR(MATCH(27,$AB$40:$AB$133,0),0)=0,"",INDEX($Y$40:$Y$133,IFERROR(MATCH(27,$AB$40:$AB$133,0),0))) -> 1500 | I40: =IF(IFERROR(MATCH(27,$AB$40:$AB$133,0),0)=0,"",INDEX($Z$40:$Z$133,IFERROR(MATCH(27,$AB$40:$AB$133,0),0))) -> 0 | J40: =IF(IFERROR(MATCH(27,$AB$40:$AB$133,0),0)=0,"",INDEX($AC$40:$AC$133,IFERROR(MATCH(27,$AB$40:$AB$133,0),0))) -> Confere | K40: =IF(IFERROR(MATCH(27,$AB$40:$AB$133,0),0)=0,"",INDEX($AD$40:$AD$133,IFERROR(MATCH(27,$AB$40:$AB$133,0),0))) -> 4 | L40: =IF(IFERROR(MATCH(27,$AB$40:$AB$133,0),0)=0,"",IF(INDEX($BB$40:$BB$133,IFERROR(MATCH(27,$AB$40:$AB$133,0),0))>=99999,"",INDEX($BB$40:$BB$133,IFERROR(MATCH(27,$AB$40:$AB$133,0),0)))) -> 46289 | M40: =IF(IFERROR(MATCH(27,$AB$40:$AB$133,0),0)=0,"",IF(INDEX($BC$40:$BC$133,IFERROR(MATCH(27,$AB$40:$AB$133,0),0))=0,"",INDEX($BC$40:$BC$133,IFERROR(MATCH(27,$AB$40:$AB$133,0),0)))) -> 46289 | N40: =IF(IFERROR(MATCH(27,$AB$40:$AB$133,0),0)=0,"",INDEX($AE$40:$AE$133,IFERROR(MATCH(27,$AB$40:$AB$133,0),0))&"") -> Sem diferença | O40: =IF(IFERROR(MATCH(27,$AB$40:$AB$133,0),0)=0,"",INDEX($BD$40:$BD$133,IFERROR(MATCH(27,$AB$40:$AB$133,0),0))&"") -> Nenhum ajuste necessário | T40: CHK-R30GOLD-BR-25A | U40: KG | V40: =SUMIFS('3 Base Entrada 2008'!$G$2:$G$5000,'3 Base Entrada 2008'!$F$2:$F$5000,">="&$F$5,'3 Base Entrada 2008'!$F$2:$F$5000,"<="&$H$5,'3 Base Entrada 2008'!$B$2:$B$5000,$T40,'3 Base Entrada 2008'!$C$2:$C$5000,$AG40,'3 Base Entrada 2008'!$K$2:$K$5000,"Recebido no 2008") -> 1025.1 | W40: =SUMIFS('3 Base Entrada 2008'!$L$2:$L$5000,'3 Base Entrada 2008'!$F$2:$F$5000,">="&$F$5,'3 Base Entrada 2008'!$F$2:$F$5000,"<="&$H$5,'3 Base Entrada 2008'!$B$2:$B$5000,$T40,'3 Base Entrada 2008'!$C$2:$C$5000,$AG40) -> 2673.3 | X40: =SUMIFS('3 Base Saídas'!$R$2:$R$5000,'3 Base Saídas'!$G$2:$G$5000,">="&$F$5,'3 Base Saídas'!$G$2:$G$5000,"<="&$H$5,'3 Base Saídas'!$B$2:$B$5000,$T40,'3 Base Saídas'!$C$2:$C$5000,$AG40) -> 1005 | Y40: =SUMIFS('3 Base Estoque Físico'!$J$2:$J$5000,'3 Base Estoque Físico'!$A$2:$A$5000,$T40,'3 Base Estoque Físico'!$B$2:$B$5000,$AG40) -> 1226.1 | Z40: =ROUND(Y40-(BH40+W40-X40),3) -> -442.2 | AA40: =IF(AND(U40=$R$3,OR($R$1="*",T40=$R$1),OR($R$2="*",AG40=$R$2),OR($R$6="*",AC40=$R$6),ABS(V40)+ABS(W40)+ABS(X40)+ABS(Y40)>0),1,0) -> 1 | AB40: =IF(AA40=1,SUM(AA$40:AA40),"") -> 1 | AC40: =IF(ABS(Z40)<=$R$5,"Confere",IF(Z40>0,"Sobrando","Faltando")) -> Faltando | AD40: =IF(OR($R$4="*",$R$4="Saída"),COUNTIFS('3 Base Saídas'!$G$2:$G$5000,">="&$F$5,'3 Base Saídas'!$G$2:$G$5000,"<="&$H$5,'3 Base Saídas'!$B$2:$B$5000,$T40,'3 Base Saídas'!$C$2:$C$5000,$AG40),0)+IF($R$4<>"Saída",COUNTIFS('3 Base Entrada 2008'!$F$2:$F$5000,">="&$F$5,'3 Base Entrada 2008'!$F$2:$F$5000,"<="&$H$5,'3 Base Entrada 2008'!$B$2:$B$5000,$T40,'3 Base Entrada 2008'!$C$2:$C$5000,$AG40,'3 Base Entrada 2008'!$K$2:$K$5000,$R$4),0) -> 17 | AE40: ='5 Conciliação'!K14 -> Estoque físico menor que o esperado: saída, ajuste ou perda não lançada no período | AF40: =IF(AND(AA40=1,AC40<>"Confere"),ABS(Z40)+ROW()/10000000,0) -> 442.2 | AG40: 261130301 | AH40: =LARGE($AF$40:$AF$133,1) -> 5737.2 | AI40: =IF(AH40>0,MATCH(AH40,$AF$40:$AF$133,0),"") -> 6 | AJ40: =IF(AI40="","",INDEX($T$40:$T$133,AI40)&" · "&INDEX($AG$40:$AG$133,AI40)) -> 811-BR-D94 · 251643289 | AK40: =IF(AI40="",0,MAX(INDEX($Z$40:$Z$133,AI40),0)) -> 5737.2 | AL40: =IF(AI40="",0,MIN(INDEX($Z$40:$Z$133,AI40),0)) -> 0 | AN40: 09/09 | AO40: 46274 | AP40: =IF(AND(AO40>=$F$5,AO40<=$H$5,$R$4<>"Saída"),SUMIFS('3 Base Entrada 2008'!$L$2:$L$5000,'3 Base Entrada 2008'!$F$2:$F$5000,$AO40,'3 Base Entrada 2008'!$B$2:$B$5000,$R$1,'3 Base Entrada 2008'!$C$2:$C$5000,$R$2,'3 Base Entrada 2008'!$H$2:$H$5000,$R$3,'3 Base Entrada 2008'!$K$2:$K$5000,$R$4),0) -> 490.96 | AQ40: =IF(AND(AO40>=$F$5,AO40<=$H$5,OR($R$4="*",$R$4="Saída")),-SUMIFS('3 Base Saídas'!$R$2:$R$5000,'3 Base Saídas'!$G$2:$G$5000,$AO40,'3 Base Saídas'!$B$2:$B$5000,$R$1,'3 Base Saídas'!$C$2:$C$5000,$R$2,'3 Base Saídas'!$I$2:$I$5000,$R$3),0) -> -11.2 | AR40: =SUM($AP$40:AP40)+SUM($AQ$40:AQ40) -> 479.76 | AS40: DCP-10BONOI-89B | AV40: =IFERROR(INDEX($AX$1:$AX$94,MATCH(39,$AY$1:$AY$94,0)),"") -> 261756201 | AW40: CHK-R30GOLD-BR-25A | AX40: 252750301 | AY40: =IF(OR($A$5="Todos",AW40=$A$5),MAX(AY$1:AY39)+1,0) -> 40 | BB40: =MIN(IF(_xlfn.MINIFS('3 Base Entrada 2008'!$F$2:$F$5000,'3 Base Entrada 2008'!$F$2:$F$5000,">="&$F$5,'3 Base Entrada 2008'!$F$2:$F$5000,"<="&$H$5,'3 Base Entrada 2008'!$B$2:$B$5000,$T40,'3 Base Entrada 2008'!$C$2:$C$5000,$AG40)=0,99999,_xlfn.MINIFS('3 Base Entrada 2008'!$F$2:$F$5000,'3 Base Entrada 2008'!$F$2:$F$5000,">="&$F$5,'3 Base Entrada 2008'!$F$2:$F$5000,"<="&$H$5,'3 Base Entrada 2008'!$B$2:$B$5000,$T40,'3 Base Entrada 2008'!$C$2:$C$5000,$AG40)),IF(_xlfn.MINIFS('3 Base Saídas'!$G$2:$G$5000,'3 Base Saídas'!$G$2:$G$5000,">="&$F$5,'3 Base Saídas'!$G$2:$G$5000,"<="&$H$5,'3 Base Saídas'!$B$2:$B$5000,$T40,'3 Base Saídas'!$C$2:$C$5000,$AG40)=0,99999,_xlfn.MINIFS('3 Base Saídas'!$G$2:$G$5000,'3 Base Saídas'!$G$2:$G$5000,">="&$F$5,'3 Base Saídas'!$G$2:$G$5000,"<="&$H$5,'3 Base Saídas'!$B$2:$B$5000,$T40,'3 Base Saídas'!$C$2:$C$5000,$AG40))) -> 46275 | BC40: =MAX(_xlfn.MAXIFS('3 Base Entrada 2008'!$F$2:$F$5000,'3 Base Entrada 2008'!$F$2:$F$5000,">="&$F$5,'3 Base Entrada 2008'!$F$2:$F$5000,"<="&$H$5,'3 Base Entrada 2008'!$B$2:$B$5000,$T40,'3 Base Entrada 2008'!$C$2:$C$5000,$AG40),_xlfn.MAXIFS('3 Base Saídas'!$G$2:$G$5000,'3 Base Saídas'!$G$2:$G$5000,">="&$F$5,'3 Base Saídas'!$G$2:$G$5000,"<="&$H$5,'3 Base Saídas'!$B$2:$B$5000,$T40,'3 Base Saídas'!$C$2:$C$5000,$AG40)) -> 46295 | BD40: ='5 Conciliação'!L14 -> Contar o lote. Se a falta se confirmar: lançar a saída esquecida (601) ou ajuste de inventário de −442.2 KG | BE40: ='5 Conciliação'!Q14 -> Falta sem explicação | BF40: ='5 Conciliação'!R14 -> Crítica | BH40: =SUMIFS('3 Base Saldo Inicial 08-09'!$E$2:$E$5000,'3 Base Saldo Inicial 08-09'!$A$2:$A$5000,$T40,'3 Base Saldo Inicial 08-09'!$B$2:$B$5000,$AG40)-SUMIFS('3 Base Saldo Inicial 08-09'!$E$2:$E$5000,'3 Base Saldo Inicial 08-09'!$A$2:$A$5000,$T40,'3 Base Saldo Inicial 08-09'!$B$2:$B$5000,$AG40,'3 Base Saldo Inicial 08-09'!$C$2:$C$5000,"2008") -> 0
A41: =IF(IFERROR(MATCH(28,$AB$40:$AB$133,0),0)=0,"",INDEX($T$40:$T$133,IFERROR(MATCH(28,$AB$40:$AB$133,0),0))) -> 811NV-132 | B41: =IF(IFERROR(MATCH(28,$AB$40:$AB$133,0),0)=0,"",INDEX($AG$40:$AG$133,IFERROR(MATCH(28,$AB$40:$AB$133,0),0))) -> 253280301 | C41: =IF(IFERROR(MATCH(28,$AB$40:$AB$133,0),0)=0,"",INDEX($U$40:$U$133,IFERROR(MATCH(28,$AB$40:$AB$133,0),0))) -> KG | D41: =IF(IFERROR(MATCH(28,$AB$40:$AB$133,0),0)=0,"",INDEX($BH$40:$BH$133,IFERROR(MATCH(28,$AB$40:$AB$133,0),0))) -> 0 | E41: =IF(IFERROR(MATCH(28,$AB$40:$AB$133,0),0)=0,"",INDEX($W$40:$W$133,IFERROR(MATCH(28,$AB$40:$AB$133,0),0))) -> 1750 | F41: =IF(IFERROR(MATCH(28,$AB$40:$AB$133,0),0)=0,"",INDEX($X$40:$X$133,IFERROR(MATCH(28,$AB$40:$AB$133,0),0))) -> 800 | G41: =IF(A41="","",D41+E41-F41) -> 950 | H41: =IF(IFERROR(MATCH(28,$AB$40:$AB$133,0),0)=0,"",INDEX($Y$40:$Y$133,IFERROR(MATCH(28,$AB$40:$AB$133,0),0))) -> 950 | I41: =IF(IFERROR(MATCH(28,$AB$40:$AB$133,0),0)=0,"",INDEX($Z$40:$Z$133,IFERROR(MATCH(28,$AB$40:$AB$133,0),0))) -> 0 | J41: =IF(IFERROR(MATCH(28,$AB$40:$AB$133,0),0)=0,"",INDEX($AC$40:$AC$133,IFERROR(MATCH(28,$AB$40:$AB$133,0),0))) -> Confere | K41: =IF(IFERROR(MATCH(28,$AB$40:$AB$133,0),0)=0,"",INDEX($AD$40:$AD$133,IFERROR(MATCH(28,$AB$40:$AB$133,0),0))) -> 9 | L41: =IF(IFERROR(MATCH(28,$AB$40:$AB$133,0),0)=0,"",IF(INDEX($BB$40:$BB$133,IFERROR(MATCH(28,$AB$40:$AB$133,0),0))>=99999,"",INDEX($BB$40:$BB$133,IFERROR(MATCH(28,$AB$40:$AB$133,0),0)))) -> 46289 | M41: =IF(IFERROR(MATCH(28,$AB$40:$AB$133,0),0)=0,"",IF(INDEX($BC$40:$BC$133,IFERROR(MATCH(28,$AB$40:$AB$133,0),0))=0,"",INDEX($BC$40:$BC$133,IFERROR(MATCH(28,$AB$40:$AB$133,0),0)))) -> 46294 | N41: =IF(IFERROR(MATCH(28,$AB$40:$AB$133,0),0)=0,"",INDEX($AE$40:$AE$133,IFERROR(MATCH(28,$AB$40:$AB$133,0),0))&"") -> Sem diferença | O41: =IF(IFERROR(MATCH(28,$AB$40:$AB$133,0),0)=0,"",INDEX($BD$40:$BD$133,IFERROR(MATCH(28,$AB$40:$AB$133,0),0))&"") -> Nenhum ajuste necessário | T41: CHM-TS-P23-E0-999 | U41: KG | V41: =SUMIFS('3 Base Entrada 2008'!$G$2:$G$5000,'3 Base Entrada 2008'!$F$2:$F$5000,">="&$F$5,'3 Base Entrada 2008'!$F$2:$F$5000,"<="&$H$5,'3 Base Entrada 2008'!$B$2:$B$5000,$T41,'3 Base Entrada 2008'!$C$2:$C$5000,$AG41,'3 Base Entrada 2008'!$K$2:$K$5000,"Recebido no 2008") -> 0 | W41: =SUMIFS('3 Base Entrada 2008'!$L$2:$L$5000,'3 Base Entrada 2008'!$F$2:$F$5000,">="&$F$5,'3 Base Entrada 2008'!$F$2:$F$5000,"<="&$H$5,'3 Base Entrada 2008'!$B$2:$B$5000,$T41,'3 Base Entrada 2008'!$C$2:$C$5000,$AG41) -> 261.12 | X41: =SUMIFS('3 Base Saídas'!$R$2:$R$5000,'3 Base Saídas'!$G$2:$G$5000,">="&$F$5,'3 Base Saídas'!$G$2:$G$5000,"<="&$H$5,'3 Base Saídas'!$B$2:$B$5000,$T41,'3 Base Saídas'!$C$2:$C$5000,$AG41) -> 0 | Y41: =SUMIFS('3 Base Estoque Físico'!$J$2:$J$5000,'3 Base Estoque Físico'!$A$2:$A$5000,$T41,'3 Base Estoque Físico'!$B$2:$B$5000,$AG41) -> 0 | Z41: =ROUND(Y41-(BH41+W41-X41),3) -> -261.12 | AA41: =IF(AND(U41=$R$3,OR($R$1="*",T41=$R$1),OR($R$2="*",AG41=$R$2),OR($R$6="*",AC41=$R$6),ABS(V41)+ABS(W41)+ABS(X41)+ABS(Y41)>0),1,0) -> 1 | AB41: =IF(AA41=1,SUM(AA$40:AA41),"") -> 2 | AC41: =IF(ABS(Z41)<=$R$5,"Confere",IF(Z41>0,"Sobrando","Faltando")) -> Faltando | AD41: =IF(OR($R$4="*",$R$4="Saída"),COUNTIFS('3 Base Saídas'!$G$2:$G$5000,">="&$F$5,'3 Base Saídas'!$G$2:$G$5000,"<="&$H$5,'3 Base Saídas'!$B$2:$B$5000,$T41,'3 Base Saídas'!$C$2:$C$5000,$AG41),0)+IF($R$4<>"Saída",COUNTIFS('3 Base Entrada 2008'!$F$2:$F$5000,">="&$F$5,'3 Base Entrada 2008'!$F$2:$F$5000,"<="&$H$5,'3 Base Entrada 2008'!$B$2:$B$5000,$T41,'3 Base Entrada 2008'!$C$2:$C$5000,$AG41,'3 Base Entrada 2008'!$K$2:$K$5000,$R$4),0) -> 1 | AE41: ='5 Conciliação'!K15 -> Entrou no ZBR, mas não está no estoque físico: não chegou ou foi guardado em outro lote | AF41: =IF(AND(AA41=1,AC41<>"Confere"),ABS(Z41)+ROW()/10000000,0) -> 261.12 | AG41: 2605567696 | AH41: =LARGE($AF$40:$AF$133,2) -> 3694.998 | AI41: =IF(AH41>0,MATCH(AH41,$AF$40:$AF$133,0),"") -> 7 | AJ41: =IF(AI41="","",INDEX($T$40:$T$133,AI41)&" · "&INDEX($AG$40:$AG$133,AI41)) -> CHM-SP-Z3L-BR-U73 · 251880301 | AK41: =IF(AI41="",0,MAX(INDEX($Z$40:$Z$133,AI41),0)) -> 3694.998 | AL41: =IF(AI41="",0,MIN(INDEX($Z$40:$Z$133,AI41),0)) -> 0 | AN41: 10/09 | AO41: 46275 | AP41: =IF(AND(AO41>=$F$5,AO41<=$H$5,$R$4<>"Saída"),SUMIFS('3 Base Entrada 2008'!$L$2:$L$5000,'3 Base Entrada 2008'!$F$2:$F$5000,$AO41,'3 Base Entrada 2008'!$B$2:$B$5000,$R$1,'3 Base Entrada 2008'!$C$2:$C$5000,$R$2,'3 Base Entrada 2008'!$H$2:$H$5000,$R$3,'3 Base Entrada 2008'!$K$2:$K$5000,$R$4),0) -> 0 | AQ41: =IF(AND(AO41>=$F$5,AO41<=$H$5,OR($R$4="*",$R$4="Saída")),-SUMIFS('3 Base Saídas'!$R$2:$R$5000,'3 Base Saídas'!$G$2:$G$5000,$AO41,'3 Base Saídas'!$B$2:$B$5000,$R$1,'3 Base Saídas'!$C$2:$C$5000,$R$2,'3 Base Saídas'!$I$2:$I$5000,$R$3),0) -> -559.4 | AR41: =SUM($AP$40:AP41)+SUM($AQ$40:AQ41) -> -79.64 | AS41: DCP-20BODEC-89B | AV41: =IFERROR(INDEX($AX$1:$AX$94,MATCH(40,$AY$1:$AY$94,0)),"") -> 252750301 | AW41: CHK-R30GOLD-BR-25A | AX41: 253620301 | AY41: =IF(OR($A$5="Todos",AW41=$A$5),MAX(AY$1:AY40)+1,0) -> 41 | BB41: =MIN(IF(_xlfn.MINIFS('3 Base Entrada 2008'!$F$2:$F$5000,'3 Base Entrada 2008'!$F$2:$F$5000,">="&$F$5,'3 Base Entrada 2008'!$F$2:$F$5000,"<="&$H$5,'3 Base Entrada 2008'!$B$2:$B$5000,$T41,'3 Base Entrada 2008'!$C$2:$C$5000,$AG41)=0,99999,_xlfn.MINIFS('3 Base Entrada 2008'!$F$2:$F$5000,'3 Base Entrada 2008'!$F$2:$F$5000,">="&$F$5,'3 Base Entrada 2008'!$F$2:$F$5000,"<="&$H$5,'3 Base Entrada 2008'!$B$2:$B$5000,$T41,'3 Base Entrada 2008'!$C$2:$C$5000,$AG41)),IF(_xlfn.MINIFS('3 Base Saídas'!$G$2:$G$5000,'3 Base Saídas'!$G$2:$G$5000,">="&$F$5,'3 Base Saídas'!$G$2:$G$5000,"<="&$H$5,'3 Base Saídas'!$B$2:$B$5000,$T41,'3 Base Saídas'!$C$2:$C$5000,$AG41)=0,99999,_xlfn.MINIFS('3 Base Saídas'!$G$2:$G$5000,'3 Base Saídas'!$G$2:$G$5000,">="&$F$5,'3 Base Saídas'!$G$2:$G$5000,"<="&$H$5,'3 Base Saídas'!$B$2:$B$5000,$T41,'3 Base Saídas'!$C$2:$C$5000,$AG41))) -> 46288 | BC41: =MAX(_xlfn.MAXIFS('3 Base Entrada 2008'!$F$2:$F$5000,'3 Base Entrada 2008'!$F$2:$F$5000,">="&$F$5,'3 Base Entrada 2008'!$F$2:$F$5000,"<="&$H$5,'3 Base Entrada 2008'!$B$2:$B$5000,$T41,'3 Base Entrada 2008'!$C$2:$C$5000,$AG41),_xlfn.MAXIFS('3 Base Saídas'!$G$2:$G$5000,'3 Base Saídas'!$G$2:$G$5000,">="&$F$5,'3 Base Saídas'!$G$2:$G$5000,"<="&$H$5,'3 Base Saídas'!$B$2:$B$5000,$T41,'3 Base Saídas'!$C$2:$C$5000,$AG41)) -> 46288 | BD41: ='5 Conciliação'!L15 -> Procurar a OT de armazenagem pendente no ZBR. Se não achar: contar e lançar ajuste de inventário de −261.1 KG | BE41: ='5 Conciliação'!Q15 -> Não localizado no estoque | BF41: ='5 Conciliação'!R15 -> Crítica | BH41: =SUMIFS('3 Base Saldo Inicial 08-09'!$E$2:$E$5000,'3 Base Saldo Inicial 08-09'!$A$2:$A$5000,$T41,'3 Base Saldo Inicial 08-09'!$B$2:$B$5000,$AG41)-SUMIFS('3 Base Saldo Inicial 08-09'!$E$2:$E$5000,'3 Base Saldo Inicial 08-09'!$A$2:$A$5000,$T41,'3 Base Saldo Inicial 08-09'!$B$2:$B$5000,$AG41,'3 Base Saldo Inicial 08-09'!$C$2:$C$5000,"2008") -> 0
A42: =IF(IFERROR(MATCH(29,$AB$40:$AB$133,0),0)=0,"",INDEX($T$40:$T$133,IFERROR(MATCH(29,$AB$40:$AB$133,0),0))) -> 811NV-595 | B42: =IF(IFERROR(MATCH(29,$AB$40:$AB$133,0),0)=0,"",INDEX($AG$40:$AG$133,IFERROR(MATCH(29,$AB$40:$AB$133,0),0))) -> 260900702 | C42: =IF(IFERROR(MATCH(29,$AB$40:$AB$133,0),0)=0,"",INDEX($U$40:$U$133,IFERROR(MATCH(29,$AB$40:$AB$133,0),0))) -> KG | D42: =IF(IFERROR(MATCH(29,$AB$40:$AB$133,0),0)=0,"",INDEX($BH$40:$BH$133,IFERROR(MATCH(29,$AB$40:$AB$133,0),0))) -> 0 | E42: =IF(IFERROR(MATCH(29,$AB$40:$AB$133,0),0)=0,"",INDEX($W$40:$W$133,IFERROR(MATCH(29,$AB$40:$AB$133,0),0))) -> 1800 | F42: =IF(IFERROR(MATCH(29,$AB$40:$AB$133,0),0)=0,"",INDEX($X$40:$X$133,IFERROR(MATCH(29,$AB$40:$AB$133,0),0))) -> 1780 | G42: =IF(A42="","",D42+E42-F42) -> 20 | H42: =IF(IFERROR(MATCH(29,$AB$40:$AB$133,0),0)=0,"",INDEX($Y$40:$Y$133,IFERROR(MATCH(29,$AB$40:$AB$133,0),0))) -> 20 | I42: =IF(IFERROR(MATCH(29,$AB$40:$AB$133,0),0)=0,"",INDEX($Z$40:$Z$133,IFERROR(MATCH(29,$AB$40:$AB$133,0),0))) -> 0 | J42: =IF(IFERROR(MATCH(29,$AB$40:$AB$133,0),0)=0,"",INDEX($AC$40:$AC$133,IFERROR(MATCH(29,$AB$40:$AB$133,0),0))) -> Confere | K42: =IF(IFERROR(MATCH(29,$AB$40:$AB$133,0),0)=0,"",INDEX($AD$40:$AD$133,IFERROR(MATCH(29,$AB$40:$AB$133,0),0))) -> 3 | L42: =IF(IFERROR(MATCH(29,$AB$40:$AB$133,0),0)=0,"",IF(INDEX($BB$40:$BB$133,IFERROR(MATCH(29,$AB$40:$AB$133,0),0))>=99999,"",INDEX($BB$40:$BB$133,IFERROR(MATCH(29,$AB$40:$AB$133,0),0)))) -> 46276 | M42: =IF(IFERROR(MATCH(29,$AB$40:$AB$133,0),0)=0,"",IF(INDEX($BC$40:$BC$133,IFERROR(MATCH(29,$AB$40:$AB$133,0),0))=0,"",INDEX($BC$40:$BC$133,IFERROR(MATCH(29,$AB$40:$AB$133,0),0)))) -> 46292 | N42: =IF(IFERROR(MATCH(29,$AB$40:$AB$133,0),0)=0,"",INDEX($AE$40:$AE$133,IFERROR(MATCH(29,$AB$40:$AB$133,0),0))&"") -> Sem diferença | O42: =IF(IFERROR(MATCH(29,$AB$40:$AB$133,0),0)=0,"",INDEX($BD$40:$BD$133,IFERROR(MATCH(29,$AB$40:$AB$133,0),0))&"") -> Nenhum ajuste necessário | T42: BIG-PF-1BO-401 | U42: KG | V42: =SUMIFS('3 Base Entrada 2008'!$G$2:$G$5000,'3 Base Entrada 2008'!$F$2:$F$5000,">="&$F$5,'3 Base Entrada 2008'!$F$2:$F$5000,"<="&$H$5,'3 Base Entrada 2008'!$B$2:$B$5000,$T42,'3 Base Entrada 2008'!$C$2:$C$5000,$AG42,'3 Base Entrada 2008'!$K$2:$K$5000,"Recebido no 2008") -> 0 | W42: =SUMIFS('3 Base Entrada 2008'!$L$2:$L$5000,'3 Base Entrada 2008'!$F$2:$F$5000,">="&$F$5,'3 Base Entrada 2008'!$F$2:$F$5000,"<="&$H$5,'3 Base Entrada 2008'!$B$2:$B$5000,$T42,'3 Base Entrada 2008'!$C$2:$C$5000,$AG42) -> 480 | X42: =SUMIFS('3 Base Saídas'!$R$2:$R$5000,'3 Base Saídas'!$G$2:$G$5000,">="&$F$5,'3 Base Saídas'!$G$2:$G$5000,"<="&$H$5,'3 Base Saídas'!$B$2:$B$5000,$T42,'3 Base Saídas'!$C$2:$C$5000,$AG42) -> 60 | Y42: =SUMIFS('3 Base Estoque Físico'!$J$2:$J$5000,'3 Base Estoque Físico'!$A$2:$A$5000,$T42,'3 Base Estoque Físico'!$B$2:$B$5000,$AG42) -> 210 | Z42: =ROUND(Y42-(BH42+W42-X42),3) -> -210 | AA42: =IF(AND(U42=$R$3,OR($R$1="*",T42=$R$1),OR($R$2="*",AG42=$R$2),OR($R$6="*",AC42=$R$6),ABS(V42)+ABS(W42)+ABS(X42)+ABS(Y42)>0),1,0) -> 1 | AB42: =IF(AA42=1,SUM(AA$40:AA42),"") -> 3 | AC42: =IF(ABS(Z42)<=$R$5,"Confere",IF(Z42>0,"Sobrando","Faltando")) -> Faltando | AD42: =IF(OR($R$4="*",$R$4="Saída"),COUNTIFS('3 Base Saídas'!$G$2:$G$5000,">="&$F$5,'3 Base Saídas'!$G$2:$G$5000,"<="&$H$5,'3 Base Saídas'!$B$2:$B$5000,$T42,'3 Base Saídas'!$C$2:$C$5000,$AG42),0)+IF($R$4<>"Saída",COUNTIFS('3 Base Entrada 2008'!$F$2:$F$5000,">="&$F$5,'3 Base Entrada 2008'!$F$2:$F$5000,"<="&$H$5,'3 Base Entrada 2008'!$B$2:$B$5000,$T42,'3 Base Entrada 2008'!$C$2:$C$5000,$AG42,'3 Base Entrada 2008'!$K$2:$K$5000,$R$4),0) -> 5 | AE42: ='5 Conciliação'!K16 -> Estoque físico menor que o esperado: saída, ajuste ou perda não lançada no período | AF42: =IF(AND(AA42=1,AC42<>"Confere"),ABS(Z42)+ROW()/10000000,0) -> 210 | AG42: 26044019 | AH42: =LARGE($AF$40:$AF$133,3) -> 3198 | AI42: =IF(AH42>0,MATCH(AH42,$AF$40:$AF$133,0),"") -> 8 | AJ42: =IF(AI42="","",INDEX($T$40:$T$133,AI42)&" · "&INDEX($AG$40:$AG$133,AI42)) -> CHD-SP-9Z4-BR-U73 · 250500301 | AK42: =IF(AI42="",0,MAX(INDEX($Z$40:$Z$133,AI42),0)) -> 3198 | AL42: =IF(AI42="",0,MIN(INDEX($Z$40:$Z$133,AI42),0)) -> 0 | AN42: 11/09 | AO42: 46276 | AP42: =IF(AND(AO42>=$F$5,AO42<=$H$5,$R$4<>"Saída"),SUMIFS('3 Base Entrada 2008'!$L$2:$L$5000,'3 Base Entrada 2008'!$F$2:$F$5000,$AO42,'3 Base Entrada 2008'!$B$2:$B$5000,$R$1,'3 Base Entrada 2008'!$C$2:$C$5000,$R$2,'3 Base Entrada 2008'!$H$2:$H$5000,$R$3,'3 Base Entrada 2008'!$K$2:$K$5000,$R$4),0) -> 6720.9 | AQ42: =IF(AND(AO42>=$F$5,AO42<=$H$5,OR($R$4="*",$R$4="Saída")),-SUMIFS('3 Base Saídas'!$R$2:$R$5000,'3 Base Saídas'!$G$2:$G$5000,$AO42,'3 Base Saídas'!$B$2:$B$5000,$R$1,'3 Base Saídas'!$C$2:$C$5000,$R$2,'3 Base Saídas'!$I$2:$I$5000,$R$3),0) -> -2836.4 | AR42: =SUM($AP$40:AP42)+SUM($AQ$40:AQ42) -> 3804.86 | AS42: DCP-22ZEPLA-89B | AV42: =IFERROR(INDEX($AX$1:$AX$94,MATCH(41,$AY$1:$AY$94,0)),"") -> 253620301 | AW42: CHK-R30GOLD-BR-25A | AX42: 261130301 | AY42: =IF(OR($A$5="Todos",AW42=$A$5),MAX(AY$1:AY41)+1,0) -> 42 | BB42: =MIN(IF(_xlfn.MINIFS('3 Base Entrada 2008'!$F$2:$F$5000,'3 Base Entrada 2008'!$F$2:$F$5000,">="&$F$5,'3 Base Entrada 2008'!$F$2:$F$5000,"<="&$H$5,'3 Base Entrada 2008'!$B$2:$B$5000,$T42,'3 Base Entrada 2008'!$C$2:$C$5000,$AG42)=0,99999,_xlfn.MINIFS('3 Base Entrada 2008'!$F$2:$F$5000,'3 Base Entrada 2008'!$F$2:$F$5000,">="&$F$5,'3 Base Entrada 2008'!$F$2:$F$5000,"<="&$H$5,'3 Base Entrada 2008'!$B$2:$B$5000,$T42,'3 Base Entrada 2008'!$C$2:$C$5000,$AG42)),IF(_xlfn.MINIFS('3 Base Saídas'!$G$2:$G$5000,'3 Base Saídas'!$G$2:$G$5000,">="&$F$5,'3 Base Saídas'!$G$2:$G$5000,"<="&$H$5,'3 Base Saídas'!$B$2:$B$5000,$T42,'3 Base Saídas'!$C$2:$C$5000,$AG42)=0,99999,_xlfn.MINIFS('3 Base Saídas'!$G$2:$G$5000,'3 Base Saídas'!$G$2:$G$5000,">="&$F$5,'3 Base Saídas'!$G$2:$G$5000,"<="&$H$5,'3 Base Saídas'!$B$2:$B$5000,$T42,'3 Base Saídas'!$C$2:$C$5000,$AG42))) -> 46275 | BC42: =MAX(_xlfn.MAXIFS('3 Base Entrada 2008'!$F$2:$F$5000,'3 Base Entrada 2008'!$F$2:$F$5000,">="&$F$5,'3 Base Entrada 2008'!$F$2:$F$5000,"<="&$H$5,'3 Base Entrada 2008'!$B$2:$B$5000,$T42,'3 Base Entrada 2008'!$C$2:$C$5000,$AG42),_xlfn.MAXIFS('3 Base Saídas'!$G$2:$G$5000,'3 Base Saídas'!$G$2:$G$5000,">="&$F$5,'3 Base Saídas'!$G$2:$G$5000,"<="&$H$5,'3 Base Saídas'!$B$2:$B$5000,$T42,'3 Base Saídas'!$C$2:$C$5000,$AG42)) -> 46295 | BD42: ='5 Conciliação'!L16 -> Contar o lote. Se a falta se confirmar: lançar a saída esquecida (601) ou ajuste de inventário de −210.0 KG | BE42: ='5 Conciliação'!Q16 -> Falta sem explicação | BF42: ='5 Conciliação'!R16 -> Crítica | BH42: =SUMIFS('3 Base Saldo Inicial 08-09'!$E$2:$E$5000,'3 Base Saldo Inicial 08-09'!$A$2:$A$5000,$T42,'3 Base Saldo Inicial 08-09'!$B$2:$B$5000,$AG42)-SUMIFS('3 Base Saldo Inicial 08-09'!$E$2:$E$5000,'3 Base Saldo Inicial 08-09'!$A$2:$A$5000,$T42,'3 Base Saldo Inicial 08-09'!$B$2:$B$5000,$AG42,'3 Base Saldo Inicial 08-09'!$C$2:$C$5000,"2008") -> 0
A43: =IF(IFERROR(MATCH(30,$AB$40:$AB$133,0),0)=0,"",INDEX($T$40:$T$133,IFERROR(MATCH(30,$AB$40:$AB$133,0),0))) -> 811NV-595 | B43: =IF(IFERROR(MATCH(30,$AB$40:$AB$133,0),0)=0,"",INDEX($AG$40:$AG$133,IFERROR(MATCH(30,$AB$40:$AB$133,0),0))) -> 260920702 | C43: =IF(IFERROR(MATCH(30,$AB$40:$AB$133,0),0)=0,"",INDEX($U$40:$U$133,IFERROR(MATCH(30,$AB$40:$AB$133,0),0))) -> KG | D43: =IF(IFERROR(MATCH(30,$AB$40:$AB$133,0),0)=0,"",INDEX($BH$40:$BH$133,IFERROR(MATCH(30,$AB$40:$AB$133,0),0))) -> 0 | E43: =IF(IFERROR(MATCH(30,$AB$40:$AB$133,0),0)=0,"",INDEX($W$40:$W$133,IFERROR(MATCH(30,$AB$40:$AB$133,0),0))) -> 600 | F43: =IF(IFERROR(MATCH(30,$AB$40:$AB$133,0),0)=0,"",INDEX($X$40:$X$133,IFERROR(MATCH(30,$AB$40:$AB$133,0),0))) -> 0 | G43: =IF(A43="","",D43+E43-F43) -> 600 | H43: =IF(IFERROR(MATCH(30,$AB$40:$AB$133,0),0)=0,"",INDEX($Y$40:$Y$133,IFERROR(MATCH(30,$AB$40:$AB$133,0),0))) -> 600 | I43: =IF(IFERROR(MATCH(30,$AB$40:$AB$133,0),0)=0,"",INDEX($Z$40:$Z$133,IFERROR(MATCH(30,$AB$40:$AB$133,0),0))) -> 0 | J43: =IF(IFERROR(MATCH(30,$AB$40:$AB$133,0),0)=0,"",INDEX($AC$40:$AC$133,IFERROR(MATCH(30,$AB$40:$AB$133,0),0))) -> Confere | K43: =IF(IFERROR(MATCH(30,$AB$40:$AB$133,0),0)=0,"",INDEX($AD$40:$AD$133,IFERROR(MATCH(30,$AB$40:$AB$133,0),0))) -> 1 | L43: =IF(IFERROR(MATCH(30,$AB$40:$AB$133,0),0)=0,"",IF(INDEX($BB$40:$BB$133,IFERROR(MATCH(30,$AB$40:$AB$133,0),0))>=99999,"",INDEX($BB$40:$BB$133,IFERROR(MATCH(30,$AB$40:$AB$133,0),0)))) -> 46276 | M43: =IF(IFERROR(MATCH(30,$AB$40:$AB$133,0),0)=0,"",IF(INDEX($BC$40:$BC$133,IFERROR(MATCH(30,$AB$40:$AB$133,0),0))=0,"",INDEX($BC$40:$BC$133,IFERROR(MATCH(30,$AB$40:$AB$133,0),0)))) -> 46276 | N43: =IF(IFERROR(MATCH(30,$AB$40:$AB$133,0),0)=0,"",INDEX($AE$40:$AE$133,IFERROR(MATCH(30,$AB$40:$AB$133,0),0))&"") -> Sem diferença | O43: =IF(IFERROR(MATCH(30,$AB$40:$AB$133,0),0)=0,"",INDEX($BD$40:$BD$133,IFERROR(MATCH(30,$AB$40:$AB$133,0),0))&"") -> Nenhum ajuste necessário | T43: NIBS-S502-X47 | U43: CX | V43: =SUMIFS('3 Base Entrada 2008'!$G$2:$G$5000,'3 Base Entrada 2008'!$F$2:$F$5000,">="&$F$5,'3 Base Entrada 2008'!$F$2:$F$5000,"<="&$H$5,'3 Base Entrada 2008'!$B$2:$B$5000,$T43,'3 Base Entrada 2008'!$C$2:$C$5000,$AG43,'3 Base Entrada 2008'!$K$2:$K$5000,"Recebido no 2008") -> 0 | W43: =SUMIFS('3 Base Entrada 2008'!$L$2:$L$5000,'3 Base Entrada 2008'!$F$2:$F$5000,">="&$F$5,'3 Base Entrada 2008'!$F$2:$F$5000,"<="&$H$5,'3 Base Entrada 2008'!$B$2:$B$5000,$T43,'3 Base Entrada 2008'!$C$2:$C$5000,$AG43) -> 487 | X43: =SUMIFS('3 Base Saídas'!$R$2:$R$5000,'3 Base Saídas'!$G$2:$G$5000,">="&$F$5,'3 Base Saídas'!$G$2:$G$5000,"<="&$H$5,'3 Base Saídas'!$B$2:$B$5000,$T43,'3 Base Saídas'!$C$2:$C$5000,$AG43) -> 0 | Y43: =SUMIFS('3 Base Estoque Físico'!$J$2:$J$5000,'3 Base Estoque Físico'!$A$2:$A$5000,$T43,'3 Base Estoque Físico'!$B$2:$B$5000,$AG43) -> 367 | Z43: =ROUND(Y43-(BH43+W43-X43),3) -> -120 | AA43: =IF(AND(U43=$R$3,OR($R$1="*",T43=$R$1),OR($R$2="*",AG43=$R$2),OR($R$6="*",AC43=$R$6),ABS(V43)+ABS(W43)+ABS(X43)+ABS(Y43)>0),1,0) -> 0 | AB43: =IF(AA43=1,SUM(AA$40:AA43),"") | AC43: =IF(ABS(Z43)<=$R$5,"Confere",IF(Z43>0,"Sobrando","Faltando")) -> Faltando | AD43: =IF(OR($R$4="*",$R$4="Saída"),COUNTIFS('3 Base Saídas'!$G$2:$G$5000,">="&$F$5,'3 Base Saídas'!$G$2:$G$5000,"<="&$H$5,'3 Base Saídas'!$B$2:$B$5000,$T43,'3 Base Saídas'!$C$2:$C$5000,$AG43),0)+IF($R$4<>"Saída",COUNTIFS('3 Base Entrada 2008'!$F$2:$F$5000,">="&$F$5,'3 Base Entrada 2008'!$F$2:$F$5000,"<="&$H$5,'3 Base Entrada 2008'!$B$2:$B$5000,$T43,'3 Base Entrada 2008'!$C$2:$C$5000,$AG43,'3 Base Entrada 2008'!$K$2:$K$5000,$R$4),0) -> 4 | AE43: ='5 Conciliação'!K17 -> Troca de lote: a mesma quantidade aparece com sinal oposto em outro lote deste SKU | AF43: =IF(AND(AA43=1,AC43<>"Confere"),ABS(Z43)+ROW()/10000000,0) -> 0 | AG43: 253490619 | AH43: =LARGE($AF$40:$AF$133,4) -> 2528.4 | AI43: =IF(AH43>0,MATCH(AH43,$AF$40:$AF$133,0),"") -> 9 | AJ43: =IF(AI43="","",INDEX($T$40:$T$133,AI43)&" · "&INDEX($AG$40:$AG$133,AI43)) -> 823-BR-D94 · 252103049 | AK43: =IF(AI43="",0,MAX(INDEX($Z$40:$Z$133,AI43),0)) -> 2528.4 | AL43: =IF(AI43="",0,MIN(INDEX($Z$40:$Z$133,AI43),0)) -> 0 | AN43: 12/09 | AO43: 46277 | AP43: =IF(AND(AO43>=$F$5,AO43<=$H$5,$R$4<>"Saída"),SUMIFS('3 Base Entrada 2008'!$L$2:$L$5000,'3 Base Entrada 2008'!$F$2:$F$5000,$AO43,'3 Base Entrada 2008'!$B$2:$B$5000,$R$1,'3 Base Entrada 2008'!$C$2:$C$5000,$R$2,'3 Base Entrada 2008'!$H$2:$H$5000,$R$3,'3 Base Entrada 2008'!$K$2:$K$5000,$R$4),0) -> 0 | AQ43: =IF(AND(AO43>=$F$5,AO43<=$H$5,OR($R$4="*",$R$4="Saída")),-SUMIFS('3 Base Saídas'!$R$2:$R$5000,'3 Base Saídas'!$G$2:$G$5000,$AO43,'3 Base Saídas'!$B$2:$B$5000,$R$1,'3 Base Saídas'!$C$2:$C$5000,$R$2,'3 Base Saídas'!$I$2:$I$5000,$R$3),0) -> -173.1 | AR43: =SUM($AP$40:AP43)+SUM($AQ$40:AQ43) -> 3631.76 | AS43: GIA-145 | AV43: =IFERROR(INDEX($AX$1:$AX$94,MATCH(42,$AY$1:$AY$94,0)),"") -> 261130301 | AW43: CHK-R30GOLD-E0-D94 | AX43: 260720939 | AY43: =IF(OR($A$5="Todos",AW43=$A$5),MAX(AY$1:AY42)+1,0) -> 43 | BB43: =MIN(IF(_xlfn.MINIFS('3 Base Entrada 2008'!$F$2:$F$5000,'3 Base Entrada 2008'!$F$2:$F$5000,">="&$F$5,'3 Base Entrada 2008'!$F$2:$F$5000,"<="&$H$5,'3 Base Entrada 2008'!$B$2:$B$5000,$T43,'3 Base Entrada 2008'!$C$2:$C$5000,$AG43)=0,99999,_xlfn.MINIFS('3 Base Entrada 2008'!$F$2:$F$5000,'3 Base Entrada 2008'!$F$2:$F$5000,">="&$F$5,'3 Base Entrada 2008'!$F$2:$F$5000,"<="&$H$5,'3 Base Entrada 2008'!$B$2:$B$5000,$T43,'3 Base Entrada 2008'!$C$2:$C$5000,$AG43)),IF(_xlfn.MINIFS('3 Base Saídas'!$G$2:$G$5000,'3 Base Saídas'!$G$2:$G$5000,">="&$F$5,'3 Base Saídas'!$G$2:$G$5000,"<="&$H$5,'3 Base Saídas'!$B$2:$B$5000,$T43,'3 Base Saídas'!$C$2:$C$5000,$AG43)=0,99999,_xlfn.MINIFS('3 Base Saídas'!$G$2:$G$5000,'3 Base Saídas'!$G$2:$G$5000,">="&$F$5,'3 Base Saídas'!$G$2:$G$5000,"<="&$H$5,'3 Base Saídas'!$B$2:$B$5000,$T43,'3 Base Saídas'!$C$2:$C$5000,$AG43))) -> 46289 | BC43: =MAX(_xlfn.MAXIFS('3 Base Entrada 2008'!$F$2:$F$5000,'3 Base Entrada 2008'!$F$2:$F$5000,">="&$F$5,'3 Base Entrada 2008'!$F$2:$F$5000,"<="&$H$5,'3 Base Entrada 2008'!$B$2:$B$5000,$T43,'3 Base Entrada 2008'!$C$2:$C$5000,$AG43),_xlfn.MAXIFS('3 Base Saídas'!$G$2:$G$5000,'3 Base Saídas'!$G$2:$G$5000,">="&$F$5,'3 Base Saídas'!$G$2:$G$5000,"<="&$H$5,'3 Base Saídas'!$B$2:$B$5000,$T43,'3 Base Saídas'!$C$2:$C$5000,$AG43)) -> 46291 | BD43: ='5 Conciliação'!L17 -> Transferir 120.0 CX entre os lotes deste SKU (transferência lote a lote, mov. 309) para corrigir o lote | BE43: ='5 Conciliação'!Q17 -> Troca de lote | BF43: ='5 Conciliação'!R17 -> Baixa | BH43: =SUMIFS('3 Base Saldo Inicial 08-09'!$E$2:$E$5000,'3 Base Saldo Inicial 08-09'!$A$2:$A$5000,$T43,'3 Base Saldo Inicial 08-09'!$B$2:$B$5000,$AG43)-SUMIFS('3 Base Saldo Inicial 08-09'!$E$2:$E$5000,'3 Base Saldo Inicial 08-09'!$A$2:$A$5000,$T43,'3 Base Saldo Inicial 08-09'!$B$2:$B$5000,$AG43,'3 Base Saldo Inicial 08-09'!$C$2:$C$5000,"2008") -> 0
A44: =IF(IFERROR(MATCH(31,$AB$40:$AB$133,0),0)=0,"",INDEX($T$40:$T$133,IFERROR(MATCH(31,$AB$40:$AB$133,0),0))) -> 811NV-595 | B44: =IF(IFERROR(MATCH(31,$AB$40:$AB$133,0),0)=0,"",INDEX($AG$40:$AG$133,IFERROR(MATCH(31,$AB$40:$AB$133,0),0))) -> 261146101 | C44: =IF(IFERROR(MATCH(31,$AB$40:$AB$133,0),0)=0,"",INDEX($U$40:$U$133,IFERROR(MATCH(31,$AB$40:$AB$133,0),0))) -> KG | D44: =IF(IFERROR(MATCH(31,$AB$40:$AB$133,0),0)=0,"",INDEX($BH$40:$BH$133,IFERROR(MATCH(31,$AB$40:$AB$133,0),0))) -> 0 | E44: =IF(IFERROR(MATCH(31,$AB$40:$AB$133,0),0)=0,"",INDEX($W$40:$W$133,IFERROR(MATCH(31,$AB$40:$AB$133,0),0))) -> 1180 | F44: =IF(IFERROR(MATCH(31,$AB$40:$AB$133,0),0)=0,"",INDEX($X$40:$X$133,IFERROR(MATCH(31,$AB$40:$AB$133,0),0))) -> 1160 | G44: =IF(A44="","",D44+E44-F44) -> 20 | H44: =IF(IFERROR(MATCH(31,$AB$40:$AB$133,0),0)=0,"",INDEX($Y$40:$Y$133,IFERROR(MATCH(31,$AB$40:$AB$133,0),0))) -> 20 | I44: =IF(IFERROR(MATCH(31,$AB$40:$AB$133,0),0)=0,"",INDEX($Z$40:$Z$133,IFERROR(MATCH(31,$AB$40:$AB$133,0),0))) -> 0 | J44: =IF(IFERROR(MATCH(31,$AB$40:$AB$133,0),0)=0,"",INDEX($AC$40:$AC$133,IFERROR(MATCH(31,$AB$40:$AB$133,0),0))) -> Confere | K44: =IF(IFERROR(MATCH(31,$AB$40:$AB$133,0),0)=0,"",INDEX($AD$40:$AD$133,IFERROR(MATCH(31,$AB$40:$AB$133,0),0))) -> 3 | L44: =IF(IFERROR(MATCH(31,$AB$40:$AB$133,0),0)=0,"",IF(INDEX($BB$40:$BB$133,IFERROR(MATCH(31,$AB$40:$AB$133,0),0))>=99999,"",INDEX($BB$40:$BB$133,IFERROR(MATCH(31,$AB$40:$AB$133,0),0)))) -> 46275 | M44: =IF(IFERROR(MATCH(31,$AB$40:$AB$133,0),0)=0,"",IF(INDEX($BC$40:$BC$133,IFERROR(MATCH(31,$AB$40:$AB$133,0),0))=0,"",INDEX($BC$40:$BC$133,IFERROR(MATCH(31,$AB$40:$AB$133,0),0)))) -> 46290 | N44: =IF(IFERROR(MATCH(31,$AB$40:$AB$133,0),0)=0,"",INDEX($AE$40:$AE$133,IFERROR(MATCH(31,$AB$40:$AB$133,0),0))&"") -> Sem diferença | O44: =IF(IFERROR(MATCH(31,$AB$40:$AB$133,0),0)=0,"",INDEX($BD$40:$BD$133,IFERROR(MATCH(31,$AB$40:$AB$133,0),0))&"") -> Nenhum ajuste necessário | T44: CHD-BB-308BY-357 | U44: UN | V44: =SUMIFS('3 Base Entrada 2008'!$G$2:$G$5000,'3 Base Entrada 2008'!$F$2:$F$5000,">="&$F$5,'3 Base Entrada 2008'!$F$2:$F$5000,"<="&$H$5,'3 Base Entrada 2008'!$B$2:$B$5000,$T44,'3 Base Entrada 2008'!$C$2:$C$5000,$AG44,'3 Base Entrada 2008'!$K$2:$K$5000,"Recebido no 2008") -> 0 | W44: =SUMIFS('3 Base Entrada 2008'!$L$2:$L$5000,'3 Base Entrada 2008'!$F$2:$F$5000,">="&$F$5,'3 Base Entrada 2008'!$F$2:$F$5000,"<="&$H$5,'3 Base Entrada 2008'!$B$2:$B$5000,$T44,'3 Base Entrada 2008'!$C$2:$C$5000,$AG44) -> 30 | X44: =SUMIFS('3 Base Saídas'!$R$2:$R$5000,'3 Base Saídas'!$G$2:$G$5000,">="&$F$5,'3 Base Saídas'!$G$2:$G$5000,"<="&$H$5,'3 Base Saídas'!$B$2:$B$5000,$T44,'3 Base Saídas'!$C$2:$C$5000,$AG44) -> 0 | Y44: =SUMIFS('3 Base Estoque Físico'!$J$2:$J$5000,'3 Base Estoque Físico'!$A$2:$A$5000,$T44,'3 Base Estoque Físico'!$B$2:$B$5000,$AG44) -> 4.219 | Z44: =ROUND(Y44-(BH44+W44-X44),3) -> -25.781 | AA44: =IF(AND(U44=$R$3,OR($R$1="*",T44=$R$1),OR($R$2="*",AG44=$R$2),OR($R$6="*",AC44=$R$6),ABS(V44)+ABS(W44)+ABS(X44)+ABS(Y44)>0),1,0) -> 0 | AB44: =IF(AA44=1,SUM(AA$40:AA44),"") | AC44: =IF(ABS(Z44)<=$R$5,"Confere",IF(Z44>0,"Sobrando","Faltando")) -> Faltando | AD44: =IF(OR($R$4="*",$R$4="Saída"),COUNTIFS('3 Base Saídas'!$G$2:$G$5000,">="&$F$5,'3 Base Saídas'!$G$2:$G$5000,"<="&$H$5,'3 Base Saídas'!$B$2:$B$5000,$T44,'3 Base Saídas'!$C$2:$C$5000,$AG44),0)+IF($R$4<>"Saída",COUNTIFS('3 Base Entrada 2008'!$F$2:$F$5000,">="&$F$5,'3 Base Entrada 2008'!$F$2:$F$5000,"<="&$H$5,'3 Base Entrada 2008'!$B$2:$B$5000,$T44,'3 Base Entrada 2008'!$C$2:$C$5000,$AG44,'3 Base Entrada 2008'!$K$2:$K$5000,$R$4),0) -> 1 | AE44: ='5 Conciliação'!K18 -> Estoque físico menor que o esperado: saída, ajuste ou perda não lançada no período | AF44: =IF(AND(AA44=1,AC44<>"Confere"),ABS(Z44)+ROW()/10000000,0) -> 0 | AG44: 250827800 | AH44: =LARGE($AF$40:$AF$133,5) -> 1268.4 | AI44: =IF(AH44>0,MATCH(AH44,$AF$40:$AF$133,0),"") -> 10 | AJ44: =IF(AI44="","",INDEX($T$40:$T$133,AI44)&" · "&INDEX($AG$40:$AG$133,AI44)) -> 805-BR-D94 · 251633359 | AK44: =IF(AI44="",0,MAX(INDEX($Z$40:$Z$133,AI44),0)) -> 1268.4 | AL44: =IF(AI44="",0,MIN(INDEX($Z$40:$Z$133,AI44),0)) -> 0 | AN44: 13/09 | AO44: 46278 | AP44: =IF(AND(AO44>=$F$5,AO44<=$H$5,$R$4<>"Saída"),SUMIFS('3 Base Entrada 2008'!$L$2:$L$5000,'3 Base Entrada 2008'!$F$2:$F$5000,$AO44,'3 Base Entrada 2008'!$B$2:$B$5000,$R$1,'3 Base Entrada 2008'!$C$2:$C$5000,$R$2,'3 Base Entrada 2008'!$H$2:$H$5000,$R$3,'3 Base Entrada 2008'!$K$2:$K$5000,$R$4),0) -> 0 | AQ44: =IF(AND(AO44>=$F$5,AO44<=$H$5,OR($R$4="*",$R$4="Saída")),-SUMIFS('3 Base Saídas'!$R$2:$R$5000,'3 Base Saídas'!$G$2:$G$5000,$AO44,'3 Base Saídas'!$B$2:$B$5000,$R$1,'3 Base Saídas'!$C$2:$C$5000,$R$2,'3 Base Saídas'!$I$2:$I$5000,$R$3),0) -> -410.8 | AR44: =SUM($AP$40:AP44)+SUM($AQ$40:AQ44) -> 3220.96 | AS44: MALCHOC-D-123 | AV44: =IFERROR(INDEX($AX$1:$AX$94,MATCH(43,$AY$1:$AY$94,0)),"") -> 260720939 | AW44: CHK-W-413 | AX44: 260536201 | AY44: =IF(OR($A$5="Todos",AW44=$A$5),MAX(AY$1:AY43)+1,0) -> 44 | BB44: =MIN(IF(_xlfn.MINIFS('3 Base Entrada 2008'!$F$2:$F$5000,'3 Base Entrada 2008'!$F$2:$F$5000,">="&$F$5,'3 Base Entrada 2008'!$F$2:$F$5000,"<="&$H$5,'3 Base Entrada 2008'!$B$2:$B$5000,$T44,'3 Base Entrada 2008'!$C$2:$C$5000,$AG44)=0,99999,_xlfn.MINIFS('3 Base Entrada 2008'!$F$2:$F$5000,'3 Base Entrada 2008'!$F$2:$F$5000,">="&$F$5,'3 Base Entrada 2008'!$F$2:$F$5000,"<="&$H$5,'3 Base Entrada 2008'!$B$2:$B$5000,$T44,'3 Base Entrada 2008'!$C$2:$C$5000,$AG44)),IF(_xlfn.MINIFS('3 Base Saídas'!$G$2:$G$5000,'3 Base Saídas'!$G$2:$G$5000,">="&$F$5,'3 Base Saídas'!$G$2:$G$5000,"<="&$H$5,'3 Base Saídas'!$B$2:$B$5000,$T44,'3 Base Saídas'!$C$2:$C$5000,$AG44)=0,99999,_xlfn.MINIFS('3 Base Saídas'!$G$2:$G$5000,'3 Base Saídas'!$G$2:$G$5000,">="&$F$5,'3 Base Saídas'!$G$2:$G$5000,"<="&$H$5,'3 Base Saídas'!$B$2:$B$5000,$T44,'3 Base Saídas'!$C$2:$C$5000,$AG44))) -> 46294 | BC44: =MAX(_xlfn.MAXIFS('3 Base Entrada 2008'!$F$2:$F$5000,'3 Base Entrada 2008'!$F$2:$F$5000,">="&$F$5,'3 Base Entrada 2008'!$F$2:$F$5000,"<="&$H$5,'3 Base Entrada 2008'!$B$2:$B$5000,$T44,'3 Base Entrada 2008'!$C$2:$C$5000,$AG44),_xlfn.MAXIFS('3 Base Saídas'!$G$2:$G$5000,'3 Base Saídas'!$G$2:$G$5000,">="&$F$5,'3 Base Saídas'!$G$2:$G$5000,"<="&$H$5,'3 Base Saídas'!$B$2:$B$5000,$T44,'3 Base Saídas'!$C$2:$C$5000,$AG44)) -> 46294 | BD44: ='5 Conciliação'!L18 -> Contar o lote. Se a falta se confirmar: lançar a saída esquecida (601) ou ajuste de inventário de −25.8 UN | BE44: ='5 Conciliação'!Q18 -> Falta sem explicação | BF44: ='5 Conciliação'!R18 -> Alta | BH44: =SUMIFS('3 Base Saldo Inicial 08-09'!$E$2:$E$5000,'3 Base Saldo Inicial 08-09'!$A$2:$A$5000,$T44,'3 Base Saldo Inicial 08-09'!$B$2:$B$5000,$AG44)-SUMIFS('3 Base Saldo Inicial 08-09'!$E$2:$E$5000,'3 Base Saldo Inicial 08-09'!$A$2:$A$5000,$T44,'3 Base Saldo Inicial 08-09'!$B$2:$B$5000,$AG44,'3 Base Saldo Inicial 08-09'!$C$2:$C$5000,"2008") -> 0
A45: =IF(IFERROR(MATCH(32,$AB$40:$AB$133,0),0)=0,"",INDEX($T$40:$T$133,IFERROR(MATCH(32,$AB$40:$AB$133,0),0))) -> 811NV-595 | B45: =IF(IFERROR(MATCH(32,$AB$40:$AB$133,0),0)=0,"",INDEX($AG$40:$AG$133,IFERROR(MATCH(32,$AB$40:$AB$133,0),0))) -> 261146102 | C45: =IF(IFERROR(MATCH(32,$AB$40:$AB$133,0),0)=0,"",INDEX($U$40:$U$133,IFERROR(MATCH(32,$AB$40:$AB$133,0),0))) -> KG | D45: =IF(IFERROR(MATCH(32,$AB$40:$AB$133,0),0)=0,"",INDEX($BH$40:$BH$133,IFERROR(MATCH(32,$AB$40:$AB$133,0),0))) -> 0 | E45: =IF(IFERROR(MATCH(32,$AB$40:$AB$133,0),0)=0,"",INDEX($W$40:$W$133,IFERROR(MATCH(32,$AB$40:$AB$133,0),0))) -> 1660 | F45: =IF(IFERROR(MATCH(32,$AB$40:$AB$133,0),0)=0,"",INDEX($X$40:$X$133,IFERROR(MATCH(32,$AB$40:$AB$133,0),0))) -> 580 | G45: =IF(A45="","",D45+E45-F45) -> 1080 | H45: =IF(IFERROR(MATCH(32,$AB$40:$AB$133,0),0)=0,"",INDEX($Y$40:$Y$133,IFERROR(MATCH(32,$AB$40:$AB$133,0),0))) -> 1080 | I45: =IF(IFERROR(MATCH(32,$AB$40:$AB$133,0),0)=0,"",INDEX($Z$40:$Z$133,IFERROR(MATCH(32,$AB$40:$AB$133,0),0))) -> 0 | J45: =IF(IFERROR(MATCH(32,$AB$40:$AB$133,0),0)=0,"",INDEX($AC$40:$AC$133,IFERROR(MATCH(32,$AB$40:$AB$133,0),0))) -> Confere | K45: =IF(IFERROR(MATCH(32,$AB$40:$AB$133,0),0)=0,"",INDEX($AD$40:$AD$133,IFERROR(MATCH(32,$AB$40:$AB$133,0),0))) -> 10 | L45: =IF(IFERROR(MATCH(32,$AB$40:$AB$133,0),0)=0,"",IF(INDEX($BB$40:$BB$133,IFERROR(MATCH(32,$AB$40:$AB$133,0),0))>=99999,"",INDEX($BB$40:$BB$133,IFERROR(MATCH(32,$AB$40:$AB$133,0),0)))) -> 46275 | M45: =IF(IFERROR(MATCH(32,$AB$40:$AB$133,0),0)=0,"",IF(INDEX($BC$40:$BC$133,IFERROR(MATCH(32,$AB$40:$AB$133,0),0))=0,"",INDEX($BC$40:$BC$133,IFERROR(MATCH(32,$AB$40:$AB$133,0),0)))) -> 46295 | N45: =IF(IFERROR(MATCH(32,$AB$40:$AB$133,0),0)=0,"",INDEX($AE$40:$AE$133,IFERROR(MATCH(32,$AB$40:$AB$133,0),0))&"") -> Sem diferença | O45: =IF(IFERROR(MATCH(32,$AB$40:$AB$133,0),0)=0,"",INDEX($BD$40:$BD$133,IFERROR(MATCH(32,$AB$40:$AB$133,0),0))&"") -> Nenhum ajuste necessário | T45: 811-BR-D94 | U45: KG | V45: =SUMIFS('3 Base Entrada 2008'!$G$2:$G$5000,'3 Base Entrada 2008'!$F$2:$F$5000,">="&$F$5,'3 Base Entrada 2008'!$F$2:$F$5000,"<="&$H$5,'3 Base Entrada 2008'!$B$2:$B$5000,$T45,'3 Base Entrada 2008'!$C$2:$C$5000,$AG45,'3 Base Entrada 2008'!$K$2:$K$5000,"Recebido no 2008") -> 0 | W45: =SUMIFS('3 Base Entrada 2008'!$L$2:$L$5000,'3 Base Entrada 2008'!$F$2:$F$5000,">="&$F$5,'3 Base Entrada 2008'!$F$2:$F$5000,"<="&$H$5,'3 Base Entrada 2008'!$B$2:$B$5000,$T45,'3 Base Entrada 2008'!$C$2:$C$5000,$AG45) -> 2.8 | X45: =SUMIFS('3 Base Saídas'!$R$2:$R$5000,'3 Base Saídas'!$G$2:$G$5000,">="&$F$5,'3 Base Saídas'!$G$2:$G$5000,"<="&$H$5,'3 Base Saídas'!$B$2:$B$5000,$T45,'3 Base Saídas'!$C$2:$C$5000,$AG45) -> 226.8 | Y45: =SUMIFS('3 Base Estoque Físico'!$J$2:$J$5000,'3 Base Estoque Físico'!$A$2:$A$5000,$T45,'3 Base Estoque Físico'!$B$2:$B$5000,$AG45) -> 5513.2 | Z45: =ROUND(Y45-(BH45+W45-X45),3) -> 5737.2 | AA45: =IF(AND(U45=$R$3,OR($R$1="*",T45=$R$1),OR($R$2="*",AG45=$R$2),OR($R$6="*",AC45=$R$6),ABS(V45)+ABS(W45)+ABS(X45)+ABS(Y45)>0),1,0) -> 1 | AB45: =IF(AA45=1,SUM(AA$40:AA45),"") -> 4 | AC45: =IF(ABS(Z45)<=$R$5,"Confere",IF(Z45>0,"Sobrando","Faltando")) -> Sobrando | AD45: =IF(OR($R$4="*",$R$4="Saída"),COUNTIFS('3 Base Saídas'!$G$2:$G$5000,">="&$F$5,'3 Base Saídas'!$G$2:$G$5000,"<="&$H$5,'3 Base Saídas'!$B$2:$B$5000,$T45,'3 Base Saídas'!$C$2:$C$5000,$AG45),0)+IF($R$4<>"Saída",COUNTIFS('3 Base Entrada 2008'!$F$2:$F$5000,">="&$F$5,'3 Base Entrada 2008'!$F$2:$F$5000,"<="&$H$5,'3 Base Entrada 2008'!$B$2:$B$5000,$T45,'3 Base Entrada 2008'!$C$2:$C$5000,$AG45,'3 Base Entrada 2008'!$K$2:$K$5000,$R$4),0) -> 17 | AE45: ='5 Conciliação'!K19 -> Explica em parte: estoque antigo 5,328.4 + doca/transferência 0.0; faltam 408.8 a explicar | AF45: =IF(AND(AA45=1,AC45<>"Confere"),ABS(Z45)+ROW()/10000000,0) -> 5737.2 | AG45: 251643289 | AH45: =LARGE($AF$40:$AF$133,6) -> 1083.39 | AI45: =IF(AH45>0,MATCH(AH45,$AF$40:$AF$133,0),"") -> 11 | AJ45: =IF(AI45="","",INDEX($T$40:$T$133,AI45)&" · "&INDEX($AG$40:$AG$133,AI45)) -> W3-BR-25A · 253540301 | AK45: =IF(AI45="",0,MAX(INDEX($Z$40:$Z$133,AI45),0)) -> 1083.39 | AL45: =IF(AI45="",0,MIN(INDEX($Z$40:$Z$133,AI45),0)) -> 0 | AN45: 14/09 | AO45: 46279 | AP45: =IF(AND(AO45>=$F$5,AO45<=$H$5,$R$4<>"Saída"),SUMIFS('3 Base Entrada 2008'!$L$2:$L$5000,'3 Base Entrada 2008'!$F$2:$F$5000,$AO45,'3 Base Entrada 2008'!$B$2:$B$5000,$R$1,'3 Base Entrada 2008'!$C$2:$C$5000,$R$2,'3 Base Entrada 2008'!$H$2:$H$5000,$R$3,'3 Base Entrada 2008'!$K$2:$K$5000,$R$4),0) -> 0 | AQ45: =IF(AND(AO45>=$F$5,AO45<=$H$5,OR($R$4="*",$R$4="Saída")),-SUMIFS('3 Base Saídas'!$R$2:$R$5000,'3 Base Saídas'!$G$2:$G$5000,$AO45,'3 Base Saídas'!$B$2:$B$5000,$R$1,'3 Base Saídas'!$C$2:$C$5000,$R$2,'3 Base Saídas'!$I$2:$I$5000,$R$3),0) -> -163 | AR45: =SUM($AP$40:AP45)+SUM($AQ$40:AQ45) -> 3057.96 | AS45: NIBS-S502-X47 | AV45: =IFERROR(INDEX($AX$1:$AX$94,MATCH(44,$AY$1:$AY$94,0)),"") -> 260536201 | AW45: CHM-BS-9U15-E0-07B | AX45: 260701069 | AY45: =IF(OR($A$5="Todos",AW45=$A$5),MAX(AY$1:AY44)+1,0) -> 45 | BB45: =MIN(IF(_xlfn.MINIFS('3 Base Entrada 2008'!$F$2:$F$5000,'3 Base Entrada 2008'!$F$2:$F$5000,">="&$F$5,'3 Base Entrada 2008'!$F$2:$F$5000,"<="&$H$5,'3 Base Entrada 2008'!$B$2:$B$5000,$T45,'3 Base Entrada 2008'!$C$2:$C$5000,$AG45)=0,99999,_xlfn.MINIFS('3 Base Entrada 2008'!$F$2:$F$5000,'3 Base Entrada 2008'!$F$2:$F$5000,">="&$F$5,'3 Base Entrada 2008'!$F$2:$F$5000,"<="&$H$5,'3 Base Entrada 2008'!$B$2:$B$5000,$T45,'3 Base Entrada 2008'!$C$2:$C$5000,$AG45)),IF(_xlfn.MINIFS('3 Base Saídas'!$G$2:$G$5000,'3 Base Saídas'!$G$2:$G$5000,">="&$F$5,'3 Base Saídas'!$G$2:$G$5000,"<="&$H$5,'3 Base Saídas'!$B$2:$B$5000,$T45,'3 Base Saídas'!$C$2:$C$5000,$AG45)=0,99999,_xlfn.MINIFS('3 Base Saídas'!$G$2:$G$5000,'3 Base Saídas'!$G$2:$G$5000,">="&$F$5,'3 Base Saídas'!$G$2:$G$5000,"<="&$H$5,'3 Base Saídas'!$B$2:$B$5000,$T45,'3 Base Saídas'!$C$2:$C$5000,$AG45))) -> 46284 | BC45: =MAX(_xlfn.MAXIFS('3 Base Entrada 2008'!$F$2:$F$5000,'3 Base Entrada 2008'!$F$2:$F$5000,">="&$F$5,'3 Base Entrada 2008'!$F$2:$F$5000,"<="&$H$5,'3 Base Entrada 2008'!$B$2:$B$5000,$T45,'3 Base Entrada 2008'!$C$2:$C$5000,$AG45),_xlfn.MAXIFS('3 Base Saídas'!$G$2:$G$5000,'3 Base Saídas'!$G$2:$G$5000,">="&$F$5,'3 Base Saídas'!$G$2:$G$5000,"<="&$H$5,'3 Base Saídas'!$B$2:$B$5000,$T45,'3 Base Saídas'!$C$2:$C$5000,$AG45)) -> 46295 | BD45: ='5 Conciliação'!L19 -> Confirmar saldo de 08/09 e OTs de doca; contar o lote para os 408.8 KG restantes e ajustar a sobra se confirmada | BE45: ='5 Conciliação'!Q19 -> Sobra parcialmente explicada | BF45: ='5 Conciliação'!R19 -> Média | BH45: =SUMIFS('3 Base Saldo Inicial 08-09'!$E$2:$E$5000,'3 Base Saldo Inicial 08-09'!$A$2:$A$5000,$T45,'3 Base Saldo Inicial 08-09'!$B$2:$B$5000,$AG45)-SUMIFS('3 Base Saldo Inicial 08-09'!$E$2:$E$5000,'3 Base Saldo Inicial 08-09'!$A$2:$A$5000,$T45,'3 Base Saldo Inicial 08-09'!$B$2:$B$5000,$AG45,'3 Base Saldo Inicial 08-09'!$C$2:$C$5000,"2008") -> 0
A46: =IF(IFERROR(MATCH(33,$AB$40:$AB$133,0),0)=0,"",INDEX($T$40:$T$133,IFERROR(MATCH(33,$AB$40:$AB$133,0),0))) -> 823-BR-25A | B46: =IF(IFERROR(MATCH(33,$AB$40:$AB$133,0),0)=0,"",INDEX($AG$40:$AG$133,IFERROR(MATCH(33,$AB$40:$AB$133,0),0))) -> 252100301 | C46: =IF(IFERROR(MATCH(33,$AB$40:$AB$133,0),0)=0,"",INDEX($U$40:$U$133,IFERROR(MATCH(33,$AB$40:$AB$133,0),0))) -> KG | D46: =IF(IFERROR(MATCH(33,$AB$40:$AB$133,0),0)=0,"",INDEX($BH$40:$BH$133,IFERROR(MATCH(33,$AB$40:$AB$133,0),0))) -> 0 | E46: =IF(IFERROR(MATCH(33,$AB$40:$AB$133,0),0)=0,"",INDEX($W$40:$W$133,IFERROR(MATCH(33,$AB$40:$AB$133,0),0))) -> 461.9 | F46: =IF(IFERROR(MATCH(33,$AB$40:$AB$133,0),0)=0,"",INDEX($X$40:$X$133,IFERROR(MATCH(33,$AB$40:$AB$133,0),0))) -> 442.2 | G46: =IF(A46="","",D46+E46-F46) -> 19.7 | H46: =IF(IFERROR(MATCH(33,$AB$40:$AB$133,0),0)=0,"",INDEX($Y$40:$Y$133,IFERROR(MATCH(33,$AB$40:$AB$133,0),0))) -> 19.7 | I46: =IF(IFERROR(MATCH(33,$AB$40:$AB$133,0),0)=0,"",INDEX($Z$40:$Z$133,IFERROR(MATCH(33,$AB$40:$AB$133,0),0))) -> 0 | J46: =IF(IFERROR(MATCH(33,$AB$40:$AB$133,0),0)=0,"",INDEX($AC$40:$AC$133,IFERROR(MATCH(33,$AB$40:$AB$133,0),0))) -> Confere | K46: =IF(IFERROR(MATCH(33,$AB$40:$AB$133,0),0)=0,"",INDEX($AD$40:$AD$133,IFERROR(MATCH(33,$AB$40:$AB$133,0),0))) -> 2 | L46: =IF(IFERROR(MATCH(33,$AB$40:$AB$133,0),0)=0,"",IF(INDEX($BB$40:$BB$133,IFERROR(MATCH(33,$AB$40:$AB$133,0),0))>=99999,"",INDEX($BB$40:$BB$133,IFERROR(MATCH(33,$AB$40:$AB$133,0),0)))) -> 46289 | M46: =IF(IFERROR(MATCH(33,$AB$40:$AB$133,0),0)=0,"",IF(INDEX($BC$40:$BC$133,IFERROR(MATCH(33,$AB$40:$AB$133,0),0))=0,"",INDEX($BC$40:$BC$133,IFERROR(MATCH(33,$AB$40:$AB$133,0),0)))) -> 46291 | N46: =IF(IFERROR(MATCH(33,$AB$40:$AB$133,0),0)=0,"",INDEX($AE$40:$AE$133,IFERROR(MATCH(33,$AB$40:$AB$133,0),0))&"") -> Sem diferença | O46: =IF(IFERROR(MATCH(33,$AB$40:$AB$133,0),0)=0,"",INDEX($BD$40:$BD$133,IFERROR(MATCH(33,$AB$40:$AB$133,0),0))&"") -> Nenhum ajuste necessário | T46: CHM-SP-Z3L-BR-U73 | U46: KG | V46: =SUMIFS('3 Base Entrada 2008'!$G$2:$G$5000,'3 Base Entrada 2008'!$F$2:$F$5000,">="&$F$5,'3 Base Entrada 2008'!$F$2:$F$5000,"<="&$H$5,'3 Base Entrada 2008'!$B$2:$B$5000,$T46,'3 Base Entrada 2008'!$C$2:$C$5000,$AG46,'3 Base Entrada 2008'!$K$2:$K$5000,"Recebido no 2008") -> 0 | W46: =SUMIFS('3 Base Entrada 2008'!$L$2:$L$5000,'3 Base Entrada 2008'!$F$2:$F$5000,">="&$F$5,'3 Base Entrada 2008'!$F$2:$F$5000,"<="&$H$5,'3 Base Entrada 2008'!$B$2:$B$5000,$T46,'3 Base Entrada 2008'!$C$2:$C$5000,$AG46) -> 966 | X46: =SUMIFS('3 Base Saídas'!$R$2:$R$5000,'3 Base Saídas'!$G$2:$G$5000,">="&$F$5,'3 Base Saídas'!$G$2:$G$5000,"<="&$H$5,'3 Base Saídas'!$B$2:$B$5000,$T46,'3 Base Saídas'!$C$2:$C$5000,$AG46) -> 906 | Y46: =SUMIFS('3 Base Estoque Físico'!$J$2:$J$5000,'3 Base Estoque Físico'!$A$2:$A$5000,$T46,'3 Base Estoque Físico'!$B$2:$B$5000,$AG46) -> 3754.998 | Z46: =ROUND(Y46-(BH46+W46-X46),3) -> 3694.998 | AA46: =IF(AND(U46=$R$3,OR($R$1="*",T46=$R$1),OR($R$2="*",AG46=$R$2),OR($R$6="*",AC46=$R$6),ABS(V46)+ABS(W46)+ABS(X46)+ABS(Y46)>0),1,0) -> 1 | AB46: =IF(AA46=1,SUM(AA$40:AA46),"") -> 5 | AC46: =IF(ABS(Z46)<=$R$5,"Confere",IF(Z46>0,"Sobrando","Faltando")) -> Sobrando | AD46: =IF(OR($R$4="*",$R$4="Saída"),COUNTIFS('3 Base Saídas'!$G$2:$G$5000,">="&$F$5,'3 Base Saídas'!$G$2:$G$5000,"<="&$H$5,'3 Base Saídas'!$B$2:$B$5000,$T46,'3 Base Saídas'!$C$2:$C$5000,$AG46),0)+IF($R$4<>"Saída",COUNTIFS('3 Base Entrada 2008'!$F$2:$F$5000,">="&$F$5,'3 Base Entrada 2008'!$F$2:$F$5000,"<="&$H$5,'3 Base Entrada 2008'!$B$2:$B$5000,$T46,'3 Base Entrada 2008'!$C$2:$C$5000,$AG46,'3 Base Entrada 2008'!$K$2:$K$5000,$R$4),0) -> 30 | AE46: ='5 Conciliação'!K20 -> Explica em parte: estoque antigo 1,343.0 + doca/transferência 204.0; faltam 2,148.0 a explicar | AF46: =IF(AND(AA46=1,AC46<>"Confere"),ABS(Z46)+ROW()/10000000,0) -> 3694.998 | AG46: 251880301 | AH46: =LARGE($AF$40:$AF$133,7) -> 924.60001 | AI46: =IF(AH46>0,MATCH(AH46,$AF$40:$AF$133,0),"") -> 12 | AJ46: =IF(AI46="","",INDEX($T$40:$T$133,AI46)&" · "&INDEX($AG$40:$AG$133,AI46)) -> CW2-BR-25A · 253470301 | AK46: =IF(AI46="",0,MAX(INDEX($Z$40:$Z$133,AI46),0)) -> 924.6 | AL46: =IF(AI46="",0,MIN(INDEX($Z$40:$Z$133,AI46),0)) -> 0 | AN46: 15/09 | AO46: 46280 | AP46: =IF(AND(AO46>=$F$5,AO46<=$H$5,$R$4<>"Saída"),SUMIFS('3 Base Entrada 2008'!$L$2:$L$5000,'3 Base Entrada 2008'!$F$2:$F$5000,$AO46,'3 Base Entrada 2008'!$B$2:$B$5000,$R$1,'3 Base Entrada 2008'!$C$2:$C$5000,$R$2,'3 Base Entrada 2008'!$H$2:$H$5000,$R$3,'3 Base Entrada 2008'!$K$2:$K$5000,$R$4),0) -> 0 | AQ46: =IF(AND(AO46>=$F$5,AO46<=$H$5,OR($R$4="*",$R$4="Saída")),-SUMIFS('3 Base Saídas'!$R$2:$R$5000,'3 Base Saídas'!$G$2:$G$5000,$AO46,'3 Base Saídas'!$B$2:$B$5000,$R$1,'3 Base Saídas'!$C$2:$C$5000,$R$2,'3 Base Saídas'!$I$2:$I$5000,$R$3),0) -> -340 | AR46: =SUM($AP$40:AP46)+SUM($AQ$40:AQ46) -> 2717.96 | AS46: PNP-T14 | AV46: =IFERROR(INDEX($AX$1:$AX$94,MATCH(45,$AY$1:$AY$94,0)),"") -> 260701069 | AW46: CHM-CU-7X80-E5-U70 | AX46: 2528749307 | AY46: =IF(OR($A$5="Todos",AW46=$A$5),MAX(AY$1:AY45)+1,0) -> 46 | BB46: =MIN(IF(_xlfn.MINIFS('3 Base Entrada 2008'!$F$2:$F$5000,'3 Base Entrada 2008'!$F$2:$F$5000,">="&$F$5,'3 Base Entrada 2008'!$F$2:$F$5000,"<="&$H$5,'3 Base Entrada 2008'!$B$2:$B$5000,$T46,'3 Base Entrada 2008'!$C$2:$C$5000,$AG46)=0,99999,_xlfn.MINIFS('3 Base Entrada 2008'!$F$2:$F$5000,'3 Base Entrada 2008'!$F$2:$F$5000,">="&$F$5,'3 Base Entrada 2008'!$F$2:$F$5000,"<="&$H$5,'3 Base Entrada 2008'!$B$2:$B$5000,$T46,'3 Base Entrada 2008'!$C$2:$C$5000,$AG46)),IF(_xlfn.MINIFS('3 Base Saídas'!$G$2:$G$5000,'3 Base Saídas'!$G$2:$G$5000,">="&$F$5,'3 Base Saídas'!$G$2:$G$5000,"<="&$H$5,'3 Base Saídas'!$B$2:$B$5000,$T46,'3 Base Saídas'!$C$2:$C$5000,$AG46)=0,99999,_xlfn.MINIFS('3 Base Saídas'!$G$2:$G$5000,'3 Base Saídas'!$G$2:$G$5000,">="&$F$5,'3 Base Saídas'!$G$2:$G$5000,"<="&$H$5,'3 Base Saídas'!$B$2:$B$5000,$T46,'3 Base Saídas'!$C$2:$C$5000,$AG46))) -> 46275 | BC46: =MAX(_xlfn.MAXIFS('3 Base Entrada 2008'!$F$2:$F$5000,'3 Base Entrada 2008'!$F$2:$F$5000,">="&$F$5,'3 Base Entrada 2008'!$F$2:$F$5000,"<="&$H$5,'3 Base Entrada 2008'!$B$2:$B$5000,$T46,'3 Base Entrada 2008'!$C$2:$C$5000,$AG46),_xlfn.MAXIFS('3 Base Saídas'!$G$2:$G$5000,'3 Base Saídas'!$G$2:$G$5000,">="&$F$5,'3 Base Saídas'!$G$2:$G$5000,"<="&$H$5,'3 Base Saídas'!$B$2:$B$5000,$T46,'3 Base Saídas'!$C$2:$C$5000,$AG46)) -> 46293 | BD46: ='5 Conciliação'!L20 -> Confirmar saldo de 08/09 e OTs de doca; contar o lote para os 2,148.0 KG restantes e ajustar a sobra se confirmada | BE46: ='5 Conciliação'!Q20 -> Sobra parcialmente explicada | BF46: ='5 Conciliação'!R20 -> Alta | BH46: =SUMIFS('3 Base Saldo Inicial 08-09'!$E$2:$E$5000,'3 Base Saldo Inicial 08-09'!$A$2:$A$5000,$T46,'3 Base Saldo Inicial 08-09'!$B$2:$B$5000,$AG46)-SUMIFS('3 Base Saldo Inicial 08-09'!$E$2:$E$5000,'3 Base Saldo Inicial 08-09'!$A$2:$A$5000,$T46,'3 Base Saldo Inicial 08-09'!$B$2:$B$5000,$AG46,'3 Base Saldo Inicial 08-09'!$C$2:$C$5000,"2008") -> 0
A47: =IF(IFERROR(MATCH(34,$AB$40:$AB$133,0),0)=0,"",INDEX($T$40:$T$133,IFERROR(MATCH(34,$AB$40:$AB$133,0),0))) -> 823-BR-25A | B47: =IF(IFERROR(MATCH(34,$AB$40:$AB$133,0),0)=0,"",INDEX($AG$40:$AG$133,IFERROR(MATCH(34,$AB$40:$AB$133,0),0))) -> 252940301 | C47: =IF(IFERROR(MATCH(34,$AB$40:$AB$133,0),0)=0,"",INDEX($U$40:$U$133,IFERROR(MATCH(34,$AB$40:$AB$133,0),0))) -> KG | D47: =IF(IFERROR(MATCH(34,$AB$40:$AB$133,0),0)=0,"",INDEX($BH$40:$BH$133,IFERROR(MATCH(34,$AB$40:$AB$133,0),0))) -> 0 | E47: =IF(IFERROR(MATCH(34,$AB$40:$AB$133,0),0)=0,"",INDEX($W$40:$W$133,IFERROR(MATCH(34,$AB$40:$AB$133,0),0))) -> 1809 | F47: =IF(IFERROR(MATCH(34,$AB$40:$AB$133,0),0)=0,"",INDEX($X$40:$X$133,IFERROR(MATCH(34,$AB$40:$AB$133,0),0))) -> 1025.1 | G47: =IF(A47="","",D47+E47-F47) -> 783.9 | H47: =IF(IFERROR(MATCH(34,$AB$40:$AB$133,0),0)=0,"",INDEX($Y$40:$Y$133,IFERROR(MATCH(34,$AB$40:$AB$133,0),0))) -> 783.9 | I47: =IF(IFERROR(MATCH(34,$AB$40:$AB$133,0),0)=0,"",INDEX($Z$40:$Z$133,IFERROR(MATCH(34,$AB$40:$AB$133,0),0))) -> 0 | J47: =IF(IFERROR(MATCH(34,$AB$40:$AB$133,0),0)=0,"",INDEX($AC$40:$AC$133,IFERROR(MATCH(34,$AB$40:$AB$133,0),0))) -> Confere | K47: =IF(IFERROR(MATCH(34,$AB$40:$AB$133,0),0)=0,"",INDEX($AD$40:$AD$133,IFERROR(MATCH(34,$AB$40:$AB$133,0),0))) -> 9 | L47: =IF(IFERROR(MATCH(34,$AB$40:$AB$133,0),0)=0,"",IF(INDEX($BB$40:$BB$133,IFERROR(MATCH(34,$AB$40:$AB$133,0),0))>=99999,"",INDEX($BB$40:$BB$133,IFERROR(MATCH(34,$AB$40:$AB$133,0),0)))) -> 46289 | M47: =IF(IFERROR(MATCH(34,$AB$40:$AB$133,0),0)=0,"",IF(INDEX($BC$40:$BC$133,IFERROR(MATCH(34,$AB$40:$AB$133,0),0))=0,"",INDEX($BC$40:$BC$133,IFERROR(MATCH(34,$AB$40:$AB$133,0),0)))) -> 46295 | N47: =IF(IFERROR(MATCH(34,$AB$40:$AB$133,0),0)=0,"",INDEX($AE$40:$AE$133,IFERROR(MATCH(34,$AB$40:$AB$133,0),0))&"") -> Sem diferença | O47: =IF(IFERROR(MATCH(34,$AB$40:$AB$133,0),0)=0,"",INDEX($BD$40:$BD$133,IFERROR(MATCH(34,$AB$40:$AB$133,0),0))&"") -> Nenhum ajuste necessário | T47: CHD-SP-9Z4-BR-U73 | U47: KG | V47: =SUMIFS('3 Base Entrada 2008'!$G$2:$G$5000,'3 Base Entrada 2008'!$F$2:$F$5000,">="&$F$5,'3 Base Entrada 2008'!$F$2:$F$5000,"<="&$H$5,'3 Base Entrada 2008'!$B$2:$B$5000,$T47,'3 Base Entrada 2008'!$C$2:$C$5000,$AG47,'3 Base Entrada 2008'!$K$2:$K$5000,"Recebido no 2008") -> 0 | W47: =SUMIFS('3 Base Entrada 2008'!$L$2:$L$5000,'3 Base Entrada 2008'!$F$2:$F$5000,">="&$F$5,'3 Base Entrada 2008'!$F$2:$F$5000,"<="&$H$5,'3 Base Entrada 2008'!$B$2:$B$5000,$T47,'3 Base Entrada 2008'!$C$2:$C$5000,$AG47) -> 240 | X47: =SUMIFS('3 Base Saídas'!$R$2:$R$5000,'3 Base Saídas'!$G$2:$G$5000,">="&$F$5,'3 Base Saídas'!$G$2:$G$5000,"<="&$H$5,'3 Base Saídas'!$B$2:$B$5000,$T47,'3 Base Saídas'!$C$2:$C$5000,$AG47) -> 6 | Y47: =SUMIFS('3 Base Estoque Físico'!$J$2:$J$5000,'3 Base Estoque Físico'!$A$2:$A$5000,$T47,'3 Base Estoque Físico'!$B$2:$B$5000,$AG47) -> 3432 | Z47: =ROUND(Y47-(BH47+W47-X47),3) -> 3198 | AA47: =IF(AND(U47=$R$3,OR($R$1="*",T47=$R$1),OR($R$2="*",AG47=$R$2),OR($R$6="*",AC47=$R$6),ABS(V47)+ABS(W47)+ABS(X47)+ABS(Y47)>0),1,0) -> 1 | AB47: =IF(AA47=1,SUM(AA$40:AA47),"") -> 6 | AC47: =IF(ABS(Z47)<=$R$5,"Confere",IF(Z47>0,"Sobrando","Faltando")) -> Sobrando | AD47: =IF(OR($R$4="*",$R$4="Saída"),COUNTIFS('3 Base Saídas'!$G$2:$G$5000,">="&$F$5,'3 Base Saídas'!$G$2:$G$5000,"<="&$H$5,'3 Base Saídas'!$B$2:$B$5000,$T47,'3 Base Saídas'!$C$2:$C$5000,$AG47),0)+IF($R$4<>"Saída",COUNTIFS('3 Base Entrada 2008'!$F$2:$F$5000,">="&$F$5,'3 Base Entrada 2008'!$F$2:$F$5000,"<="&$H$5,'3 Base Entrada 2008'!$B$2:$B$5000,$T47,'3 Base Entrada 2008'!$C$2:$C$5000,$AG47,'3 Base Entrada 2008'!$K$2:$K$5000,$R$4),0) -> 2 | AE47: ='5 Conciliação'!K21 -> Explica em parte: estoque antigo 2,898.0 + doca/transferência 0.0; faltam 300.0 a explicar | AF47: =IF(AND(AA47=1,AC47<>"Confere"),ABS(Z47)+ROW()/10000000,0) -> 3198 | AG47: 250500301 | AH47: =LARGE($AF$40:$AF$133,8) -> 540.00001 | AI47: =IF(AH47>0,MATCH(AH47,$AF$40:$AF$133,0),"") -> 13 | AJ47: =IF(AI47="","",INDEX($T$40:$T$133,AI47)&" · "&INDEX($AG$40:$AG$133,AI47)) -> CHP-20SICHP-760 · 252843369 | AK47: =IF(AI47="",0,MAX(INDEX($Z$40:$Z$133,AI47),0)) -> 540 | AL47: =IF(AI47="",0,MIN(INDEX($Z$40:$Z$133,AI47),0)) -> 0 | AN47: 16/09 | AO47: 46281 | AP47: =IF(AND(AO47>=$F$5,AO47<=$H$5,$R$4<>"Saída"),SUMIFS('3 Base Entrada 2008'!$L$2:$L$5000,'3 Base Entrada 2008'!$F$2:$F$5000,$AO47,'3 Base Entrada 2008'!$B$2:$B$5000,$R$1,'3 Base Entrada 2008'!$C$2:$C$5000,$R$2,'3 Base Entrada 2008'!$H$2:$H$5000,$R$3,'3 Base Entrada 2008'!$K$2:$K$5000,$R$4),0) -> 0 | AQ47: =IF(AND(AO47>=$F$5,AO47<=$H$5,OR($R$4="*",$R$4="Saída")),-SUMIFS('3 Base Saídas'!$R$2:$R$5000,'3 Base Saídas'!$G$2:$G$5000,$AO47,'3 Base Saídas'!$B$2:$B$5000,$R$1,'3 Base Saídas'!$C$2:$C$5000,$R$2,'3 Base Saídas'!$I$2:$I$5000,$R$3),0) -> -94.6 | AR47: =SUM($AP$40:AP47)+SUM($AQ$40:AQ47) -> 2623.36 | AS47: PRA-T14 | AV47: =IFERROR(INDEX($AX$1:$AX$94,MATCH(46,$AY$1:$AY$94,0)),"") -> 2528749307 | AW47: CHM-Q41ALUN-2B-U73 | AX47: 260660303 | AY47: =IF(OR($A$5="Todos",AW47=$A$5),MAX(AY$1:AY46)+1,0) -> 47 | BB47: =MIN(IF(_xlfn.MINIFS('3 Base Entrada 2008'!$F$2:$F$5000,'3 Base Entrada 2008'!$F$2:$F$5000,">="&$F$5,'3 Base Entrada 2008'!$F$2:$F$5000,"<="&$H$5,'3 Base Entrada 2008'!$B$2:$B$5000,$T47,'3 Base Entrada 2008'!$C$2:$C$5000,$AG47)=0,99999,_xlfn.MINIFS('3 Base Entrada 2008'!$F$2:$F$5000,'3 Base Entrada 2008'!$F$2:$F$5000,">="&$F$5,'3 Base Entrada 2008'!$F$2:$F$5000,"<="&$H$5,'3 Base Entrada 2008'!$B$2:$B$5000,$T47,'3 Base Entrada 2008'!$C$2:$C$5000,$AG47)),IF(_xlfn.MINIFS('3 Base Saídas'!$G$2:$G$5000,'3 Base Saídas'!$G$2:$G$5000,">="&$F$5,'3 Base Saídas'!$G$2:$G$5000,"<="&$H$5,'3 Base Saídas'!$B$2:$B$5000,$T47,'3 Base Saídas'!$C$2:$C$5000,$AG47)=0,99999,_xlfn.MINIFS('3 Base Saídas'!$G$2:$G$5000,'3 Base Saídas'!$G$2:$G$5000,">="&$F$5,'3 Base Saídas'!$G$2:$G$5000,"<="&$H$5,'3 Base Saídas'!$B$2:$B$5000,$T47,'3 Base Saídas'!$C$2:$C$5000,$AG47))) -> 46279 | BC47: =MAX(_xlfn.MAXIFS('3 Base Entrada 2008'!$F$2:$F$5000,'3 Base Entrada 2008'!$F$2:$F$5000,">="&$F$5,'3 Base Entrada 2008'!$F$2:$F$5000,"<="&$H$5,'3 Base Entrada 2008'!$B$2:$B$5000,$T47,'3 Base Entrada 2008'!$C$2:$C$5000,$AG47),_xlfn.MAXIFS('3 Base Saídas'!$G$2:$G$5000,'3 Base Saídas'!$G$2:$G$5000,">="&$F$5,'3 Base Saídas'!$G$2:$G$5000,"<="&$H$5,'3 Base Saídas'!$B$2:$B$5000,$T47,'3 Base Saídas'!$C$2:$C$5000,$AG47)) -> 46294 | BD47: ='5 Conciliação'!L21 -> Confirmar saldo de 08/09 e OTs de doca; contar o lote para os 300.0 KG restantes e ajustar a sobra se confirmada | BE47: ='5 Conciliação'!Q21 -> Sobra parcialmente explicada | BF47: ='5 Conciliação'!R21 -> Média | BH47: =SUMIFS('3 Base Saldo Inicial 08-09'!$E$2:$E$5000,'3 Base Saldo Inicial 08-09'!$A$2:$A$5000,$T47,'3 Base Saldo Inicial 08-09'!$B$2:$B$5000,$AG47)-SUMIFS('3 Base Saldo Inicial 08-09'!$E$2:$E$5000,'3 Base Saldo Inicial 08-09'!$A$2:$A$5000,$T47,'3 Base Saldo Inicial 08-09'!$B$2:$B$5000,$AG47,'3 Base Saldo Inicial 08-09'!$C$2:$C$5000,"2008") -> 0
